package com.tencent.mm.app;

import android.content.ComponentName;
import android.content.ServiceConnection;
import android.os.IBinder;
import com.tencent.gmtrace.GMTrace;
import com.tencent.mm.ad.n;
import com.tencent.mm.kernel.a;
import com.tencent.mm.kernel.b;
import com.tencent.mm.kernel.h;
import com.tencent.mm.network.g.a;
import com.tencent.mm.network.s.a;
import com.tencent.mm.sdk.platformtools.ab;
import com.tencent.mm.sdk.platformtools.af;
import com.tencent.mm.sdk.platformtools.w;
import com.tencent.mm.y.ah;
import java.util.concurrent.locks.ReentrantLock;

public final class e
  implements ServiceConnection
{
  private static boolean esg;
  private static Object lock;
  public ReentrantLock esh;
  private boolean esi;
  public IBinder esj;
  private Runnable esk;
  
  static
  {
    GMTrace.i(13714099011584L, 102178);
    esg = false;
    lock = new Object();
    GMTrace.o(13714099011584L, 102178);
  }
  
  public e()
  {
    GMTrace.i(13713293705216L, 102172);
    this.esh = new ReentrantLock();
    this.esi = false;
    this.esj = null;
    this.esk = new Runnable()
    {
      private int eso;
      
      /* Error */
      public final void run()
      {
        // Byte code:
        //   0: ldc2_w 38
        //   3: ldc 40
        //   5: invokestatic 28	com/tencent/gmtrace/GMTrace:i	(JI)V
        //   8: aload_0
        //   9: getfield 16	com/tencent/mm/app/e$3:esl	Lcom/tencent/mm/app/e;
        //   12: getfield 44	com/tencent/mm/app/e:esh	Ljava/util/concurrent/locks/ReentrantLock;
        //   15: invokevirtual 49	java/util/concurrent/locks/ReentrantLock:lock	()V
        //   18: aload_0
        //   19: getfield 16	com/tencent/mm/app/e$3:esl	Lcom/tencent/mm/app/e;
        //   22: getfield 53	com/tencent/mm/app/e:esj	Landroid/os/IBinder;
        //   25: ifnull +78 -> 103
        //   28: aload_0
        //   29: getfield 16	com/tencent/mm/app/e$3:esl	Lcom/tencent/mm/app/e;
        //   32: getfield 53	com/tencent/mm/app/e:esj	Landroid/os/IBinder;
        //   35: invokeinterface 59 1 0
        //   40: ifeq +63 -> 103
        //   43: iconst_1
        //   44: istore_2
        //   45: ldc 61
        //   47: ldc 63
        //   49: iconst_2
        //   50: anewarray 4	java/lang/Object
        //   53: dup
        //   54: iconst_0
        //   55: aload_0
        //   56: getfield 16	com/tencent/mm/app/e$3:esl	Lcom/tencent/mm/app/e;
        //   59: getfield 53	com/tencent/mm/app/e:esj	Landroid/os/IBinder;
        //   62: aastore
        //   63: dup
        //   64: iconst_1
        //   65: iload_2
        //   66: invokestatic 69	java/lang/Boolean:valueOf	(Z)Ljava/lang/Boolean;
        //   69: aastore
        //   70: invokestatic 74	com/tencent/mm/sdk/platformtools/w:i	(Ljava/lang/String;Ljava/lang/String;[Ljava/lang/Object;)V
        //   73: iload_2
        //   74: ifeq +34 -> 108
        //   77: ldc 61
        //   79: ldc 76
        //   81: invokestatic 80	com/tencent/mm/sdk/platformtools/w:w	(Ljava/lang/String;Ljava/lang/String;)V
        //   84: aload_0
        //   85: getfield 16	com/tencent/mm/app/e$3:esl	Lcom/tencent/mm/app/e;
        //   88: getfield 44	com/tencent/mm/app/e:esh	Ljava/util/concurrent/locks/ReentrantLock;
        //   91: invokevirtual 83	java/util/concurrent/locks/ReentrantLock:unlock	()V
        //   94: ldc2_w 38
        //   97: ldc 40
        //   99: invokestatic 33	com/tencent/gmtrace/GMTrace:o	(JI)V
        //   102: return
        //   103: iconst_0
        //   104: istore_2
        //   105: goto -60 -> 45
        //   108: aload_0
        //   109: getfield 16	com/tencent/mm/app/e$3:esl	Lcom/tencent/mm/app/e;
        //   112: getfield 44	com/tencent/mm/app/e:esh	Ljava/util/concurrent/locks/ReentrantLock;
        //   115: invokevirtual 83	java/util/concurrent/locks/ReentrantLock:unlock	()V
        //   118: ldc 61
        //   120: ldc 85
        //   122: iconst_1
        //   123: anewarray 4	java/lang/Object
        //   126: dup
        //   127: iconst_0
        //   128: aload_0
        //   129: getfield 30	com/tencent/mm/app/e$3:eso	I
        //   132: invokestatic 90	java/lang/Integer:valueOf	(I)Ljava/lang/Integer;
        //   135: aastore
        //   136: invokestatic 96	java/lang/String:format	(Ljava/lang/String;[Ljava/lang/Object;)Ljava/lang/String;
        //   139: invokestatic 99	com/tencent/mm/sdk/platformtools/w:e	(Ljava/lang/String;Ljava/lang/String;)V
        //   142: aload_0
        //   143: getfield 30	com/tencent/mm/app/e$3:eso	I
        //   146: iconst_1
        //   147: if_icmpne +42 -> 189
        //   150: ldc 101
        //   152: invokestatic 105	com/tencent/mm/app/e:bz	(Ljava/lang/String;)I
        //   155: istore_1
        //   156: iload_1
        //   157: iconst_m1
        //   158: if_icmpeq +154 -> 312
        //   161: ldc 61
        //   163: ldc 107
        //   165: iconst_1
        //   166: anewarray 4	java/lang/Object
        //   169: dup
        //   170: iconst_0
        //   171: iload_1
        //   172: invokestatic 90	java/lang/Integer:valueOf	(I)Ljava/lang/Integer;
        //   175: aastore
        //   176: invokestatic 96	java/lang/String:format	(Ljava/lang/String;[Ljava/lang/Object;)Ljava/lang/String;
        //   179: invokestatic 109	com/tencent/mm/sdk/platformtools/w:i	(Ljava/lang/String;Ljava/lang/String;)V
        //   182: invokestatic 112	com/tencent/mm/sdk/platformtools/w:bPM	()V
        //   185: iload_1
        //   186: invokestatic 118	android/os/Process:killProcess	(I)V
        //   189: invokestatic 124	com/tencent/mm/sdk/platformtools/ab:getContext	()Landroid/content/Context;
        //   192: astore_3
        //   193: new 126	android/content/Intent
        //   196: dup
        //   197: aload_3
        //   198: ldc -128
        //   200: invokespecial 131	android/content/Intent:<init>	(Landroid/content/Context;Ljava/lang/Class;)V
        //   203: astore 4
        //   205: ldc 61
        //   207: ldc -123
        //   209: invokestatic 109	com/tencent/mm/sdk/platformtools/w:i	(Ljava/lang/String;Ljava/lang/String;)V
        //   212: aload_3
        //   213: aload_0
        //   214: getfield 16	com/tencent/mm/app/e$3:esl	Lcom/tencent/mm/app/e;
        //   217: invokevirtual 139	android/content/Context:unbindService	(Landroid/content/ServiceConnection;)V
        //   220: aload_3
        //   221: aload 4
        //   223: invokevirtual 143	android/content/Context:stopService	(Landroid/content/Intent;)Z
        //   226: pop
        //   227: aload_3
        //   228: aload 4
        //   230: aload_0
        //   231: getfield 16	com/tencent/mm/app/e$3:esl	Lcom/tencent/mm/app/e;
        //   234: iconst_1
        //   235: invokevirtual 147	android/content/Context:bindService	(Landroid/content/Intent;Landroid/content/ServiceConnection;I)Z
        //   238: pop
        //   239: aload_3
        //   240: aload 4
        //   242: invokevirtual 151	android/content/Context:startService	(Landroid/content/Intent;)Landroid/content/ComponentName;
        //   245: pop
        //   246: aload_0
        //   247: getfield 30	com/tencent/mm/app/e$3:eso	I
        //   250: iconst_1
        //   251: if_icmpne +133 -> 384
        //   254: aload_0
        //   255: iconst_0
        //   256: putfield 30	com/tencent/mm/app/e$3:eso	I
        //   259: aload_0
        //   260: ldc2_w 152
        //   263: invokestatic 158	com/tencent/mm/sdk/platformtools/af:i	(Ljava/lang/Runnable;J)V
        //   266: ldc 61
        //   268: ldc -96
        //   270: iconst_1
        //   271: anewarray 4	java/lang/Object
        //   274: dup
        //   275: iconst_0
        //   276: aload_0
        //   277: getfield 30	com/tencent/mm/app/e$3:eso	I
        //   280: invokestatic 90	java/lang/Integer:valueOf	(I)Ljava/lang/Integer;
        //   283: aastore
        //   284: invokestatic 96	java/lang/String:format	(Ljava/lang/String;[Ljava/lang/Object;)Ljava/lang/String;
        //   287: invokestatic 109	com/tencent/mm/sdk/platformtools/w:i	(Ljava/lang/String;Ljava/lang/String;)V
        //   290: ldc2_w 38
        //   293: ldc 40
        //   295: invokestatic 33	com/tencent/gmtrace/GMTrace:o	(JI)V
        //   298: return
        //   299: astore_3
        //   300: aload_0
        //   301: getfield 16	com/tencent/mm/app/e$3:esl	Lcom/tencent/mm/app/e;
        //   304: getfield 44	com/tencent/mm/app/e:esh	Ljava/util/concurrent/locks/ReentrantLock;
        //   307: invokevirtual 83	java/util/concurrent/locks/ReentrantLock:unlock	()V
        //   310: aload_3
        //   311: athrow
        //   312: ldc 61
        //   314: ldc -94
        //   316: invokestatic 109	com/tencent/mm/sdk/platformtools/w:i	(Ljava/lang/String;Ljava/lang/String;)V
        //   319: goto -130 -> 189
        //   322: astore 5
        //   324: aload_3
        //   325: aload 4
        //   327: invokevirtual 143	android/content/Context:stopService	(Landroid/content/Intent;)Z
        //   330: pop
        //   331: aload_3
        //   332: aload 4
        //   334: aload_0
        //   335: getfield 16	com/tencent/mm/app/e$3:esl	Lcom/tencent/mm/app/e;
        //   338: iconst_1
        //   339: invokevirtual 147	android/content/Context:bindService	(Landroid/content/Intent;Landroid/content/ServiceConnection;I)Z
        //   342: pop
        //   343: aload_3
        //   344: aload 4
        //   346: invokevirtual 151	android/content/Context:startService	(Landroid/content/Intent;)Landroid/content/ComponentName;
        //   349: pop
        //   350: goto -104 -> 246
        //   353: astore 5
        //   355: aload_3
        //   356: aload 4
        //   358: invokevirtual 143	android/content/Context:stopService	(Landroid/content/Intent;)Z
        //   361: pop
        //   362: aload_3
        //   363: aload 4
        //   365: aload_0
        //   366: getfield 16	com/tencent/mm/app/e$3:esl	Lcom/tencent/mm/app/e;
        //   369: iconst_1
        //   370: invokevirtual 147	android/content/Context:bindService	(Landroid/content/Intent;Landroid/content/ServiceConnection;I)Z
        //   373: pop
        //   374: aload_3
        //   375: aload 4
        //   377: invokevirtual 151	android/content/Context:startService	(Landroid/content/Intent;)Landroid/content/ComponentName;
        //   380: pop
        //   381: aload 5
        //   383: athrow
        //   384: aload_0
        //   385: aload_0
        //   386: getfield 30	com/tencent/mm/app/e$3:eso	I
        //   389: iconst_1
        //   390: iadd
        //   391: putfield 30	com/tencent/mm/app/e$3:eso	I
        //   394: goto -135 -> 259
        // Local variable table:
        //   start	length	slot	name	signature
        //   0	397	0	this	3
        //   155	31	1	i	int
        //   44	61	2	bool	boolean
        //   192	48	3	localContext	android.content.Context
        //   299	76	3	localObject1	Object
        //   203	173	4	localIntent	android.content.Intent
        //   322	1	5	localException	Exception
        //   353	29	5	localObject2	Object
        // Exception table:
        //   from	to	target	type
        //   8	43	299	finally
        //   45	73	299	finally
        //   77	84	299	finally
        //   205	220	322	java/lang/Exception
        //   205	220	353	finally
      }
    };
    GMTrace.o(13713293705216L, 102172);
  }
  
  /* Error */
  public static int bz(String paramString)
  {
    // Byte code:
    //   0: iconst_m1
    //   1: istore_1
    //   2: ldc2_w 69
    //   5: ldc 71
    //   7: invokestatic 36	com/tencent/gmtrace/GMTrace:i	(JI)V
    //   10: new 73	java/io/File
    //   13: dup
    //   14: ldc 75
    //   16: invokespecial 78	java/io/File:<init>	(Ljava/lang/String;)V
    //   19: invokevirtual 82	java/io/File:listFiles	()[Ljava/io/File;
    //   22: astore 9
    //   24: aload 9
    //   26: arraylength
    //   27: istore 4
    //   29: iconst_0
    //   30: istore_2
    //   31: aconst_null
    //   32: astore 7
    //   34: iload_1
    //   35: istore_3
    //   36: iload_2
    //   37: iload 4
    //   39: if_icmpge +196 -> 235
    //   42: aload 9
    //   44: iload_2
    //   45: aaload
    //   46: astore 8
    //   48: aload 8
    //   50: invokevirtual 86	java/io/File:getName	()Ljava/lang/String;
    //   53: iconst_m1
    //   54: invokestatic 92	com/tencent/mm/sdk/platformtools/bg:getInt	(Ljava/lang/String;I)I
    //   57: istore_3
    //   58: iload_3
    //   59: istore_1
    //   60: aload 7
    //   62: astore 6
    //   64: new 73	java/io/File
    //   67: dup
    //   68: aload 8
    //   70: ldc 94
    //   72: invokespecial 97	java/io/File:<init>	(Ljava/io/File;Ljava/lang/String;)V
    //   75: astore 8
    //   77: aload 7
    //   79: astore 6
    //   81: aload 8
    //   83: invokevirtual 101	java/io/File:canRead	()Z
    //   86: istore 5
    //   88: iload 5
    //   90: ifne +61 -> 151
    //   93: iload_1
    //   94: istore_3
    //   95: aload 7
    //   97: astore 6
    //   99: aload 7
    //   101: ifnull +13 -> 114
    //   104: aload 7
    //   106: invokevirtual 106	java/io/BufferedReader:close	()V
    //   109: aconst_null
    //   110: astore 6
    //   112: iload_1
    //   113: istore_3
    //   114: iload_2
    //   115: iconst_1
    //   116: iadd
    //   117: istore_2
    //   118: iload_3
    //   119: istore_1
    //   120: aload 6
    //   122: astore 7
    //   124: goto -90 -> 34
    //   127: astore 6
    //   129: ldc 108
    //   131: aload 6
    //   133: ldc 110
    //   135: iconst_0
    //   136: anewarray 4	java/lang/Object
    //   139: invokestatic 116	com/tencent/mm/sdk/platformtools/w:printErrStackTrace	(Ljava/lang/String;Ljava/lang/Throwable;Ljava/lang/String;[Ljava/lang/Object;)V
    //   142: iload_1
    //   143: istore_3
    //   144: aload 7
    //   146: astore 6
    //   148: goto -34 -> 114
    //   151: aload 7
    //   153: astore 6
    //   155: new 103	java/io/BufferedReader
    //   158: dup
    //   159: new 118	java/io/FileReader
    //   162: dup
    //   163: aload 8
    //   165: invokespecial 121	java/io/FileReader:<init>	(Ljava/io/File;)V
    //   168: invokespecial 124	java/io/BufferedReader:<init>	(Ljava/io/Reader;)V
    //   171: astore 8
    //   173: aload 8
    //   175: invokevirtual 127	java/io/BufferedReader:readLine	()Ljava/lang/String;
    //   178: astore 6
    //   180: aload 6
    //   182: ifnull +123 -> 305
    //   185: aload 6
    //   187: aload_0
    //   188: invokevirtual 133	java/lang/String:startsWith	(Ljava/lang/String;)Z
    //   191: ifeq +114 -> 305
    //   194: aload 6
    //   196: invokevirtual 137	java/lang/String:length	()I
    //   199: aload_0
    //   200: invokevirtual 137	java/lang/String:length	()I
    //   203: if_icmpne +42 -> 245
    //   206: ldc 108
    //   208: ldc -117
    //   210: iconst_2
    //   211: anewarray 4	java/lang/Object
    //   214: dup
    //   215: iconst_0
    //   216: aload_0
    //   217: aastore
    //   218: dup
    //   219: iconst_1
    //   220: iload_1
    //   221: invokestatic 145	java/lang/Integer:valueOf	(I)Ljava/lang/Integer;
    //   224: aastore
    //   225: invokestatic 148	com/tencent/mm/sdk/platformtools/w:i	(Ljava/lang/String;Ljava/lang/String;[Ljava/lang/Object;)V
    //   228: aload 8
    //   230: invokevirtual 106	java/io/BufferedReader:close	()V
    //   233: iload_1
    //   234: istore_3
    //   235: ldc2_w 69
    //   238: ldc 71
    //   240: invokestatic 46	com/tencent/gmtrace/GMTrace:o	(JI)V
    //   243: iload_3
    //   244: ireturn
    //   245: aload 6
    //   247: aload_0
    //   248: invokevirtual 137	java/lang/String:length	()I
    //   251: invokevirtual 152	java/lang/String:charAt	(I)C
    //   254: istore_3
    //   255: iload_3
    //   256: bipush 32
    //   258: if_icmple +9 -> 267
    //   261: iload_3
    //   262: bipush 127
    //   264: if_icmplt +41 -> 305
    //   267: ldc 108
    //   269: ldc -117
    //   271: iconst_2
    //   272: anewarray 4	java/lang/Object
    //   275: dup
    //   276: iconst_0
    //   277: aload_0
    //   278: aastore
    //   279: dup
    //   280: iconst_1
    //   281: iload_1
    //   282: invokestatic 145	java/lang/Integer:valueOf	(I)Ljava/lang/Integer;
    //   285: aastore
    //   286: invokestatic 148	com/tencent/mm/sdk/platformtools/w:i	(Ljava/lang/String;Ljava/lang/String;[Ljava/lang/Object;)V
    //   289: aload 8
    //   291: invokevirtual 106	java/io/BufferedReader:close	()V
    //   294: iload_1
    //   295: istore_3
    //   296: goto -61 -> 235
    //   299: astore_0
    //   300: iload_1
    //   301: istore_3
    //   302: goto -67 -> 235
    //   305: aload 8
    //   307: invokevirtual 106	java/io/BufferedReader:close	()V
    //   310: aconst_null
    //   311: astore 6
    //   313: iload_1
    //   314: istore_3
    //   315: goto -201 -> 114
    //   318: astore 6
    //   320: aload 8
    //   322: astore 7
    //   324: aload 6
    //   326: astore 8
    //   328: aload 7
    //   330: astore 6
    //   332: ldc 108
    //   334: aload 8
    //   336: ldc -102
    //   338: iconst_0
    //   339: anewarray 4	java/lang/Object
    //   342: invokestatic 116	com/tencent/mm/sdk/platformtools/w:printErrStackTrace	(Ljava/lang/String;Ljava/lang/Throwable;Ljava/lang/String;[Ljava/lang/Object;)V
    //   345: aload 7
    //   347: astore 6
    //   349: invokestatic 157	com/tencent/mm/sdk/platformtools/w:bPM	()V
    //   352: iload_1
    //   353: istore_3
    //   354: aload 7
    //   356: astore 6
    //   358: aload 7
    //   360: ifnull -246 -> 114
    //   363: aload 7
    //   365: invokevirtual 106	java/io/BufferedReader:close	()V
    //   368: aconst_null
    //   369: astore 6
    //   371: iload_1
    //   372: istore_3
    //   373: goto -259 -> 114
    //   376: astore_0
    //   377: aload 8
    //   379: ifnull +8 -> 387
    //   382: aload 8
    //   384: invokevirtual 106	java/io/BufferedReader:close	()V
    //   387: aload_0
    //   388: athrow
    //   389: astore 6
    //   391: goto -282 -> 109
    //   394: astore_0
    //   395: iload_1
    //   396: istore_3
    //   397: goto -162 -> 235
    //   400: astore 6
    //   402: goto -92 -> 310
    //   405: astore 6
    //   407: goto -39 -> 368
    //   410: astore 6
    //   412: goto -25 -> 387
    //   415: astore_0
    //   416: aload 6
    //   418: astore 8
    //   420: goto -43 -> 377
    //   423: astore 8
    //   425: goto -97 -> 328
    // Local variable table:
    //   start	length	slot	name	signature
    //   0	428	0	paramString	String
    //   1	395	1	i	int
    //   30	88	2	j	int
    //   35	362	3	k	int
    //   27	13	4	m	int
    //   86	3	5	bool	boolean
    //   62	59	6	localObject1	Object
    //   127	5	6	localThrowable1	Throwable
    //   146	166	6	localObject2	Object
    //   318	7	6	localThrowable2	Throwable
    //   330	40	6	localObject3	Object
    //   389	1	6	localThrowable3	Throwable
    //   400	1	6	localThrowable4	Throwable
    //   405	1	6	localThrowable5	Throwable
    //   410	7	6	localThrowable6	Throwable
    //   32	332	7	localObject4	Object
    //   46	373	8	localObject5	Object
    //   423	1	8	localThrowable7	Throwable
    //   22	21	9	arrayOfFile	java.io.File[]
    // Exception table:
    //   from	to	target	type
    //   48	58	127	java/lang/Throwable
    //   289	294	299	java/lang/Throwable
    //   173	180	318	java/lang/Throwable
    //   185	228	318	java/lang/Throwable
    //   245	255	318	java/lang/Throwable
    //   267	289	318	java/lang/Throwable
    //   173	180	376	finally
    //   185	228	376	finally
    //   245	255	376	finally
    //   267	289	376	finally
    //   104	109	389	java/lang/Throwable
    //   228	233	394	java/lang/Throwable
    //   305	310	400	java/lang/Throwable
    //   363	368	405	java/lang/Throwable
    //   382	387	410	java/lang/Throwable
    //   64	77	415	finally
    //   81	88	415	finally
    //   155	173	415	finally
    //   332	345	415	finally
    //   349	352	415	finally
    //   64	77	423	java/lang/Throwable
    //   81	88	423	java/lang/Throwable
    //   155	173	423	java/lang/Throwable
  }
  
  /* Error */
  public final void ah(android.content.Context arg1)
  {
    // Byte code:
    //   0: iconst_0
    //   1: istore_3
    //   2: ldc2_w 160
    //   5: ldc -94
    //   7: invokestatic 36	com/tencent/gmtrace/GMTrace:i	(JI)V
    //   10: aload_0
    //   11: getfield 55	com/tencent/mm/app/e:esh	Ljava/util/concurrent/locks/ReentrantLock;
    //   14: invokevirtual 164	java/util/concurrent/locks/ReentrantLock:lock	()V
    //   17: iload_3
    //   18: istore_2
    //   19: aload_0
    //   20: getfield 59	com/tencent/mm/app/e:esj	Landroid/os/IBinder;
    //   23: ifnull +19 -> 42
    //   26: iload_3
    //   27: istore_2
    //   28: aload_0
    //   29: getfield 59	com/tencent/mm/app/e:esj	Landroid/os/IBinder;
    //   32: invokeinterface 169 1 0
    //   37: ifeq +5 -> 42
    //   40: iconst_1
    //   41: istore_2
    //   42: ldc 108
    //   44: ldc -85
    //   46: iconst_2
    //   47: anewarray 4	java/lang/Object
    //   50: dup
    //   51: iconst_0
    //   52: aload_0
    //   53: getfield 57	com/tencent/mm/app/e:esi	Z
    //   56: invokestatic 176	java/lang/Boolean:valueOf	(Z)Ljava/lang/Boolean;
    //   59: aastore
    //   60: dup
    //   61: iconst_1
    //   62: iload_2
    //   63: invokestatic 176	java/lang/Boolean:valueOf	(Z)Ljava/lang/Boolean;
    //   66: aastore
    //   67: invokestatic 148	com/tencent/mm/sdk/platformtools/w:i	(Ljava/lang/String;Ljava/lang/String;[Ljava/lang/Object;)V
    //   70: aload_0
    //   71: getfield 57	com/tencent/mm/app/e:esi	Z
    //   74: ifne +7 -> 81
    //   77: iload_2
    //   78: ifeq +47 -> 125
    //   81: ldc 108
    //   83: ldc -78
    //   85: iconst_2
    //   86: anewarray 4	java/lang/Object
    //   89: dup
    //   90: iconst_0
    //   91: aload_0
    //   92: getfield 57	com/tencent/mm/app/e:esi	Z
    //   95: invokestatic 176	java/lang/Boolean:valueOf	(Z)Ljava/lang/Boolean;
    //   98: aastore
    //   99: dup
    //   100: iconst_1
    //   101: iload_2
    //   102: invokestatic 176	java/lang/Boolean:valueOf	(Z)Ljava/lang/Boolean;
    //   105: aastore
    //   106: invokestatic 181	com/tencent/mm/sdk/platformtools/w:w	(Ljava/lang/String;Ljava/lang/String;[Ljava/lang/Object;)V
    //   109: aload_0
    //   110: getfield 55	com/tencent/mm/app/e:esh	Ljava/util/concurrent/locks/ReentrantLock;
    //   113: invokevirtual 184	java/util/concurrent/locks/ReentrantLock:unlock	()V
    //   116: ldc2_w 160
    //   119: ldc -94
    //   121: invokestatic 46	com/tencent/gmtrace/GMTrace:o	(JI)V
    //   124: return
    //   125: aload_0
    //   126: getfield 55	com/tencent/mm/app/e:esh	Ljava/util/concurrent/locks/ReentrantLock;
    //   129: invokevirtual 184	java/util/concurrent/locks/ReentrantLock:unlock	()V
    //   132: aload_1
    //   133: ldc -70
    //   135: invokestatic 192	com/tencent/mm/booter/b:r	(Landroid/content/Context;Ljava/lang/String;)Z
    //   138: ifne +29 -> 167
    //   141: ldc 108
    //   143: ldc -62
    //   145: invokestatic 197	com/tencent/mm/sdk/platformtools/w:i	(Ljava/lang/String;Ljava/lang/String;)V
    //   148: ldc2_w 160
    //   151: ldc -94
    //   153: invokestatic 46	com/tencent/gmtrace/GMTrace:o	(JI)V
    //   156: return
    //   157: astore_1
    //   158: aload_0
    //   159: getfield 55	com/tencent/mm/app/e:esh	Ljava/util/concurrent/locks/ReentrantLock;
    //   162: invokevirtual 184	java/util/concurrent/locks/ReentrantLock:unlock	()V
    //   165: aload_1
    //   166: athrow
    //   167: new 199	android/content/Intent
    //   170: dup
    //   171: aload_1
    //   172: ldc -55
    //   174: invokespecial 204	android/content/Intent:<init>	(Landroid/content/Context;Ljava/lang/Class;)V
    //   177: astore 4
    //   179: ldc 108
    //   181: ldc -50
    //   183: invokestatic 197	com/tencent/mm/sdk/platformtools/w:i	(Ljava/lang/String;Ljava/lang/String;)V
    //   186: aload_1
    //   187: aload 4
    //   189: aload_0
    //   190: iconst_1
    //   191: invokevirtual 212	android/content/Context:bindService	(Landroid/content/Intent;Landroid/content/ServiceConnection;I)Z
    //   194: ifne +19 -> 213
    //   197: ldc 108
    //   199: ldc -42
    //   201: invokestatic 217	com/tencent/mm/sdk/platformtools/w:e	(Ljava/lang/String;Ljava/lang/String;)V
    //   204: ldc2_w 160
    //   207: ldc -94
    //   209: invokestatic 46	com/tencent/gmtrace/GMTrace:o	(JI)V
    //   212: return
    //   213: aload_0
    //   214: getfield 55	com/tencent/mm/app/e:esh	Ljava/util/concurrent/locks/ReentrantLock;
    //   217: invokevirtual 164	java/util/concurrent/locks/ReentrantLock:lock	()V
    //   220: aload_0
    //   221: iconst_1
    //   222: putfield 57	com/tencent/mm/app/e:esi	Z
    //   225: aload_0
    //   226: getfield 55	com/tencent/mm/app/e:esh	Ljava/util/concurrent/locks/ReentrantLock;
    //   229: invokevirtual 184	java/util/concurrent/locks/ReentrantLock:unlock	()V
    //   232: getstatic 43	com/tencent/mm/app/e:lock	Ljava/lang/Object;
    //   235: astore_1
    //   236: aload_1
    //   237: monitorenter
    //   238: getstatic 38	com/tencent/mm/app/e:esg	Z
    //   241: ifne +24 -> 265
    //   244: iconst_1
    //   245: putstatic 38	com/tencent/mm/app/e:esg	Z
    //   248: ldc 108
    //   250: ldc -37
    //   252: invokestatic 197	com/tencent/mm/sdk/platformtools/w:i	(Ljava/lang/String;Ljava/lang/String;)V
    //   255: aload_0
    //   256: getfield 64	com/tencent/mm/app/e:esk	Ljava/lang/Runnable;
    //   259: ldc2_w 220
    //   262: invokestatic 226	com/tencent/mm/sdk/platformtools/af:i	(Ljava/lang/Runnable;J)V
    //   265: aload_1
    //   266: monitorexit
    //   267: ldc2_w 160
    //   270: ldc -94
    //   272: invokestatic 46	com/tencent/gmtrace/GMTrace:o	(JI)V
    //   275: return
    //   276: astore_1
    //   277: aload_0
    //   278: getfield 55	com/tencent/mm/app/e:esh	Ljava/util/concurrent/locks/ReentrantLock;
    //   281: invokevirtual 184	java/util/concurrent/locks/ReentrantLock:unlock	()V
    //   284: aload_1
    //   285: athrow
    //   286: astore 4
    //   288: aload_1
    //   289: monitorexit
    //   290: aload 4
    //   292: athrow
    // Local variable table:
    //   start	length	slot	name	signature
    //   0	293	0	this	e
    //   18	84	2	bool1	boolean
    //   1	26	3	bool2	boolean
    //   177	11	4	localIntent	android.content.Intent
    //   286	5	4	localObject	Object
    // Exception table:
    //   from	to	target	type
    //   10	17	157	finally
    //   19	26	157	finally
    //   28	40	157	finally
    //   42	77	157	finally
    //   81	109	157	finally
    //   213	225	276	finally
    //   238	265	286	finally
    //   265	267	286	finally
    //   288	290	286	finally
  }
  
  /* Error */
  public final void onServiceConnected(ComponentName paramComponentName, IBinder paramIBinder)
  {
    // Byte code:
    //   0: ldc2_w 233
    //   3: ldc -21
    //   5: invokestatic 36	com/tencent/gmtrace/GMTrace:i	(JI)V
    //   8: ldc 108
    //   10: ldc -19
    //   12: invokestatic 239	com/tencent/mm/sdk/platformtools/w:w	(Ljava/lang/String;Ljava/lang/String;)V
    //   15: getstatic 43	com/tencent/mm/app/e:lock	Ljava/lang/Object;
    //   18: astore_1
    //   19: aload_1
    //   20: monitorenter
    //   21: ldc 108
    //   23: ldc -15
    //   25: invokestatic 197	com/tencent/mm/sdk/platformtools/w:i	(Ljava/lang/String;Ljava/lang/String;)V
    //   28: aload_0
    //   29: getfield 64	com/tencent/mm/app/e:esk	Ljava/lang/Runnable;
    //   32: invokestatic 245	com/tencent/mm/sdk/platformtools/af:F	(Ljava/lang/Runnable;)V
    //   35: iconst_0
    //   36: putstatic 38	com/tencent/mm/app/e:esg	Z
    //   39: aload_1
    //   40: monitorexit
    //   41: aload_2
    //   42: ifnonnull +16 -> 58
    //   45: ldc -9
    //   47: iconst_0
    //   48: invokestatic 253	junit/framework/Assert:assertTrue	(Ljava/lang/String;Z)V
    //   51: ldc -9
    //   53: ldc -1
    //   55: invokestatic 259	com/tencent/mm/sdk/a/b:r	(Ljava/lang/String;Ljava/lang/String;)V
    //   58: aload_0
    //   59: getfield 55	com/tencent/mm/app/e:esh	Ljava/util/concurrent/locks/ReentrantLock;
    //   62: invokevirtual 164	java/util/concurrent/locks/ReentrantLock:lock	()V
    //   65: aload_0
    //   66: iconst_0
    //   67: putfield 57	com/tencent/mm/app/e:esi	Z
    //   70: aload_0
    //   71: aload_2
    //   72: putfield 59	com/tencent/mm/app/e:esj	Landroid/os/IBinder;
    //   75: aload_0
    //   76: getfield 55	com/tencent/mm/app/e:esh	Ljava/util/concurrent/locks/ReentrantLock;
    //   79: invokevirtual 184	java/util/concurrent/locks/ReentrantLock:unlock	()V
    //   82: new 261	com/tencent/mm/ad/p
    //   85: dup
    //   86: aload_2
    //   87: invokestatic 267	com/tencent/mm/network/f$a:B	(Landroid/os/IBinder;)Lcom/tencent/mm/network/f;
    //   90: invokespecial 270	com/tencent/mm/ad/p:<init>	(Lcom/tencent/mm/network/f;)V
    //   93: astore_1
    //   94: new 8	com/tencent/mm/app/e$1
    //   97: dup
    //   98: aload_0
    //   99: invokespecial 271	com/tencent/mm/app/e$1:<init>	(Lcom/tencent/mm/app/e;)V
    //   102: astore_2
    //   103: aload_1
    //   104: getfield 275	com/tencent/mm/ad/p:guI	Lcom/tencent/mm/network/f;
    //   107: aload_2
    //   108: invokeinterface 281 2 0
    //   113: new 10	com/tencent/mm/app/e$2
    //   116: dup
    //   117: aload_0
    //   118: invokespecial 282	com/tencent/mm/app/e$2:<init>	(Lcom/tencent/mm/app/e;)V
    //   121: astore_2
    //   122: aload_1
    //   123: getfield 275	com/tencent/mm/ad/p:guI	Lcom/tencent/mm/network/f;
    //   126: aload_2
    //   127: invokeinterface 285 2 0
    //   132: invokestatic 291	com/tencent/mm/kernel/h:xz	()Lcom/tencent/mm/kernel/h;
    //   135: pop
    //   136: invokestatic 295	com/tencent/mm/kernel/h:xx	()Lcom/tencent/mm/kernel/b;
    //   139: astore_2
    //   140: ldc_w 297
    //   143: new 299	java/lang/StringBuilder
    //   146: dup
    //   147: ldc_w 301
    //   150: invokespecial 302	java/lang/StringBuilder:<init>	(Ljava/lang/String;)V
    //   153: aload_1
    //   154: invokevirtual 306	java/lang/StringBuilder:append	(Ljava/lang/Object;)Ljava/lang/StringBuilder;
    //   157: invokevirtual 309	java/lang/StringBuilder:toString	()Ljava/lang/String;
    //   160: invokestatic 239	com/tencent/mm/sdk/platformtools/w:w	(Ljava/lang/String;Ljava/lang/String;)V
    //   163: aload_2
    //   164: getfield 315	com/tencent/mm/kernel/b:fYq	Lcom/tencent/mm/kernel/b$a;
    //   167: aload_1
    //   168: invokevirtual 321	com/tencent/mm/kernel/b$a:b	(Lcom/tencent/mm/network/e;)V
    //   171: aload_1
    //   172: new 323	com/tencent/mm/kernel/b$4
    //   175: dup
    //   176: aload_2
    //   177: invokespecial 326	com/tencent/mm/kernel/b$4:<init>	(Lcom/tencent/mm/kernel/b;)V
    //   180: invokeinterface 331 2 0
    //   185: aload_1
    //   186: invokeinterface 335 1 0
    //   191: astore 7
    //   193: aload 7
    //   195: ifnull +15 -> 210
    //   198: aload 7
    //   200: aload_2
    //   201: getfield 339	com/tencent/mm/kernel/b:fYt	Lcom/tencent/mm/network/n;
    //   204: invokeinterface 345 2 0
    //   209: pop
    //   210: aload_1
    //   211: new 347	com/tencent/mm/kernel/b$5
    //   214: dup
    //   215: aload_2
    //   216: invokespecial 348	com/tencent/mm/kernel/b$5:<init>	(Lcom/tencent/mm/kernel/b;)V
    //   219: invokeinterface 351 2 0
    //   224: aload_1
    //   225: invokeinterface 355 1 0
    //   230: astore 7
    //   232: aload 7
    //   234: ifnonnull +278 -> 512
    //   237: ldc_w 297
    //   240: ldc_w 357
    //   243: invokestatic 360	com/tencent/mm/sdk/platformtools/w:f	(Ljava/lang/String;Ljava/lang/String;)V
    //   246: aload_2
    //   247: getfield 364	com/tencent/mm/kernel/b:fYr	Lcom/tencent/mm/ad/n;
    //   250: invokevirtual 369	com/tencent/mm/ad/n:reset	()V
    //   253: aload_2
    //   254: getfield 364	com/tencent/mm/kernel/b:fYr	Lcom/tencent/mm/ad/n;
    //   257: invokevirtual 372	com/tencent/mm/ad/n:DQ	()V
    //   260: invokestatic 377	com/tencent/mm/y/a:yB	()Z
    //   263: ifeq +94 -> 357
    //   266: invokestatic 291	com/tencent/mm/kernel/h:xz	()Lcom/tencent/mm/kernel/h;
    //   269: pop
    //   270: invokestatic 381	com/tencent/mm/kernel/h:xw	()Lcom/tencent/mm/kernel/a;
    //   273: getfield 387	com/tencent/mm/kernel/a:fYa	Lcom/tencent/mm/y/a;
    //   276: ifnull +1356 -> 1632
    //   279: invokestatic 291	com/tencent/mm/kernel/h:xz	()Lcom/tencent/mm/kernel/h;
    //   282: pop
    //   283: invokestatic 295	com/tencent/mm/kernel/h:xx	()Lcom/tencent/mm/kernel/b;
    //   286: getfield 364	com/tencent/mm/kernel/b:fYr	Lcom/tencent/mm/ad/n;
    //   289: getfield 391	com/tencent/mm/ad/n:gus	Lcom/tencent/mm/network/e;
    //   292: ifnull +1340 -> 1632
    //   295: invokestatic 291	com/tencent/mm/kernel/h:xz	()Lcom/tencent/mm/kernel/h;
    //   298: pop
    //   299: invokestatic 381	com/tencent/mm/kernel/h:xw	()Lcom/tencent/mm/kernel/a;
    //   302: getfield 387	com/tencent/mm/kernel/a:fYa	Lcom/tencent/mm/y/a;
    //   305: astore_1
    //   306: invokestatic 291	com/tencent/mm/kernel/h:xz	()Lcom/tencent/mm/kernel/h;
    //   309: pop
    //   310: invokestatic 295	com/tencent/mm/kernel/h:xx	()Lcom/tencent/mm/kernel/b;
    //   313: getfield 364	com/tencent/mm/kernel/b:fYr	Lcom/tencent/mm/ad/n;
    //   316: getfield 391	com/tencent/mm/ad/n:gus	Lcom/tencent/mm/network/e;
    //   319: invokeinterface 355 1 0
    //   324: astore_2
    //   325: invokestatic 395	com/tencent/mm/sdk/platformtools/bg:Pv	()J
    //   328: lstore 4
    //   330: aload_2
    //   331: ifnonnull +980 -> 1311
    //   334: ldc_w 397
    //   337: ldc_w 399
    //   340: invokestatic 217	com/tencent/mm/sdk/platformtools/w:e	(Ljava/lang/String;Ljava/lang/String;)V
    //   343: getstatic 405	com/tencent/mm/plugin/report/d:oqe	Lcom/tencent/mm/plugin/report/d;
    //   346: ldc2_w 406
    //   349: ldc2_w 408
    //   352: lconst_1
    //   353: iconst_0
    //   354: invokevirtual 412	com/tencent/mm/plugin/report/d:a	(JJJZ)V
    //   357: invokestatic 381	com/tencent/mm/kernel/h:xw	()Lcom/tencent/mm/kernel/a;
    //   360: invokevirtual 415	com/tencent/mm/kernel/a:wL	()Z
    //   363: ifeq +51 -> 414
    //   366: invokestatic 291	com/tencent/mm/kernel/h:xz	()Lcom/tencent/mm/kernel/h;
    //   369: pop
    //   370: invokestatic 295	com/tencent/mm/kernel/h:xx	()Lcom/tencent/mm/kernel/b;
    //   373: getfield 364	com/tencent/mm/kernel/b:fYr	Lcom/tencent/mm/ad/n;
    //   376: ifnull +38 -> 414
    //   379: invokestatic 291	com/tencent/mm/kernel/h:xz	()Lcom/tencent/mm/kernel/h;
    //   382: pop
    //   383: invokestatic 295	com/tencent/mm/kernel/h:xx	()Lcom/tencent/mm/kernel/b;
    //   386: getfield 364	com/tencent/mm/kernel/b:fYr	Lcom/tencent/mm/ad/n;
    //   389: getfield 391	com/tencent/mm/ad/n:gus	Lcom/tencent/mm/network/e;
    //   392: ifnull +22 -> 414
    //   395: invokestatic 291	com/tencent/mm/kernel/h:xz	()Lcom/tencent/mm/kernel/h;
    //   398: pop
    //   399: invokestatic 295	com/tencent/mm/kernel/h:xx	()Lcom/tencent/mm/kernel/b;
    //   402: getfield 364	com/tencent/mm/kernel/b:fYr	Lcom/tencent/mm/ad/n;
    //   405: getfield 391	com/tencent/mm/ad/n:gus	Lcom/tencent/mm/network/e;
    //   408: iconst_1
    //   409: invokeinterface 419 2 0
    //   414: ldc2_w 233
    //   417: ldc -21
    //   419: invokestatic 46	com/tencent/gmtrace/GMTrace:o	(JI)V
    //   422: return
    //   423: astore_2
    //   424: aload_1
    //   425: monitorexit
    //   426: aload_2
    //   427: athrow
    //   428: astore_1
    //   429: aload_0
    //   430: getfield 55	com/tencent/mm/app/e:esh	Ljava/util/concurrent/locks/ReentrantLock;
    //   433: invokevirtual 184	java/util/concurrent/locks/ReentrantLock:unlock	()V
    //   436: aload_1
    //   437: athrow
    //   438: astore_2
    //   439: ldc_w 421
    //   442: ldc_w 423
    //   445: iconst_1
    //   446: anewarray 4	java/lang/Object
    //   449: dup
    //   450: iconst_0
    //   451: aload_2
    //   452: invokestatic 426	com/tencent/mm/sdk/platformtools/bg:f	(Ljava/lang/Throwable;)Ljava/lang/String;
    //   455: aastore
    //   456: invokestatic 428	com/tencent/mm/sdk/platformtools/w:e	(Ljava/lang/String;Ljava/lang/String;[Ljava/lang/Object;)V
    //   459: goto -346 -> 113
    //   462: astore_2
    //   463: ldc_w 421
    //   466: ldc_w 423
    //   469: iconst_1
    //   470: anewarray 4	java/lang/Object
    //   473: dup
    //   474: iconst_0
    //   475: aload_2
    //   476: invokestatic 426	com/tencent/mm/sdk/platformtools/bg:f	(Ljava/lang/Throwable;)Ljava/lang/String;
    //   479: aastore
    //   480: invokestatic 428	com/tencent/mm/sdk/platformtools/w:e	(Ljava/lang/String;Ljava/lang/String;[Ljava/lang/Object;)V
    //   483: goto -351 -> 132
    //   486: astore 7
    //   488: ldc_w 297
    //   491: ldc_w 423
    //   494: iconst_1
    //   495: anewarray 4	java/lang/Object
    //   498: dup
    //   499: iconst_0
    //   500: aload 7
    //   502: invokestatic 426	com/tencent/mm/sdk/platformtools/bg:f	(Ljava/lang/Throwable;)Ljava/lang/String;
    //   505: aastore
    //   506: invokestatic 428	com/tencent/mm/sdk/platformtools/w:e	(Ljava/lang/String;Ljava/lang/String;[Ljava/lang/Object;)V
    //   509: goto -299 -> 210
    //   512: new 430	com/tencent/mm/kernel/b$6
    //   515: dup
    //   516: aload_2
    //   517: invokespecial 431	com/tencent/mm/kernel/b$6:<init>	(Lcom/tencent/mm/kernel/b;)V
    //   520: invokestatic 434	com/tencent/mm/sdk/a/b:a	(Lcom/tencent/mm/sdk/a/a;)V
    //   523: invokestatic 291	com/tencent/mm/kernel/h:xz	()Lcom/tencent/mm/kernel/h;
    //   526: pop
    //   527: invokestatic 438	com/tencent/mm/kernel/h:xy	()Lcom/tencent/mm/kernel/e;
    //   530: getfield 444	com/tencent/mm/kernel/e:fYL	Lcom/tencent/mm/storage/s;
    //   533: astore 13
    //   535: new 299	java/lang/StringBuilder
    //   538: dup
    //   539: ldc_w 446
    //   542: invokespecial 302	java/lang/StringBuilder:<init>	(Ljava/lang/String;)V
    //   545: invokestatic 450	com/tencent/mm/sdk/platformtools/bg:bQW	()Lcom/tencent/mm/sdk/platformtools/ah;
    //   548: invokevirtual 306	java/lang/StringBuilder:append	(Ljava/lang/Object;)Ljava/lang/StringBuilder;
    //   551: invokevirtual 309	java/lang/StringBuilder:toString	()Ljava/lang/String;
    //   554: astore 8
    //   556: aload 13
    //   558: ifnull +488 -> 1046
    //   561: iconst_1
    //   562: istore 6
    //   564: aload 8
    //   566: iload 6
    //   568: invokestatic 253	junit/framework/Assert:assertTrue	(Ljava/lang/String;Z)V
    //   571: aload 13
    //   573: bipush 47
    //   575: invokevirtual 456	com/tencent/mm/storage/s:Ar	(I)I
    //   578: istore_3
    //   579: aload 13
    //   581: iconst_2
    //   582: invokevirtual 460	com/tencent/mm/storage/s:get	(I)Ljava/lang/Object;
    //   585: checkcast 129	java/lang/String
    //   588: astore 8
    //   590: aload 13
    //   592: iconst_3
    //   593: invokevirtual 460	com/tencent/mm/storage/s:get	(I)Ljava/lang/Object;
    //   596: checkcast 129	java/lang/String
    //   599: astore 9
    //   601: aload 13
    //   603: bipush 6
    //   605: invokevirtual 460	com/tencent/mm/storage/s:get	(I)Ljava/lang/Object;
    //   608: checkcast 129	java/lang/String
    //   611: astore 10
    //   613: aload 13
    //   615: bipush 7
    //   617: invokevirtual 460	com/tencent/mm/storage/s:get	(I)Ljava/lang/Object;
    //   620: checkcast 129	java/lang/String
    //   623: astore 11
    //   625: aload 13
    //   627: bipush 25
    //   629: invokevirtual 460	com/tencent/mm/storage/s:get	(I)Ljava/lang/Object;
    //   632: checkcast 129	java/lang/String
    //   635: astore 12
    //   637: aload 13
    //   639: bipush 24
    //   641: invokevirtual 460	com/tencent/mm/storage/s:get	(I)Ljava/lang/Object;
    //   644: checkcast 129	java/lang/String
    //   647: astore 13
    //   649: aload 10
    //   651: aload 11
    //   653: invokestatic 466	com/tencent/mm/protocal/n:eN	(Ljava/lang/String;Ljava/lang/String;)Lcom/tencent/mm/protocal/n$a;
    //   656: astore 14
    //   658: ldc_w 297
    //   661: ldc_w 468
    //   664: bipush 7
    //   666: anewarray 4	java/lang/Object
    //   669: dup
    //   670: iconst_0
    //   671: aload 13
    //   673: aastore
    //   674: dup
    //   675: iconst_1
    //   676: aload 12
    //   678: aastore
    //   679: dup
    //   680: iconst_2
    //   681: aload 8
    //   683: aastore
    //   684: dup
    //   685: iconst_3
    //   686: aload 9
    //   688: aastore
    //   689: dup
    //   690: iconst_4
    //   691: aload 10
    //   693: aastore
    //   694: dup
    //   695: iconst_5
    //   696: aload 11
    //   698: aastore
    //   699: dup
    //   700: bipush 6
    //   702: iload_3
    //   703: invokestatic 145	java/lang/Integer:valueOf	(I)Ljava/lang/Integer;
    //   706: aastore
    //   707: invokestatic 471	com/tencent/mm/sdk/platformtools/w:d	(Ljava/lang/String;Ljava/lang/String;[Ljava/lang/Object;)V
    //   710: new 299	java/lang/StringBuilder
    //   713: dup
    //   714: ldc_w 473
    //   717: invokespecial 302	java/lang/StringBuilder:<init>	(Ljava/lang/String;)V
    //   720: invokestatic 450	com/tencent/mm/sdk/platformtools/bg:bQW	()Lcom/tencent/mm/sdk/platformtools/ah;
    //   723: invokevirtual 306	java/lang/StringBuilder:append	(Ljava/lang/Object;)Ljava/lang/StringBuilder;
    //   726: invokevirtual 309	java/lang/StringBuilder:toString	()Ljava/lang/String;
    //   729: iconst_1
    //   730: invokestatic 253	junit/framework/Assert:assertTrue	(Ljava/lang/String;Z)V
    //   733: aload_1
    //   734: iconst_0
    //   735: aload 8
    //   737: aload 9
    //   739: aload 14
    //   741: getfield 479	com/tencent/mm/protocal/n$a:tKz	[I
    //   744: aload 14
    //   746: getfield 482	com/tencent/mm/protocal/n$a:tKA	[I
    //   749: aload 14
    //   751: getfield 486	com/tencent/mm/protocal/n$a:tKB	I
    //   754: aload 14
    //   756: getfield 489	com/tencent/mm/protocal/n$a:tKC	I
    //   759: aload 13
    //   761: aload 12
    //   763: invokeinterface 492 10 0
    //   768: iload_3
    //   769: iconst_1
    //   770: iand
    //   771: ifne +281 -> 1052
    //   774: iconst_1
    //   775: istore 6
    //   777: aload_1
    //   778: iload 6
    //   780: invokeinterface 495 2 0
    //   785: invokestatic 291	com/tencent/mm/kernel/h:xz	()Lcom/tencent/mm/kernel/h;
    //   788: pop
    //   789: invokestatic 381	com/tencent/mm/kernel/h:xw	()Lcom/tencent/mm/kernel/a;
    //   792: pop
    //   793: new 299	java/lang/StringBuilder
    //   796: dup
    //   797: ldc_w 497
    //   800: invokespecial 302	java/lang/StringBuilder:<init>	(Ljava/lang/String;)V
    //   803: invokestatic 450	com/tencent/mm/sdk/platformtools/bg:bQW	()Lcom/tencent/mm/sdk/platformtools/ah;
    //   806: invokevirtual 306	java/lang/StringBuilder:append	(Ljava/lang/Object;)Ljava/lang/StringBuilder;
    //   809: invokevirtual 309	java/lang/StringBuilder:toString	()Ljava/lang/String;
    //   812: astore 8
    //   814: aload 7
    //   816: ifnull +242 -> 1058
    //   819: iconst_1
    //   820: istore 6
    //   822: aload 8
    //   824: iload 6
    //   826: invokestatic 253	junit/framework/Assert:assertTrue	(Ljava/lang/String;Z)V
    //   829: invokestatic 381	com/tencent/mm/kernel/h:xw	()Lcom/tencent/mm/kernel/a;
    //   832: invokevirtual 415	com/tencent/mm/kernel/a:wL	()Z
    //   835: ifeq +12 -> 847
    //   838: invokestatic 381	com/tencent/mm/kernel/h:xw	()Lcom/tencent/mm/kernel/a;
    //   841: getfield 500	com/tencent/mm/kernel/a:fYg	Z
    //   844: ifne +266 -> 1110
    //   847: ldc_w 297
    //   850: ldc_w 502
    //   853: iconst_2
    //   854: anewarray 4	java/lang/Object
    //   857: dup
    //   858: iconst_0
    //   859: invokestatic 381	com/tencent/mm/kernel/h:xw	()Lcom/tencent/mm/kernel/a;
    //   862: invokevirtual 415	com/tencent/mm/kernel/a:wL	()Z
    //   865: invokestatic 176	java/lang/Boolean:valueOf	(Z)Ljava/lang/Boolean;
    //   868: aastore
    //   869: dup
    //   870: iconst_1
    //   871: invokestatic 381	com/tencent/mm/kernel/h:xw	()Lcom/tencent/mm/kernel/a;
    //   874: getfield 500	com/tencent/mm/kernel/a:fYg	Z
    //   877: invokestatic 176	java/lang/Boolean:valueOf	(Z)Ljava/lang/Boolean;
    //   880: aastore
    //   881: invokestatic 181	com/tencent/mm/sdk/platformtools/w:w	(Ljava/lang/String;Ljava/lang/String;[Ljava/lang/Object;)V
    //   884: getstatic 405	com/tencent/mm/plugin/report/d:oqe	Lcom/tencent/mm/plugin/report/d;
    //   887: astore 8
    //   889: invokestatic 381	com/tencent/mm/kernel/h:xw	()Lcom/tencent/mm/kernel/a;
    //   892: invokevirtual 415	com/tencent/mm/kernel/a:wL	()Z
    //   895: ifeq +169 -> 1064
    //   898: ldc2_w 503
    //   901: lstore 4
    //   903: aload 8
    //   905: ldc2_w 505
    //   908: lload 4
    //   910: lconst_1
    //   911: iconst_0
    //   912: invokevirtual 412	com/tencent/mm/plugin/report/d:a	(JJJZ)V
    //   915: aload 7
    //   917: invokeinterface 509 1 0
    //   922: aload_1
    //   923: invokeinterface 510 1 0
    //   928: aload_2
    //   929: getfield 364	com/tencent/mm/kernel/b:fYr	Lcom/tencent/mm/ad/n;
    //   932: aload_1
    //   933: invokevirtual 512	com/tencent/mm/ad/n:d	(Lcom/tencent/mm/network/e;)V
    //   936: new 514	com/tencent/mm/kernel/b$7
    //   939: dup
    //   940: aload_2
    //   941: invokespecial 515	com/tencent/mm/kernel/b$7:<init>	(Lcom/tencent/mm/kernel/b;)V
    //   944: invokestatic 520	com/tencent/mm/network/b:a	(Lcom/tencent/mm/network/b$a;)V
    //   947: invokestatic 523	com/tencent/mm/kernel/a:ww	()I
    //   950: aload 7
    //   952: invokeinterface 524 1 0
    //   957: if_icmpeq +115 -> 1072
    //   960: getstatic 405	com/tencent/mm/plugin/report/d:oqe	Lcom/tencent/mm/plugin/report/d;
    //   963: ldc2_w 505
    //   966: ldc2_w 525
    //   969: lconst_1
    //   970: iconst_0
    //   971: invokevirtual 412	com/tencent/mm/plugin/report/d:a	(JJJZ)V
    //   974: ldc_w 297
    //   977: ldc_w 528
    //   980: iconst_4
    //   981: anewarray 4	java/lang/Object
    //   984: dup
    //   985: iconst_0
    //   986: aload 7
    //   988: invokeinterface 524 1 0
    //   993: invokestatic 145	java/lang/Integer:valueOf	(I)Ljava/lang/Integer;
    //   996: aastore
    //   997: dup
    //   998: iconst_1
    //   999: invokestatic 523	com/tencent/mm/kernel/a:ww	()I
    //   1002: invokestatic 145	java/lang/Integer:valueOf	(I)Ljava/lang/Integer;
    //   1005: aastore
    //   1006: dup
    //   1007: iconst_2
    //   1008: invokestatic 381	com/tencent/mm/kernel/h:xw	()Lcom/tencent/mm/kernel/a;
    //   1011: invokevirtual 415	com/tencent/mm/kernel/a:wL	()Z
    //   1014: invokestatic 176	java/lang/Boolean:valueOf	(Z)Ljava/lang/Boolean;
    //   1017: aastore
    //   1018: dup
    //   1019: iconst_3
    //   1020: invokestatic 381	com/tencent/mm/kernel/h:xw	()Lcom/tencent/mm/kernel/a;
    //   1023: getfield 500	com/tencent/mm/kernel/a:fYg	Z
    //   1026: invokestatic 176	java/lang/Boolean:valueOf	(Z)Ljava/lang/Boolean;
    //   1029: aastore
    //   1030: invokestatic 181	com/tencent/mm/sdk/platformtools/w:w	(Ljava/lang/String;Ljava/lang/String;[Ljava/lang/Object;)V
    //   1033: aload 7
    //   1035: invokestatic 523	com/tencent/mm/kernel/a:ww	()I
    //   1038: invokeinterface 532 2 0
    //   1043: goto -783 -> 260
    //   1046: iconst_0
    //   1047: istore 6
    //   1049: goto -485 -> 564
    //   1052: iconst_0
    //   1053: istore 6
    //   1055: goto -278 -> 777
    //   1058: iconst_0
    //   1059: istore 6
    //   1061: goto -239 -> 822
    //   1064: ldc2_w 533
    //   1067: lstore 4
    //   1069: goto -166 -> 903
    //   1072: ldc_w 297
    //   1075: ldc_w 536
    //   1078: iconst_2
    //   1079: anewarray 4	java/lang/Object
    //   1082: dup
    //   1083: iconst_0
    //   1084: aload 7
    //   1086: invokeinterface 524 1 0
    //   1091: invokestatic 145	java/lang/Integer:valueOf	(I)Ljava/lang/Integer;
    //   1094: aastore
    //   1095: dup
    //   1096: iconst_1
    //   1097: invokestatic 523	com/tencent/mm/kernel/a:ww	()I
    //   1100: invokestatic 145	java/lang/Integer:valueOf	(I)Ljava/lang/Integer;
    //   1103: aastore
    //   1104: invokestatic 148	com/tencent/mm/sdk/platformtools/w:i	(Ljava/lang/String;Ljava/lang/String;[Ljava/lang/Object;)V
    //   1107: goto -847 -> 260
    //   1110: aload_2
    //   1111: getfield 364	com/tencent/mm/kernel/b:fYr	Lcom/tencent/mm/ad/n;
    //   1114: aload_1
    //   1115: invokevirtual 512	com/tencent/mm/ad/n:d	(Lcom/tencent/mm/network/e;)V
    //   1118: new 538	com/tencent/mm/kernel/b$8
    //   1121: dup
    //   1122: aload_2
    //   1123: invokespecial 539	com/tencent/mm/kernel/b$8:<init>	(Lcom/tencent/mm/kernel/b;)V
    //   1126: invokestatic 520	com/tencent/mm/network/b:a	(Lcom/tencent/mm/network/b$a;)V
    //   1129: ldc_w 297
    //   1132: ldc_w 541
    //   1135: iconst_3
    //   1136: anewarray 4	java/lang/Object
    //   1139: dup
    //   1140: iconst_0
    //   1141: invokestatic 523	com/tencent/mm/kernel/a:ww	()I
    //   1144: invokestatic 145	java/lang/Integer:valueOf	(I)Ljava/lang/Integer;
    //   1147: aastore
    //   1148: dup
    //   1149: iconst_1
    //   1150: aload 7
    //   1152: invokeinterface 524 1 0
    //   1157: invokestatic 145	java/lang/Integer:valueOf	(I)Ljava/lang/Integer;
    //   1160: aastore
    //   1161: dup
    //   1162: iconst_2
    //   1163: invokestatic 381	com/tencent/mm/kernel/h:xw	()Lcom/tencent/mm/kernel/a;
    //   1166: invokevirtual 415	com/tencent/mm/kernel/a:wL	()Z
    //   1169: invokestatic 176	java/lang/Boolean:valueOf	(Z)Ljava/lang/Boolean;
    //   1172: aastore
    //   1173: invokestatic 148	com/tencent/mm/sdk/platformtools/w:i	(Ljava/lang/String;Ljava/lang/String;[Ljava/lang/Object;)V
    //   1176: invokestatic 523	com/tencent/mm/kernel/a:ww	()I
    //   1179: aload 7
    //   1181: invokeinterface 524 1 0
    //   1186: if_icmpeq -926 -> 260
    //   1189: ldc_w 297
    //   1192: new 299	java/lang/StringBuilder
    //   1195: dup
    //   1196: ldc_w 543
    //   1199: invokespecial 302	java/lang/StringBuilder:<init>	(Ljava/lang/String;)V
    //   1202: aload 7
    //   1204: invokeinterface 524 1 0
    //   1209: invokevirtual 546	java/lang/StringBuilder:append	(I)Ljava/lang/StringBuilder;
    //   1212: invokevirtual 309	java/lang/StringBuilder:toString	()Ljava/lang/String;
    //   1215: invokestatic 239	com/tencent/mm/sdk/platformtools/w:w	(Ljava/lang/String;Ljava/lang/String;)V
    //   1218: new 299	java/lang/StringBuilder
    //   1221: dup
    //   1222: ldc_w 548
    //   1225: invokespecial 302	java/lang/StringBuilder:<init>	(Ljava/lang/String;)V
    //   1228: invokestatic 450	com/tencent/mm/sdk/platformtools/bg:bQW	()Lcom/tencent/mm/sdk/platformtools/ah;
    //   1231: invokevirtual 306	java/lang/StringBuilder:append	(Ljava/lang/Object;)Ljava/lang/StringBuilder;
    //   1234: invokevirtual 309	java/lang/StringBuilder:toString	()Ljava/lang/String;
    //   1237: astore_1
    //   1238: invokestatic 291	com/tencent/mm/kernel/h:xz	()Lcom/tencent/mm/kernel/h;
    //   1241: pop
    //   1242: invokestatic 438	com/tencent/mm/kernel/h:xy	()Lcom/tencent/mm/kernel/e;
    //   1245: invokevirtual 552	com/tencent/mm/kernel/e:xh	()Lcom/tencent/mm/storage/t;
    //   1248: ifnull +57 -> 1305
    //   1251: iconst_1
    //   1252: istore 6
    //   1254: aload_1
    //   1255: iload 6
    //   1257: invokestatic 253	junit/framework/Assert:assertTrue	(Ljava/lang/String;Z)V
    //   1260: invokestatic 291	com/tencent/mm/kernel/h:xz	()Lcom/tencent/mm/kernel/h;
    //   1263: pop
    //   1264: invokestatic 438	com/tencent/mm/kernel/h:xy	()Lcom/tencent/mm/kernel/e;
    //   1267: invokevirtual 552	com/tencent/mm/kernel/e:xh	()Lcom/tencent/mm/storage/t;
    //   1270: iconst_2
    //   1271: aconst_null
    //   1272: invokevirtual 557	com/tencent/mm/storage/t:get	(ILjava/lang/Object;)Ljava/lang/Object;
    //   1275: checkcast 129	java/lang/String
    //   1278: astore_1
    //   1279: invokestatic 523	com/tencent/mm/kernel/a:ww	()I
    //   1282: istore_3
    //   1283: aload 7
    //   1285: iconst_0
    //   1286: newarray <illegal type>
    //   1288: iload_3
    //   1289: invokeinterface 560 3 0
    //   1294: aload 7
    //   1296: aload_1
    //   1297: invokeinterface 563 2 0
    //   1302: goto -1042 -> 260
    //   1305: iconst_0
    //   1306: istore 6
    //   1308: goto -54 -> 1254
    //   1311: ldc_w 397
    //   1314: ldc_w 565
    //   1317: iconst_2
    //   1318: anewarray 4	java/lang/Object
    //   1321: dup
    //   1322: iconst_0
    //   1323: aload_2
    //   1324: invokeinterface 568 1 0
    //   1329: invokestatic 176	java/lang/Boolean:valueOf	(Z)Ljava/lang/Boolean;
    //   1332: aastore
    //   1333: dup
    //   1334: iconst_1
    //   1335: aload_1
    //   1336: invokevirtual 571	com/tencent/mm/y/a:yA	()I
    //   1339: invokestatic 145	java/lang/Integer:valueOf	(I)Ljava/lang/Integer;
    //   1342: aastore
    //   1343: invokestatic 148	com/tencent/mm/sdk/platformtools/w:i	(Ljava/lang/String;Ljava/lang/String;[Ljava/lang/Object;)V
    //   1346: aload_2
    //   1347: invokeinterface 568 1 0
    //   1352: ifeq +128 -> 1480
    //   1355: aload_1
    //   1356: invokevirtual 571	com/tencent/mm/y/a:yA	()I
    //   1359: ifle +95 -> 1454
    //   1362: getstatic 405	com/tencent/mm/plugin/report/d:oqe	Lcom/tencent/mm/plugin/report/d;
    //   1365: ldc2_w 406
    //   1368: ldc2_w 572
    //   1371: lconst_1
    //   1372: iconst_0
    //   1373: invokevirtual 412	com/tencent/mm/plugin/report/d:a	(JJJZ)V
    //   1376: ldc_w 397
    //   1379: ldc_w 575
    //   1382: invokestatic 217	com/tencent/mm/sdk/platformtools/w:e	(Ljava/lang/String;Ljava/lang/String;)V
    //   1385: aload_1
    //   1386: aconst_null
    //   1387: putfield 579	com/tencent/mm/y/a:glL	[B
    //   1390: aload_1
    //   1391: aload_2
    //   1392: invokeinterface 583 1 0
    //   1397: putfield 579	com/tencent/mm/y/a:glL	[B
    //   1400: getstatic 405	com/tencent/mm/plugin/report/d:oqe	Lcom/tencent/mm/plugin/report/d;
    //   1403: astore_2
    //   1404: aload_1
    //   1405: invokevirtual 571	com/tencent/mm/y/a:yA	()I
    //   1408: ifle +271 -> 1679
    //   1411: ldc2_w 584
    //   1414: lstore 4
    //   1416: aload_2
    //   1417: ldc2_w 406
    //   1420: lload 4
    //   1422: lconst_1
    //   1423: iconst_0
    //   1424: invokevirtual 412	com/tencent/mm/plugin/report/d:a	(JJJZ)V
    //   1427: goto -1070 -> 357
    //   1430: astore_1
    //   1431: ldc_w 397
    //   1434: ldc_w 587
    //   1437: iconst_1
    //   1438: anewarray 4	java/lang/Object
    //   1441: dup
    //   1442: iconst_0
    //   1443: aload_1
    //   1444: invokestatic 426	com/tencent/mm/sdk/platformtools/bg:f	(Ljava/lang/Throwable;)Ljava/lang/String;
    //   1447: aastore
    //   1448: invokestatic 428	com/tencent/mm/sdk/platformtools/w:e	(Ljava/lang/String;Ljava/lang/String;[Ljava/lang/Object;)V
    //   1451: goto -1094 -> 357
    //   1454: ldc_w 397
    //   1457: ldc_w 589
    //   1460: invokestatic 239	com/tencent/mm/sdk/platformtools/w:w	(Ljava/lang/String;Ljava/lang/String;)V
    //   1463: getstatic 405	com/tencent/mm/plugin/report/d:oqe	Lcom/tencent/mm/plugin/report/d;
    //   1466: ldc2_w 406
    //   1469: ldc2_w 590
    //   1472: lconst_1
    //   1473: iconst_0
    //   1474: invokevirtual 412	com/tencent/mm/plugin/report/d:a	(JJJZ)V
    //   1477: goto -87 -> 1390
    //   1480: aload_1
    //   1481: invokevirtual 571	com/tencent/mm/y/a:yA	()I
    //   1484: ifgt +40 -> 1524
    //   1487: getstatic 405	com/tencent/mm/plugin/report/d:oqe	Lcom/tencent/mm/plugin/report/d;
    //   1490: ldc2_w 406
    //   1493: ldc2_w 592
    //   1496: lconst_1
    //   1497: iconst_0
    //   1498: invokevirtual 412	com/tencent/mm/plugin/report/d:a	(JJJZ)V
    //   1501: ldc_w 397
    //   1504: ldc_w 595
    //   1507: iconst_1
    //   1508: anewarray 4	java/lang/Object
    //   1511: dup
    //   1512: iconst_0
    //   1513: aload_1
    //   1514: invokevirtual 596	java/lang/Object:toString	()Ljava/lang/String;
    //   1517: aastore
    //   1518: invokestatic 181	com/tencent/mm/sdk/platformtools/w:w	(Ljava/lang/String;Ljava/lang/String;[Ljava/lang/Object;)V
    //   1521: goto -1164 -> 357
    //   1524: aload_2
    //   1525: aload_1
    //   1526: getfield 579	com/tencent/mm/y/a:glL	[B
    //   1529: invokeinterface 600 2 0
    //   1534: istore_3
    //   1535: ldc_w 397
    //   1538: ldc_w 602
    //   1541: iconst_3
    //   1542: anewarray 4	java/lang/Object
    //   1545: dup
    //   1546: iconst_0
    //   1547: iload_3
    //   1548: invokestatic 145	java/lang/Integer:valueOf	(I)Ljava/lang/Integer;
    //   1551: aastore
    //   1552: dup
    //   1553: iconst_1
    //   1554: lload 4
    //   1556: invokestatic 606	com/tencent/mm/sdk/platformtools/bg:aH	(J)J
    //   1559: invokestatic 611	java/lang/Long:valueOf	(J)Ljava/lang/Long;
    //   1562: aastore
    //   1563: dup
    //   1564: iconst_2
    //   1565: aload_1
    //   1566: invokevirtual 571	com/tencent/mm/y/a:yA	()I
    //   1569: invokestatic 145	java/lang/Integer:valueOf	(I)Ljava/lang/Integer;
    //   1572: aastore
    //   1573: invokestatic 148	com/tencent/mm/sdk/platformtools/w:i	(Ljava/lang/String;Ljava/lang/String;[Ljava/lang/Object;)V
    //   1576: iload_3
    //   1577: ifeq +47 -> 1624
    //   1580: ldc_w 397
    //   1583: ldc_w 613
    //   1586: iconst_1
    //   1587: anewarray 4	java/lang/Object
    //   1590: dup
    //   1591: iconst_0
    //   1592: iload_3
    //   1593: invokestatic 145	java/lang/Integer:valueOf	(I)Ljava/lang/Integer;
    //   1596: aastore
    //   1597: invokestatic 428	com/tencent/mm/sdk/platformtools/w:e	(Ljava/lang/String;Ljava/lang/String;[Ljava/lang/Object;)V
    //   1600: aload_1
    //   1601: aconst_null
    //   1602: putfield 579	com/tencent/mm/y/a:glL	[B
    //   1605: getstatic 405	com/tencent/mm/plugin/report/d:oqe	Lcom/tencent/mm/plugin/report/d;
    //   1608: ldc2_w 406
    //   1611: iload_3
    //   1612: bipush 20
    //   1614: iadd
    //   1615: i2l
    //   1616: lconst_1
    //   1617: iconst_0
    //   1618: invokevirtual 412	com/tencent/mm/plugin/report/d:a	(JJJZ)V
    //   1621: goto -1264 -> 357
    //   1624: aload_1
    //   1625: lconst_0
    //   1626: putfield 617	com/tencent/mm/y/a:glM	J
    //   1629: goto -24 -> 1605
    //   1632: invokestatic 291	com/tencent/mm/kernel/h:xz	()Lcom/tencent/mm/kernel/h;
    //   1635: pop
    //   1636: invokestatic 381	com/tencent/mm/kernel/h:xw	()Lcom/tencent/mm/kernel/a;
    //   1639: getfield 387	com/tencent/mm/kernel/a:fYa	Lcom/tencent/mm/y/a;
    //   1642: astore_1
    //   1643: invokestatic 291	com/tencent/mm/kernel/h:xz	()Lcom/tencent/mm/kernel/h;
    //   1646: pop
    //   1647: ldc_w 397
    //   1650: ldc_w 619
    //   1653: iconst_2
    //   1654: anewarray 4	java/lang/Object
    //   1657: dup
    //   1658: iconst_0
    //   1659: aload_1
    //   1660: aastore
    //   1661: dup
    //   1662: iconst_1
    //   1663: invokestatic 295	com/tencent/mm/kernel/h:xx	()Lcom/tencent/mm/kernel/b;
    //   1666: getfield 364	com/tencent/mm/kernel/b:fYr	Lcom/tencent/mm/ad/n;
    //   1669: getfield 391	com/tencent/mm/ad/n:gus	Lcom/tencent/mm/network/e;
    //   1672: aastore
    //   1673: invokestatic 148	com/tencent/mm/sdk/platformtools/w:i	(Ljava/lang/String;Ljava/lang/String;[Ljava/lang/Object;)V
    //   1676: goto -1319 -> 357
    //   1679: ldc2_w 620
    //   1682: lstore 4
    //   1684: goto -268 -> 1416
    // Local variable table:
    //   start	length	slot	name	signature
    //   0	1687	0	this	e
    //   0	1687	1	paramComponentName	ComponentName
    //   0	1687	2	paramIBinder	IBinder
    //   578	1037	3	i	int
    //   328	1355	4	l	long
    //   562	745	6	bool	boolean
    //   191	42	7	localObject1	Object
    //   486	809	7	localRemoteException	android.os.RemoteException
    //   554	350	8	localObject2	Object
    //   599	139	9	str1	String
    //   611	81	10	str2	String
    //   623	74	11	str3	String
    //   635	127	12	str4	String
    //   533	227	13	localObject3	Object
    //   656	99	14	locala	com.tencent.mm.protocal.n.a
    // Exception table:
    //   from	to	target	type
    //   21	41	423	finally
    //   424	426	423	finally
    //   58	75	428	finally
    //   103	113	438	java/lang/Exception
    //   122	132	462	java/lang/Exception
    //   185	193	486	android/os/RemoteException
    //   198	210	486	android/os/RemoteException
    //   266	330	1430	java/lang/Throwable
    //   334	357	1430	java/lang/Throwable
    //   1311	1390	1430	java/lang/Throwable
    //   1390	1411	1430	java/lang/Throwable
    //   1416	1427	1430	java/lang/Throwable
    //   1454	1477	1430	java/lang/Throwable
    //   1480	1521	1430	java/lang/Throwable
    //   1524	1576	1430	java/lang/Throwable
    //   1580	1605	1430	java/lang/Throwable
    //   1605	1621	1430	java/lang/Throwable
    //   1624	1629	1430	java/lang/Throwable
    //   1632	1676	1430	java/lang/Throwable
  }
  
  public final void onServiceDisconnected(ComponentName paramComponentName)
  {
    GMTrace.i(13713562140672L, 102174);
    w.w("MicroMsg.CoreServiceConnection", "onServiceDisconnected ");
    try
    {
      this.esh.lock();
      this.esi = false;
      this.esj = null;
      this.esh.unlock();
      h.xw();
      if ((a.wK()) && (!a.wF()))
      {
        h.xz();
        h.xx().fYr.DP();
        ah(ab.getContext());
        GMTrace.o(13713562140672L, 102174);
        return;
      }
    }
    finally
    {
      this.esh.unlock();
    }
    h.xz();
    h.xx().fYr.DQ();
    h.xz();
    h.xx().fYr.reset();
    GMTrace.o(13713562140672L, 102174);
  }
}


/* Location:              D:\tools\apktool\weixin6519android1140\jar\classes-dex2jar.jar!\com\tencent\mm\app\e.class
 * Java compiler version: 6 (50.0)
 * JD-Core Version:       0.7.1
 */