package com.tencent.mm.plugin.secinforeport;

import android.content.Context;
import android.util.Base64;
import com.tencent.c.a.d.1;
import com.tencent.c.e.a.e;
import com.tencent.gmtrace.GMTrace;
import com.tencent.mm.ad.b.a;
import com.tencent.mm.ad.b.b;
import com.tencent.mm.ad.k;
import com.tencent.mm.ad.u;
import com.tencent.mm.ad.u.a;
import com.tencent.mm.compatible.d.p;
import com.tencent.mm.protocal.c.ayk;
import com.tencent.mm.protocal.c.ayl;
import com.tencent.mm.sdk.platformtools.ab;
import com.tencent.mm.sdk.platformtools.w;
import java.util.HashMap;
import java.util.Map;
import java.util.Random;

 enum c
  implements com.tencent.mm.plugin.secinforeport.a.c
{
  static
  {
    GMTrace.i(17520513777664L, 130538);
    oET = new c("INSTANCE");
    oEU = new c[] { oET };
    GMTrace.o(17520513777664L, 130538);
  }
  
  private c()
  {
    GMTrace.i(17519440035840L, 130530);
    GMTrace.o(17519440035840L, 130530);
  }
  
  private void ap(final int paramInt, String paramString)
  {
    GMTrace.i(20148899545088L, 150121);
    Object localObject = new b.a();
    ((b.a)localObject).uri = com.tencent.mm.plugin.normsg.a.d.nxJ.DX("Q\036\033\022W\033\021\031Y\030\035\020\000\036\035\034\t@\016\002\004F\032\002\026\n\026\027\001\r\t:0)?3?:3");
    ((b.a)localObject).gtE = 771;
    ((b.a)localObject).gtF = new ayk();
    ((b.a)localObject).gtG = new ayl();
    localObject = ((b.a)localObject).DA();
    ayk localayk = (ayk)((com.tencent.mm.ad.b)localObject).gtC.gtK;
    localayk.uMN = paramInt;
    localayk.uMM = paramString;
    com.tencent.mm.plugin.report.d.oqe.a(416L, 0L, 1L, false);
    u.a((com.tencent.mm.ad.b)localObject, new u.a()
    {
      public final int a(int paramAnonymousInt1, int paramAnonymousInt2, String paramAnonymousString, com.tencent.mm.ad.b paramAnonymousb, k paramAnonymousk)
      {
        GMTrace.i(20847100166144L, 155323);
        if ((paramAnonymousInt1 == 0) && (paramAnonymousInt2 == 0))
        {
          w.d("MicroMsg.SecInfoReporterImpl", "cgireport succ, ctx: %d", new Object[] { Integer.valueOf(paramInt) });
          com.tencent.mm.plugin.report.d.oqe.a(416L, 1L, 1L, false);
        }
        for (;;)
        {
          GMTrace.o(20847100166144L, 155323);
          return 0;
          w.d("MicroMsg.SecInfoReporterImpl", "cgireport failed, ctx: %d, err: %d:%d %s", new Object[] { Integer.valueOf(paramInt), Integer.valueOf(paramAnonymousInt1), Integer.valueOf(paramAnonymousInt2), paramAnonymousString });
          com.tencent.mm.plugin.report.d.oqe.a(416L, 2L, 1L, false);
        }
      }
    }, false);
    GMTrace.o(20148899545088L, 150121);
  }
  
  public final boolean F(int paramInt, long paramLong)
  {
    GMTrace.i(20846026424320L, 155315);
    boolean bool = a.F(paramInt, paramLong);
    GMTrace.o(20846026424320L, 155315);
    return bool;
  }
  
  public final void Gj(String paramString)
  {
    GMTrace.i(18974628642816L, 141372);
    int k = new Random().nextInt();
    int m = paramString.length();
    int j = m / 1000;
    if (m % 1000 > 0) {}
    int n;
    for (int i = 1;; i = 0)
    {
      n = j + i;
      i = 0;
      j = 0;
      while (j < paramString.length())
      {
        int i1 = Math.min(1000, m - j);
        String str = paramString.substring(j, j + i1);
        com.tencent.mm.plugin.report.d.oqe.a(13690, k + "," + n + "," + i + ",0,0" + ",," + str, false, true);
        j += i1;
        i += 1;
      }
    }
    w.d("MicroMsg.SecInfoReporterImpl", "kvreport: ctxId: %d, dataLen: %d, pkgCount: %d", new Object[] { Integer.valueOf(k), Integer.valueOf(m), Integer.valueOf(n) });
    GMTrace.o(18974628642816L, 141372);
  }
  
  public final void Gk(String paramString)
  {
    GMTrace.i(20148765327360L, 150120);
    ap(Integer.MIN_VALUE, paramString);
    GMTrace.o(20148765327360L, 150120);
  }
  
  public final void bI(String paramString, int paramInt)
  {
    GMTrace.i(18974762860544L, 141373);
    ap(paramInt, paramString);
    GMTrace.o(18974762860544L, 141373);
  }
  
  public final void bed()
  {
    GMTrace.i(20846160642048L, 155316);
    e.cnz().qt();
    Context localContext = ab.getContext();
    String str = p.sZ();
    com.tencent.c.a.b local1 = new com.tencent.c.a.b()
    {
      public final boolean l(int paramAnonymousInt, byte[] paramAnonymousArrayOfByte)
      {
        GMTrace.i(20846563295232L, 155319);
        if (paramAnonymousInt == 0)
        {
          paramAnonymousArrayOfByte = Base64.encodeToString(paramAnonymousArrayOfByte, 2);
          paramAnonymousArrayOfByte = com.tencent.mm.plugin.normsg.a.d.nxJ.a(new Object[][] { { "\036<:& *\036&3\005!3'\007%(?ol", paramAnonymousArrayOfByte } });
          c.a(c.this, paramAnonymousArrayOfByte);
          GMTrace.o(20846563295232L, 155319);
          return true;
        }
        w.w("MicroMsg.SecInfoReporterImpl", "TuringService recvReqData failed, code: " + paramAnonymousInt);
        GMTrace.o(20846563295232L, 155319);
        return false;
      }
    };
    com.tencent.c.b.c localc = new com.tencent.c.b.c(localContext);
    e.cnz().a(localContext, str, new d.1(local1, localc));
    GMTrace.o(20846160642048L, 155316);
  }
  
  static final class a
  {
    private static final Map<Integer, Long> oEX;
    
    static
    {
      GMTrace.i(17521855954944L, 130548);
      oEX = new HashMap();
      GMTrace.o(17521855954944L, 130548);
    }
    
    /* Error */
    static boolean F(int paramInt, long paramLong)
    {
      // Byte code:
      //   0: ldc 2
      //   2: monitorenter
      //   3: ldc2_w 35
      //   6: ldc 37
      //   8: invokestatic 21	com/tencent/gmtrace/GMTrace:i	(JI)V
      //   11: lload_1
      //   12: lconst_0
      //   13: lcmp
      //   14: ifge +38 -> 52
      //   17: ldc 39
      //   19: ldc 41
      //   21: iconst_1
      //   22: anewarray 4	java/lang/Object
      //   25: dup
      //   26: iconst_0
      //   27: lload_1
      //   28: invokestatic 47	java/lang/Long:valueOf	(J)Ljava/lang/Long;
      //   31: aastore
      //   32: invokestatic 53	com/tencent/mm/sdk/platformtools/w:w	(Ljava/lang/String;Ljava/lang/String;[Ljava/lang/Object;)V
      //   35: ldc2_w 35
      //   38: ldc 37
      //   40: invokestatic 31	com/tencent/gmtrace/GMTrace:o	(JI)V
      //   43: iconst_0
      //   44: istore 5
      //   46: ldc 2
      //   48: monitorexit
      //   49: iload 5
      //   51: ireturn
      //   52: getstatic 28	com/tencent/mm/plugin/secinforeport/c$a:oEX	Ljava/util/Map;
      //   55: iload_0
      //   56: invokestatic 58	java/lang/Integer:valueOf	(I)Ljava/lang/Integer;
      //   59: invokeinterface 64 2 0
      //   64: ifne +6 -> 70
      //   67: invokestatic 67	com/tencent/mm/plugin/secinforeport/c$a:load	()V
      //   70: getstatic 28	com/tencent/mm/plugin/secinforeport/c$a:oEX	Ljava/util/Map;
      //   73: iload_0
      //   74: invokestatic 58	java/lang/Integer:valueOf	(I)Ljava/lang/Integer;
      //   77: invokeinterface 71 2 0
      //   82: checkcast 43	java/lang/Long
      //   85: astore 6
      //   87: invokestatic 77	java/lang/System:currentTimeMillis	()J
      //   90: lstore_3
      //   91: aload 6
      //   93: ifnull +13 -> 106
      //   96: lload_3
      //   97: aload 6
      //   99: invokevirtual 80	java/lang/Long:longValue	()J
      //   102: lcmp
      //   103: ifge +37 -> 140
      //   106: getstatic 28	com/tencent/mm/plugin/secinforeport/c$a:oEX	Ljava/util/Map;
      //   109: iload_0
      //   110: invokestatic 58	java/lang/Integer:valueOf	(I)Ljava/lang/Integer;
      //   113: lconst_0
      //   114: invokestatic 47	java/lang/Long:valueOf	(J)Ljava/lang/Long;
      //   117: invokeinterface 84 3 0
      //   122: pop
      //   123: invokestatic 87	com/tencent/mm/plugin/secinforeport/c$a:save	()V
      //   126: ldc2_w 35
      //   129: ldc 37
      //   131: invokestatic 31	com/tencent/gmtrace/GMTrace:o	(JI)V
      //   134: iconst_0
      //   135: istore 5
      //   137: goto -91 -> 46
      //   140: lload_3
      //   141: aload 6
      //   143: invokevirtual 80	java/lang/Long:longValue	()J
      //   146: lsub
      //   147: lload_1
      //   148: lcmp
      //   149: ifle +37 -> 186
      //   152: getstatic 28	com/tencent/mm/plugin/secinforeport/c$a:oEX	Ljava/util/Map;
      //   155: iload_0
      //   156: invokestatic 58	java/lang/Integer:valueOf	(I)Ljava/lang/Integer;
      //   159: lload_3
      //   160: invokestatic 47	java/lang/Long:valueOf	(J)Ljava/lang/Long;
      //   163: invokeinterface 84 3 0
      //   168: pop
      //   169: invokestatic 87	com/tencent/mm/plugin/secinforeport/c$a:save	()V
      //   172: ldc2_w 35
      //   175: ldc 37
      //   177: invokestatic 31	com/tencent/gmtrace/GMTrace:o	(JI)V
      //   180: iconst_1
      //   181: istore 5
      //   183: goto -137 -> 46
      //   186: ldc2_w 35
      //   189: ldc 37
      //   191: invokestatic 31	com/tencent/gmtrace/GMTrace:o	(JI)V
      //   194: iconst_0
      //   195: istore 5
      //   197: goto -151 -> 46
      //   200: astore 6
      //   202: ldc 2
      //   204: monitorexit
      //   205: aload 6
      //   207: athrow
      // Local variable table:
      //   start	length	slot	name	signature
      //   0	208	0	paramInt	int
      //   0	208	1	paramLong	long
      //   90	70	3	l	long
      //   44	152	5	bool	boolean
      //   85	57	6	localLong	Long
      //   200	6	6	localObject	Object
      // Exception table:
      //   from	to	target	type
      //   3	11	200	finally
      //   17	43	200	finally
      //   52	70	200	finally
      //   70	91	200	finally
      //   96	106	200	finally
      //   106	134	200	finally
      //   140	180	200	finally
      //   186	194	200	finally
    }
    
    /* Error */
    private static void load()
    {
      // Byte code:
      //   0: iconst_0
      //   1: istore_0
      //   2: ldc 2
      //   4: monitorenter
      //   5: ldc2_w 90
      //   8: ldc 92
      //   10: invokestatic 21	com/tencent/gmtrace/GMTrace:i	(JI)V
      //   13: new 94	java/io/File
      //   16: dup
      //   17: invokestatic 100	com/tencent/mm/kernel/h:xy	()Lcom/tencent/mm/kernel/e;
      //   20: getfield 106	com/tencent/mm/kernel/e:cachePath	Ljava/lang/String;
      //   23: getstatic 112	com/tencent/mm/plugin/normsg/a/d:nxJ	Lcom/tencent/mm/plugin/normsg/a/d;
      //   26: ldc 114
      //   28: invokevirtual 118	com/tencent/mm/plugin/normsg/a/d:DX	(Ljava/lang/String;)Ljava/lang/String;
      //   31: invokespecial 121	java/io/File:<init>	(Ljava/lang/String;Ljava/lang/String;)V
      //   34: astore 5
      //   36: new 123	java/io/DataInputStream
      //   39: dup
      //   40: new 125	java/io/FileInputStream
      //   43: dup
      //   44: aload 5
      //   46: invokespecial 128	java/io/FileInputStream:<init>	(Ljava/io/File;)V
      //   49: invokespecial 131	java/io/DataInputStream:<init>	(Ljava/io/InputStream;)V
      //   52: astore 6
      //   54: aload 6
      //   56: astore 5
      //   58: aload 6
      //   60: invokevirtual 135	java/io/DataInputStream:readShort	()S
      //   63: sipush 64762
      //   66: if_icmpeq +61 -> 127
      //   69: aload 6
      //   71: astore 5
      //   73: new 137	java/lang/IllegalStateException
      //   76: dup
      //   77: ldc -117
      //   79: invokespecial 142	java/lang/IllegalStateException:<init>	(Ljava/lang/String;)V
      //   82: athrow
      //   83: astore 7
      //   85: aload 6
      //   87: astore 5
      //   89: ldc 39
      //   91: ldc -112
      //   93: iconst_1
      //   94: anewarray 4	java/lang/Object
      //   97: dup
      //   98: iconst_0
      //   99: aload 7
      //   101: aastore
      //   102: invokestatic 147	com/tencent/mm/sdk/platformtools/w:e	(Ljava/lang/String;Ljava/lang/String;[Ljava/lang/Object;)V
      //   105: aload 6
      //   107: ifnull +195 -> 302
      //   110: aload 6
      //   112: invokevirtual 150	java/io/DataInputStream:close	()V
      //   115: ldc2_w 90
      //   118: ldc 92
      //   120: invokestatic 31	com/tencent/gmtrace/GMTrace:o	(JI)V
      //   123: ldc 2
      //   125: monitorexit
      //   126: return
      //   127: aload 6
      //   129: astore 5
      //   131: aload 6
      //   133: invokevirtual 135	java/io/DataInputStream:readShort	()S
      //   136: pop
      //   137: aload 6
      //   139: astore 5
      //   141: aload 6
      //   143: invokevirtual 154	java/io/DataInputStream:readInt	()I
      //   146: istore_1
      //   147: iload_1
      //   148: ifge +48 -> 196
      //   151: aload 6
      //   153: astore 5
      //   155: new 137	java/lang/IllegalStateException
      //   158: dup
      //   159: ldc -100
      //   161: invokespecial 142	java/lang/IllegalStateException:<init>	(Ljava/lang/String;)V
      //   164: athrow
      //   165: astore 7
      //   167: aload 5
      //   169: astore 6
      //   171: aload 7
      //   173: astore 5
      //   175: aload 6
      //   177: ifnull +8 -> 185
      //   180: aload 6
      //   182: invokevirtual 150	java/io/DataInputStream:close	()V
      //   185: aload 5
      //   187: athrow
      //   188: astore 5
      //   190: ldc 2
      //   192: monitorexit
      //   193: aload 5
      //   195: athrow
      //   196: iload_0
      //   197: iload_1
      //   198: if_icmpge +51 -> 249
      //   201: aload 6
      //   203: astore 5
      //   205: aload 6
      //   207: invokevirtual 154	java/io/DataInputStream:readInt	()I
      //   210: istore_2
      //   211: aload 6
      //   213: astore 5
      //   215: aload 6
      //   217: invokevirtual 159	java/io/DataInputStream:readLong	()J
      //   220: lstore_3
      //   221: aload 6
      //   223: astore 5
      //   225: getstatic 28	com/tencent/mm/plugin/secinforeport/c$a:oEX	Ljava/util/Map;
      //   228: iload_2
      //   229: invokestatic 58	java/lang/Integer:valueOf	(I)Ljava/lang/Integer;
      //   232: lload_3
      //   233: invokestatic 47	java/lang/Long:valueOf	(J)Ljava/lang/Long;
      //   236: invokeinterface 84 3 0
      //   241: pop
      //   242: iload_0
      //   243: iconst_1
      //   244: iadd
      //   245: istore_0
      //   246: goto -50 -> 196
      //   249: aload 6
      //   251: astore 5
      //   253: ldc 39
      //   255: ldc -95
      //   257: invokestatic 163	com/tencent/mm/sdk/platformtools/w:i	(Ljava/lang/String;Ljava/lang/String;)V
      //   260: aload 6
      //   262: invokevirtual 150	java/io/DataInputStream:close	()V
      //   265: ldc2_w 90
      //   268: ldc 92
      //   270: invokestatic 31	com/tencent/gmtrace/GMTrace:o	(JI)V
      //   273: goto -150 -> 123
      //   276: astore 5
      //   278: ldc2_w 90
      //   281: ldc 92
      //   283: invokestatic 31	com/tencent/gmtrace/GMTrace:o	(JI)V
      //   286: goto -163 -> 123
      //   289: astore 5
      //   291: ldc2_w 90
      //   294: ldc 92
      //   296: invokestatic 31	com/tencent/gmtrace/GMTrace:o	(JI)V
      //   299: goto -176 -> 123
      //   302: ldc2_w 90
      //   305: ldc 92
      //   307: invokestatic 31	com/tencent/gmtrace/GMTrace:o	(JI)V
      //   310: goto -187 -> 123
      //   313: astore 6
      //   315: goto -130 -> 185
      //   318: astore 5
      //   320: aconst_null
      //   321: astore 6
      //   323: goto -148 -> 175
      //   326: astore 7
      //   328: aconst_null
      //   329: astore 6
      //   331: goto -246 -> 85
      // Local variable table:
      //   start	length	slot	name	signature
      //   1	245	0	i	int
      //   146	53	1	j	int
      //   210	19	2	k	int
      //   220	13	3	l	long
      //   34	152	5	localObject1	Object
      //   188	6	5	localObject2	Object
      //   203	49	5	localObject3	Object
      //   276	1	5	localException1	Exception
      //   289	1	5	localException2	Exception
      //   318	1	5	localObject4	Object
      //   52	209	6	localObject5	Object
      //   313	1	6	localException3	Exception
      //   321	9	6	localObject6	Object
      //   83	17	7	localException4	Exception
      //   165	7	7	localObject7	Object
      //   326	1	7	localException5	Exception
      // Exception table:
      //   from	to	target	type
      //   58	69	83	java/lang/Exception
      //   73	83	83	java/lang/Exception
      //   131	137	83	java/lang/Exception
      //   141	147	83	java/lang/Exception
      //   155	165	83	java/lang/Exception
      //   205	211	83	java/lang/Exception
      //   215	221	83	java/lang/Exception
      //   225	242	83	java/lang/Exception
      //   253	260	83	java/lang/Exception
      //   58	69	165	finally
      //   73	83	165	finally
      //   89	105	165	finally
      //   131	137	165	finally
      //   141	147	165	finally
      //   155	165	165	finally
      //   205	211	165	finally
      //   215	221	165	finally
      //   225	242	165	finally
      //   253	260	165	finally
      //   5	36	188	finally
      //   110	115	188	finally
      //   115	123	188	finally
      //   180	185	188	finally
      //   185	188	188	finally
      //   260	265	188	finally
      //   265	273	188	finally
      //   278	286	188	finally
      //   291	299	188	finally
      //   302	310	188	finally
      //   260	265	276	java/lang/Exception
      //   110	115	289	java/lang/Exception
      //   180	185	313	java/lang/Exception
      //   36	54	318	finally
      //   36	54	326	java/lang/Exception
    }
    
    /* Error */
    private static void save()
    {
      // Byte code:
      //   0: ldc 2
      //   2: monitorenter
      //   3: ldc2_w 164
      //   6: ldc -90
      //   8: invokestatic 21	com/tencent/gmtrace/GMTrace:i	(JI)V
      //   11: new 94	java/io/File
      //   14: dup
      //   15: invokestatic 100	com/tencent/mm/kernel/h:xy	()Lcom/tencent/mm/kernel/e;
      //   18: getfield 106	com/tencent/mm/kernel/e:cachePath	Ljava/lang/String;
      //   21: getstatic 112	com/tencent/mm/plugin/normsg/a/d:nxJ	Lcom/tencent/mm/plugin/normsg/a/d;
      //   24: ldc 114
      //   26: invokevirtual 118	com/tencent/mm/plugin/normsg/a/d:DX	(Ljava/lang/String;)Ljava/lang/String;
      //   29: invokespecial 121	java/io/File:<init>	(Ljava/lang/String;Ljava/lang/String;)V
      //   32: astore_1
      //   33: aload_1
      //   34: invokevirtual 170	java/io/File:exists	()Z
      //   37: ifne +11 -> 48
      //   40: aload_1
      //   41: invokevirtual 174	java/io/File:getParentFile	()Ljava/io/File;
      //   44: invokevirtual 177	java/io/File:mkdirs	()Z
      //   47: pop
      //   48: aconst_null
      //   49: astore_0
      //   50: new 179	java/io/DataOutputStream
      //   53: dup
      //   54: new 181	java/io/FileOutputStream
      //   57: dup
      //   58: aload_1
      //   59: invokespecial 182	java/io/FileOutputStream:<init>	(Ljava/io/File;)V
      //   62: invokespecial 185	java/io/DataOutputStream:<init>	(Ljava/io/OutputStream;)V
      //   65: astore_1
      //   66: aload_1
      //   67: sipush 64762
      //   70: invokevirtual 189	java/io/DataOutputStream:writeShort	(I)V
      //   73: aload_1
      //   74: iconst_1
      //   75: invokevirtual 189	java/io/DataOutputStream:writeShort	(I)V
      //   78: aload_1
      //   79: getstatic 28	com/tencent/mm/plugin/secinforeport/c$a:oEX	Ljava/util/Map;
      //   82: invokeinterface 192 1 0
      //   87: invokevirtual 195	java/io/DataOutputStream:writeInt	(I)V
      //   90: getstatic 28	com/tencent/mm/plugin/secinforeport/c$a:oEX	Ljava/util/Map;
      //   93: invokeinterface 199 1 0
      //   98: invokeinterface 205 1 0
      //   103: astore_0
      //   104: aload_0
      //   105: invokeinterface 210 1 0
      //   110: ifeq +78 -> 188
      //   113: aload_0
      //   114: invokeinterface 214 1 0
      //   119: checkcast 216	java/util/Map$Entry
      //   122: astore_2
      //   123: aload_1
      //   124: aload_2
      //   125: invokeinterface 219 1 0
      //   130: checkcast 55	java/lang/Integer
      //   133: invokevirtual 222	java/lang/Integer:intValue	()I
      //   136: invokevirtual 195	java/io/DataOutputStream:writeInt	(I)V
      //   139: aload_1
      //   140: aload_2
      //   141: invokeinterface 225 1 0
      //   146: checkcast 43	java/lang/Long
      //   149: invokevirtual 80	java/lang/Long:longValue	()J
      //   152: invokevirtual 229	java/io/DataOutputStream:writeLong	(J)V
      //   155: goto -51 -> 104
      //   158: astore_0
      //   159: aload_1
      //   160: astore_0
      //   161: ldc 39
      //   163: ldc -25
      //   165: invokestatic 233	com/tencent/mm/sdk/platformtools/w:e	(Ljava/lang/String;Ljava/lang/String;)V
      //   168: aload_0
      //   169: ifnull +84 -> 253
      //   172: aload_0
      //   173: invokevirtual 234	java/io/DataOutputStream:close	()V
      //   176: ldc2_w 164
      //   179: ldc -90
      //   181: invokestatic 31	com/tencent/gmtrace/GMTrace:o	(JI)V
      //   184: ldc 2
      //   186: monitorexit
      //   187: return
      //   188: ldc 39
      //   190: ldc -20
      //   192: invokestatic 163	com/tencent/mm/sdk/platformtools/w:i	(Ljava/lang/String;Ljava/lang/String;)V
      //   195: aload_1
      //   196: invokevirtual 234	java/io/DataOutputStream:close	()V
      //   199: ldc2_w 164
      //   202: ldc -90
      //   204: invokestatic 31	com/tencent/gmtrace/GMTrace:o	(JI)V
      //   207: goto -23 -> 184
      //   210: astore_0
      //   211: ldc 2
      //   213: monitorexit
      //   214: aload_0
      //   215: athrow
      //   216: astore_0
      //   217: ldc2_w 164
      //   220: ldc -90
      //   222: invokestatic 31	com/tencent/gmtrace/GMTrace:o	(JI)V
      //   225: goto -41 -> 184
      //   228: astore_0
      //   229: ldc2_w 164
      //   232: ldc -90
      //   234: invokestatic 31	com/tencent/gmtrace/GMTrace:o	(JI)V
      //   237: goto -53 -> 184
      //   240: astore_0
      //   241: aconst_null
      //   242: astore_1
      //   243: aload_1
      //   244: ifnull +7 -> 251
      //   247: aload_1
      //   248: invokevirtual 234	java/io/DataOutputStream:close	()V
      //   251: aload_0
      //   252: athrow
      //   253: ldc2_w 164
      //   256: ldc -90
      //   258: invokestatic 31	com/tencent/gmtrace/GMTrace:o	(JI)V
      //   261: goto -77 -> 184
      //   264: astore_1
      //   265: goto -14 -> 251
      //   268: astore_0
      //   269: goto -26 -> 243
      //   272: astore_2
      //   273: aload_0
      //   274: astore_1
      //   275: aload_2
      //   276: astore_0
      //   277: goto -34 -> 243
      //   280: astore_1
      //   281: goto -120 -> 161
      // Local variable table:
      //   start	length	slot	name	signature
      //   49	65	0	localIterator	java.util.Iterator
      //   158	1	0	localException1	Exception
      //   160	13	0	localObject1	Object
      //   210	5	0	localObject2	Object
      //   216	1	0	localException2	Exception
      //   228	1	0	localException3	Exception
      //   240	12	0	localObject3	Object
      //   268	6	0	localObject4	Object
      //   276	1	0	localObject5	Object
      //   32	216	1	localObject6	Object
      //   264	1	1	localException4	Exception
      //   274	1	1	localObject7	Object
      //   280	1	1	localException5	Exception
      //   122	19	2	localEntry	java.util.Map.Entry
      //   272	4	2	localObject8	Object
      // Exception table:
      //   from	to	target	type
      //   66	104	158	java/lang/Exception
      //   104	155	158	java/lang/Exception
      //   188	195	158	java/lang/Exception
      //   3	48	210	finally
      //   172	176	210	finally
      //   176	184	210	finally
      //   195	199	210	finally
      //   199	207	210	finally
      //   217	225	210	finally
      //   229	237	210	finally
      //   247	251	210	finally
      //   251	253	210	finally
      //   253	261	210	finally
      //   195	199	216	java/lang/Exception
      //   172	176	228	java/lang/Exception
      //   50	66	240	finally
      //   247	251	264	java/lang/Exception
      //   66	104	268	finally
      //   104	155	268	finally
      //   188	195	268	finally
      //   161	168	272	finally
      //   50	66	280	java/lang/Exception
    }
  }
}


/* Location:              D:\tools\apktool\weixin6519android1140\jar\classes3-dex2jar.jar!\com\tencent\mm\plugin\secinforeport\c.class
 * Java compiler version: 6 (50.0)
 * JD-Core Version:       0.7.1
 */