package com.tencent.mm.plugin.sns.storage.AdLandingPagesStorage;

import android.os.AsyncTask;
import com.tencent.gmtrace.GMTrace;
import java.util.Collections;
import java.util.HashSet;
import java.util.Set;

public final class b
  extends AsyncTask<String, Void, String>
{
  private static Set<String> pLe;
  private String filePath;
  private boolean pJq;
  private int pJr;
  private a pLf;
  private int scene;
  
  static
  {
    GMTrace.i(8207011414016L, 61147);
    pLe = Collections.synchronizedSet(new HashSet());
    GMTrace.o(8207011414016L, 61147);
  }
  
  public b(String paramString, boolean paramBoolean, int paramInt1, int paramInt2, a parama)
  {
    GMTrace.i(8206340325376L, 61142);
    this.filePath = paramString;
    this.pJq = paramBoolean;
    this.pJr = paramInt1;
    this.scene = paramInt2;
    this.pLf = parama;
    GMTrace.o(8206340325376L, 61142);
  }
  
  private int bjR()
  {
    GMTrace.i(8206608760832L, 61144);
    switch (this.pJr)
    {
    default: 
      GMTrace.o(8206608760832L, 61144);
      return 0;
    case 41: 
      GMTrace.o(8206608760832L, 61144);
      return 1;
    case 44: 
      GMTrace.o(8206608760832L, 61144);
      return 1;
    case 45: 
      GMTrace.o(8206608760832L, 61144);
      return 1;
    case 1000000001: 
      GMTrace.o(8206608760832L, 61144);
      return 1;
    case 61: 
      GMTrace.o(8206608760832L, 61144);
      return 2;
    }
    GMTrace.o(8206608760832L, 61144);
    return 3;
  }
  
  /* Error */
  private String z(String... paramVarArgs)
  {
    // Byte code:
    //   0: ldc2_w 75
    //   3: ldc 77
    //   5: invokestatic 31	com/tencent/gmtrace/GMTrace:i	(JI)V
    //   8: aload_0
    //   9: getfield 55	com/tencent/mm/plugin/sns/storage/AdLandingPagesStorage/b:filePath	Ljava/lang/String;
    //   12: invokestatic 83	com/tencent/mm/modelsfs/FileOp:aZ	(Ljava/lang/String;)Z
    //   15: ifeq +13 -> 28
    //   18: ldc2_w 75
    //   21: ldc 77
    //   23: invokestatic 47	com/tencent/gmtrace/GMTrace:o	(JI)V
    //   26: aconst_null
    //   27: areturn
    //   28: getstatic 44	com/tencent/mm/plugin/sns/storage/AdLandingPagesStorage/b:pLe	Ljava/util/Set;
    //   31: aload_1
    //   32: iconst_0
    //   33: aaload
    //   34: invokeinterface 89 2 0
    //   39: ifeq +14 -> 53
    //   42: ldc2_w 75
    //   45: ldc 77
    //   47: invokestatic 47	com/tencent/gmtrace/GMTrace:o	(JI)V
    //   50: ldc 91
    //   52: areturn
    //   53: invokestatic 97	com/tencent/mm/sdk/platformtools/bg:Pv	()J
    //   56: lstore 6
    //   58: iconst_0
    //   59: istore 4
    //   61: iconst_0
    //   62: istore_3
    //   63: getstatic 44	com/tencent/mm/plugin/sns/storage/AdLandingPagesStorage/b:pLe	Ljava/util/Set;
    //   66: aload_1
    //   67: iconst_0
    //   68: aaload
    //   69: invokeinterface 100 2 0
    //   74: pop
    //   75: aload_0
    //   76: getfield 55	com/tencent/mm/plugin/sns/storage/AdLandingPagesStorage/b:filePath	Ljava/lang/String;
    //   79: iconst_0
    //   80: aload_0
    //   81: getfield 55	com/tencent/mm/plugin/sns/storage/AdLandingPagesStorage/b:filePath	Ljava/lang/String;
    //   84: ldc 102
    //   86: invokevirtual 108	java/lang/String:lastIndexOf	(Ljava/lang/String;)I
    //   89: invokevirtual 112	java/lang/String:substring	(II)Ljava/lang/String;
    //   92: invokestatic 115	com/tencent/mm/modelsfs/FileOp:la	(Ljava/lang/String;)Z
    //   95: pop
    //   96: aconst_null
    //   97: astore 9
    //   99: aconst_null
    //   100: astore 10
    //   102: aload_0
    //   103: getfield 63	com/tencent/mm/plugin/sns/storage/AdLandingPagesStorage/b:pLf	Lcom/tencent/mm/plugin/sns/storage/AdLandingPagesStorage/b$a;
    //   106: invokeinterface 118 1 0
    //   111: new 120	java/net/URL
    //   114: dup
    //   115: aload_1
    //   116: iconst_0
    //   117: aaload
    //   118: invokespecial 123	java/net/URL:<init>	(Ljava/lang/String;)V
    //   121: invokevirtual 127	java/net/URL:openConnection	()Ljava/net/URLConnection;
    //   124: checkcast 129	java/net/HttpURLConnection
    //   127: astore 8
    //   129: aload 8
    //   131: invokevirtual 132	java/net/HttpURLConnection:connect	()V
    //   134: aload 8
    //   136: invokevirtual 135	java/net/HttpURLConnection:getResponseCode	()I
    //   139: istore_2
    //   140: iload_2
    //   141: sipush 200
    //   144: if_icmpeq +371 -> 515
    //   147: aload_0
    //   148: getfield 63	com/tencent/mm/plugin/sns/storage/AdLandingPagesStorage/b:pLf	Lcom/tencent/mm/plugin/sns/storage/AdLandingPagesStorage/b$a;
    //   151: invokeinterface 138 1 0
    //   156: new 140	java/lang/StringBuilder
    //   159: dup
    //   160: ldc -114
    //   162: invokespecial 143	java/lang/StringBuilder:<init>	(Ljava/lang/String;)V
    //   165: aload 8
    //   167: invokevirtual 135	java/net/HttpURLConnection:getResponseCode	()I
    //   170: invokevirtual 147	java/lang/StringBuilder:append	(I)Ljava/lang/StringBuilder;
    //   173: ldc -107
    //   175: invokevirtual 152	java/lang/StringBuilder:append	(Ljava/lang/String;)Ljava/lang/StringBuilder;
    //   178: aload 8
    //   180: invokevirtual 156	java/net/HttpURLConnection:getResponseMessage	()Ljava/lang/String;
    //   183: invokevirtual 152	java/lang/StringBuilder:append	(Ljava/lang/String;)Ljava/lang/StringBuilder;
    //   186: invokevirtual 159	java/lang/StringBuilder:toString	()Ljava/lang/String;
    //   189: astore 11
    //   191: aload 8
    //   193: ifnull +8 -> 201
    //   196: aload 8
    //   198: invokevirtual 162	java/net/HttpURLConnection:disconnect	()V
    //   201: getstatic 44	com/tencent/mm/plugin/sns/storage/AdLandingPagesStorage/b:pLe	Ljava/util/Set;
    //   204: aload_1
    //   205: iconst_0
    //   206: aaload
    //   207: invokeinterface 165 2 0
    //   212: pop
    //   213: aload_1
    //   214: iconst_0
    //   215: aaload
    //   216: invokestatic 171	com/tencent/mm/sdk/platformtools/aa:RP	(Ljava/lang/String;)Ljava/lang/String;
    //   219: astore 8
    //   221: aload_0
    //   222: invokespecial 173	com/tencent/mm/plugin/sns/storage/AdLandingPagesStorage/b:bjR	()I
    //   225: istore_3
    //   226: lload 6
    //   228: invokestatic 177	com/tencent/mm/sdk/platformtools/bg:aH	(J)J
    //   231: l2i
    //   232: istore 4
    //   234: new 179	com/tencent/mm/modelsns/d
    //   237: dup
    //   238: invokespecial 180	com/tencent/mm/modelsns/d:<init>	()V
    //   241: astore_1
    //   242: aload_1
    //   243: ldc -74
    //   245: new 140	java/lang/StringBuilder
    //   248: dup
    //   249: invokespecial 183	java/lang/StringBuilder:<init>	()V
    //   252: aload 8
    //   254: invokevirtual 152	java/lang/StringBuilder:append	(Ljava/lang/String;)Ljava/lang/StringBuilder;
    //   257: ldc -71
    //   259: invokevirtual 152	java/lang/StringBuilder:append	(Ljava/lang/String;)Ljava/lang/StringBuilder;
    //   262: invokevirtual 159	java/lang/StringBuilder:toString	()Ljava/lang/String;
    //   265: invokevirtual 189	com/tencent/mm/modelsns/d:q	(Ljava/lang/String;Ljava/lang/Object;)V
    //   268: aload_1
    //   269: ldc -65
    //   271: new 140	java/lang/StringBuilder
    //   274: dup
    //   275: invokespecial 183	java/lang/StringBuilder:<init>	()V
    //   278: iload_3
    //   279: invokevirtual 147	java/lang/StringBuilder:append	(I)Ljava/lang/StringBuilder;
    //   282: ldc -71
    //   284: invokevirtual 152	java/lang/StringBuilder:append	(Ljava/lang/String;)Ljava/lang/StringBuilder;
    //   287: invokevirtual 159	java/lang/StringBuilder:toString	()Ljava/lang/String;
    //   290: invokevirtual 189	com/tencent/mm/modelsns/d:q	(Ljava/lang/String;Ljava/lang/Object;)V
    //   293: new 140	java/lang/StringBuilder
    //   296: dup
    //   297: invokespecial 183	java/lang/StringBuilder:<init>	()V
    //   300: astore 8
    //   302: aload_0
    //   303: getfield 57	com/tencent/mm/plugin/sns/storage/AdLandingPagesStorage/b:pJq	Z
    //   306: ifeq +204 -> 510
    //   309: iconst_1
    //   310: istore_3
    //   311: aload_1
    //   312: ldc -63
    //   314: aload 8
    //   316: iload_3
    //   317: invokevirtual 147	java/lang/StringBuilder:append	(I)Ljava/lang/StringBuilder;
    //   320: ldc -71
    //   322: invokevirtual 152	java/lang/StringBuilder:append	(Ljava/lang/String;)Ljava/lang/StringBuilder;
    //   325: invokevirtual 159	java/lang/StringBuilder:toString	()Ljava/lang/String;
    //   328: invokevirtual 189	com/tencent/mm/modelsns/d:q	(Ljava/lang/String;Ljava/lang/Object;)V
    //   331: aload_1
    //   332: ldc -61
    //   334: new 140	java/lang/StringBuilder
    //   337: dup
    //   338: invokespecial 183	java/lang/StringBuilder:<init>	()V
    //   341: iload 4
    //   343: invokevirtual 147	java/lang/StringBuilder:append	(I)Ljava/lang/StringBuilder;
    //   346: ldc -71
    //   348: invokevirtual 152	java/lang/StringBuilder:append	(Ljava/lang/String;)Ljava/lang/StringBuilder;
    //   351: invokevirtual 159	java/lang/StringBuilder:toString	()Ljava/lang/String;
    //   354: invokevirtual 189	com/tencent/mm/modelsns/d:q	(Ljava/lang/String;Ljava/lang/Object;)V
    //   357: aload_1
    //   358: ldc -59
    //   360: new 140	java/lang/StringBuilder
    //   363: dup
    //   364: invokespecial 183	java/lang/StringBuilder:<init>	()V
    //   367: iload_2
    //   368: invokevirtual 147	java/lang/StringBuilder:append	(I)Ljava/lang/StringBuilder;
    //   371: ldc -71
    //   373: invokevirtual 152	java/lang/StringBuilder:append	(Ljava/lang/String;)Ljava/lang/StringBuilder;
    //   376: invokevirtual 159	java/lang/StringBuilder:toString	()Ljava/lang/String;
    //   379: invokevirtual 189	com/tencent/mm/modelsns/d:q	(Ljava/lang/String;Ljava/lang/Object;)V
    //   382: aload_1
    //   383: ldc -57
    //   385: new 140	java/lang/StringBuilder
    //   388: dup
    //   389: invokespecial 183	java/lang/StringBuilder:<init>	()V
    //   392: aload_0
    //   393: getfield 61	com/tencent/mm/plugin/sns/storage/AdLandingPagesStorage/b:scene	I
    //   396: invokevirtual 147	java/lang/StringBuilder:append	(I)Ljava/lang/StringBuilder;
    //   399: ldc -71
    //   401: invokevirtual 152	java/lang/StringBuilder:append	(Ljava/lang/String;)Ljava/lang/StringBuilder;
    //   404: invokevirtual 159	java/lang/StringBuilder:toString	()Ljava/lang/String;
    //   407: invokevirtual 189	com/tencent/mm/modelsns/d:q	(Ljava/lang/String;Ljava/lang/Object;)V
    //   410: aload_1
    //   411: ldc -55
    //   413: new 140	java/lang/StringBuilder
    //   416: dup
    //   417: ldc -53
    //   419: invokespecial 143	java/lang/StringBuilder:<init>	(Ljava/lang/String;)V
    //   422: invokevirtual 159	java/lang/StringBuilder:toString	()Ljava/lang/String;
    //   425: invokevirtual 189	com/tencent/mm/modelsns/d:q	(Ljava/lang/String;Ljava/lang/Object;)V
    //   428: aload_1
    //   429: ldc -51
    //   431: new 140	java/lang/StringBuilder
    //   434: dup
    //   435: invokespecial 183	java/lang/StringBuilder:<init>	()V
    //   438: lload 6
    //   440: ldc2_w 206
    //   443: ldiv
    //   444: invokevirtual 210	java/lang/StringBuilder:append	(J)Ljava/lang/StringBuilder;
    //   447: ldc -71
    //   449: invokevirtual 152	java/lang/StringBuilder:append	(Ljava/lang/String;)Ljava/lang/StringBuilder;
    //   452: invokevirtual 159	java/lang/StringBuilder:toString	()Ljava/lang/String;
    //   455: invokevirtual 189	com/tencent/mm/modelsns/d:q	(Ljava/lang/String;Ljava/lang/Object;)V
    //   458: ldc -44
    //   460: new 140	java/lang/StringBuilder
    //   463: dup
    //   464: ldc -42
    //   466: invokespecial 143	java/lang/StringBuilder:<init>	(Ljava/lang/String;)V
    //   469: aload_1
    //   470: invokevirtual 217	com/tencent/mm/modelsns/d:LT	()Ljava/lang/String;
    //   473: invokevirtual 152	java/lang/StringBuilder:append	(Ljava/lang/String;)Ljava/lang/StringBuilder;
    //   476: invokevirtual 159	java/lang/StringBuilder:toString	()Ljava/lang/String;
    //   479: invokestatic 222	com/tencent/mm/sdk/platformtools/w:i	(Ljava/lang/String;Ljava/lang/String;)V
    //   482: getstatic 228	com/tencent/mm/plugin/report/service/g:ork	Lcom/tencent/mm/plugin/report/service/g;
    //   485: sipush 13572
    //   488: iconst_1
    //   489: anewarray 230	java/lang/Object
    //   492: dup
    //   493: iconst_0
    //   494: aload_1
    //   495: aastore
    //   496: invokevirtual 233	com/tencent/mm/plugin/report/service/g:i	(I[Ljava/lang/Object;)V
    //   499: ldc2_w 75
    //   502: ldc 77
    //   504: invokestatic 47	com/tencent/gmtrace/GMTrace:o	(JI)V
    //   507: aload 11
    //   509: areturn
    //   510: iconst_0
    //   511: istore_3
    //   512: goto -201 -> 311
    //   515: aload 8
    //   517: invokevirtual 236	java/net/HttpURLConnection:getContentLength	()I
    //   520: pop
    //   521: aload 8
    //   523: invokevirtual 240	java/net/HttpURLConnection:getInputStream	()Ljava/io/InputStream;
    //   526: astore 11
    //   528: new 242	java/io/FileOutputStream
    //   531: dup
    //   532: aload_0
    //   533: getfield 55	com/tencent/mm/plugin/sns/storage/AdLandingPagesStorage/b:filePath	Ljava/lang/String;
    //   536: invokespecial 243	java/io/FileOutputStream:<init>	(Ljava/lang/String;)V
    //   539: astore 9
    //   541: sipush 4096
    //   544: newarray <illegal type>
    //   546: astore 10
    //   548: iconst_0
    //   549: istore_3
    //   550: aload 11
    //   552: aload 10
    //   554: invokevirtual 249	java/io/InputStream:read	([B)I
    //   557: istore 4
    //   559: iload 4
    //   561: iconst_m1
    //   562: if_icmpeq +383 -> 945
    //   565: aload_0
    //   566: invokevirtual 253	com/tencent/mm/plugin/sns/storage/AdLandingPagesStorage/b:isCancelled	()Z
    //   569: ifeq +358 -> 927
    //   572: aload 11
    //   574: invokevirtual 256	java/io/InputStream:close	()V
    //   577: aload 9
    //   579: invokevirtual 259	java/io/OutputStream:close	()V
    //   582: aload 11
    //   584: ifnull +8 -> 592
    //   587: aload 11
    //   589: invokevirtual 256	java/io/InputStream:close	()V
    //   592: aload 8
    //   594: ifnull +8 -> 602
    //   597: aload 8
    //   599: invokevirtual 162	java/net/HttpURLConnection:disconnect	()V
    //   602: getstatic 44	com/tencent/mm/plugin/sns/storage/AdLandingPagesStorage/b:pLe	Ljava/util/Set;
    //   605: aload_1
    //   606: iconst_0
    //   607: aaload
    //   608: invokeinterface 165 2 0
    //   613: pop
    //   614: aload_1
    //   615: iconst_0
    //   616: aaload
    //   617: invokestatic 171	com/tencent/mm/sdk/platformtools/aa:RP	(Ljava/lang/String;)Ljava/lang/String;
    //   620: astore 8
    //   622: aload_0
    //   623: invokespecial 173	com/tencent/mm/plugin/sns/storage/AdLandingPagesStorage/b:bjR	()I
    //   626: istore 4
    //   628: lload 6
    //   630: invokestatic 177	com/tencent/mm/sdk/platformtools/bg:aH	(J)J
    //   633: l2i
    //   634: istore 5
    //   636: new 179	com/tencent/mm/modelsns/d
    //   639: dup
    //   640: invokespecial 180	com/tencent/mm/modelsns/d:<init>	()V
    //   643: astore_1
    //   644: aload_1
    //   645: ldc -74
    //   647: new 140	java/lang/StringBuilder
    //   650: dup
    //   651: invokespecial 183	java/lang/StringBuilder:<init>	()V
    //   654: aload 8
    //   656: invokevirtual 152	java/lang/StringBuilder:append	(Ljava/lang/String;)Ljava/lang/StringBuilder;
    //   659: ldc -71
    //   661: invokevirtual 152	java/lang/StringBuilder:append	(Ljava/lang/String;)Ljava/lang/StringBuilder;
    //   664: invokevirtual 159	java/lang/StringBuilder:toString	()Ljava/lang/String;
    //   667: invokevirtual 189	com/tencent/mm/modelsns/d:q	(Ljava/lang/String;Ljava/lang/Object;)V
    //   670: aload_1
    //   671: ldc -65
    //   673: new 140	java/lang/StringBuilder
    //   676: dup
    //   677: invokespecial 183	java/lang/StringBuilder:<init>	()V
    //   680: iload 4
    //   682: invokevirtual 147	java/lang/StringBuilder:append	(I)Ljava/lang/StringBuilder;
    //   685: ldc -71
    //   687: invokevirtual 152	java/lang/StringBuilder:append	(Ljava/lang/String;)Ljava/lang/StringBuilder;
    //   690: invokevirtual 159	java/lang/StringBuilder:toString	()Ljava/lang/String;
    //   693: invokevirtual 189	com/tencent/mm/modelsns/d:q	(Ljava/lang/String;Ljava/lang/Object;)V
    //   696: new 140	java/lang/StringBuilder
    //   699: dup
    //   700: invokespecial 183	java/lang/StringBuilder:<init>	()V
    //   703: astore 8
    //   705: aload_0
    //   706: getfield 57	com/tencent/mm/plugin/sns/storage/AdLandingPagesStorage/b:pJq	Z
    //   709: ifeq +212 -> 921
    //   712: iconst_1
    //   713: istore 4
    //   715: aload_1
    //   716: ldc -63
    //   718: aload 8
    //   720: iload 4
    //   722: invokevirtual 147	java/lang/StringBuilder:append	(I)Ljava/lang/StringBuilder;
    //   725: ldc -71
    //   727: invokevirtual 152	java/lang/StringBuilder:append	(Ljava/lang/String;)Ljava/lang/StringBuilder;
    //   730: invokevirtual 159	java/lang/StringBuilder:toString	()Ljava/lang/String;
    //   733: invokevirtual 189	com/tencent/mm/modelsns/d:q	(Ljava/lang/String;Ljava/lang/Object;)V
    //   736: aload_1
    //   737: ldc -61
    //   739: new 140	java/lang/StringBuilder
    //   742: dup
    //   743: invokespecial 183	java/lang/StringBuilder:<init>	()V
    //   746: iload 5
    //   748: invokevirtual 147	java/lang/StringBuilder:append	(I)Ljava/lang/StringBuilder;
    //   751: ldc -71
    //   753: invokevirtual 152	java/lang/StringBuilder:append	(Ljava/lang/String;)Ljava/lang/StringBuilder;
    //   756: invokevirtual 159	java/lang/StringBuilder:toString	()Ljava/lang/String;
    //   759: invokevirtual 189	com/tencent/mm/modelsns/d:q	(Ljava/lang/String;Ljava/lang/Object;)V
    //   762: aload_1
    //   763: ldc -59
    //   765: new 140	java/lang/StringBuilder
    //   768: dup
    //   769: invokespecial 183	java/lang/StringBuilder:<init>	()V
    //   772: iload_2
    //   773: invokevirtual 147	java/lang/StringBuilder:append	(I)Ljava/lang/StringBuilder;
    //   776: ldc -71
    //   778: invokevirtual 152	java/lang/StringBuilder:append	(Ljava/lang/String;)Ljava/lang/StringBuilder;
    //   781: invokevirtual 159	java/lang/StringBuilder:toString	()Ljava/lang/String;
    //   784: invokevirtual 189	com/tencent/mm/modelsns/d:q	(Ljava/lang/String;Ljava/lang/Object;)V
    //   787: aload_1
    //   788: ldc -57
    //   790: new 140	java/lang/StringBuilder
    //   793: dup
    //   794: invokespecial 183	java/lang/StringBuilder:<init>	()V
    //   797: aload_0
    //   798: getfield 61	com/tencent/mm/plugin/sns/storage/AdLandingPagesStorage/b:scene	I
    //   801: invokevirtual 147	java/lang/StringBuilder:append	(I)Ljava/lang/StringBuilder;
    //   804: ldc -71
    //   806: invokevirtual 152	java/lang/StringBuilder:append	(Ljava/lang/String;)Ljava/lang/StringBuilder;
    //   809: invokevirtual 159	java/lang/StringBuilder:toString	()Ljava/lang/String;
    //   812: invokevirtual 189	com/tencent/mm/modelsns/d:q	(Ljava/lang/String;Ljava/lang/Object;)V
    //   815: aload_1
    //   816: ldc -55
    //   818: new 140	java/lang/StringBuilder
    //   821: dup
    //   822: invokespecial 183	java/lang/StringBuilder:<init>	()V
    //   825: iload_3
    //   826: invokevirtual 147	java/lang/StringBuilder:append	(I)Ljava/lang/StringBuilder;
    //   829: ldc -71
    //   831: invokevirtual 152	java/lang/StringBuilder:append	(Ljava/lang/String;)Ljava/lang/StringBuilder;
    //   834: invokevirtual 159	java/lang/StringBuilder:toString	()Ljava/lang/String;
    //   837: invokevirtual 189	com/tencent/mm/modelsns/d:q	(Ljava/lang/String;Ljava/lang/Object;)V
    //   840: aload_1
    //   841: ldc -51
    //   843: new 140	java/lang/StringBuilder
    //   846: dup
    //   847: invokespecial 183	java/lang/StringBuilder:<init>	()V
    //   850: lload 6
    //   852: ldc2_w 206
    //   855: ldiv
    //   856: invokevirtual 210	java/lang/StringBuilder:append	(J)Ljava/lang/StringBuilder;
    //   859: ldc -71
    //   861: invokevirtual 152	java/lang/StringBuilder:append	(Ljava/lang/String;)Ljava/lang/StringBuilder;
    //   864: invokevirtual 159	java/lang/StringBuilder:toString	()Ljava/lang/String;
    //   867: invokevirtual 189	com/tencent/mm/modelsns/d:q	(Ljava/lang/String;Ljava/lang/Object;)V
    //   870: ldc -44
    //   872: new 140	java/lang/StringBuilder
    //   875: dup
    //   876: ldc -42
    //   878: invokespecial 143	java/lang/StringBuilder:<init>	(Ljava/lang/String;)V
    //   881: aload_1
    //   882: invokevirtual 217	com/tencent/mm/modelsns/d:LT	()Ljava/lang/String;
    //   885: invokevirtual 152	java/lang/StringBuilder:append	(Ljava/lang/String;)Ljava/lang/StringBuilder;
    //   888: invokevirtual 159	java/lang/StringBuilder:toString	()Ljava/lang/String;
    //   891: invokestatic 222	com/tencent/mm/sdk/platformtools/w:i	(Ljava/lang/String;Ljava/lang/String;)V
    //   894: getstatic 228	com/tencent/mm/plugin/report/service/g:ork	Lcom/tencent/mm/plugin/report/service/g;
    //   897: sipush 13572
    //   900: iconst_1
    //   901: anewarray 230	java/lang/Object
    //   904: dup
    //   905: iconst_0
    //   906: aload_1
    //   907: aastore
    //   908: invokevirtual 233	com/tencent/mm/plugin/report/service/g:i	(I[Ljava/lang/Object;)V
    //   911: ldc2_w 75
    //   914: ldc 77
    //   916: invokestatic 47	com/tencent/gmtrace/GMTrace:o	(JI)V
    //   919: aconst_null
    //   920: areturn
    //   921: iconst_0
    //   922: istore 4
    //   924: goto -209 -> 715
    //   927: aload 9
    //   929: aload 10
    //   931: iconst_0
    //   932: iload 4
    //   934: invokevirtual 263	java/io/OutputStream:write	([BII)V
    //   937: iload_3
    //   938: iload 4
    //   940: iadd
    //   941: istore_3
    //   942: goto -392 -> 550
    //   945: aload 9
    //   947: invokevirtual 259	java/io/OutputStream:close	()V
    //   950: aload 11
    //   952: ifnull +8 -> 960
    //   955: aload 11
    //   957: invokevirtual 256	java/io/InputStream:close	()V
    //   960: aload 8
    //   962: ifnull +8 -> 970
    //   965: aload 8
    //   967: invokevirtual 162	java/net/HttpURLConnection:disconnect	()V
    //   970: getstatic 44	com/tencent/mm/plugin/sns/storage/AdLandingPagesStorage/b:pLe	Ljava/util/Set;
    //   973: aload_1
    //   974: iconst_0
    //   975: aaload
    //   976: invokeinterface 165 2 0
    //   981: pop
    //   982: aload_1
    //   983: iconst_0
    //   984: aaload
    //   985: invokestatic 171	com/tencent/mm/sdk/platformtools/aa:RP	(Ljava/lang/String;)Ljava/lang/String;
    //   988: astore 8
    //   990: aload_0
    //   991: invokespecial 173	com/tencent/mm/plugin/sns/storage/AdLandingPagesStorage/b:bjR	()I
    //   994: istore 4
    //   996: lload 6
    //   998: invokestatic 177	com/tencent/mm/sdk/platformtools/bg:aH	(J)J
    //   1001: l2i
    //   1002: istore 5
    //   1004: new 179	com/tencent/mm/modelsns/d
    //   1007: dup
    //   1008: invokespecial 180	com/tencent/mm/modelsns/d:<init>	()V
    //   1011: astore_1
    //   1012: aload_1
    //   1013: ldc -74
    //   1015: new 140	java/lang/StringBuilder
    //   1018: dup
    //   1019: invokespecial 183	java/lang/StringBuilder:<init>	()V
    //   1022: aload 8
    //   1024: invokevirtual 152	java/lang/StringBuilder:append	(Ljava/lang/String;)Ljava/lang/StringBuilder;
    //   1027: ldc -71
    //   1029: invokevirtual 152	java/lang/StringBuilder:append	(Ljava/lang/String;)Ljava/lang/StringBuilder;
    //   1032: invokevirtual 159	java/lang/StringBuilder:toString	()Ljava/lang/String;
    //   1035: invokevirtual 189	com/tencent/mm/modelsns/d:q	(Ljava/lang/String;Ljava/lang/Object;)V
    //   1038: aload_1
    //   1039: ldc -65
    //   1041: new 140	java/lang/StringBuilder
    //   1044: dup
    //   1045: invokespecial 183	java/lang/StringBuilder:<init>	()V
    //   1048: iload 4
    //   1050: invokevirtual 147	java/lang/StringBuilder:append	(I)Ljava/lang/StringBuilder;
    //   1053: ldc -71
    //   1055: invokevirtual 152	java/lang/StringBuilder:append	(Ljava/lang/String;)Ljava/lang/StringBuilder;
    //   1058: invokevirtual 159	java/lang/StringBuilder:toString	()Ljava/lang/String;
    //   1061: invokevirtual 189	com/tencent/mm/modelsns/d:q	(Ljava/lang/String;Ljava/lang/Object;)V
    //   1064: new 140	java/lang/StringBuilder
    //   1067: dup
    //   1068: invokespecial 183	java/lang/StringBuilder:<init>	()V
    //   1071: astore 8
    //   1073: aload_0
    //   1074: getfield 57	com/tencent/mm/plugin/sns/storage/AdLandingPagesStorage/b:pJq	Z
    //   1077: ifeq +212 -> 1289
    //   1080: iconst_1
    //   1081: istore 4
    //   1083: aload_1
    //   1084: ldc -63
    //   1086: aload 8
    //   1088: iload 4
    //   1090: invokevirtual 147	java/lang/StringBuilder:append	(I)Ljava/lang/StringBuilder;
    //   1093: ldc -71
    //   1095: invokevirtual 152	java/lang/StringBuilder:append	(Ljava/lang/String;)Ljava/lang/StringBuilder;
    //   1098: invokevirtual 159	java/lang/StringBuilder:toString	()Ljava/lang/String;
    //   1101: invokevirtual 189	com/tencent/mm/modelsns/d:q	(Ljava/lang/String;Ljava/lang/Object;)V
    //   1104: aload_1
    //   1105: ldc -61
    //   1107: new 140	java/lang/StringBuilder
    //   1110: dup
    //   1111: invokespecial 183	java/lang/StringBuilder:<init>	()V
    //   1114: iload 5
    //   1116: invokevirtual 147	java/lang/StringBuilder:append	(I)Ljava/lang/StringBuilder;
    //   1119: ldc -71
    //   1121: invokevirtual 152	java/lang/StringBuilder:append	(Ljava/lang/String;)Ljava/lang/StringBuilder;
    //   1124: invokevirtual 159	java/lang/StringBuilder:toString	()Ljava/lang/String;
    //   1127: invokevirtual 189	com/tencent/mm/modelsns/d:q	(Ljava/lang/String;Ljava/lang/Object;)V
    //   1130: aload_1
    //   1131: ldc -59
    //   1133: new 140	java/lang/StringBuilder
    //   1136: dup
    //   1137: invokespecial 183	java/lang/StringBuilder:<init>	()V
    //   1140: iload_2
    //   1141: invokevirtual 147	java/lang/StringBuilder:append	(I)Ljava/lang/StringBuilder;
    //   1144: ldc -71
    //   1146: invokevirtual 152	java/lang/StringBuilder:append	(Ljava/lang/String;)Ljava/lang/StringBuilder;
    //   1149: invokevirtual 159	java/lang/StringBuilder:toString	()Ljava/lang/String;
    //   1152: invokevirtual 189	com/tencent/mm/modelsns/d:q	(Ljava/lang/String;Ljava/lang/Object;)V
    //   1155: aload_1
    //   1156: ldc -57
    //   1158: new 140	java/lang/StringBuilder
    //   1161: dup
    //   1162: invokespecial 183	java/lang/StringBuilder:<init>	()V
    //   1165: aload_0
    //   1166: getfield 61	com/tencent/mm/plugin/sns/storage/AdLandingPagesStorage/b:scene	I
    //   1169: invokevirtual 147	java/lang/StringBuilder:append	(I)Ljava/lang/StringBuilder;
    //   1172: ldc -71
    //   1174: invokevirtual 152	java/lang/StringBuilder:append	(Ljava/lang/String;)Ljava/lang/StringBuilder;
    //   1177: invokevirtual 159	java/lang/StringBuilder:toString	()Ljava/lang/String;
    //   1180: invokevirtual 189	com/tencent/mm/modelsns/d:q	(Ljava/lang/String;Ljava/lang/Object;)V
    //   1183: aload_1
    //   1184: ldc -55
    //   1186: new 140	java/lang/StringBuilder
    //   1189: dup
    //   1190: invokespecial 183	java/lang/StringBuilder:<init>	()V
    //   1193: iload_3
    //   1194: invokevirtual 147	java/lang/StringBuilder:append	(I)Ljava/lang/StringBuilder;
    //   1197: ldc -71
    //   1199: invokevirtual 152	java/lang/StringBuilder:append	(Ljava/lang/String;)Ljava/lang/StringBuilder;
    //   1202: invokevirtual 159	java/lang/StringBuilder:toString	()Ljava/lang/String;
    //   1205: invokevirtual 189	com/tencent/mm/modelsns/d:q	(Ljava/lang/String;Ljava/lang/Object;)V
    //   1208: aload_1
    //   1209: ldc -51
    //   1211: new 140	java/lang/StringBuilder
    //   1214: dup
    //   1215: invokespecial 183	java/lang/StringBuilder:<init>	()V
    //   1218: lload 6
    //   1220: ldc2_w 206
    //   1223: ldiv
    //   1224: invokevirtual 210	java/lang/StringBuilder:append	(J)Ljava/lang/StringBuilder;
    //   1227: ldc -71
    //   1229: invokevirtual 152	java/lang/StringBuilder:append	(Ljava/lang/String;)Ljava/lang/StringBuilder;
    //   1232: invokevirtual 159	java/lang/StringBuilder:toString	()Ljava/lang/String;
    //   1235: invokevirtual 189	com/tencent/mm/modelsns/d:q	(Ljava/lang/String;Ljava/lang/Object;)V
    //   1238: ldc -44
    //   1240: new 140	java/lang/StringBuilder
    //   1243: dup
    //   1244: ldc -42
    //   1246: invokespecial 143	java/lang/StringBuilder:<init>	(Ljava/lang/String;)V
    //   1249: aload_1
    //   1250: invokevirtual 217	com/tencent/mm/modelsns/d:LT	()Ljava/lang/String;
    //   1253: invokevirtual 152	java/lang/StringBuilder:append	(Ljava/lang/String;)Ljava/lang/StringBuilder;
    //   1256: invokevirtual 159	java/lang/StringBuilder:toString	()Ljava/lang/String;
    //   1259: invokestatic 222	com/tencent/mm/sdk/platformtools/w:i	(Ljava/lang/String;Ljava/lang/String;)V
    //   1262: getstatic 228	com/tencent/mm/plugin/report/service/g:ork	Lcom/tencent/mm/plugin/report/service/g;
    //   1265: sipush 13572
    //   1268: iconst_1
    //   1269: anewarray 230	java/lang/Object
    //   1272: dup
    //   1273: iconst_0
    //   1274: aload_1
    //   1275: aastore
    //   1276: invokevirtual 233	com/tencent/mm/plugin/report/service/g:i	(I[Ljava/lang/Object;)V
    //   1279: ldc2_w 75
    //   1282: ldc 77
    //   1284: invokestatic 47	com/tencent/gmtrace/GMTrace:o	(JI)V
    //   1287: aconst_null
    //   1288: areturn
    //   1289: iconst_0
    //   1290: istore 4
    //   1292: goto -209 -> 1083
    //   1295: astore 10
    //   1297: iconst_0
    //   1298: istore_2
    //   1299: aconst_null
    //   1300: astore 11
    //   1302: aconst_null
    //   1303: astore 9
    //   1305: aconst_null
    //   1306: astore 8
    //   1308: aload_0
    //   1309: getfield 63	com/tencent/mm/plugin/sns/storage/AdLandingPagesStorage/b:pLf	Lcom/tencent/mm/plugin/sns/storage/AdLandingPagesStorage/b$a;
    //   1312: invokeinterface 138 1 0
    //   1317: aload_0
    //   1318: getfield 55	com/tencent/mm/plugin/sns/storage/AdLandingPagesStorage/b:filePath	Ljava/lang/String;
    //   1321: invokestatic 266	com/tencent/mm/modelsfs/FileOp:deleteFile	(Ljava/lang/String;)Z
    //   1324: pop
    //   1325: iconst_m1
    //   1326: istore_2
    //   1327: aload 10
    //   1329: invokevirtual 267	java/lang/Exception:toString	()Ljava/lang/String;
    //   1332: astore 10
    //   1334: aload 9
    //   1336: ifnull +8 -> 1344
    //   1339: aload 9
    //   1341: invokevirtual 259	java/io/OutputStream:close	()V
    //   1344: aload 11
    //   1346: ifnull +8 -> 1354
    //   1349: aload 11
    //   1351: invokevirtual 256	java/io/InputStream:close	()V
    //   1354: aload 8
    //   1356: ifnull +8 -> 1364
    //   1359: aload 8
    //   1361: invokevirtual 162	java/net/HttpURLConnection:disconnect	()V
    //   1364: getstatic 44	com/tencent/mm/plugin/sns/storage/AdLandingPagesStorage/b:pLe	Ljava/util/Set;
    //   1367: aload_1
    //   1368: iconst_0
    //   1369: aaload
    //   1370: invokeinterface 165 2 0
    //   1375: pop
    //   1376: aload_1
    //   1377: iconst_0
    //   1378: aaload
    //   1379: invokestatic 171	com/tencent/mm/sdk/platformtools/aa:RP	(Ljava/lang/String;)Ljava/lang/String;
    //   1382: astore 8
    //   1384: aload_0
    //   1385: invokespecial 173	com/tencent/mm/plugin/sns/storage/AdLandingPagesStorage/b:bjR	()I
    //   1388: istore_2
    //   1389: lload 6
    //   1391: invokestatic 177	com/tencent/mm/sdk/platformtools/bg:aH	(J)J
    //   1394: l2i
    //   1395: istore 4
    //   1397: new 179	com/tencent/mm/modelsns/d
    //   1400: dup
    //   1401: invokespecial 180	com/tencent/mm/modelsns/d:<init>	()V
    //   1404: astore_1
    //   1405: aload_1
    //   1406: ldc -74
    //   1408: new 140	java/lang/StringBuilder
    //   1411: dup
    //   1412: invokespecial 183	java/lang/StringBuilder:<init>	()V
    //   1415: aload 8
    //   1417: invokevirtual 152	java/lang/StringBuilder:append	(Ljava/lang/String;)Ljava/lang/StringBuilder;
    //   1420: ldc -71
    //   1422: invokevirtual 152	java/lang/StringBuilder:append	(Ljava/lang/String;)Ljava/lang/StringBuilder;
    //   1425: invokevirtual 159	java/lang/StringBuilder:toString	()Ljava/lang/String;
    //   1428: invokevirtual 189	com/tencent/mm/modelsns/d:q	(Ljava/lang/String;Ljava/lang/Object;)V
    //   1431: aload_1
    //   1432: ldc -65
    //   1434: new 140	java/lang/StringBuilder
    //   1437: dup
    //   1438: invokespecial 183	java/lang/StringBuilder:<init>	()V
    //   1441: iload_2
    //   1442: invokevirtual 147	java/lang/StringBuilder:append	(I)Ljava/lang/StringBuilder;
    //   1445: ldc -71
    //   1447: invokevirtual 152	java/lang/StringBuilder:append	(Ljava/lang/String;)Ljava/lang/StringBuilder;
    //   1450: invokevirtual 159	java/lang/StringBuilder:toString	()Ljava/lang/String;
    //   1453: invokevirtual 189	com/tencent/mm/modelsns/d:q	(Ljava/lang/String;Ljava/lang/Object;)V
    //   1456: new 140	java/lang/StringBuilder
    //   1459: dup
    //   1460: invokespecial 183	java/lang/StringBuilder:<init>	()V
    //   1463: astore 8
    //   1465: aload_0
    //   1466: getfield 57	com/tencent/mm/plugin/sns/storage/AdLandingPagesStorage/b:pJq	Z
    //   1469: ifeq +205 -> 1674
    //   1472: iconst_1
    //   1473: istore_2
    //   1474: aload_1
    //   1475: ldc -63
    //   1477: aload 8
    //   1479: iload_2
    //   1480: invokevirtual 147	java/lang/StringBuilder:append	(I)Ljava/lang/StringBuilder;
    //   1483: ldc -71
    //   1485: invokevirtual 152	java/lang/StringBuilder:append	(Ljava/lang/String;)Ljava/lang/StringBuilder;
    //   1488: invokevirtual 159	java/lang/StringBuilder:toString	()Ljava/lang/String;
    //   1491: invokevirtual 189	com/tencent/mm/modelsns/d:q	(Ljava/lang/String;Ljava/lang/Object;)V
    //   1494: aload_1
    //   1495: ldc -61
    //   1497: new 140	java/lang/StringBuilder
    //   1500: dup
    //   1501: invokespecial 183	java/lang/StringBuilder:<init>	()V
    //   1504: iload 4
    //   1506: invokevirtual 147	java/lang/StringBuilder:append	(I)Ljava/lang/StringBuilder;
    //   1509: ldc -71
    //   1511: invokevirtual 152	java/lang/StringBuilder:append	(Ljava/lang/String;)Ljava/lang/StringBuilder;
    //   1514: invokevirtual 159	java/lang/StringBuilder:toString	()Ljava/lang/String;
    //   1517: invokevirtual 189	com/tencent/mm/modelsns/d:q	(Ljava/lang/String;Ljava/lang/Object;)V
    //   1520: aload_1
    //   1521: ldc -59
    //   1523: new 140	java/lang/StringBuilder
    //   1526: dup
    //   1527: ldc_w 269
    //   1530: invokespecial 143	java/lang/StringBuilder:<init>	(Ljava/lang/String;)V
    //   1533: invokevirtual 159	java/lang/StringBuilder:toString	()Ljava/lang/String;
    //   1536: invokevirtual 189	com/tencent/mm/modelsns/d:q	(Ljava/lang/String;Ljava/lang/Object;)V
    //   1539: aload_1
    //   1540: ldc -57
    //   1542: new 140	java/lang/StringBuilder
    //   1545: dup
    //   1546: invokespecial 183	java/lang/StringBuilder:<init>	()V
    //   1549: aload_0
    //   1550: getfield 61	com/tencent/mm/plugin/sns/storage/AdLandingPagesStorage/b:scene	I
    //   1553: invokevirtual 147	java/lang/StringBuilder:append	(I)Ljava/lang/StringBuilder;
    //   1556: ldc -71
    //   1558: invokevirtual 152	java/lang/StringBuilder:append	(Ljava/lang/String;)Ljava/lang/StringBuilder;
    //   1561: invokevirtual 159	java/lang/StringBuilder:toString	()Ljava/lang/String;
    //   1564: invokevirtual 189	com/tencent/mm/modelsns/d:q	(Ljava/lang/String;Ljava/lang/Object;)V
    //   1567: aload_1
    //   1568: ldc -55
    //   1570: new 140	java/lang/StringBuilder
    //   1573: dup
    //   1574: invokespecial 183	java/lang/StringBuilder:<init>	()V
    //   1577: iload_3
    //   1578: invokevirtual 147	java/lang/StringBuilder:append	(I)Ljava/lang/StringBuilder;
    //   1581: ldc -71
    //   1583: invokevirtual 152	java/lang/StringBuilder:append	(Ljava/lang/String;)Ljava/lang/StringBuilder;
    //   1586: invokevirtual 159	java/lang/StringBuilder:toString	()Ljava/lang/String;
    //   1589: invokevirtual 189	com/tencent/mm/modelsns/d:q	(Ljava/lang/String;Ljava/lang/Object;)V
    //   1592: aload_1
    //   1593: ldc -51
    //   1595: new 140	java/lang/StringBuilder
    //   1598: dup
    //   1599: invokespecial 183	java/lang/StringBuilder:<init>	()V
    //   1602: lload 6
    //   1604: ldc2_w 206
    //   1607: ldiv
    //   1608: invokevirtual 210	java/lang/StringBuilder:append	(J)Ljava/lang/StringBuilder;
    //   1611: ldc -71
    //   1613: invokevirtual 152	java/lang/StringBuilder:append	(Ljava/lang/String;)Ljava/lang/StringBuilder;
    //   1616: invokevirtual 159	java/lang/StringBuilder:toString	()Ljava/lang/String;
    //   1619: invokevirtual 189	com/tencent/mm/modelsns/d:q	(Ljava/lang/String;Ljava/lang/Object;)V
    //   1622: ldc -44
    //   1624: new 140	java/lang/StringBuilder
    //   1627: dup
    //   1628: ldc -42
    //   1630: invokespecial 143	java/lang/StringBuilder:<init>	(Ljava/lang/String;)V
    //   1633: aload_1
    //   1634: invokevirtual 217	com/tencent/mm/modelsns/d:LT	()Ljava/lang/String;
    //   1637: invokevirtual 152	java/lang/StringBuilder:append	(Ljava/lang/String;)Ljava/lang/StringBuilder;
    //   1640: invokevirtual 159	java/lang/StringBuilder:toString	()Ljava/lang/String;
    //   1643: invokestatic 222	com/tencent/mm/sdk/platformtools/w:i	(Ljava/lang/String;Ljava/lang/String;)V
    //   1646: getstatic 228	com/tencent/mm/plugin/report/service/g:ork	Lcom/tencent/mm/plugin/report/service/g;
    //   1649: sipush 13572
    //   1652: iconst_1
    //   1653: anewarray 230	java/lang/Object
    //   1656: dup
    //   1657: iconst_0
    //   1658: aload_1
    //   1659: aastore
    //   1660: invokevirtual 233	com/tencent/mm/plugin/report/service/g:i	(I[Ljava/lang/Object;)V
    //   1663: ldc2_w 75
    //   1666: ldc 77
    //   1668: invokestatic 47	com/tencent/gmtrace/GMTrace:o	(JI)V
    //   1671: aload 10
    //   1673: areturn
    //   1674: iconst_0
    //   1675: istore_2
    //   1676: goto -202 -> 1474
    //   1679: astore 8
    //   1681: iconst_0
    //   1682: istore_2
    //   1683: aconst_null
    //   1684: astore 11
    //   1686: iload 4
    //   1688: istore_3
    //   1689: aload 10
    //   1691: ifnull +8 -> 1699
    //   1694: aload 10
    //   1696: invokevirtual 259	java/io/OutputStream:close	()V
    //   1699: aload 9
    //   1701: ifnull +8 -> 1709
    //   1704: aload 9
    //   1706: invokevirtual 256	java/io/InputStream:close	()V
    //   1709: aload 11
    //   1711: ifnull +8 -> 1719
    //   1714: aload 11
    //   1716: invokevirtual 162	java/net/HttpURLConnection:disconnect	()V
    //   1719: getstatic 44	com/tencent/mm/plugin/sns/storage/AdLandingPagesStorage/b:pLe	Ljava/util/Set;
    //   1722: aload_1
    //   1723: iconst_0
    //   1724: aaload
    //   1725: invokeinterface 165 2 0
    //   1730: pop
    //   1731: aload_1
    //   1732: iconst_0
    //   1733: aaload
    //   1734: invokestatic 171	com/tencent/mm/sdk/platformtools/aa:RP	(Ljava/lang/String;)Ljava/lang/String;
    //   1737: astore 9
    //   1739: aload_0
    //   1740: invokespecial 173	com/tencent/mm/plugin/sns/storage/AdLandingPagesStorage/b:bjR	()I
    //   1743: istore 4
    //   1745: lload 6
    //   1747: invokestatic 177	com/tencent/mm/sdk/platformtools/bg:aH	(J)J
    //   1750: l2i
    //   1751: istore 5
    //   1753: new 179	com/tencent/mm/modelsns/d
    //   1756: dup
    //   1757: invokespecial 180	com/tencent/mm/modelsns/d:<init>	()V
    //   1760: astore_1
    //   1761: aload_1
    //   1762: ldc -74
    //   1764: new 140	java/lang/StringBuilder
    //   1767: dup
    //   1768: invokespecial 183	java/lang/StringBuilder:<init>	()V
    //   1771: aload 9
    //   1773: invokevirtual 152	java/lang/StringBuilder:append	(Ljava/lang/String;)Ljava/lang/StringBuilder;
    //   1776: ldc -71
    //   1778: invokevirtual 152	java/lang/StringBuilder:append	(Ljava/lang/String;)Ljava/lang/StringBuilder;
    //   1781: invokevirtual 159	java/lang/StringBuilder:toString	()Ljava/lang/String;
    //   1784: invokevirtual 189	com/tencent/mm/modelsns/d:q	(Ljava/lang/String;Ljava/lang/Object;)V
    //   1787: aload_1
    //   1788: ldc -65
    //   1790: new 140	java/lang/StringBuilder
    //   1793: dup
    //   1794: invokespecial 183	java/lang/StringBuilder:<init>	()V
    //   1797: iload 4
    //   1799: invokevirtual 147	java/lang/StringBuilder:append	(I)Ljava/lang/StringBuilder;
    //   1802: ldc -71
    //   1804: invokevirtual 152	java/lang/StringBuilder:append	(Ljava/lang/String;)Ljava/lang/StringBuilder;
    //   1807: invokevirtual 159	java/lang/StringBuilder:toString	()Ljava/lang/String;
    //   1810: invokevirtual 189	com/tencent/mm/modelsns/d:q	(Ljava/lang/String;Ljava/lang/Object;)V
    //   1813: new 140	java/lang/StringBuilder
    //   1816: dup
    //   1817: invokespecial 183	java/lang/StringBuilder:<init>	()V
    //   1820: astore 9
    //   1822: aload_0
    //   1823: getfield 57	com/tencent/mm/plugin/sns/storage/AdLandingPagesStorage/b:pJq	Z
    //   1826: ifeq +205 -> 2031
    //   1829: iconst_1
    //   1830: istore 4
    //   1832: aload_1
    //   1833: ldc -63
    //   1835: aload 9
    //   1837: iload 4
    //   1839: invokevirtual 147	java/lang/StringBuilder:append	(I)Ljava/lang/StringBuilder;
    //   1842: ldc -71
    //   1844: invokevirtual 152	java/lang/StringBuilder:append	(Ljava/lang/String;)Ljava/lang/StringBuilder;
    //   1847: invokevirtual 159	java/lang/StringBuilder:toString	()Ljava/lang/String;
    //   1850: invokevirtual 189	com/tencent/mm/modelsns/d:q	(Ljava/lang/String;Ljava/lang/Object;)V
    //   1853: aload_1
    //   1854: ldc -61
    //   1856: new 140	java/lang/StringBuilder
    //   1859: dup
    //   1860: invokespecial 183	java/lang/StringBuilder:<init>	()V
    //   1863: iload 5
    //   1865: invokevirtual 147	java/lang/StringBuilder:append	(I)Ljava/lang/StringBuilder;
    //   1868: ldc -71
    //   1870: invokevirtual 152	java/lang/StringBuilder:append	(Ljava/lang/String;)Ljava/lang/StringBuilder;
    //   1873: invokevirtual 159	java/lang/StringBuilder:toString	()Ljava/lang/String;
    //   1876: invokevirtual 189	com/tencent/mm/modelsns/d:q	(Ljava/lang/String;Ljava/lang/Object;)V
    //   1879: aload_1
    //   1880: ldc -59
    //   1882: new 140	java/lang/StringBuilder
    //   1885: dup
    //   1886: invokespecial 183	java/lang/StringBuilder:<init>	()V
    //   1889: iload_2
    //   1890: invokevirtual 147	java/lang/StringBuilder:append	(I)Ljava/lang/StringBuilder;
    //   1893: ldc -71
    //   1895: invokevirtual 152	java/lang/StringBuilder:append	(Ljava/lang/String;)Ljava/lang/StringBuilder;
    //   1898: invokevirtual 159	java/lang/StringBuilder:toString	()Ljava/lang/String;
    //   1901: invokevirtual 189	com/tencent/mm/modelsns/d:q	(Ljava/lang/String;Ljava/lang/Object;)V
    //   1904: aload_1
    //   1905: ldc -57
    //   1907: new 140	java/lang/StringBuilder
    //   1910: dup
    //   1911: invokespecial 183	java/lang/StringBuilder:<init>	()V
    //   1914: aload_0
    //   1915: getfield 61	com/tencent/mm/plugin/sns/storage/AdLandingPagesStorage/b:scene	I
    //   1918: invokevirtual 147	java/lang/StringBuilder:append	(I)Ljava/lang/StringBuilder;
    //   1921: ldc -71
    //   1923: invokevirtual 152	java/lang/StringBuilder:append	(Ljava/lang/String;)Ljava/lang/StringBuilder;
    //   1926: invokevirtual 159	java/lang/StringBuilder:toString	()Ljava/lang/String;
    //   1929: invokevirtual 189	com/tencent/mm/modelsns/d:q	(Ljava/lang/String;Ljava/lang/Object;)V
    //   1932: aload_1
    //   1933: ldc -55
    //   1935: new 140	java/lang/StringBuilder
    //   1938: dup
    //   1939: invokespecial 183	java/lang/StringBuilder:<init>	()V
    //   1942: iload_3
    //   1943: invokevirtual 147	java/lang/StringBuilder:append	(I)Ljava/lang/StringBuilder;
    //   1946: ldc -71
    //   1948: invokevirtual 152	java/lang/StringBuilder:append	(Ljava/lang/String;)Ljava/lang/StringBuilder;
    //   1951: invokevirtual 159	java/lang/StringBuilder:toString	()Ljava/lang/String;
    //   1954: invokevirtual 189	com/tencent/mm/modelsns/d:q	(Ljava/lang/String;Ljava/lang/Object;)V
    //   1957: aload_1
    //   1958: ldc -51
    //   1960: new 140	java/lang/StringBuilder
    //   1963: dup
    //   1964: invokespecial 183	java/lang/StringBuilder:<init>	()V
    //   1967: lload 6
    //   1969: ldc2_w 206
    //   1972: ldiv
    //   1973: invokevirtual 210	java/lang/StringBuilder:append	(J)Ljava/lang/StringBuilder;
    //   1976: ldc -71
    //   1978: invokevirtual 152	java/lang/StringBuilder:append	(Ljava/lang/String;)Ljava/lang/StringBuilder;
    //   1981: invokevirtual 159	java/lang/StringBuilder:toString	()Ljava/lang/String;
    //   1984: invokevirtual 189	com/tencent/mm/modelsns/d:q	(Ljava/lang/String;Ljava/lang/Object;)V
    //   1987: ldc -44
    //   1989: new 140	java/lang/StringBuilder
    //   1992: dup
    //   1993: ldc -42
    //   1995: invokespecial 143	java/lang/StringBuilder:<init>	(Ljava/lang/String;)V
    //   1998: aload_1
    //   1999: invokevirtual 217	com/tencent/mm/modelsns/d:LT	()Ljava/lang/String;
    //   2002: invokevirtual 152	java/lang/StringBuilder:append	(Ljava/lang/String;)Ljava/lang/StringBuilder;
    //   2005: invokevirtual 159	java/lang/StringBuilder:toString	()Ljava/lang/String;
    //   2008: invokestatic 222	com/tencent/mm/sdk/platformtools/w:i	(Ljava/lang/String;Ljava/lang/String;)V
    //   2011: getstatic 228	com/tencent/mm/plugin/report/service/g:ork	Lcom/tencent/mm/plugin/report/service/g;
    //   2014: sipush 13572
    //   2017: iconst_1
    //   2018: anewarray 230	java/lang/Object
    //   2021: dup
    //   2022: iconst_0
    //   2023: aload_1
    //   2024: aastore
    //   2025: invokevirtual 233	com/tencent/mm/plugin/report/service/g:i	(I[Ljava/lang/Object;)V
    //   2028: aload 8
    //   2030: athrow
    //   2031: iconst_0
    //   2032: istore 4
    //   2034: goto -202 -> 1832
    //   2037: astore 9
    //   2039: goto -330 -> 1709
    //   2042: astore 12
    //   2044: iconst_0
    //   2045: istore_2
    //   2046: aload 8
    //   2048: astore 11
    //   2050: aload 12
    //   2052: astore 8
    //   2054: iload 4
    //   2056: istore_3
    //   2057: goto -368 -> 1689
    //   2060: astore 12
    //   2062: aload 8
    //   2064: astore 11
    //   2066: aload 12
    //   2068: astore 8
    //   2070: iload 4
    //   2072: istore_3
    //   2073: goto -384 -> 1689
    //   2076: astore 12
    //   2078: aload 11
    //   2080: astore 9
    //   2082: aload 8
    //   2084: astore 11
    //   2086: aload 12
    //   2088: astore 8
    //   2090: iload 4
    //   2092: istore_3
    //   2093: goto -404 -> 1689
    //   2096: astore 10
    //   2098: aload 11
    //   2100: astore 12
    //   2102: aload 8
    //   2104: astore 11
    //   2106: aload 10
    //   2108: astore 8
    //   2110: aload 9
    //   2112: astore 10
    //   2114: aload 12
    //   2116: astore 9
    //   2118: iload 4
    //   2120: istore_3
    //   2121: goto -432 -> 1689
    //   2124: astore 10
    //   2126: aload 11
    //   2128: astore 12
    //   2130: aload 8
    //   2132: astore 11
    //   2134: aload 10
    //   2136: astore 8
    //   2138: aload 9
    //   2140: astore 10
    //   2142: aload 12
    //   2144: astore 9
    //   2146: goto -457 -> 1689
    //   2149: astore 10
    //   2151: aload 11
    //   2153: astore 12
    //   2155: aload 8
    //   2157: astore 11
    //   2159: aload 10
    //   2161: astore 8
    //   2163: aload 9
    //   2165: astore 10
    //   2167: aload 12
    //   2169: astore 9
    //   2171: goto -482 -> 1689
    //   2174: astore 10
    //   2176: aload 11
    //   2178: astore 12
    //   2180: aload 8
    //   2182: astore 11
    //   2184: aload 10
    //   2186: astore 8
    //   2188: aload 9
    //   2190: astore 10
    //   2192: aload 12
    //   2194: astore 9
    //   2196: goto -507 -> 1689
    //   2199: astore 9
    //   2201: goto -847 -> 1354
    //   2204: astore 10
    //   2206: iconst_0
    //   2207: istore_2
    //   2208: aconst_null
    //   2209: astore 11
    //   2211: aconst_null
    //   2212: astore 9
    //   2214: goto -906 -> 1308
    //   2217: astore 10
    //   2219: aconst_null
    //   2220: astore 11
    //   2222: aconst_null
    //   2223: astore 9
    //   2225: goto -917 -> 1308
    //   2228: astore 10
    //   2230: aconst_null
    //   2231: astore 9
    //   2233: goto -925 -> 1308
    //   2236: astore 10
    //   2238: goto -930 -> 1308
    //   2241: astore 10
    //   2243: goto -935 -> 1308
    //   2246: astore 9
    //   2248: goto -1288 -> 960
    //   2251: astore 9
    //   2253: goto -1661 -> 592
    // Local variable table:
    //   start	length	slot	name	signature
    //   0	2256	0	this	b
    //   0	2256	1	paramVarArgs	String[]
    //   139	2069	2	i	int
    //   62	2059	3	j	int
    //   59	2060	4	k	int
    //   634	1230	5	m	int
    //   56	1912	6	l	long
    //   127	1351	8	localObject1	Object
    //   1679	368	8	localObject2	Object
    //   2052	135	8	localObject3	Object
    //   97	1739	9	localObject4	Object
    //   2037	1	9	localIOException1	java.io.IOException
    //   2080	115	9	localObject5	Object
    //   2199	1	9	localIOException2	java.io.IOException
    //   2212	20	9	localObject6	Object
    //   2246	1	9	localIOException3	java.io.IOException
    //   2251	1	9	localIOException4	java.io.IOException
    //   100	830	10	arrayOfByte	byte[]
    //   1295	33	10	localException1	Exception
    //   1332	363	10	str	String
    //   2096	11	10	localObject7	Object
    //   2112	1	10	localObject8	Object
    //   2124	11	10	localObject9	Object
    //   2140	1	10	localObject10	Object
    //   2149	11	10	localObject11	Object
    //   2165	1	10	localObject12	Object
    //   2174	11	10	localObject13	Object
    //   2190	1	10	localObject14	Object
    //   2204	1	10	localException2	Exception
    //   2217	1	10	localException3	Exception
    //   2228	1	10	localException4	Exception
    //   2236	1	10	localException5	Exception
    //   2241	1	10	localException6	Exception
    //   189	2032	11	localObject15	Object
    //   2042	9	12	localObject16	Object
    //   2060	7	12	localObject17	Object
    //   2076	11	12	localObject18	Object
    //   2100	93	12	localObject19	Object
    // Exception table:
    //   from	to	target	type
    //   111	129	1295	java/lang/Exception
    //   111	129	1679	finally
    //   1694	1699	2037	java/io/IOException
    //   1704	1709	2037	java/io/IOException
    //   129	140	2042	finally
    //   147	191	2060	finally
    //   515	528	2060	finally
    //   528	541	2076	finally
    //   541	548	2096	finally
    //   550	559	2124	finally
    //   565	577	2124	finally
    //   927	937	2124	finally
    //   1308	1325	2149	finally
    //   1327	1334	2174	finally
    //   1339	1344	2199	java/io/IOException
    //   1349	1354	2199	java/io/IOException
    //   129	140	2204	java/lang/Exception
    //   147	191	2217	java/lang/Exception
    //   515	528	2217	java/lang/Exception
    //   528	541	2228	java/lang/Exception
    //   541	548	2236	java/lang/Exception
    //   550	559	2241	java/lang/Exception
    //   565	577	2241	java/lang/Exception
    //   927	937	2241	java/lang/Exception
    //   945	950	2246	java/io/IOException
    //   955	960	2246	java/io/IOException
    //   577	582	2251	java/io/IOException
    //   587	592	2251	java/io/IOException
  }
  
  public static abstract interface a
  {
    public abstract void bkK();
    
    public abstract void bkL();
    
    public abstract void blu();
  }
}


/* Location:              D:\tools\apktool\weixin6519android1140\jar\classes2-dex2jar.jar!\com\tencent\mm\plugin\sns\storage\AdLandingPagesStorage\b.class
 * Java compiler version: 6 (50.0)
 * JD-Core Version:       0.7.1
 */