package com.tencent.mm.modelvideo;

import android.os.HandlerThread;
import com.tencent.gmtrace.GMTrace;
import com.tencent.mm.ad.d.c;
import com.tencent.mm.bu.g.d;
import com.tencent.mm.g.a.jg;
import com.tencent.mm.kernel.h;
import com.tencent.mm.modelcdntran.f;
import com.tencent.mm.sdk.b.c;
import com.tencent.mm.sdk.platformtools.ae;
import com.tencent.mm.sdk.platformtools.af;
import com.tencent.mm.sdk.platformtools.bg;
import com.tencent.mm.y.aq;
import com.tencent.mm.y.p;
import java.io.File;
import java.util.HashMap;
import java.util.Iterator;
import java.util.List;

public class o
  implements aq
{
  private static HashMap<Integer, g.d> fIv;
  private static af hcg;
  private static ae hch;
  public static boolean hck;
  private u hbZ;
  private s hca;
  private w hcb;
  private x.a hcc;
  private l hcd;
  private k hce;
  private m hcf;
  private f hci;
  private i hcj;
  private c<jg> hcl;
  
  static
  {
    GMTrace.i(328967651328L, 2451);
    hcg = null;
    hch = null;
    HashMap localHashMap = new HashMap();
    fIv = localHashMap;
    localHashMap.put(Integer.valueOf("VIDEOINFO_TABLE".hashCode()), new g.d()
    {
      public final String[] rf()
      {
        GMTrace.i(351784665088L, 2621);
        String[] arrayOfString = s.fTX;
        GMTrace.o(351784665088L, 2621);
        return arrayOfString;
      }
    });
    fIv.put(Integer.valueOf("VIDEOPLAYHISTORY_TABLE".hashCode()), new g.d()
    {
      public final String[] rf()
      {
        GMTrace.i(346013302784L, 2578);
        String[] arrayOfString = w.fTX;
        GMTrace.o(346013302784L, 2578);
        return arrayOfString;
      }
    });
    fIv.put(Integer.valueOf("SIGHTDRAFTSINFO_TABLE".hashCode()), new g.d()
    {
      public final String[] rf()
      {
        GMTrace.i(316351184896L, 2357);
        String[] arrayOfString = l.fTX;
        GMTrace.o(316351184896L, 2357);
        return arrayOfString;
      }
    });
    hck = false;
    GMTrace.o(328967651328L, 2451);
  }
  
  public o()
  {
    GMTrace.i(326820167680L, 2435);
    this.hbZ = new u();
    this.hcc = null;
    this.hcd = null;
    this.hce = null;
    this.hcf = null;
    this.hci = null;
    this.hcj = null;
    this.hcl = new c() {};
    GMTrace.o(326820167680L, 2435);
  }
  
  public static o Ng()
  {
    GMTrace.i(326954385408L, 2436);
    o localo = (o)p.o(o.class);
    GMTrace.o(326954385408L, 2436);
    return localo;
  }
  
  public static s Nh()
  {
    GMTrace.i(327088603136L, 2437);
    if (!h.xw().wL()) {
      throw new com.tencent.mm.y.b();
    }
    if (Ng().hca == null) {
      Ng().hca = new s(h.xy().fYV);
    }
    s locals = Ng().hca;
    GMTrace.o(327088603136L, 2437);
    return locals;
  }
  
  public static f Ni()
  {
    GMTrace.i(14451625426944L, 107673);
    h.xw().wG();
    if (Ng().hci == null) {
      Ng().hci = new f();
    }
    if (com.tencent.mm.modelcdntran.g.Gl().gzA == null) {}
    for (int i = 1;; i = 0)
    {
      if (i != 0) {
        com.tencent.mm.modelcdntran.g.Gl().gzA = Ng().hci;
      }
      f localf = Ng().hci;
      GMTrace.o(14451625426944L, 107673);
      return localf;
    }
  }
  
  public static i Nj()
  {
    GMTrace.i(17453673349120L, 130040);
    h.xw().wG();
    if (Ng().hcj == null) {
      Ng().hcj = new i();
    }
    i locali = Ng().hcj;
    GMTrace.o(17453673349120L, 130040);
    return locali;
  }
  
  public static w Nk()
  {
    GMTrace.i(327222820864L, 2438);
    if (!h.xw().wL()) {
      throw new com.tencent.mm.y.b();
    }
    if (Ng().hcb == null) {
      Ng().hcb = new w(h.xy().fYV);
    }
    w localw = Ng().hcb;
    GMTrace.o(327222820864L, 2438);
    return localw;
  }
  
  public static l Nl()
  {
    GMTrace.i(327357038592L, 2439);
    if (!h.xw().wL()) {
      throw new com.tencent.mm.y.b();
    }
    if (Ng().hcd == null) {
      Ng().hcd = new l(h.xy().fYV);
    }
    l locall = Ng().hcd;
    GMTrace.o(327357038592L, 2439);
    return locall;
  }
  
  public static x.a Nm()
  {
    GMTrace.i(327491256320L, 2440);
    if (!h.xw().wL()) {
      throw new com.tencent.mm.y.b();
    }
    if (Ng().hcc == null) {
      Ng().hcc = new x.a();
    }
    x.a locala = Ng().hcc;
    GMTrace.o(327491256320L, 2440);
    return locala;
  }
  
  public static m Nn()
  {
    GMTrace.i(327625474048L, 2441);
    if (!h.xw().wL()) {
      throw new com.tencent.mm.y.b();
    }
    if (Ng().hcf == null) {
      Ng().hcf = new m();
    }
    m localm = Ng().hcf;
    GMTrace.o(327625474048L, 2441);
    return localm;
  }
  
  private static void No()
  {
    boolean bool2 = false;
    GMTrace.i(327893909504L, 2443);
    if ((hch != null) && (hcg != null))
    {
      GMTrace.o(327893909504L, 2443);
      return;
    }
    boolean bool1;
    if (hch != null)
    {
      bool1 = true;
      if (hcg != null) {
        bool2 = true;
      }
      com.tencent.mm.sdk.platformtools.w.w("MicroMsg.SubCoreVideo", "check decoder thread available fail, handler[%B] thread[%B] stack[%s]", new Object[] { Boolean.valueOf(bool1), Boolean.valueOf(bool2), bg.bQW() });
      if (hch != null) {
        hch.removeCallbacksAndMessages(null);
      }
      if (hcg == null) {
        break label141;
      }
      hcg.a(null);
    }
    for (;;)
    {
      hch = new ae(hcg.ngv.getLooper());
      GMTrace.o(327893909504L, 2443);
      return;
      bool1 = false;
      break;
      label141:
      hcg = new af("Short-Video-Decoder-Thread-" + System.currentTimeMillis());
    }
  }
  
  public static boolean d(Runnable paramRunnable, long paramLong)
  {
    GMTrace.i(328028127232L, 2444);
    if (paramRunnable == null)
    {
      GMTrace.o(328028127232L, 2444);
      return false;
    }
    No();
    if (paramLong > 0L) {
      hch.postDelayed(paramRunnable, paramLong);
    }
    for (;;)
    {
      GMTrace.o(328028127232L, 2444);
      return true;
      hch.post(paramRunnable);
    }
  }
  
  public static boolean g(Runnable paramRunnable)
  {
    GMTrace.i(328162344960L, 2445);
    if (paramRunnable == null)
    {
      GMTrace.o(328162344960L, 2445);
      return true;
    }
    No();
    if (hch == null)
    {
      com.tencent.mm.sdk.platformtools.w.e("MicroMsg.SubCoreVideo", "short video decoder handler is null");
      GMTrace.o(328162344960L, 2445);
      return false;
    }
    hch.removeCallbacks(paramRunnable);
    GMTrace.o(328162344960L, 2445);
    return true;
  }
  
  public static String getAccVideoPath()
  {
    GMTrace.i(18681631342592L, 139189);
    Object localObject = new StringBuilder();
    h.xz();
    localObject = h.xy().fYU + "video/";
    GMTrace.o(18681631342592L, 139189);
    return (String)localObject;
  }
  
  public final void aX(boolean paramBoolean)
  {
    GMTrace.i(328699215872L, 2449);
    com.tencent.mm.sdk.platformtools.w.i("MicroMsg.SubCoreVideo", "%d onAccountPostReset ", new Object[] { Integer.valueOf(hashCode()) });
    d.c.a(Integer.valueOf(43), this.hbZ);
    d.c.a(Integer.valueOf(44), this.hbZ);
    d.c.a(Integer.valueOf(62), this.hbZ);
    com.tencent.mm.sdk.b.a.vgX.a(this.hcl);
    if (hch != null) {
      hch.removeCallbacksAndMessages(null);
    }
    h.xB().A(new Runnable()
    {
      public final void run()
      {
        GMTrace.i(351113576448L, 2616);
        if (!h.xw().wL())
        {
          GMTrace.o(351113576448L, 2616);
          return;
        }
        Object localObject1 = o.Nh();
        long l = System.currentTimeMillis() / 1000L;
        Object localObject2 = "UPDATE videoinfo2 SET status = 198, lastmodifytime = " + l + " WHERE masssendid > 0  AND status" + " = 200";
        com.tencent.mm.sdk.platformtools.w.i("MicroMsg.VideoInfoStorage", "fail all massSendInfos, sql %s", new Object[] { localObject2 });
        ((s)localObject1).goN.eZ("videoinfo2", (String)localObject2);
        o.Nl().fTZ.eZ("SightDraftInfo", "UPDATE SightDraftInfo SET fileStatus = 1 WHERE fileStatus = 6");
        localObject1 = o.Nl();
        if (1209600000L <= 0L)
        {
          com.tencent.mm.sdk.platformtools.w.w("MicroMsg.SightDraftStorage", "keep 0 sight draft");
          ((l)localObject1).fTZ.eZ("SightDraftInfo", "UPDATE SightDraftInfo SET fileStatus = 7 WHERE fileStatus = 1");
        }
        for (;;)
        {
          localObject1 = o.Nl().Ne().iterator();
          while (((Iterator)localObject1).hasNext())
          {
            localObject2 = (j)((Iterator)localObject1).next();
            com.tencent.mm.sdk.platformtools.w.i("MicroMsg.SubCoreVideo", "do delete sight draft file, name %s", new Object[] { ((j)localObject2).field_fileName });
            com.tencent.mm.loader.stub.b.deleteFile(k.ma(((j)localObject2).field_fileName));
            com.tencent.mm.loader.stub.b.deleteFile(k.mb(((j)localObject2).field_fileName));
          }
          l = bg.Pv() - 1209600000L;
          com.tencent.mm.sdk.platformtools.w.i("MicroMsg.SightDraftStorage", "check delete ITEM, create time %d", new Object[] { Long.valueOf(l) });
          localObject2 = "UPDATE SightDraftInfo SET fileStatus = 7 WHERE fileStatus = 1 AND createTime < " + l;
          ((l)localObject1).fTZ.eZ("SightDraftInfo", (String)localObject2);
        }
        GMTrace.o(351113576448L, 2616);
      }
    });
    File localFile = new File(k.Nd());
    if ((!localFile.exists()) || (!localFile.isDirectory())) {
      localFile.mkdirs();
    }
    GMTrace.o(328699215872L, 2449);
  }
  
  public final void aY(boolean paramBoolean)
  {
    GMTrace.i(328833433600L, 2450);
    GMTrace.o(328833433600L, 2450);
  }
  
  public final void eI(int paramInt)
  {
    GMTrace.i(328564998144L, 2448);
    GMTrace.o(328564998144L, 2448);
  }
  
  /* Error */
  public final void onAccountRelease()
  {
    // Byte code:
    //   0: ldc2_w 408
    //   3: sipush 2446
    //   6: invokestatic 56	com/tencent/gmtrace/GMTrace:i	(JI)V
    //   9: ldc -18
    //   11: ldc_w 411
    //   14: iconst_1
    //   15: anewarray 4	java/lang/Object
    //   18: dup
    //   19: iconst_0
    //   20: aload_0
    //   21: invokevirtual 355	java/lang/Object:hashCode	()I
    //   24: invokestatic 81	java/lang/Integer:valueOf	(I)Ljava/lang/Integer;
    //   27: aastore
    //   28: invokestatic 357	com/tencent/mm/sdk/platformtools/w:i	(Ljava/lang/String;Ljava/lang/String;[Ljava/lang/Object;)V
    //   31: invokestatic 153	com/tencent/mm/modelvideo/o:Ng	()Lcom/tencent/mm/modelvideo/o;
    //   34: getfield 108	com/tencent/mm/modelvideo/o:hcc	Lcom/tencent/mm/modelvideo/x$a;
    //   37: ifnull +69 -> 106
    //   40: invokestatic 153	com/tencent/mm/modelvideo/o:Ng	()Lcom/tencent/mm/modelvideo/o;
    //   43: getfield 108	com/tencent/mm/modelvideo/o:hcc	Lcom/tencent/mm/modelvideo/x$a;
    //   46: astore_1
    //   47: aload_1
    //   48: iconst_0
    //   49: putfield 415	com/tencent/mm/modelvideo/x$a:eyZ	I
    //   52: aload_1
    //   53: getfield 419	com/tencent/mm/modelvideo/x$a:hdf	Lcom/tencent/mm/modelvideo/d;
    //   56: ifnull +13 -> 69
    //   59: invokestatic 423	com/tencent/mm/kernel/h:wS	()Lcom/tencent/mm/ad/n;
    //   62: aload_1
    //   63: getfield 419	com/tencent/mm/modelvideo/x$a:hdf	Lcom/tencent/mm/modelvideo/d;
    //   66: invokevirtual 429	com/tencent/mm/ad/n:c	(Lcom/tencent/mm/ad/k;)V
    //   69: aload_1
    //   70: getfield 433	com/tencent/mm/modelvideo/x$a:hdg	Lcom/tencent/mm/modelvideo/g;
    //   73: ifnull +13 -> 86
    //   76: invokestatic 423	com/tencent/mm/kernel/h:wS	()Lcom/tencent/mm/ad/n;
    //   79: aload_1
    //   80: getfield 433	com/tencent/mm/modelvideo/x$a:hdg	Lcom/tencent/mm/modelvideo/g;
    //   83: invokevirtual 429	com/tencent/mm/ad/n:c	(Lcom/tencent/mm/ad/k;)V
    //   86: invokestatic 423	com/tencent/mm/kernel/h:wS	()Lcom/tencent/mm/ad/n;
    //   89: sipush 149
    //   92: aload_1
    //   93: invokevirtual 437	com/tencent/mm/ad/n:b	(ILcom/tencent/mm/ad/e;)V
    //   96: invokestatic 423	com/tencent/mm/kernel/h:wS	()Lcom/tencent/mm/ad/n;
    //   99: sipush 150
    //   102: aload_1
    //   103: invokevirtual 437	com/tencent/mm/ad/n:b	(ILcom/tencent/mm/ad/e;)V
    //   106: invokestatic 153	com/tencent/mm/modelvideo/o:Ng	()Lcom/tencent/mm/modelvideo/o;
    //   109: getfield 114	com/tencent/mm/modelvideo/o:hcf	Lcom/tencent/mm/modelvideo/m;
    //   112: ifnull +56 -> 168
    //   115: invokestatic 153	com/tencent/mm/modelvideo/o:Ng	()Lcom/tencent/mm/modelvideo/o;
    //   118: getfield 114	com/tencent/mm/modelvideo/o:hcf	Lcom/tencent/mm/modelvideo/m;
    //   121: astore_1
    //   122: aload_1
    //   123: iconst_0
    //   124: putfield 438	com/tencent/mm/modelvideo/m:eyZ	I
    //   127: ldc_w 440
    //   130: ldc_w 442
    //   133: iconst_1
    //   134: anewarray 4	java/lang/Object
    //   137: dup
    //   138: iconst_0
    //   139: aload_1
    //   140: getfield 445	com/tencent/mm/modelvideo/m:hbE	Ljava/lang/String;
    //   143: aastore
    //   144: invokestatic 357	com/tencent/mm/sdk/platformtools/w:i	(Ljava/lang/String;Ljava/lang/String;[Ljava/lang/Object;)V
    //   147: aload_1
    //   148: getfield 445	com/tencent/mm/modelvideo/m:hbE	Ljava/lang/String;
    //   151: invokestatic 449	com/tencent/mm/sdk/platformtools/bg:nm	(Ljava/lang/String;)Z
    //   154: ifne +14 -> 168
    //   157: invokestatic 453	com/tencent/mm/modelcdntran/g:Gk	()Lcom/tencent/mm/modelcdntran/c;
    //   160: aload_1
    //   161: getfield 445	com/tencent/mm/modelvideo/m:hbE	Ljava/lang/String;
    //   164: invokevirtual 458	com/tencent/mm/modelcdntran/c:jy	(Ljava/lang/String;)Z
    //   167: pop
    //   168: invokestatic 153	com/tencent/mm/modelvideo/o:Ng	()Lcom/tencent/mm/modelvideo/o;
    //   171: getfield 118	com/tencent/mm/modelvideo/o:hcj	Lcom/tencent/mm/modelvideo/i;
    //   174: ifnull +21 -> 195
    //   177: invokestatic 153	com/tencent/mm/modelvideo/o:Ng	()Lcom/tencent/mm/modelvideo/o;
    //   180: getfield 118	com/tencent/mm/modelvideo/o:hcj	Lcom/tencent/mm/modelvideo/i;
    //   183: astore_1
    //   184: aload_1
    //   185: invokevirtual 461	com/tencent/mm/modelvideo/i:stopDownload	()V
    //   188: aload_1
    //   189: getfield 465	com/tencent/mm/modelvideo/i:hbo	Ljava/util/LinkedList;
    //   192: invokevirtual 470	java/util/LinkedList:clear	()V
    //   195: invokestatic 153	com/tencent/mm/modelvideo/o:Ng	()Lcom/tencent/mm/modelvideo/o;
    //   198: getfield 116	com/tencent/mm/modelvideo/o:hci	Lcom/tencent/mm/modelcdntran/f;
    //   201: ifnull +20 -> 221
    //   204: invokestatic 153	com/tencent/mm/modelvideo/o:Ng	()Lcom/tencent/mm/modelvideo/o;
    //   207: getfield 116	com/tencent/mm/modelvideo/o:hci	Lcom/tencent/mm/modelcdntran/f;
    //   210: astore_1
    //   211: invokestatic 423	com/tencent/mm/kernel/h:wS	()Lcom/tencent/mm/ad/n;
    //   214: sipush 379
    //   217: aload_1
    //   218: invokevirtual 437	com/tencent/mm/ad/n:b	(ILcom/tencent/mm/ad/e;)V
    //   221: bipush 43
    //   223: invokestatic 81	java/lang/Integer:valueOf	(I)Ljava/lang/Integer;
    //   226: invokestatic 473	com/tencent/mm/ad/d$c:aE	(Ljava/lang/Object;)V
    //   229: bipush 44
    //   231: invokestatic 81	java/lang/Integer:valueOf	(I)Ljava/lang/Integer;
    //   234: invokestatic 473	com/tencent/mm/ad/d$c:aE	(Ljava/lang/Object;)V
    //   237: bipush 62
    //   239: invokestatic 81	java/lang/Integer:valueOf	(I)Ljava/lang/Integer;
    //   242: invokestatic 473	com/tencent/mm/ad/d$c:aE	(Ljava/lang/Object;)V
    //   245: getstatic 368	com/tencent/mm/sdk/b/a:vgX	Lcom/tencent/mm/sdk/b/a;
    //   248: aload_0
    //   249: getfield 123	com/tencent/mm/modelvideo/o:hcl	Lcom/tencent/mm/sdk/b/c;
    //   252: invokevirtual 476	com/tencent/mm/sdk/b/a:c	(Lcom/tencent/mm/sdk/b/c;)Z
    //   255: pop
    //   256: getstatic 60	com/tencent/mm/modelvideo/o:hch	Lcom/tencent/mm/sdk/platformtools/ae;
    //   259: ifnull +10 -> 269
    //   262: getstatic 60	com/tencent/mm/modelvideo/o:hch	Lcom/tencent/mm/sdk/platformtools/ae;
    //   265: aconst_null
    //   266: invokevirtual 263	com/tencent/mm/sdk/platformtools/ae:removeCallbacksAndMessages	(Ljava/lang/Object;)V
    //   269: invokestatic 478	com/tencent/mm/modelvideo/o:Nm	()Lcom/tencent/mm/modelvideo/x$a;
    //   272: astore_1
    //   273: ldc_w 480
    //   276: ldc_w 482
    //   279: iconst_1
    //   280: anewarray 4	java/lang/Object
    //   283: dup
    //   284: iconst_0
    //   285: aload_1
    //   286: getfield 485	com/tencent/mm/modelvideo/x$a:hcZ	Landroid/os/HandlerThread;
    //   289: aastore
    //   290: invokestatic 357	com/tencent/mm/sdk/platformtools/w:i	(Ljava/lang/String;Ljava/lang/String;[Ljava/lang/Object;)V
    //   293: aload_1
    //   294: getfield 485	com/tencent/mm/modelvideo/x$a:hcZ	Landroid/os/HandlerThread;
    //   297: astore_2
    //   298: aload_2
    //   299: ifnull +74 -> 373
    //   302: aload_1
    //   303: getfield 485	com/tencent/mm/modelvideo/x$a:hcZ	Landroid/os/HandlerThread;
    //   306: invokevirtual 488	android/os/HandlerThread:quit	()Z
    //   309: pop
    //   310: aload_1
    //   311: iconst_0
    //   312: putfield 491	com/tencent/mm/modelvideo/x$a:hdb	Z
    //   315: aload_1
    //   316: aconst_null
    //   317: putfield 494	com/tencent/mm/modelvideo/x$a:hda	Lcom/tencent/mm/sdk/platformtools/ae;
    //   320: aload_1
    //   321: aconst_null
    //   322: putfield 485	com/tencent/mm/modelvideo/x$a:hcZ	Landroid/os/HandlerThread;
    //   325: ldc2_w 408
    //   328: sipush 2446
    //   331: invokestatic 97	com/tencent/gmtrace/GMTrace:o	(JI)V
    //   334: return
    //   335: astore_1
    //   336: ldc -18
    //   338: aload_1
    //   339: ldc_w 496
    //   342: iconst_0
    //   343: anewarray 4	java/lang/Object
    //   346: invokestatic 500	com/tencent/mm/sdk/platformtools/w:printErrStackTrace	(Ljava/lang/String;Ljava/lang/Throwable;Ljava/lang/String;[Ljava/lang/Object;)V
    //   349: goto -128 -> 221
    //   352: astore_1
    //   353: ldc_w 480
    //   356: ldc_w 502
    //   359: iconst_1
    //   360: anewarray 4	java/lang/Object
    //   363: dup
    //   364: iconst_0
    //   365: aload_1
    //   366: invokevirtual 505	java/lang/Exception:getMessage	()Ljava/lang/String;
    //   369: aastore
    //   370: invokestatic 507	com/tencent/mm/sdk/platformtools/w:e	(Ljava/lang/String;Ljava/lang/String;[Ljava/lang/Object;)V
    //   373: ldc2_w 408
    //   376: sipush 2446
    //   379: invokestatic 97	com/tencent/gmtrace/GMTrace:o	(JI)V
    //   382: return
    //   383: astore_1
    //   384: ldc -18
    //   386: ldc_w 509
    //   389: iconst_1
    //   390: anewarray 4	java/lang/Object
    //   393: dup
    //   394: iconst_0
    //   395: aload_1
    //   396: invokevirtual 505	java/lang/Exception:getMessage	()Ljava/lang/String;
    //   399: aastore
    //   400: invokestatic 507	com/tencent/mm/sdk/platformtools/w:e	(Ljava/lang/String;Ljava/lang/String;[Ljava/lang/Object;)V
    //   403: ldc2_w 408
    //   406: sipush 2446
    //   409: invokestatic 97	com/tencent/gmtrace/GMTrace:o	(JI)V
    //   412: return
    // Local variable table:
    //   start	length	slot	name	signature
    //   0	413	0	this	o
    //   46	275	1	localObject	Object
    //   335	4	1	localException1	Exception
    //   352	14	1	localException2	Exception
    //   383	13	1	localException3	Exception
    //   297	2	2	localHandlerThread	HandlerThread
    // Exception table:
    //   from	to	target	type
    //   31	69	335	java/lang/Exception
    //   69	86	335	java/lang/Exception
    //   86	106	335	java/lang/Exception
    //   106	168	335	java/lang/Exception
    //   168	195	335	java/lang/Exception
    //   195	221	335	java/lang/Exception
    //   302	325	352	java/lang/Exception
    //   269	298	383	java/lang/Exception
    //   325	334	383	java/lang/Exception
    //   353	373	383	java/lang/Exception
  }
  
  public final HashMap<Integer, g.d> vH()
  {
    GMTrace.i(328430780416L, 2447);
    HashMap localHashMap = fIv;
    GMTrace.o(328430780416L, 2447);
    return localHashMap;
  }
}


/* Location:              D:\tools\apktool\weixin6519android1140\jar\classes-dex2jar.jar!\com\tencent\mm\modelvideo\o.class
 * Java compiler version: 6 (50.0)
 * JD-Core Version:       0.7.1
 */