package com.tencent.mm.modelvideo;

import com.tencent.gmtrace.GMTrace;

public final class q
{
  private static String E(byte[] paramArrayOfByte)
  {
    GMTrace.i(333799489536L, 2487);
    StringBuilder localStringBuilder = new StringBuilder();
    if (paramArrayOfByte.length <= 0)
    {
      GMTrace.o(333799489536L, 2487);
      return null;
    }
    int i = 0;
    while (i < paramArrayOfByte.length)
    {
      String str = Integer.toHexString(paramArrayOfByte[i] & 0xFF);
      if (str.length() < 2) {
        localStringBuilder.append(0);
      }
      localStringBuilder.append(str);
      i += 1;
    }
    paramArrayOfByte = localStringBuilder.toString();
    GMTrace.o(333799489536L, 2487);
    return paramArrayOfByte;
  }
  
  /* Error */
  public static boolean mc(String paramString)
  {
    // Byte code:
    //   0: ldc2_w 54
    //   3: sipush 2488
    //   6: invokestatic 14	com/tencent/gmtrace/GMTrace:i	(JI)V
    //   9: ldc 57
    //   11: new 16	java/lang/StringBuilder
    //   14: dup
    //   15: ldc 59
    //   17: invokespecial 62	java/lang/StringBuilder:<init>	(Ljava/lang/String;)V
    //   20: aload_0
    //   21: invokevirtual 42	java/lang/StringBuilder:append	(Ljava/lang/String;)Ljava/lang/StringBuilder;
    //   24: invokevirtual 46	java/lang/StringBuilder:toString	()Ljava/lang/String;
    //   27: invokestatic 68	com/tencent/mm/sdk/platformtools/w:d	(Ljava/lang/String;Ljava/lang/String;)V
    //   30: aload_0
    //   31: invokestatic 73	com/tencent/mm/sdk/platformtools/bg:nm	(Ljava/lang/String;)Z
    //   34: ifeq +14 -> 48
    //   37: ldc2_w 54
    //   40: sipush 2488
    //   43: invokestatic 23	com/tencent/gmtrace/GMTrace:o	(JI)V
    //   46: iconst_0
    //   47: ireturn
    //   48: new 75	java/io/FileInputStream
    //   51: dup
    //   52: aload_0
    //   53: invokespecial 76	java/io/FileInputStream:<init>	(Ljava/lang/String;)V
    //   56: astore_1
    //   57: aload_1
    //   58: astore_0
    //   59: bipush 10
    //   61: newarray <illegal type>
    //   63: astore_2
    //   64: aload_1
    //   65: astore_0
    //   66: aload_1
    //   67: aload_2
    //   68: iconst_0
    //   69: bipush 10
    //   71: invokevirtual 80	java/io/FileInputStream:read	([BII)I
    //   74: pop
    //   75: aload_1
    //   76: astore_0
    //   77: aload_2
    //   78: invokestatic 82	com/tencent/mm/modelvideo/q:E	([B)Ljava/lang/String;
    //   81: astore_2
    //   82: aload_1
    //   83: astore_0
    //   84: aload_2
    //   85: invokestatic 73	com/tencent/mm/sdk/platformtools/bg:nm	(Ljava/lang/String;)Z
    //   88: ifne +68 -> 156
    //   91: aload_1
    //   92: astore_0
    //   93: aload_2
    //   94: invokevirtual 85	java/lang/String:toUpperCase	()Ljava/lang/String;
    //   97: astore_2
    //   98: aload_1
    //   99: astore_0
    //   100: ldc 57
    //   102: new 16	java/lang/StringBuilder
    //   105: dup
    //   106: ldc 87
    //   108: invokespecial 62	java/lang/StringBuilder:<init>	(Ljava/lang/String;)V
    //   111: aload_2
    //   112: invokevirtual 42	java/lang/StringBuilder:append	(Ljava/lang/String;)Ljava/lang/StringBuilder;
    //   115: invokevirtual 46	java/lang/StringBuilder:toString	()Ljava/lang/String;
    //   118: invokestatic 68	com/tencent/mm/sdk/platformtools/w:d	(Ljava/lang/String;Ljava/lang/String;)V
    //   121: aload_1
    //   122: astore_0
    //   123: aload_2
    //   124: ldc 89
    //   126: invokevirtual 93	java/lang/String:contains	(Ljava/lang/CharSequence;)Z
    //   129: ifeq +27 -> 156
    //   132: aload_1
    //   133: astore_0
    //   134: ldc 57
    //   136: ldc 95
    //   138: invokestatic 68	com/tencent/mm/sdk/platformtools/w:d	(Ljava/lang/String;Ljava/lang/String;)V
    //   141: aload_1
    //   142: invokevirtual 98	java/io/FileInputStream:close	()V
    //   145: ldc2_w 54
    //   148: sipush 2488
    //   151: invokestatic 23	com/tencent/gmtrace/GMTrace:o	(JI)V
    //   154: iconst_1
    //   155: ireturn
    //   156: aload_1
    //   157: invokevirtual 98	java/io/FileInputStream:close	()V
    //   160: ldc2_w 54
    //   163: sipush 2488
    //   166: invokestatic 23	com/tencent/gmtrace/GMTrace:o	(JI)V
    //   169: iconst_0
    //   170: ireturn
    //   171: astore_2
    //   172: aconst_null
    //   173: astore_1
    //   174: aload_1
    //   175: astore_0
    //   176: ldc 57
    //   178: ldc 100
    //   180: iconst_1
    //   181: anewarray 4	java/lang/Object
    //   184: dup
    //   185: iconst_0
    //   186: aload_2
    //   187: invokestatic 104	com/tencent/mm/sdk/platformtools/bg:f	(Ljava/lang/Throwable;)Ljava/lang/String;
    //   190: aastore
    //   191: invokestatic 108	com/tencent/mm/sdk/platformtools/w:e	(Ljava/lang/String;Ljava/lang/String;[Ljava/lang/Object;)V
    //   194: aload_1
    //   195: ifnull -35 -> 160
    //   198: aload_1
    //   199: invokevirtual 98	java/io/FileInputStream:close	()V
    //   202: goto -42 -> 160
    //   205: astore_0
    //   206: goto -46 -> 160
    //   209: astore_1
    //   210: aconst_null
    //   211: astore_0
    //   212: aload_0
    //   213: ifnull +7 -> 220
    //   216: aload_0
    //   217: invokevirtual 98	java/io/FileInputStream:close	()V
    //   220: aload_1
    //   221: athrow
    //   222: astore_0
    //   223: goto -78 -> 145
    //   226: astore_0
    //   227: goto -67 -> 160
    //   230: astore_0
    //   231: goto -11 -> 220
    //   234: astore_1
    //   235: goto -23 -> 212
    //   238: astore_2
    //   239: goto -65 -> 174
    // Local variable table:
    //   start	length	slot	name	signature
    //   0	242	0	paramString	String
    //   56	143	1	localFileInputStream	java.io.FileInputStream
    //   209	12	1	localObject1	Object
    //   234	1	1	localObject2	Object
    //   63	61	2	localObject3	Object
    //   171	16	2	localException1	Exception
    //   238	1	2	localException2	Exception
    // Exception table:
    //   from	to	target	type
    //   48	57	171	java/lang/Exception
    //   198	202	205	java/io/IOException
    //   48	57	209	finally
    //   141	145	222	java/io/IOException
    //   156	160	226	java/io/IOException
    //   216	220	230	java/io/IOException
    //   59	64	234	finally
    //   66	75	234	finally
    //   77	82	234	finally
    //   84	91	234	finally
    //   93	98	234	finally
    //   100	121	234	finally
    //   123	132	234	finally
    //   134	141	234	finally
    //   176	194	234	finally
    //   59	64	238	java/lang/Exception
    //   66	75	238	java/lang/Exception
    //   77	82	238	java/lang/Exception
    //   84	91	238	java/lang/Exception
    //   93	98	238	java/lang/Exception
    //   100	121	238	java/lang/Exception
    //   123	132	238	java/lang/Exception
    //   134	141	238	java/lang/Exception
  }
  
  /* Error */
  public static boolean md(String paramString)
  {
    // Byte code:
    //   0: ldc2_w 110
    //   3: ldc 112
    //   5: invokestatic 14	com/tencent/gmtrace/GMTrace:i	(JI)V
    //   8: aload_0
    //   9: invokestatic 117	com/tencent/mm/a/e:aZ	(Ljava/lang/String;)Z
    //   12: ifne +13 -> 25
    //   15: ldc2_w 110
    //   18: ldc 112
    //   20: invokestatic 23	com/tencent/gmtrace/GMTrace:o	(JI)V
    //   23: iconst_0
    //   24: ireturn
    //   25: new 75	java/io/FileInputStream
    //   28: dup
    //   29: aload_0
    //   30: invokespecial 76	java/io/FileInputStream:<init>	(Ljava/lang/String;)V
    //   33: astore_2
    //   34: aload_2
    //   35: astore_0
    //   36: bipush 32
    //   38: newarray <illegal type>
    //   40: astore_3
    //   41: aload_2
    //   42: astore_0
    //   43: aload_2
    //   44: aload_3
    //   45: iconst_0
    //   46: bipush 32
    //   48: invokevirtual 80	java/io/FileInputStream:read	([BII)I
    //   51: pop
    //   52: aload_2
    //   53: astore_0
    //   54: aload_3
    //   55: invokestatic 82	com/tencent/mm/modelvideo/q:E	([B)Ljava/lang/String;
    //   58: astore_3
    //   59: aload_2
    //   60: astore_0
    //   61: aload_3
    //   62: invokestatic 73	com/tencent/mm/sdk/platformtools/bg:nm	(Ljava/lang/String;)Z
    //   65: ifne +33 -> 98
    //   68: aload_2
    //   69: astore_0
    //   70: aload_3
    //   71: invokevirtual 85	java/lang/String:toUpperCase	()Ljava/lang/String;
    //   74: ldc 119
    //   76: invokevirtual 93	java/lang/String:contains	(Ljava/lang/CharSequence;)Z
    //   79: istore_1
    //   80: iload_1
    //   81: ifeq +17 -> 98
    //   84: aload_2
    //   85: invokevirtual 98	java/io/FileInputStream:close	()V
    //   88: ldc2_w 110
    //   91: ldc 112
    //   93: invokestatic 23	com/tencent/gmtrace/GMTrace:o	(JI)V
    //   96: iconst_1
    //   97: ireturn
    //   98: aload_2
    //   99: invokevirtual 98	java/io/FileInputStream:close	()V
    //   102: ldc2_w 110
    //   105: ldc 112
    //   107: invokestatic 23	com/tencent/gmtrace/GMTrace:o	(JI)V
    //   110: iconst_0
    //   111: ireturn
    //   112: astore_3
    //   113: aconst_null
    //   114: astore_2
    //   115: aload_2
    //   116: astore_0
    //   117: ldc 57
    //   119: ldc 100
    //   121: iconst_1
    //   122: anewarray 4	java/lang/Object
    //   125: dup
    //   126: iconst_0
    //   127: aload_3
    //   128: invokestatic 104	com/tencent/mm/sdk/platformtools/bg:f	(Ljava/lang/Throwable;)Ljava/lang/String;
    //   131: aastore
    //   132: invokestatic 108	com/tencent/mm/sdk/platformtools/w:e	(Ljava/lang/String;Ljava/lang/String;[Ljava/lang/Object;)V
    //   135: aload_2
    //   136: ifnull -34 -> 102
    //   139: aload_2
    //   140: invokevirtual 98	java/io/FileInputStream:close	()V
    //   143: goto -41 -> 102
    //   146: astore_0
    //   147: goto -45 -> 102
    //   150: astore_2
    //   151: aconst_null
    //   152: astore_0
    //   153: aload_0
    //   154: ifnull +7 -> 161
    //   157: aload_0
    //   158: invokevirtual 98	java/io/FileInputStream:close	()V
    //   161: aload_2
    //   162: athrow
    //   163: astore_0
    //   164: goto -76 -> 88
    //   167: astore_0
    //   168: goto -66 -> 102
    //   171: astore_0
    //   172: goto -11 -> 161
    //   175: astore_2
    //   176: goto -23 -> 153
    //   179: astore_3
    //   180: goto -65 -> 115
    // Local variable table:
    //   start	length	slot	name	signature
    //   0	183	0	paramString	String
    //   79	2	1	bool	boolean
    //   33	107	2	localFileInputStream	java.io.FileInputStream
    //   150	12	2	localObject1	Object
    //   175	1	2	localObject2	Object
    //   40	31	3	localObject3	Object
    //   112	16	3	localException1	Exception
    //   179	1	3	localException2	Exception
    // Exception table:
    //   from	to	target	type
    //   25	34	112	java/lang/Exception
    //   139	143	146	java/io/IOException
    //   25	34	150	finally
    //   84	88	163	java/io/IOException
    //   98	102	167	java/io/IOException
    //   157	161	171	java/io/IOException
    //   36	41	175	finally
    //   43	52	175	finally
    //   54	59	175	finally
    //   61	68	175	finally
    //   70	80	175	finally
    //   117	135	175	finally
    //   36	41	179	java/lang/Exception
    //   43	52	179	java/lang/Exception
    //   54	59	179	java/lang/Exception
    //   61	68	179	java/lang/Exception
    //   70	80	179	java/lang/Exception
  }
  
  /* Error */
  public static boolean me(String paramString)
  {
    // Byte code:
    //   0: ldc2_w 123
    //   3: ldc 125
    //   5: invokestatic 14	com/tencent/gmtrace/GMTrace:i	(JI)V
    //   8: aload_0
    //   9: invokestatic 117	com/tencent/mm/a/e:aZ	(Ljava/lang/String;)Z
    //   12: ifne +13 -> 25
    //   15: ldc2_w 123
    //   18: ldc 125
    //   20: invokestatic 23	com/tencent/gmtrace/GMTrace:o	(JI)V
    //   23: iconst_0
    //   24: ireturn
    //   25: ldc 57
    //   27: ldc 127
    //   29: iconst_1
    //   30: anewarray 4	java/lang/Object
    //   33: dup
    //   34: iconst_0
    //   35: aload_0
    //   36: aastore
    //   37: invokestatic 129	com/tencent/mm/sdk/platformtools/w:d	(Ljava/lang/String;Ljava/lang/String;[Ljava/lang/Object;)V
    //   40: aconst_null
    //   41: astore 4
    //   43: new 131	android/media/MediaExtractor
    //   46: dup
    //   47: invokespecial 132	android/media/MediaExtractor:<init>	()V
    //   50: astore 5
    //   52: aload 5
    //   54: aload_0
    //   55: invokevirtual 135	android/media/MediaExtractor:setDataSource	(Ljava/lang/String;)V
    //   58: aload 5
    //   60: invokevirtual 138	android/media/MediaExtractor:getTrackCount	()I
    //   63: istore_2
    //   64: iconst_0
    //   65: istore_1
    //   66: iload_1
    //   67: iload_2
    //   68: if_icmpge +107 -> 175
    //   71: aconst_null
    //   72: astore 4
    //   74: aload 5
    //   76: iload_1
    //   77: invokevirtual 142	android/media/MediaExtractor:getTrackFormat	(I)Landroid/media/MediaFormat;
    //   80: ldc -112
    //   82: invokevirtual 150	android/media/MediaFormat:getString	(Ljava/lang/String;)Ljava/lang/String;
    //   85: astore 6
    //   87: aload 6
    //   89: astore 4
    //   91: ldc -104
    //   93: aload 6
    //   95: invokevirtual 155	java/lang/String:equalsIgnoreCase	(Ljava/lang/String;)Z
    //   98: istore_3
    //   99: aload 6
    //   101: astore 4
    //   103: iload_3
    //   104: ifeq +37 -> 141
    //   107: aload 5
    //   109: invokevirtual 158	android/media/MediaExtractor:release	()V
    //   112: ldc2_w 123
    //   115: ldc 125
    //   117: invokestatic 23	com/tencent/gmtrace/GMTrace:o	(JI)V
    //   120: iconst_1
    //   121: ireturn
    //   122: astore 6
    //   124: ldc 57
    //   126: aload 6
    //   128: ldc 127
    //   130: iconst_1
    //   131: anewarray 4	java/lang/Object
    //   134: dup
    //   135: iconst_0
    //   136: aload_0
    //   137: aastore
    //   138: invokestatic 162	com/tencent/mm/sdk/platformtools/w:printErrStackTrace	(Ljava/lang/String;Ljava/lang/Throwable;Ljava/lang/String;[Ljava/lang/Object;)V
    //   141: ldc -104
    //   143: aload 4
    //   145: invokevirtual 155	java/lang/String:equalsIgnoreCase	(Ljava/lang/String;)Z
    //   148: istore_3
    //   149: iload_3
    //   150: ifeq +18 -> 168
    //   153: aload 5
    //   155: invokevirtual 158	android/media/MediaExtractor:release	()V
    //   158: ldc2_w 123
    //   161: ldc 125
    //   163: invokestatic 23	com/tencent/gmtrace/GMTrace:o	(JI)V
    //   166: iconst_1
    //   167: ireturn
    //   168: iload_1
    //   169: iconst_1
    //   170: iadd
    //   171: istore_1
    //   172: goto -106 -> 66
    //   175: aload 5
    //   177: invokevirtual 158	android/media/MediaExtractor:release	()V
    //   180: ldc2_w 123
    //   183: ldc 125
    //   185: invokestatic 23	com/tencent/gmtrace/GMTrace:o	(JI)V
    //   188: iconst_0
    //   189: ireturn
    //   190: astore 5
    //   192: ldc 57
    //   194: aload 5
    //   196: ldc 127
    //   198: iconst_1
    //   199: anewarray 4	java/lang/Object
    //   202: dup
    //   203: iconst_0
    //   204: aload_0
    //   205: aastore
    //   206: invokestatic 162	com/tencent/mm/sdk/platformtools/w:printErrStackTrace	(Ljava/lang/String;Ljava/lang/Throwable;Ljava/lang/String;[Ljava/lang/Object;)V
    //   209: aload 4
    //   211: ifnull -31 -> 180
    //   214: aload 4
    //   216: invokevirtual 158	android/media/MediaExtractor:release	()V
    //   219: goto -39 -> 180
    //   222: astore_0
    //   223: aconst_null
    //   224: astore 4
    //   226: aload 4
    //   228: ifnull +8 -> 236
    //   231: aload 4
    //   233: invokevirtual 158	android/media/MediaExtractor:release	()V
    //   236: aload_0
    //   237: athrow
    //   238: astore_0
    //   239: aload 5
    //   241: astore 4
    //   243: goto -17 -> 226
    //   246: astore_0
    //   247: goto -21 -> 226
    //   250: astore 6
    //   252: aload 5
    //   254: astore 4
    //   256: aload 6
    //   258: astore 5
    //   260: goto -68 -> 192
    // Local variable table:
    //   start	length	slot	name	signature
    //   0	263	0	paramString	String
    //   65	107	1	i	int
    //   63	6	2	j	int
    //   98	52	3	bool	boolean
    //   41	214	4	localObject1	Object
    //   50	126	5	localMediaExtractor	android.media.MediaExtractor
    //   190	63	5	localThrowable1	Throwable
    //   258	1	5	localObject2	Object
    //   85	15	6	str	String
    //   122	5	6	localThrowable2	Throwable
    //   250	7	6	localThrowable3	Throwable
    // Exception table:
    //   from	to	target	type
    //   74	87	122	java/lang/Throwable
    //   91	99	122	java/lang/Throwable
    //   43	52	190	java/lang/Throwable
    //   43	52	222	finally
    //   52	64	238	finally
    //   74	87	238	finally
    //   91	99	238	finally
    //   124	141	238	finally
    //   141	149	238	finally
    //   192	209	246	finally
    //   52	64	250	java/lang/Throwable
    //   124	141	250	java/lang/Throwable
    //   141	149	250	java/lang/Throwable
  }
  
  /* Error */
  public static boolean mf(String paramString)
  {
    // Byte code:
    //   0: ldc2_w 164
    //   3: ldc -90
    //   5: invokestatic 14	com/tencent/gmtrace/GMTrace:i	(JI)V
    //   8: ldc 57
    //   10: new 16	java/lang/StringBuilder
    //   13: dup
    //   14: ldc 59
    //   16: invokespecial 62	java/lang/StringBuilder:<init>	(Ljava/lang/String;)V
    //   19: aload_0
    //   20: invokevirtual 42	java/lang/StringBuilder:append	(Ljava/lang/String;)Ljava/lang/StringBuilder;
    //   23: invokevirtual 46	java/lang/StringBuilder:toString	()Ljava/lang/String;
    //   26: invokestatic 68	com/tencent/mm/sdk/platformtools/w:d	(Ljava/lang/String;Ljava/lang/String;)V
    //   29: aload_0
    //   30: invokestatic 73	com/tencent/mm/sdk/platformtools/bg:nm	(Ljava/lang/String;)Z
    //   33: ifeq +13 -> 46
    //   36: ldc2_w 164
    //   39: ldc -90
    //   41: invokestatic 23	com/tencent/gmtrace/GMTrace:o	(JI)V
    //   44: iconst_0
    //   45: ireturn
    //   46: new 75	java/io/FileInputStream
    //   49: dup
    //   50: aload_0
    //   51: invokespecial 76	java/io/FileInputStream:<init>	(Ljava/lang/String;)V
    //   54: astore_1
    //   55: aload_1
    //   56: astore_0
    //   57: bipush 7
    //   59: newarray <illegal type>
    //   61: astore_2
    //   62: aload_1
    //   63: astore_0
    //   64: aload_1
    //   65: aload_2
    //   66: iconst_0
    //   67: bipush 7
    //   69: invokevirtual 80	java/io/FileInputStream:read	([BII)I
    //   72: pop
    //   73: aload_1
    //   74: astore_0
    //   75: aload_2
    //   76: invokestatic 82	com/tencent/mm/modelvideo/q:E	([B)Ljava/lang/String;
    //   79: astore_2
    //   80: aload_1
    //   81: astore_0
    //   82: aload_2
    //   83: invokestatic 73	com/tencent/mm/sdk/platformtools/bg:nm	(Ljava/lang/String;)Z
    //   86: ifne +67 -> 153
    //   89: aload_1
    //   90: astore_0
    //   91: aload_2
    //   92: invokevirtual 85	java/lang/String:toUpperCase	()Ljava/lang/String;
    //   95: astore_2
    //   96: aload_1
    //   97: astore_0
    //   98: ldc 57
    //   100: new 16	java/lang/StringBuilder
    //   103: dup
    //   104: ldc 87
    //   106: invokespecial 62	java/lang/StringBuilder:<init>	(Ljava/lang/String;)V
    //   109: aload_2
    //   110: invokevirtual 42	java/lang/StringBuilder:append	(Ljava/lang/String;)Ljava/lang/StringBuilder;
    //   113: invokevirtual 46	java/lang/StringBuilder:toString	()Ljava/lang/String;
    //   116: invokestatic 68	com/tencent/mm/sdk/platformtools/w:d	(Ljava/lang/String;Ljava/lang/String;)V
    //   119: aload_1
    //   120: astore_0
    //   121: aload_2
    //   122: ldc -88
    //   124: invokevirtual 93	java/lang/String:contains	(Ljava/lang/CharSequence;)Z
    //   127: ifeq +26 -> 153
    //   130: aload_1
    //   131: astore_0
    //   132: ldc 57
    //   134: ldc -86
    //   136: invokestatic 68	com/tencent/mm/sdk/platformtools/w:d	(Ljava/lang/String;Ljava/lang/String;)V
    //   139: aload_1
    //   140: invokevirtual 98	java/io/FileInputStream:close	()V
    //   143: ldc2_w 164
    //   146: ldc -90
    //   148: invokestatic 23	com/tencent/gmtrace/GMTrace:o	(JI)V
    //   151: iconst_1
    //   152: ireturn
    //   153: aload_1
    //   154: invokevirtual 98	java/io/FileInputStream:close	()V
    //   157: ldc2_w 164
    //   160: ldc -90
    //   162: invokestatic 23	com/tencent/gmtrace/GMTrace:o	(JI)V
    //   165: iconst_0
    //   166: ireturn
    //   167: astore_2
    //   168: aconst_null
    //   169: astore_1
    //   170: aload_1
    //   171: astore_0
    //   172: ldc 57
    //   174: ldc 100
    //   176: iconst_1
    //   177: anewarray 4	java/lang/Object
    //   180: dup
    //   181: iconst_0
    //   182: aload_2
    //   183: invokestatic 104	com/tencent/mm/sdk/platformtools/bg:f	(Ljava/lang/Throwable;)Ljava/lang/String;
    //   186: aastore
    //   187: invokestatic 108	com/tencent/mm/sdk/platformtools/w:e	(Ljava/lang/String;Ljava/lang/String;[Ljava/lang/Object;)V
    //   190: aload_1
    //   191: ifnull -34 -> 157
    //   194: aload_1
    //   195: invokevirtual 98	java/io/FileInputStream:close	()V
    //   198: goto -41 -> 157
    //   201: astore_0
    //   202: goto -45 -> 157
    //   205: astore_1
    //   206: aconst_null
    //   207: astore_0
    //   208: aload_0
    //   209: ifnull +7 -> 216
    //   212: aload_0
    //   213: invokevirtual 98	java/io/FileInputStream:close	()V
    //   216: aload_1
    //   217: athrow
    //   218: astore_0
    //   219: goto -76 -> 143
    //   222: astore_0
    //   223: goto -66 -> 157
    //   226: astore_0
    //   227: goto -11 -> 216
    //   230: astore_1
    //   231: goto -23 -> 208
    //   234: astore_2
    //   235: goto -65 -> 170
    // Local variable table:
    //   start	length	slot	name	signature
    //   0	238	0	paramString	String
    //   54	141	1	localFileInputStream	java.io.FileInputStream
    //   205	12	1	localObject1	Object
    //   230	1	1	localObject2	Object
    //   61	61	2	localObject3	Object
    //   167	16	2	localException1	Exception
    //   234	1	2	localException2	Exception
    // Exception table:
    //   from	to	target	type
    //   46	55	167	java/lang/Exception
    //   194	198	201	java/io/IOException
    //   46	55	205	finally
    //   139	143	218	java/io/IOException
    //   153	157	222	java/io/IOException
    //   212	216	226	java/io/IOException
    //   57	62	230	finally
    //   64	73	230	finally
    //   75	80	230	finally
    //   82	89	230	finally
    //   91	96	230	finally
    //   98	119	230	finally
    //   121	130	230	finally
    //   132	139	230	finally
    //   172	190	230	finally
    //   57	62	234	java/lang/Exception
    //   64	73	234	java/lang/Exception
    //   75	80	234	java/lang/Exception
    //   82	89	234	java/lang/Exception
    //   91	96	234	java/lang/Exception
    //   98	119	234	java/lang/Exception
    //   121	130	234	java/lang/Exception
    //   132	139	234	java/lang/Exception
  }
}


/* Location:              D:\tools\apktool\weixin6519android1140\jar\classes-dex2jar.jar!\com\tencent\mm\modelvideo\q.class
 * Java compiler version: 6 (50.0)
 * JD-Core Version:       0.7.1
 */