package com.tencent.mm.plugin.appbrand.h;

import android.text.TextUtils;
import com.tencent.gmtrace.GMTrace;
import com.tencent.mm.plugin.appbrand.a;
import com.tencent.mm.plugin.appbrand.config.AppBrandSysConfig;
import com.tencent.mm.sdk.f.e;
import com.tencent.mm.sdk.platformtools.w;
import java.net.HttpURLConnection;
import java.util.ArrayList;
import java.util.Iterator;
import java.util.Map;
import javax.net.ssl.SSLContext;
import org.json.JSONObject;

public final class f
{
  public String hyD;
  private int isH;
  public SSLContext isJ;
  public final String isK;
  protected final ArrayList<String> isL;
  private final ArrayList<g> itl;
  
  public f(String paramString1, String paramString2)
  {
    GMTrace.i(19902475796480L, 148285);
    this.itl = new ArrayList();
    this.isL = new ArrayList();
    this.hyD = paramString1;
    this.isH = a.nK(paramString1).hQS;
    this.isK = paramString2;
    GMTrace.o(19902475796480L, 148285);
  }
  
  public final void a(int paramInt, String paramString1, String arg3, JSONObject paramJSONObject, Map<String, String> paramMap, ArrayList<String> paramArrayList, a parama, String paramString3, String paramString4)
  {
    GMTrace.i(18360314101760L, 136795);
    String str1 = paramJSONObject.optString("url");
    String str2 = paramJSONObject.optString("name");
    paramJSONObject = i.p(paramJSONObject);
    synchronized (this.itl)
    {
      if (this.itl.size() >= this.isH)
      {
        parama.qI("tasked refused max connected");
        w.i("MicroMsg.AppBrandNetworkUpload", "max connected");
        GMTrace.o(18360314101760L, 136795);
        return;
      }
      if (TextUtils.isEmpty(str2))
      {
        parama.qI("fileName error");
        w.i("MicroMsg.AppBrandNetworkUpload", "fileName error");
        GMTrace.o(18360314101760L, 136795);
        return;
      }
    }
    paramString1 = new g(???, str1, str2, paramInt, paramString1, parama);
    paramString1.itp = paramJSONObject;
    paramString1.ite = paramMap;
    paramString1.itf = paramArrayList;
    paramString1.aDI = true;
    paramString1.hXm = paramString3;
    paramString1.itj = paramString4;
    synchronized (this.itl)
    {
      this.itl.add(paramString1);
      e.post(new b(paramString1), "appbrand_upload_thread");
      GMTrace.o(18360314101760L, 136795);
      return;
    }
  }
  
  public final void a(g paramg)
  {
    GMTrace.i(20766166876160L, 154720);
    if (paramg == null)
    {
      GMTrace.o(20766166876160L, 154720);
      return;
    }
    this.isL.add(paramg.hXm);
    paramg.aDI = false;
    a(paramg.hXm, paramg.iti);
    GMTrace.o(20766166876160L, 154720);
  }
  
  public final void a(String paramString, HttpURLConnection paramHttpURLConnection)
  {
    GMTrace.i(20766435311616L, 154722);
    if (paramString != null) {}
    synchronized (this.itl)
    {
      Iterator localIterator = this.itl.iterator();
      while (localIterator.hasNext())
      {
        g localg = (g)localIterator.next();
        if (paramString.equals(localg.hXm)) {
          this.itl.remove(localg);
        }
      }
      if (paramHttpURLConnection != null) {
        paramHttpURLConnection.disconnect();
      }
      GMTrace.o(20766435311616L, 154722);
      return;
    }
  }
  
  public final boolean rm(String paramString)
  {
    GMTrace.i(20766301093888L, 154721);
    boolean bool = this.isL.contains(paramString);
    GMTrace.o(20766301093888L, 154721);
    return bool;
  }
  
  public final g rs(String paramString)
  {
    GMTrace.i(17695533694976L, 131842);
    if (paramString == null)
    {
      GMTrace.o(17695533694976L, 131842);
      return null;
    }
    synchronized (this.itl)
    {
      Iterator localIterator = this.itl.iterator();
      while (localIterator.hasNext())
      {
        g localg = (g)localIterator.next();
        if (paramString.equals(localg.hXm))
        {
          GMTrace.o(17695533694976L, 131842);
          return localg;
        }
      }
      GMTrace.o(17695533694976L, 131842);
      return null;
    }
  }
  
  public static abstract interface a
  {
    public abstract void b(int paramInt1, String paramString, int paramInt2);
    
    public abstract void c(int paramInt, long paramLong1, long paramLong2);
    
    public abstract void qI(String paramString);
  }
  
  public final class b
    implements Runnable
  {
    private g itm;
    
    public b(g paramg)
    {
      GMTrace.i(10676349173760L, 79545);
      this.itm = paramg;
      GMTrace.o(10676349173760L, 79545);
    }
    
    /* Error */
    private void b(g paramg)
    {
      // Byte code:
      //   0: ldc2_w 51
      //   3: ldc 53
      //   5: invokestatic 29	com/tencent/gmtrace/GMTrace:i	(JI)V
      //   8: aload_1
      //   9: getfield 59	com/tencent/mm/plugin/appbrand/h/g:mUrl	Ljava/lang/String;
      //   12: astore 30
      //   14: aload_1
      //   15: getfield 62	com/tencent/mm/plugin/appbrand/h/g:ito	Ljava/lang/String;
      //   18: astore 31
      //   20: aload_1
      //   21: getfield 65	com/tencent/mm/plugin/appbrand/h/g:mName	Ljava/lang/String;
      //   24: astore 35
      //   26: aload_1
      //   27: getfield 68	com/tencent/mm/plugin/appbrand/h/g:mMimeType	Ljava/lang/String;
      //   30: astore 36
      //   32: new 70	java/lang/StringBuilder
      //   35: dup
      //   36: ldc 72
      //   38: invokespecial 75	java/lang/StringBuilder:<init>	(Ljava/lang/String;)V
      //   41: astore 20
      //   43: aload 36
      //   45: invokestatic 81	com/tencent/mm/pluginsdk/ui/tools/s:OV	(Ljava/lang/String;)Ljava/lang/String;
      //   48: astore 18
      //   50: ldc 83
      //   52: astore 19
      //   54: aload 18
      //   56: invokestatic 89	com/tencent/mm/sdk/platformtools/bg:nm	(Ljava/lang/String;)Z
      //   59: ifeq +152 -> 211
      //   62: aload 19
      //   64: astore 18
      //   66: aload 20
      //   68: aload 18
      //   70: invokevirtual 93	java/lang/StringBuilder:append	(Ljava/lang/String;)Ljava/lang/StringBuilder;
      //   73: invokevirtual 97	java/lang/StringBuilder:toString	()Ljava/lang/String;
      //   76: astore 37
      //   78: aload_1
      //   79: getfield 101	com/tencent/mm/plugin/appbrand/h/g:itp	Ljava/util/Map;
      //   82: astore 38
      //   84: aload_1
      //   85: getfield 104	com/tencent/mm/plugin/appbrand/h/g:ite	Ljava/util/Map;
      //   88: astore 40
      //   90: iconst_0
      //   91: istore 6
      //   93: iconst_0
      //   94: istore 7
      //   96: iconst_0
      //   97: istore 8
      //   99: iconst_0
      //   100: istore 4
      //   102: iconst_0
      //   103: istore 5
      //   105: iconst_0
      //   106: istore 9
      //   108: iconst_0
      //   109: istore 10
      //   111: iconst_0
      //   112: istore 11
      //   114: iconst_0
      //   115: istore 12
      //   117: iconst_0
      //   118: istore_3
      //   119: lconst_0
      //   120: lstore 14
      //   122: aload_1
      //   123: getfield 108	com/tencent/mm/plugin/appbrand/h/g:itq	Lcom/tencent/mm/plugin/appbrand/h/f$a;
      //   126: astore 32
      //   128: aload_1
      //   129: getfield 112	com/tencent/mm/plugin/appbrand/h/g:itf	Ljava/util/ArrayList;
      //   132: astore 41
      //   134: aload 41
      //   136: ifnull +78 -> 214
      //   139: aload 41
      //   141: aload 30
      //   143: invokestatic 118	com/tencent/mm/plugin/appbrand/h/i:a	(Ljava/util/ArrayList;Ljava/lang/String;)Z
      //   146: ifne +68 -> 214
      //   149: aload 32
      //   151: ldc 120
      //   153: invokeinterface 125 2 0
      //   158: aload_0
      //   159: getfield 17	com/tencent/mm/plugin/appbrand/h/f$b:itn	Lcom/tencent/mm/plugin/appbrand/h/f;
      //   162: getfield 128	com/tencent/mm/plugin/appbrand/h/f:hyD	Ljava/lang/String;
      //   165: aload_1
      //   166: getfield 131	com/tencent/mm/plugin/appbrand/h/g:itj	Ljava/lang/String;
      //   169: ldc -123
      //   171: aload_1
      //   172: getfield 59	com/tencent/mm/plugin/appbrand/h/g:mUrl	Ljava/lang/String;
      //   175: lconst_0
      //   176: lconst_0
      //   177: iconst_0
      //   178: iconst_2
      //   179: aload_1
      //   180: invokevirtual 137	com/tencent/mm/plugin/appbrand/h/g:YQ	()I
      //   183: invokestatic 142	com/tencent/mm/plugin/appbrand/report/a/d:a	(Ljava/lang/String;Ljava/lang/String;Ljava/lang/String;Ljava/lang/String;JJIII)V
      //   186: ldc -112
      //   188: ldc -110
      //   190: iconst_1
      //   191: anewarray 4	java/lang/Object
      //   194: dup
      //   195: iconst_0
      //   196: aload 30
      //   198: aastore
      //   199: invokestatic 151	com/tencent/mm/sdk/platformtools/w:i	(Ljava/lang/String;Ljava/lang/String;[Ljava/lang/Object;)V
      //   202: ldc2_w 51
      //   205: ldc 53
      //   207: invokestatic 34	com/tencent/gmtrace/GMTrace:o	(JI)V
      //   210: return
      //   211: goto -145 -> 66
      //   214: aconst_null
      //   215: astore 20
      //   217: aconst_null
      //   218: astore 26
      //   220: aconst_null
      //   221: astore 21
      //   223: aconst_null
      //   224: astore 24
      //   226: aconst_null
      //   227: astore 18
      //   229: aconst_null
      //   230: astore 28
      //   232: aconst_null
      //   233: astore 29
      //   235: aconst_null
      //   236: astore 25
      //   238: aconst_null
      //   239: astore 27
      //   241: aload_1
      //   242: getfield 155	com/tencent/mm/plugin/appbrand/h/g:aDI	Z
      //   245: ifne +56 -> 301
      //   248: aload 32
      //   250: ldc -99
      //   252: invokeinterface 125 2 0
      //   257: aload_0
      //   258: getfield 17	com/tencent/mm/plugin/appbrand/h/f$b:itn	Lcom/tencent/mm/plugin/appbrand/h/f;
      //   261: getfield 128	com/tencent/mm/plugin/appbrand/h/f:hyD	Ljava/lang/String;
      //   264: aload_1
      //   265: getfield 131	com/tencent/mm/plugin/appbrand/h/g:itj	Ljava/lang/String;
      //   268: ldc -123
      //   270: aload_1
      //   271: getfield 59	com/tencent/mm/plugin/appbrand/h/g:mUrl	Ljava/lang/String;
      //   274: lconst_0
      //   275: lconst_0
      //   276: iconst_0
      //   277: iconst_2
      //   278: aload_1
      //   279: invokevirtual 137	com/tencent/mm/plugin/appbrand/h/g:YQ	()I
      //   282: invokestatic 142	com/tencent/mm/plugin/appbrand/report/a/d:a	(Ljava/lang/String;Ljava/lang/String;Ljava/lang/String;Ljava/lang/String;JJIII)V
      //   285: ldc -112
      //   287: ldc -97
      //   289: invokestatic 163	com/tencent/mm/sdk/platformtools/w:e	(Ljava/lang/String;Ljava/lang/String;)V
      //   292: ldc2_w 51
      //   295: ldc 53
      //   297: invokestatic 34	com/tencent/gmtrace/GMTrace:o	(JI)V
      //   300: return
      //   301: aload_1
      //   302: getfield 59	com/tencent/mm/plugin/appbrand/h/g:mUrl	Ljava/lang/String;
      //   305: invokestatic 168	android/webkit/URLUtil:isHttpsUrl	(Ljava/lang/String;)Z
      //   308: ifne +59 -> 367
      //   311: aload_1
      //   312: getfield 59	com/tencent/mm/plugin/appbrand/h/g:mUrl	Ljava/lang/String;
      //   315: invokestatic 171	android/webkit/URLUtil:isHttpUrl	(Ljava/lang/String;)Z
      //   318: ifne +49 -> 367
      //   321: aload 32
      //   323: ldc -83
      //   325: invokeinterface 125 2 0
      //   330: aload_0
      //   331: getfield 17	com/tencent/mm/plugin/appbrand/h/f$b:itn	Lcom/tencent/mm/plugin/appbrand/h/f;
      //   334: getfield 128	com/tencent/mm/plugin/appbrand/h/f:hyD	Ljava/lang/String;
      //   337: aload_1
      //   338: getfield 131	com/tencent/mm/plugin/appbrand/h/g:itj	Ljava/lang/String;
      //   341: ldc -123
      //   343: aload_1
      //   344: getfield 59	com/tencent/mm/plugin/appbrand/h/g:mUrl	Ljava/lang/String;
      //   347: lconst_0
      //   348: lconst_0
      //   349: iconst_0
      //   350: iconst_2
      //   351: aload_1
      //   352: invokevirtual 137	com/tencent/mm/plugin/appbrand/h/g:YQ	()I
      //   355: invokestatic 142	com/tencent/mm/plugin/appbrand/report/a/d:a	(Ljava/lang/String;Ljava/lang/String;Ljava/lang/String;Ljava/lang/String;JJIII)V
      //   358: ldc2_w 51
      //   361: ldc 53
      //   363: invokestatic 34	com/tencent/gmtrace/GMTrace:o	(JI)V
      //   366: return
      //   367: invokestatic 179	java/lang/System:currentTimeMillis	()J
      //   370: invokestatic 184	java/lang/Long:toString	(J)Ljava/lang/String;
      //   373: astore 39
      //   375: getstatic 190	com/tencent/mm/plugin/report/service/g:ork	Lcom/tencent/mm/plugin/report/service/g;
      //   378: ldc2_w 191
      //   381: lconst_0
      //   382: lconst_1
      //   383: iconst_0
      //   384: invokevirtual 195	com/tencent/mm/plugin/report/service/g:a	(JJJZ)V
      //   387: new 197	java/io/File
      //   390: dup
      //   391: aload 31
      //   393: invokespecial 198	java/io/File:<init>	(Ljava/lang/String;)V
      //   396: astore 34
      //   398: new 200	java/io/FileInputStream
      //   401: dup
      //   402: aload 34
      //   404: invokespecial 203	java/io/FileInputStream:<init>	(Ljava/io/File;)V
      //   407: astore 19
      //   409: aload 25
      //   411: astore 24
      //   413: aload 26
      //   415: astore 22
      //   417: aload 28
      //   419: astore 20
      //   421: aload 29
      //   423: astore 23
      //   425: new 205	java/net/URL
      //   428: dup
      //   429: aload 30
      //   431: invokespecial 206	java/net/URL:<init>	(Ljava/lang/String;)V
      //   434: astore 33
      //   436: aload 25
      //   438: astore 24
      //   440: aload 26
      //   442: astore 22
      //   444: aload 28
      //   446: astore 20
      //   448: aload 29
      //   450: astore 23
      //   452: aload 33
      //   454: invokevirtual 210	java/net/URL:openConnection	()Ljava/net/URLConnection;
      //   457: checkcast 212	java/net/HttpURLConnection
      //   460: astore 18
      //   462: aload 18
      //   464: astore 24
      //   466: aload 18
      //   468: astore 22
      //   470: aload 18
      //   472: astore 20
      //   474: aload 18
      //   476: astore 23
      //   478: aload_1
      //   479: getfield 215	com/tencent/mm/plugin/appbrand/h/g:hXm	Ljava/lang/String;
      //   482: invokestatic 89	com/tencent/mm/sdk/platformtools/bg:nm	(Ljava/lang/String;)Z
      //   485: ifne +25 -> 510
      //   488: aload 18
      //   490: astore 24
      //   492: aload 18
      //   494: astore 22
      //   496: aload 18
      //   498: astore 20
      //   500: aload 18
      //   502: astore 23
      //   504: aload_1
      //   505: aload 18
      //   507: putfield 219	com/tencent/mm/plugin/appbrand/h/g:iti	Ljava/net/HttpURLConnection;
      //   510: aload 18
      //   512: astore 24
      //   514: aload 18
      //   516: astore 22
      //   518: aload 18
      //   520: astore 20
      //   522: aload 18
      //   524: astore 23
      //   526: aload 18
      //   528: instanceof 221
      //   531: ifeq +145 -> 676
      //   534: aload 18
      //   536: astore 24
      //   538: aload 18
      //   540: astore 22
      //   542: aload 18
      //   544: astore 20
      //   546: aload 18
      //   548: astore 23
      //   550: aload_0
      //   551: getfield 17	com/tencent/mm/plugin/appbrand/h/f$b:itn	Lcom/tencent/mm/plugin/appbrand/h/f;
      //   554: getfield 225	com/tencent/mm/plugin/appbrand/h/f:isJ	Ljavax/net/ssl/SSLContext;
      //   557: ifnonnull +36 -> 593
      //   560: aload 18
      //   562: astore 24
      //   564: aload 18
      //   566: astore 22
      //   568: aload 18
      //   570: astore 20
      //   572: aload 18
      //   574: astore 23
      //   576: aload_0
      //   577: getfield 17	com/tencent/mm/plugin/appbrand/h/f$b:itn	Lcom/tencent/mm/plugin/appbrand/h/f;
      //   580: aload_0
      //   581: getfield 17	com/tencent/mm/plugin/appbrand/h/f$b:itn	Lcom/tencent/mm/plugin/appbrand/h/f;
      //   584: getfield 128	com/tencent/mm/plugin/appbrand/h/f:hyD	Ljava/lang/String;
      //   587: invokestatic 229	com/tencent/mm/plugin/appbrand/h/i:rv	(Ljava/lang/String;)Ljavax/net/ssl/SSLContext;
      //   590: putfield 225	com/tencent/mm/plugin/appbrand/h/f:isJ	Ljavax/net/ssl/SSLContext;
      //   593: aload 18
      //   595: astore 24
      //   597: aload 18
      //   599: astore 22
      //   601: aload 18
      //   603: astore 20
      //   605: aload 18
      //   607: astore 23
      //   609: aload_0
      //   610: getfield 17	com/tencent/mm/plugin/appbrand/h/f$b:itn	Lcom/tencent/mm/plugin/appbrand/h/f;
      //   613: getfield 225	com/tencent/mm/plugin/appbrand/h/f:isJ	Ljavax/net/ssl/SSLContext;
      //   616: ifnull +60 -> 676
      //   619: aload 18
      //   621: astore 24
      //   623: aload 18
      //   625: astore 22
      //   627: aload 18
      //   629: astore 20
      //   631: aload 18
      //   633: astore 23
      //   635: aload 18
      //   637: checkcast 221	javax/net/ssl/HttpsURLConnection
      //   640: aload_0
      //   641: getfield 17	com/tencent/mm/plugin/appbrand/h/f$b:itn	Lcom/tencent/mm/plugin/appbrand/h/f;
      //   644: getfield 225	com/tencent/mm/plugin/appbrand/h/f:isJ	Ljavax/net/ssl/SSLContext;
      //   647: invokevirtual 235	javax/net/ssl/SSLContext:getSocketFactory	()Ljavax/net/ssl/SSLSocketFactory;
      //   650: invokevirtual 239	javax/net/ssl/HttpsURLConnection:setSSLSocketFactory	(Ljavax/net/ssl/SSLSocketFactory;)V
      //   653: aload 18
      //   655: astore 24
      //   657: aload 18
      //   659: astore 22
      //   661: aload 18
      //   663: astore 20
      //   665: aload 18
      //   667: astore 23
      //   669: aload 18
      //   671: aload 41
      //   673: invokestatic 242	com/tencent/mm/plugin/appbrand/h/i:a	(Ljava/net/HttpURLConnection;Ljava/util/ArrayList;)V
      //   676: aload 18
      //   678: astore 24
      //   680: aload 18
      //   682: astore 22
      //   684: aload 18
      //   686: astore 20
      //   688: aload 18
      //   690: astore 23
      //   692: aload 18
      //   694: iconst_1
      //   695: invokevirtual 246	java/net/HttpURLConnection:setDoInput	(Z)V
      //   698: aload 18
      //   700: astore 24
      //   702: aload 18
      //   704: astore 22
      //   706: aload 18
      //   708: astore 20
      //   710: aload 18
      //   712: astore 23
      //   714: aload 18
      //   716: iconst_1
      //   717: invokevirtual 249	java/net/HttpURLConnection:setDoOutput	(Z)V
      //   720: aload 18
      //   722: astore 24
      //   724: aload 18
      //   726: astore 22
      //   728: aload 18
      //   730: astore 20
      //   732: aload 18
      //   734: astore 23
      //   736: aload 18
      //   738: iconst_0
      //   739: invokevirtual 252	java/net/HttpURLConnection:setUseCaches	(Z)V
      //   742: aload 18
      //   744: astore 24
      //   746: aload 18
      //   748: astore 22
      //   750: aload 18
      //   752: astore 20
      //   754: aload 18
      //   756: astore 23
      //   758: aload 18
      //   760: aload_1
      //   761: getfield 256	com/tencent/mm/plugin/appbrand/h/g:ita	I
      //   764: invokevirtual 260	java/net/HttpURLConnection:setConnectTimeout	(I)V
      //   767: aload 18
      //   769: astore 24
      //   771: aload 18
      //   773: astore 22
      //   775: aload 18
      //   777: astore 20
      //   779: aload 18
      //   781: astore 23
      //   783: aload 18
      //   785: aload_1
      //   786: getfield 256	com/tencent/mm/plugin/appbrand/h/g:ita	I
      //   789: invokevirtual 263	java/net/HttpURLConnection:setReadTimeout	(I)V
      //   792: aload 18
      //   794: astore 24
      //   796: aload 18
      //   798: astore 22
      //   800: aload 18
      //   802: astore 20
      //   804: aload 18
      //   806: astore 23
      //   808: aload 18
      //   810: ldc -123
      //   812: invokevirtual 266	java/net/HttpURLConnection:setRequestMethod	(Ljava/lang/String;)V
      //   815: aload 18
      //   817: astore 24
      //   819: aload 18
      //   821: astore 22
      //   823: aload 18
      //   825: astore 20
      //   827: aload 18
      //   829: astore 23
      //   831: aload 18
      //   833: ldc_w 268
      //   836: ldc_w 270
      //   839: invokevirtual 273	java/net/HttpURLConnection:setRequestProperty	(Ljava/lang/String;Ljava/lang/String;)V
      //   842: aload 18
      //   844: astore 24
      //   846: aload 18
      //   848: astore 22
      //   850: aload 18
      //   852: astore 20
      //   854: aload 18
      //   856: astore 23
      //   858: aload 18
      //   860: ldc_w 275
      //   863: ldc_w 277
      //   866: invokevirtual 273	java/net/HttpURLConnection:setRequestProperty	(Ljava/lang/String;Ljava/lang/String;)V
      //   869: aload 18
      //   871: astore 24
      //   873: aload 18
      //   875: astore 22
      //   877: aload 18
      //   879: astore 20
      //   881: aload 18
      //   883: astore 23
      //   885: ldc -112
      //   887: ldc_w 279
      //   890: iconst_2
      //   891: anewarray 4	java/lang/Object
      //   894: dup
      //   895: iconst_0
      //   896: aload 34
      //   898: invokevirtual 282	java/io/File:getAbsolutePath	()Ljava/lang/String;
      //   901: aastore
      //   902: dup
      //   903: iconst_1
      //   904: aload 34
      //   906: invokevirtual 285	java/io/File:length	()J
      //   909: invokestatic 289	java/lang/Long:valueOf	(J)Ljava/lang/Long;
      //   912: aastore
      //   913: invokestatic 151	com/tencent/mm/sdk/platformtools/w:i	(Ljava/lang/String;Ljava/lang/String;[Ljava/lang/Object;)V
      //   916: aload 18
      //   918: astore 24
      //   920: aload 18
      //   922: astore 22
      //   924: aload 18
      //   926: astore 20
      //   928: aload 18
      //   930: astore 23
      //   932: aload 18
      //   934: iconst_0
      //   935: invokevirtual 292	java/net/HttpURLConnection:setInstanceFollowRedirects	(Z)V
      //   938: aload 40
      //   940: ifnull +773 -> 1713
      //   943: aload 18
      //   945: astore 24
      //   947: aload 18
      //   949: astore 22
      //   951: aload 18
      //   953: astore 20
      //   955: aload 18
      //   957: astore 23
      //   959: ldc -112
      //   961: ldc_w 294
      //   964: iconst_1
      //   965: anewarray 4	java/lang/Object
      //   968: dup
      //   969: iconst_0
      //   970: aload 30
      //   972: aastore
      //   973: invokestatic 151	com/tencent/mm/sdk/platformtools/w:i	(Ljava/lang/String;Ljava/lang/String;[Ljava/lang/Object;)V
      //   976: aload 18
      //   978: astore 24
      //   980: aload 18
      //   982: astore 22
      //   984: aload 18
      //   986: astore 20
      //   988: aload 18
      //   990: astore 23
      //   992: aload 40
      //   994: invokeinterface 300 1 0
      //   999: invokeinterface 306 1 0
      //   1004: astore 21
      //   1006: aload 18
      //   1008: astore 24
      //   1010: aload 18
      //   1012: astore 22
      //   1014: aload 18
      //   1016: astore 20
      //   1018: aload 18
      //   1020: astore 23
      //   1022: aload 21
      //   1024: invokeinterface 312 1 0
      //   1029: ifeq +684 -> 1713
      //   1032: aload 18
      //   1034: astore 24
      //   1036: aload 18
      //   1038: astore 22
      //   1040: aload 18
      //   1042: astore 20
      //   1044: aload 18
      //   1046: astore 23
      //   1048: aload 21
      //   1050: invokeinterface 316 1 0
      //   1055: checkcast 318	java/util/Map$Entry
      //   1058: astore 25
      //   1060: aload 18
      //   1062: astore 24
      //   1064: aload 18
      //   1066: astore 22
      //   1068: aload 18
      //   1070: astore 20
      //   1072: aload 18
      //   1074: astore 23
      //   1076: ldc -112
      //   1078: ldc_w 320
      //   1081: iconst_3
      //   1082: anewarray 4	java/lang/Object
      //   1085: dup
      //   1086: iconst_0
      //   1087: aload 30
      //   1089: aastore
      //   1090: dup
      //   1091: iconst_1
      //   1092: aload 25
      //   1094: invokeinterface 323 1 0
      //   1099: aastore
      //   1100: dup
      //   1101: iconst_2
      //   1102: aload 25
      //   1104: invokeinterface 326 1 0
      //   1109: aastore
      //   1110: invokestatic 151	com/tencent/mm/sdk/platformtools/w:i	(Ljava/lang/String;Ljava/lang/String;[Ljava/lang/Object;)V
      //   1113: aload 18
      //   1115: astore 24
      //   1117: aload 18
      //   1119: astore 22
      //   1121: aload 18
      //   1123: astore 20
      //   1125: aload 18
      //   1127: astore 23
      //   1129: aload 25
      //   1131: invokeinterface 323 1 0
      //   1136: checkcast 328	java/lang/String
      //   1139: invokestatic 89	com/tencent/mm/sdk/platformtools/bg:nm	(Ljava/lang/String;)Z
      //   1142: ifne -136 -> 1006
      //   1145: aload 18
      //   1147: astore 24
      //   1149: aload 18
      //   1151: astore 22
      //   1153: aload 18
      //   1155: astore 20
      //   1157: aload 18
      //   1159: astore 23
      //   1161: aload 25
      //   1163: invokeinterface 326 1 0
      //   1168: checkcast 328	java/lang/String
      //   1171: invokestatic 89	com/tencent/mm/sdk/platformtools/bg:nm	(Ljava/lang/String;)Z
      //   1174: ifne -168 -> 1006
      //   1177: aload 18
      //   1179: astore 24
      //   1181: aload 18
      //   1183: astore 22
      //   1185: aload 18
      //   1187: astore 20
      //   1189: aload 18
      //   1191: astore 23
      //   1193: aload 25
      //   1195: invokeinterface 323 1 0
      //   1200: checkcast 328	java/lang/String
      //   1203: invokevirtual 331	java/lang/String:toLowerCase	()Ljava/lang/String;
      //   1206: ldc_w 333
      //   1209: invokevirtual 337	java/lang/String:contains	(Ljava/lang/CharSequence;)Z
      //   1212: ifeq +205 -> 1417
      //   1215: aload 18
      //   1217: astore 24
      //   1219: aload 18
      //   1221: astore 22
      //   1223: aload 18
      //   1225: astore 20
      //   1227: aload 18
      //   1229: astore 23
      //   1231: ldc -112
      //   1233: ldc_w 339
      //   1236: invokestatic 163	com/tencent/mm/sdk/platformtools/w:e	(Ljava/lang/String;Ljava/lang/String;)V
      //   1239: goto -233 -> 1006
      //   1242: astore 21
      //   1244: aload 18
      //   1246: astore 20
      //   1248: aload 19
      //   1250: astore 18
      //   1252: aconst_null
      //   1253: astore 19
      //   1255: iconst_0
      //   1256: istore_2
      //   1257: aload 27
      //   1259: astore 22
      //   1261: getstatic 190	com/tencent/mm/plugin/report/service/g:ork	Lcom/tencent/mm/plugin/report/service/g;
      //   1264: ldc2_w 191
      //   1267: lconst_1
      //   1268: lconst_1
      //   1269: iconst_0
      //   1270: invokevirtual 195	com/tencent/mm/plugin/report/service/g:a	(JJJZ)V
      //   1273: ldc -112
      //   1275: ldc_w 341
      //   1278: iconst_3
      //   1279: anewarray 4	java/lang/Object
      //   1282: dup
      //   1283: iconst_0
      //   1284: aload 21
      //   1286: invokevirtual 342	java/io/UnsupportedEncodingException:toString	()Ljava/lang/String;
      //   1289: aastore
      //   1290: dup
      //   1291: iconst_1
      //   1292: aload 30
      //   1294: aastore
      //   1295: dup
      //   1296: iconst_2
      //   1297: aload 31
      //   1299: aastore
      //   1300: invokestatic 344	com/tencent/mm/sdk/platformtools/w:e	(Ljava/lang/String;Ljava/lang/String;[Ljava/lang/Object;)V
      //   1303: aload 32
      //   1305: iconst_m1
      //   1306: ldc_w 346
      //   1309: iload_3
      //   1310: invokeinterface 349 4 0
      //   1315: aload_0
      //   1316: getfield 17	com/tencent/mm/plugin/appbrand/h/f$b:itn	Lcom/tencent/mm/plugin/appbrand/h/f;
      //   1319: getfield 128	com/tencent/mm/plugin/appbrand/h/f:hyD	Ljava/lang/String;
      //   1322: aload_1
      //   1323: getfield 131	com/tencent/mm/plugin/appbrand/h/g:itj	Ljava/lang/String;
      //   1326: ldc -123
      //   1328: aload_1
      //   1329: getfield 59	com/tencent/mm/plugin/appbrand/h/g:mUrl	Ljava/lang/String;
      //   1332: lload 14
      //   1334: iload_2
      //   1335: i2l
      //   1336: iload_3
      //   1337: iconst_2
      //   1338: aload_1
      //   1339: invokevirtual 137	com/tencent/mm/plugin/appbrand/h/g:YQ	()I
      //   1342: invokestatic 142	com/tencent/mm/plugin/appbrand/report/a/d:a	(Ljava/lang/String;Ljava/lang/String;Ljava/lang/String;Ljava/lang/String;JJIII)V
      //   1345: aload_1
      //   1346: iconst_0
      //   1347: putfield 155	com/tencent/mm/plugin/appbrand/h/g:aDI	Z
      //   1350: aload_0
      //   1351: getfield 17	com/tencent/mm/plugin/appbrand/h/f$b:itn	Lcom/tencent/mm/plugin/appbrand/h/f;
      //   1354: aload_1
      //   1355: getfield 215	com/tencent/mm/plugin/appbrand/h/g:hXm	Ljava/lang/String;
      //   1358: aload 20
      //   1360: invokevirtual 352	com/tencent/mm/plugin/appbrand/h/f:a	(Ljava/lang/String;Ljava/net/HttpURLConnection;)V
      //   1363: aload 18
      //   1365: ifnull +8 -> 1373
      //   1368: aload 18
      //   1370: invokevirtual 355	java/io/FileInputStream:close	()V
      //   1373: aload 19
      //   1375: ifnull +8 -> 1383
      //   1378: aload 19
      //   1380: invokevirtual 358	java/io/InputStream:close	()V
      //   1383: aload 22
      //   1385: ifnull +8 -> 1393
      //   1388: aload 22
      //   1390: invokevirtual 361	java/io/DataOutputStream:close	()V
      //   1393: aload_0
      //   1394: getfield 17	com/tencent/mm/plugin/appbrand/h/f$b:itn	Lcom/tencent/mm/plugin/appbrand/h/f;
      //   1397: getfield 364	com/tencent/mm/plugin/appbrand/h/f:isL	Ljava/util/ArrayList;
      //   1400: aload_1
      //   1401: getfield 215	com/tencent/mm/plugin/appbrand/h/g:hXm	Ljava/lang/String;
      //   1404: invokevirtual 370	java/util/ArrayList:remove	(Ljava/lang/Object;)Z
      //   1407: pop
      //   1408: ldc2_w 51
      //   1411: ldc 53
      //   1413: invokestatic 34	com/tencent/gmtrace/GMTrace:o	(JI)V
      //   1416: return
      //   1417: aload 18
      //   1419: astore 24
      //   1421: aload 18
      //   1423: astore 22
      //   1425: aload 18
      //   1427: astore 20
      //   1429: aload 18
      //   1431: astore 23
      //   1433: aload 18
      //   1435: aload 25
      //   1437: invokeinterface 323 1 0
      //   1442: checkcast 328	java/lang/String
      //   1445: aload 25
      //   1447: invokeinterface 326 1 0
      //   1452: checkcast 328	java/lang/String
      //   1455: invokevirtual 273	java/net/HttpURLConnection:setRequestProperty	(Ljava/lang/String;Ljava/lang/String;)V
      //   1458: goto -452 -> 1006
      //   1461: astore 22
      //   1463: aconst_null
      //   1464: astore 25
      //   1466: aconst_null
      //   1467: astore 20
      //   1469: iload 9
      //   1471: istore_2
      //   1472: aload 19
      //   1474: astore 26
      //   1476: aload 24
      //   1478: astore 18
      //   1480: aload 26
      //   1482: astore 23
      //   1484: aload 20
      //   1486: astore 19
      //   1488: aload 25
      //   1490: astore 21
      //   1492: iload_2
      //   1493: istore 4
      //   1495: lload 14
      //   1497: lstore 16
      //   1499: iload 5
      //   1501: istore_3
      //   1502: getstatic 190	com/tencent/mm/plugin/report/service/g:ork	Lcom/tencent/mm/plugin/report/service/g;
      //   1505: ldc2_w 191
      //   1508: ldc2_w 371
      //   1511: lconst_1
      //   1512: iconst_0
      //   1513: invokevirtual 195	com/tencent/mm/plugin/report/service/g:a	(JJJZ)V
      //   1516: aload 24
      //   1518: astore 18
      //   1520: aload 26
      //   1522: astore 23
      //   1524: aload 20
      //   1526: astore 19
      //   1528: aload 25
      //   1530: astore 21
      //   1532: iload_2
      //   1533: istore 4
      //   1535: lload 14
      //   1537: lstore 16
      //   1539: iload 5
      //   1541: istore_3
      //   1542: ldc -112
      //   1544: ldc_w 374
      //   1547: iconst_3
      //   1548: anewarray 4	java/lang/Object
      //   1551: dup
      //   1552: iconst_0
      //   1553: aload 22
      //   1555: invokevirtual 375	java/io/FileNotFoundException:toString	()Ljava/lang/String;
      //   1558: aastore
      //   1559: dup
      //   1560: iconst_1
      //   1561: aload 30
      //   1563: aastore
      //   1564: dup
      //   1565: iconst_2
      //   1566: aload 31
      //   1568: aastore
      //   1569: invokestatic 344	com/tencent/mm/sdk/platformtools/w:e	(Ljava/lang/String;Ljava/lang/String;[Ljava/lang/Object;)V
      //   1572: aload 24
      //   1574: astore 18
      //   1576: aload 26
      //   1578: astore 23
      //   1580: aload 20
      //   1582: astore 19
      //   1584: aload 25
      //   1586: astore 21
      //   1588: iload_2
      //   1589: istore 4
      //   1591: lload 14
      //   1593: lstore 16
      //   1595: iload 5
      //   1597: istore_3
      //   1598: aload 32
      //   1600: iconst_m1
      //   1601: ldc_w 377
      //   1604: iload_2
      //   1605: invokeinterface 349 4 0
      //   1610: aload_0
      //   1611: getfield 17	com/tencent/mm/plugin/appbrand/h/f$b:itn	Lcom/tencent/mm/plugin/appbrand/h/f;
      //   1614: getfield 128	com/tencent/mm/plugin/appbrand/h/f:hyD	Ljava/lang/String;
      //   1617: aload_1
      //   1618: getfield 131	com/tencent/mm/plugin/appbrand/h/g:itj	Ljava/lang/String;
      //   1621: ldc -123
      //   1623: aload_1
      //   1624: getfield 59	com/tencent/mm/plugin/appbrand/h/g:mUrl	Ljava/lang/String;
      //   1627: lload 14
      //   1629: iload 5
      //   1631: i2l
      //   1632: iload_2
      //   1633: iconst_2
      //   1634: aload_1
      //   1635: invokevirtual 137	com/tencent/mm/plugin/appbrand/h/g:YQ	()I
      //   1638: invokestatic 142	com/tencent/mm/plugin/appbrand/report/a/d:a	(Ljava/lang/String;Ljava/lang/String;Ljava/lang/String;Ljava/lang/String;JJIII)V
      //   1641: aload_1
      //   1642: iconst_0
      //   1643: putfield 155	com/tencent/mm/plugin/appbrand/h/g:aDI	Z
      //   1646: aload_0
      //   1647: getfield 17	com/tencent/mm/plugin/appbrand/h/f$b:itn	Lcom/tencent/mm/plugin/appbrand/h/f;
      //   1650: aload_1
      //   1651: getfield 215	com/tencent/mm/plugin/appbrand/h/g:hXm	Ljava/lang/String;
      //   1654: aload 24
      //   1656: invokevirtual 352	com/tencent/mm/plugin/appbrand/h/f:a	(Ljava/lang/String;Ljava/net/HttpURLConnection;)V
      //   1659: aload 26
      //   1661: ifnull +8 -> 1669
      //   1664: aload 26
      //   1666: invokevirtual 355	java/io/FileInputStream:close	()V
      //   1669: aload 20
      //   1671: ifnull +8 -> 1679
      //   1674: aload 20
      //   1676: invokevirtual 358	java/io/InputStream:close	()V
      //   1679: aload 25
      //   1681: ifnull +8 -> 1689
      //   1684: aload 25
      //   1686: invokevirtual 361	java/io/DataOutputStream:close	()V
      //   1689: aload_0
      //   1690: getfield 17	com/tencent/mm/plugin/appbrand/h/f$b:itn	Lcom/tencent/mm/plugin/appbrand/h/f;
      //   1693: getfield 364	com/tencent/mm/plugin/appbrand/h/f:isL	Ljava/util/ArrayList;
      //   1696: aload_1
      //   1697: getfield 215	com/tencent/mm/plugin/appbrand/h/g:hXm	Ljava/lang/String;
      //   1700: invokevirtual 370	java/util/ArrayList:remove	(Ljava/lang/Object;)Z
      //   1703: pop
      //   1704: ldc2_w 51
      //   1707: ldc 53
      //   1709: invokestatic 34	com/tencent/gmtrace/GMTrace:o	(JI)V
      //   1712: return
      //   1713: aload 18
      //   1715: astore 24
      //   1717: aload 18
      //   1719: astore 22
      //   1721: aload 18
      //   1723: astore 20
      //   1725: aload 18
      //   1727: astore 23
      //   1729: aload 18
      //   1731: ldc_w 379
      //   1734: invokestatic 385	com/tencent/mm/sdk/platformtools/ab:getContext	()Landroid/content/Context;
      //   1737: aload_0
      //   1738: getfield 17	com/tencent/mm/plugin/appbrand/h/f$b:itn	Lcom/tencent/mm/plugin/appbrand/h/f;
      //   1741: getfield 388	com/tencent/mm/plugin/appbrand/h/f:isK	Ljava/lang/String;
      //   1744: invokestatic 392	com/tencent/mm/pluginsdk/ui/tools/s:aZ	(Landroid/content/Context;Ljava/lang/String;)Ljava/lang/String;
      //   1747: invokevirtual 273	java/net/HttpURLConnection:setRequestProperty	(Ljava/lang/String;Ljava/lang/String;)V
      //   1750: aload 18
      //   1752: astore 24
      //   1754: aload 18
      //   1756: astore 22
      //   1758: aload 18
      //   1760: astore 20
      //   1762: aload 18
      //   1764: astore 23
      //   1766: aload 34
      //   1768: invokevirtual 285	java/io/File:length	()J
      //   1771: lstore 16
      //   1773: aload 18
      //   1775: astore 24
      //   1777: aload 18
      //   1779: astore 22
      //   1781: aload 18
      //   1783: astore 20
      //   1785: aload 18
      //   1787: astore 23
      //   1789: new 70	java/lang/StringBuilder
      //   1792: dup
      //   1793: invokespecial 393	java/lang/StringBuilder:<init>	()V
      //   1796: astore 21
      //   1798: aload 18
      //   1800: astore 24
      //   1802: aload 18
      //   1804: astore 22
      //   1806: aload 18
      //   1808: astore 20
      //   1810: aload 18
      //   1812: astore 23
      //   1814: new 70	java/lang/StringBuilder
      //   1817: dup
      //   1818: invokespecial 393	java/lang/StringBuilder:<init>	()V
      //   1821: astore 25
      //   1823: aload 38
      //   1825: ifnull +921 -> 2746
      //   1828: aload 18
      //   1830: astore 24
      //   1832: aload 18
      //   1834: astore 22
      //   1836: aload 18
      //   1838: astore 20
      //   1840: aload 18
      //   1842: astore 23
      //   1844: aload 18
      //   1846: ldc_w 395
      //   1849: new 70	java/lang/StringBuilder
      //   1852: dup
      //   1853: ldc_w 397
      //   1856: invokespecial 75	java/lang/StringBuilder:<init>	(Ljava/lang/String;)V
      //   1859: aload 39
      //   1861: invokevirtual 93	java/lang/StringBuilder:append	(Ljava/lang/String;)Ljava/lang/StringBuilder;
      //   1864: invokevirtual 97	java/lang/StringBuilder:toString	()Ljava/lang/String;
      //   1867: invokevirtual 273	java/net/HttpURLConnection:setRequestProperty	(Ljava/lang/String;Ljava/lang/String;)V
      //   1870: aload 18
      //   1872: astore 24
      //   1874: aload 18
      //   1876: astore 22
      //   1878: aload 18
      //   1880: astore 20
      //   1882: aload 18
      //   1884: astore 23
      //   1886: aload 38
      //   1888: invokeinterface 400 1 0
      //   1893: invokeinterface 306 1 0
      //   1898: astore 26
      //   1900: aload 18
      //   1902: astore 24
      //   1904: aload 18
      //   1906: astore 22
      //   1908: aload 18
      //   1910: astore 20
      //   1912: aload 18
      //   1914: astore 23
      //   1916: aload 26
      //   1918: invokeinterface 312 1 0
      //   1923: ifeq +560 -> 2483
      //   1926: aload 18
      //   1928: astore 24
      //   1930: aload 18
      //   1932: astore 22
      //   1934: aload 18
      //   1936: astore 20
      //   1938: aload 18
      //   1940: astore 23
      //   1942: aload 26
      //   1944: invokeinterface 316 1 0
      //   1949: checkcast 328	java/lang/String
      //   1952: astore 28
      //   1954: aload 18
      //   1956: astore 24
      //   1958: aload 18
      //   1960: astore 22
      //   1962: aload 18
      //   1964: astore 20
      //   1966: aload 18
      //   1968: astore 23
      //   1970: aload 38
      //   1972: aload 28
      //   1974: invokeinterface 404 2 0
      //   1979: checkcast 328	java/lang/String
      //   1982: astore 29
      //   1984: aload 18
      //   1986: astore 24
      //   1988: aload 18
      //   1990: astore 22
      //   1992: aload 18
      //   1994: astore 20
      //   1996: aload 18
      //   1998: astore 23
      //   2000: ldc -112
      //   2002: ldc_w 406
      //   2005: iconst_2
      //   2006: anewarray 4	java/lang/Object
      //   2009: dup
      //   2010: iconst_0
      //   2011: aload 28
      //   2013: aastore
      //   2014: dup
      //   2015: iconst_1
      //   2016: aload 29
      //   2018: aastore
      //   2019: invokestatic 151	com/tencent/mm/sdk/platformtools/w:i	(Ljava/lang/String;Ljava/lang/String;[Ljava/lang/Object;)V
      //   2022: aload 18
      //   2024: astore 24
      //   2026: aload 18
      //   2028: astore 22
      //   2030: aload 18
      //   2032: astore 20
      //   2034: aload 18
      //   2036: astore 23
      //   2038: aload 21
      //   2040: new 70	java/lang/StringBuilder
      //   2043: dup
      //   2044: invokespecial 393	java/lang/StringBuilder:<init>	()V
      //   2047: ldc_w 408
      //   2050: invokevirtual 93	java/lang/StringBuilder:append	(Ljava/lang/String;)Ljava/lang/StringBuilder;
      //   2053: aload 39
      //   2055: invokevirtual 93	java/lang/StringBuilder:append	(Ljava/lang/String;)Ljava/lang/StringBuilder;
      //   2058: ldc_w 410
      //   2061: invokevirtual 93	java/lang/StringBuilder:append	(Ljava/lang/String;)Ljava/lang/StringBuilder;
      //   2064: invokevirtual 97	java/lang/StringBuilder:toString	()Ljava/lang/String;
      //   2067: invokevirtual 93	java/lang/StringBuilder:append	(Ljava/lang/String;)Ljava/lang/StringBuilder;
      //   2070: pop
      //   2071: aload 18
      //   2073: astore 24
      //   2075: aload 18
      //   2077: astore 22
      //   2079: aload 18
      //   2081: astore 20
      //   2083: aload 18
      //   2085: astore 23
      //   2087: aload 21
      //   2089: new 70	java/lang/StringBuilder
      //   2092: dup
      //   2093: ldc_w 412
      //   2096: invokespecial 75	java/lang/StringBuilder:<init>	(Ljava/lang/String;)V
      //   2099: aload 28
      //   2101: invokevirtual 93	java/lang/StringBuilder:append	(Ljava/lang/String;)Ljava/lang/StringBuilder;
      //   2104: ldc_w 414
      //   2107: invokevirtual 93	java/lang/StringBuilder:append	(Ljava/lang/String;)Ljava/lang/StringBuilder;
      //   2110: invokevirtual 97	java/lang/StringBuilder:toString	()Ljava/lang/String;
      //   2113: invokevirtual 93	java/lang/StringBuilder:append	(Ljava/lang/String;)Ljava/lang/StringBuilder;
      //   2116: pop
      //   2117: aload 18
      //   2119: astore 24
      //   2121: aload 18
      //   2123: astore 22
      //   2125: aload 18
      //   2127: astore 20
      //   2129: aload 18
      //   2131: astore 23
      //   2133: aload 21
      //   2135: ldc_w 410
      //   2138: invokevirtual 93	java/lang/StringBuilder:append	(Ljava/lang/String;)Ljava/lang/StringBuilder;
      //   2141: pop
      //   2142: aload 18
      //   2144: astore 24
      //   2146: aload 18
      //   2148: astore 22
      //   2150: aload 18
      //   2152: astore 20
      //   2154: aload 18
      //   2156: astore 23
      //   2158: aload 21
      //   2160: ldc_w 410
      //   2163: invokevirtual 93	java/lang/StringBuilder:append	(Ljava/lang/String;)Ljava/lang/StringBuilder;
      //   2166: pop
      //   2167: aload 18
      //   2169: astore 24
      //   2171: aload 18
      //   2173: astore 22
      //   2175: aload 18
      //   2177: astore 20
      //   2179: aload 18
      //   2181: astore 23
      //   2183: aload 21
      //   2185: aload 29
      //   2187: invokevirtual 93	java/lang/StringBuilder:append	(Ljava/lang/String;)Ljava/lang/StringBuilder;
      //   2190: pop
      //   2191: aload 18
      //   2193: astore 24
      //   2195: aload 18
      //   2197: astore 22
      //   2199: aload 18
      //   2201: astore 20
      //   2203: aload 18
      //   2205: astore 23
      //   2207: aload 21
      //   2209: ldc_w 410
      //   2212: invokevirtual 93	java/lang/StringBuilder:append	(Ljava/lang/String;)Ljava/lang/StringBuilder;
      //   2215: pop
      //   2216: goto -316 -> 1900
      //   2219: astore 18
      //   2221: aconst_null
      //   2222: astore 25
      //   2224: aconst_null
      //   2225: astore 20
      //   2227: iload 6
      //   2229: istore 5
      //   2231: iload 10
      //   2233: istore_2
      //   2234: aload 19
      //   2236: astore 26
      //   2238: aload 22
      //   2240: astore 24
      //   2242: aload 18
      //   2244: astore 22
      //   2246: aload 24
      //   2248: astore 18
      //   2250: aload 26
      //   2252: astore 23
      //   2254: aload 20
      //   2256: astore 19
      //   2258: aload 25
      //   2260: astore 21
      //   2262: iload_2
      //   2263: istore 4
      //   2265: lload 14
      //   2267: lstore 16
      //   2269: iload 5
      //   2271: istore_3
      //   2272: getstatic 190	com/tencent/mm/plugin/report/service/g:ork	Lcom/tencent/mm/plugin/report/service/g;
      //   2275: ldc2_w 191
      //   2278: ldc2_w 415
      //   2281: lconst_1
      //   2282: iconst_0
      //   2283: invokevirtual 195	com/tencent/mm/plugin/report/service/g:a	(JJJZ)V
      //   2286: aload 24
      //   2288: astore 18
      //   2290: aload 26
      //   2292: astore 23
      //   2294: aload 20
      //   2296: astore 19
      //   2298: aload 25
      //   2300: astore 21
      //   2302: iload_2
      //   2303: istore 4
      //   2305: lload 14
      //   2307: lstore 16
      //   2309: iload 5
      //   2311: istore_3
      //   2312: ldc -112
      //   2314: ldc_w 418
      //   2317: iconst_3
      //   2318: anewarray 4	java/lang/Object
      //   2321: dup
      //   2322: iconst_0
      //   2323: aload 22
      //   2325: invokevirtual 419	javax/net/ssl/SSLHandshakeException:toString	()Ljava/lang/String;
      //   2328: aastore
      //   2329: dup
      //   2330: iconst_1
      //   2331: aload 30
      //   2333: aastore
      //   2334: dup
      //   2335: iconst_2
      //   2336: aload 31
      //   2338: aastore
      //   2339: invokestatic 344	com/tencent/mm/sdk/platformtools/w:e	(Ljava/lang/String;Ljava/lang/String;[Ljava/lang/Object;)V
      //   2342: aload 24
      //   2344: astore 18
      //   2346: aload 26
      //   2348: astore 23
      //   2350: aload 20
      //   2352: astore 19
      //   2354: aload 25
      //   2356: astore 21
      //   2358: iload_2
      //   2359: istore 4
      //   2361: lload 14
      //   2363: lstore 16
      //   2365: iload 5
      //   2367: istore_3
      //   2368: aload 32
      //   2370: iconst_m1
      //   2371: ldc_w 421
      //   2374: iload_2
      //   2375: invokeinterface 349 4 0
      //   2380: aload_0
      //   2381: getfield 17	com/tencent/mm/plugin/appbrand/h/f$b:itn	Lcom/tencent/mm/plugin/appbrand/h/f;
      //   2384: getfield 128	com/tencent/mm/plugin/appbrand/h/f:hyD	Ljava/lang/String;
      //   2387: aload_1
      //   2388: getfield 131	com/tencent/mm/plugin/appbrand/h/g:itj	Ljava/lang/String;
      //   2391: ldc -123
      //   2393: aload_1
      //   2394: getfield 59	com/tencent/mm/plugin/appbrand/h/g:mUrl	Ljava/lang/String;
      //   2397: lload 14
      //   2399: iload 5
      //   2401: i2l
      //   2402: iload_2
      //   2403: iconst_2
      //   2404: aload_1
      //   2405: invokevirtual 137	com/tencent/mm/plugin/appbrand/h/g:YQ	()I
      //   2408: invokestatic 142	com/tencent/mm/plugin/appbrand/report/a/d:a	(Ljava/lang/String;Ljava/lang/String;Ljava/lang/String;Ljava/lang/String;JJIII)V
      //   2411: aload_1
      //   2412: iconst_0
      //   2413: putfield 155	com/tencent/mm/plugin/appbrand/h/g:aDI	Z
      //   2416: aload_0
      //   2417: getfield 17	com/tencent/mm/plugin/appbrand/h/f$b:itn	Lcom/tencent/mm/plugin/appbrand/h/f;
      //   2420: aload_1
      //   2421: getfield 215	com/tencent/mm/plugin/appbrand/h/g:hXm	Ljava/lang/String;
      //   2424: aload 24
      //   2426: invokevirtual 352	com/tencent/mm/plugin/appbrand/h/f:a	(Ljava/lang/String;Ljava/net/HttpURLConnection;)V
      //   2429: aload 26
      //   2431: ifnull +8 -> 2439
      //   2434: aload 26
      //   2436: invokevirtual 355	java/io/FileInputStream:close	()V
      //   2439: aload 20
      //   2441: ifnull +8 -> 2449
      //   2444: aload 20
      //   2446: invokevirtual 358	java/io/InputStream:close	()V
      //   2449: aload 25
      //   2451: ifnull +8 -> 2459
      //   2454: aload 25
      //   2456: invokevirtual 361	java/io/DataOutputStream:close	()V
      //   2459: aload_0
      //   2460: getfield 17	com/tencent/mm/plugin/appbrand/h/f$b:itn	Lcom/tencent/mm/plugin/appbrand/h/f;
      //   2463: getfield 364	com/tencent/mm/plugin/appbrand/h/f:isL	Ljava/util/ArrayList;
      //   2466: aload_1
      //   2467: getfield 215	com/tencent/mm/plugin/appbrand/h/g:hXm	Ljava/lang/String;
      //   2470: invokevirtual 370	java/util/ArrayList:remove	(Ljava/lang/Object;)Z
      //   2473: pop
      //   2474: ldc2_w 51
      //   2477: ldc 53
      //   2479: invokestatic 34	com/tencent/gmtrace/GMTrace:o	(JI)V
      //   2482: return
      //   2483: aload 18
      //   2485: astore 24
      //   2487: aload 18
      //   2489: astore 22
      //   2491: aload 18
      //   2493: astore 20
      //   2495: aload 18
      //   2497: astore 23
      //   2499: aload 21
      //   2501: new 70	java/lang/StringBuilder
      //   2504: dup
      //   2505: invokespecial 393	java/lang/StringBuilder:<init>	()V
      //   2508: ldc_w 408
      //   2511: invokevirtual 93	java/lang/StringBuilder:append	(Ljava/lang/String;)Ljava/lang/StringBuilder;
      //   2514: aload 39
      //   2516: invokevirtual 93	java/lang/StringBuilder:append	(Ljava/lang/String;)Ljava/lang/StringBuilder;
      //   2519: ldc_w 410
      //   2522: invokevirtual 93	java/lang/StringBuilder:append	(Ljava/lang/String;)Ljava/lang/StringBuilder;
      //   2525: invokevirtual 97	java/lang/StringBuilder:toString	()Ljava/lang/String;
      //   2528: invokevirtual 93	java/lang/StringBuilder:append	(Ljava/lang/String;)Ljava/lang/StringBuilder;
      //   2531: pop
      //   2532: aload 18
      //   2534: astore 24
      //   2536: aload 18
      //   2538: astore 22
      //   2540: aload 18
      //   2542: astore 20
      //   2544: aload 18
      //   2546: astore 23
      //   2548: aload 21
      //   2550: new 70	java/lang/StringBuilder
      //   2553: dup
      //   2554: ldc_w 412
      //   2557: invokespecial 75	java/lang/StringBuilder:<init>	(Ljava/lang/String;)V
      //   2560: aload 35
      //   2562: invokevirtual 93	java/lang/StringBuilder:append	(Ljava/lang/String;)Ljava/lang/StringBuilder;
      //   2565: ldc_w 423
      //   2568: invokevirtual 93	java/lang/StringBuilder:append	(Ljava/lang/String;)Ljava/lang/StringBuilder;
      //   2571: aload 37
      //   2573: invokevirtual 93	java/lang/StringBuilder:append	(Ljava/lang/String;)Ljava/lang/StringBuilder;
      //   2576: ldc_w 414
      //   2579: invokevirtual 93	java/lang/StringBuilder:append	(Ljava/lang/String;)Ljava/lang/StringBuilder;
      //   2582: ldc_w 410
      //   2585: invokevirtual 93	java/lang/StringBuilder:append	(Ljava/lang/String;)Ljava/lang/StringBuilder;
      //   2588: invokevirtual 97	java/lang/StringBuilder:toString	()Ljava/lang/String;
      //   2591: invokevirtual 93	java/lang/StringBuilder:append	(Ljava/lang/String;)Ljava/lang/StringBuilder;
      //   2594: pop
      //   2595: aload 18
      //   2597: astore 24
      //   2599: aload 18
      //   2601: astore 22
      //   2603: aload 18
      //   2605: astore 20
      //   2607: aload 18
      //   2609: astore 23
      //   2611: aload 21
      //   2613: new 70	java/lang/StringBuilder
      //   2616: dup
      //   2617: ldc_w 425
      //   2620: invokespecial 75	java/lang/StringBuilder:<init>	(Ljava/lang/String;)V
      //   2623: aload 36
      //   2625: invokevirtual 93	java/lang/StringBuilder:append	(Ljava/lang/String;)Ljava/lang/StringBuilder;
      //   2628: invokevirtual 97	java/lang/StringBuilder:toString	()Ljava/lang/String;
      //   2631: invokevirtual 93	java/lang/StringBuilder:append	(Ljava/lang/String;)Ljava/lang/StringBuilder;
      //   2634: pop
      //   2635: aload 18
      //   2637: astore 24
      //   2639: aload 18
      //   2641: astore 22
      //   2643: aload 18
      //   2645: astore 20
      //   2647: aload 18
      //   2649: astore 23
      //   2651: aload 21
      //   2653: ldc_w 410
      //   2656: invokevirtual 93	java/lang/StringBuilder:append	(Ljava/lang/String;)Ljava/lang/StringBuilder;
      //   2659: pop
      //   2660: aload 18
      //   2662: astore 24
      //   2664: aload 18
      //   2666: astore 22
      //   2668: aload 18
      //   2670: astore 20
      //   2672: aload 18
      //   2674: astore 23
      //   2676: aload 21
      //   2678: ldc_w 410
      //   2681: invokevirtual 93	java/lang/StringBuilder:append	(Ljava/lang/String;)Ljava/lang/StringBuilder;
      //   2684: pop
      //   2685: aload 18
      //   2687: astore 24
      //   2689: aload 18
      //   2691: astore 22
      //   2693: aload 18
      //   2695: astore 20
      //   2697: aload 18
      //   2699: astore 23
      //   2701: aload 25
      //   2703: new 70	java/lang/StringBuilder
      //   2706: dup
      //   2707: invokespecial 393	java/lang/StringBuilder:<init>	()V
      //   2710: ldc_w 410
      //   2713: invokevirtual 93	java/lang/StringBuilder:append	(Ljava/lang/String;)Ljava/lang/StringBuilder;
      //   2716: ldc_w 408
      //   2719: invokevirtual 93	java/lang/StringBuilder:append	(Ljava/lang/String;)Ljava/lang/StringBuilder;
      //   2722: aload 39
      //   2724: invokevirtual 93	java/lang/StringBuilder:append	(Ljava/lang/String;)Ljava/lang/StringBuilder;
      //   2727: ldc_w 408
      //   2730: invokevirtual 93	java/lang/StringBuilder:append	(Ljava/lang/String;)Ljava/lang/StringBuilder;
      //   2733: ldc_w 410
      //   2736: invokevirtual 93	java/lang/StringBuilder:append	(Ljava/lang/String;)Ljava/lang/StringBuilder;
      //   2739: invokevirtual 97	java/lang/StringBuilder:toString	()Ljava/lang/String;
      //   2742: invokevirtual 93	java/lang/StringBuilder:append	(Ljava/lang/String;)Ljava/lang/StringBuilder;
      //   2745: pop
      //   2746: aload 18
      //   2748: astore 24
      //   2750: aload 18
      //   2752: astore 22
      //   2754: aload 18
      //   2756: astore 20
      //   2758: aload 18
      //   2760: astore 23
      //   2762: aload 21
      //   2764: invokevirtual 97	java/lang/StringBuilder:toString	()Ljava/lang/String;
      //   2767: ldc_w 427
      //   2770: invokevirtual 431	java/lang/String:getBytes	(Ljava/lang/String;)[B
      //   2773: astore 21
      //   2775: aload 18
      //   2777: astore 24
      //   2779: aload 18
      //   2781: astore 22
      //   2783: aload 18
      //   2785: astore 20
      //   2787: aload 18
      //   2789: astore 23
      //   2791: aload 25
      //   2793: invokevirtual 97	java/lang/StringBuilder:toString	()Ljava/lang/String;
      //   2796: ldc_w 427
      //   2799: invokevirtual 431	java/lang/String:getBytes	(Ljava/lang/String;)[B
      //   2802: astore 26
      //   2804: aload 21
      //   2806: astore 25
      //   2808: aload 21
      //   2810: ifnonnull +24 -> 2834
      //   2813: aload 18
      //   2815: astore 24
      //   2817: aload 18
      //   2819: astore 22
      //   2821: aload 18
      //   2823: astore 20
      //   2825: aload 18
      //   2827: astore 23
      //   2829: iconst_0
      //   2830: newarray <illegal type>
      //   2832: astore 25
      //   2834: aload 26
      //   2836: ifnonnull +4290 -> 7126
      //   2839: aload 18
      //   2841: astore 24
      //   2843: aload 18
      //   2845: astore 22
      //   2847: aload 18
      //   2849: astore 20
      //   2851: aload 18
      //   2853: astore 23
      //   2855: iconst_0
      //   2856: newarray <illegal type>
      //   2858: astore 26
      //   2860: aload 18
      //   2862: astore 24
      //   2864: aload 18
      //   2866: astore 22
      //   2868: aload 18
      //   2870: astore 20
      //   2872: aload 18
      //   2874: astore 23
      //   2876: lload 16
      //   2878: aload 25
      //   2880: arraylength
      //   2881: i2l
      //   2882: ladd
      //   2883: aload 26
      //   2885: arraylength
      //   2886: i2l
      //   2887: ladd
      //   2888: lstore 16
      //   2890: aload 18
      //   2892: astore 24
      //   2894: aload 18
      //   2896: astore 22
      //   2898: aload 18
      //   2900: astore 20
      //   2902: aload 18
      //   2904: astore 23
      //   2906: ldc -112
      //   2908: ldc_w 433
      //   2911: iconst_1
      //   2912: anewarray 4	java/lang/Object
      //   2915: dup
      //   2916: iconst_0
      //   2917: lload 16
      //   2919: invokestatic 289	java/lang/Long:valueOf	(J)Ljava/lang/Long;
      //   2922: aastore
      //   2923: invokestatic 151	com/tencent/mm/sdk/platformtools/w:i	(Ljava/lang/String;Ljava/lang/String;[Ljava/lang/Object;)V
      //   2926: aload 18
      //   2928: astore 24
      //   2930: aload 18
      //   2932: astore 22
      //   2934: aload 18
      //   2936: astore 20
      //   2938: aload 18
      //   2940: astore 23
      //   2942: aload 18
      //   2944: ldc_w 435
      //   2947: lload 16
      //   2949: invokestatic 437	java/lang/String:valueOf	(J)Ljava/lang/String;
      //   2952: invokevirtual 273	java/net/HttpURLConnection:setRequestProperty	(Ljava/lang/String;Ljava/lang/String;)V
      //   2955: aload 18
      //   2957: astore 24
      //   2959: aload 18
      //   2961: astore 22
      //   2963: aload 18
      //   2965: astore 20
      //   2967: aload 18
      //   2969: astore 23
      //   2971: new 360	java/io/DataOutputStream
      //   2974: dup
      //   2975: aload 18
      //   2977: invokevirtual 441	java/net/HttpURLConnection:getOutputStream	()Ljava/io/OutputStream;
      //   2980: invokespecial 444	java/io/DataOutputStream:<init>	(Ljava/io/OutputStream;)V
      //   2983: astore 21
      //   2985: aload 21
      //   2987: aload 25
      //   2989: invokevirtual 448	java/io/DataOutputStream:write	([B)V
      //   2992: sipush 8192
      //   2995: newarray <illegal type>
      //   2997: astore 20
      //   2999: aload 34
      //   3001: invokevirtual 285	java/io/File:length	()J
      //   3004: lstore 16
      //   3006: lconst_0
      //   3007: lstore 14
      //   3009: aload 19
      //   3011: aload 20
      //   3013: invokevirtual 452	java/io/FileInputStream:read	([B)I
      //   3016: istore 13
      //   3018: iload 13
      //   3020: iconst_m1
      //   3021: if_icmpeq +340 -> 3361
      //   3024: aload_1
      //   3025: getfield 155	com/tencent/mm/plugin/appbrand/h/g:aDI	Z
      //   3028: ifeq +333 -> 3361
      //   3031: aload_0
      //   3032: getfield 17	com/tencent/mm/plugin/appbrand/h/f$b:itn	Lcom/tencent/mm/plugin/appbrand/h/f;
      //   3035: getfield 128	com/tencent/mm/plugin/appbrand/h/f:hyD	Ljava/lang/String;
      //   3038: invokestatic 458	com/tencent/mm/plugin/appbrand/a:nI	(Ljava/lang/String;)Lcom/tencent/mm/plugin/appbrand/e;
      //   3041: astore 22
      //   3043: aload 22
      //   3045: ifnonnull +100 -> 3145
      //   3048: iconst_1
      //   3049: istore_2
      //   3050: iload_2
      //   3051: ifeq +217 -> 3268
      //   3054: aload 32
      //   3056: ldc_w 460
      //   3059: invokeinterface 125 2 0
      //   3064: aload_0
      //   3065: getfield 17	com/tencent/mm/plugin/appbrand/h/f$b:itn	Lcom/tencent/mm/plugin/appbrand/h/f;
      //   3068: getfield 128	com/tencent/mm/plugin/appbrand/h/f:hyD	Ljava/lang/String;
      //   3071: aload_1
      //   3072: getfield 131	com/tencent/mm/plugin/appbrand/h/g:itj	Ljava/lang/String;
      //   3075: ldc -123
      //   3077: aload_1
      //   3078: getfield 59	com/tencent/mm/plugin/appbrand/h/g:mUrl	Ljava/lang/String;
      //   3081: lload 14
      //   3083: lconst_0
      //   3084: iconst_0
      //   3085: iconst_2
      //   3086: aload_1
      //   3087: invokevirtual 137	com/tencent/mm/plugin/appbrand/h/g:YQ	()I
      //   3090: invokestatic 142	com/tencent/mm/plugin/appbrand/report/a/d:a	(Ljava/lang/String;Ljava/lang/String;Ljava/lang/String;Ljava/lang/String;JJIII)V
      //   3093: aload_1
      //   3094: iconst_0
      //   3095: putfield 155	com/tencent/mm/plugin/appbrand/h/g:aDI	Z
      //   3098: aload_0
      //   3099: getfield 17	com/tencent/mm/plugin/appbrand/h/f$b:itn	Lcom/tencent/mm/plugin/appbrand/h/f;
      //   3102: aload_1
      //   3103: getfield 215	com/tencent/mm/plugin/appbrand/h/g:hXm	Ljava/lang/String;
      //   3106: aload 18
      //   3108: invokevirtual 352	com/tencent/mm/plugin/appbrand/h/f:a	(Ljava/lang/String;Ljava/net/HttpURLConnection;)V
      //   3111: aload 19
      //   3113: invokevirtual 355	java/io/FileInputStream:close	()V
      //   3116: aload 21
      //   3118: invokevirtual 361	java/io/DataOutputStream:close	()V
      //   3121: aload_0
      //   3122: getfield 17	com/tencent/mm/plugin/appbrand/h/f$b:itn	Lcom/tencent/mm/plugin/appbrand/h/f;
      //   3125: getfield 364	com/tencent/mm/plugin/appbrand/h/f:isL	Ljava/util/ArrayList;
      //   3128: aload_1
      //   3129: getfield 215	com/tencent/mm/plugin/appbrand/h/g:hXm	Ljava/lang/String;
      //   3132: invokevirtual 370	java/util/ArrayList:remove	(Ljava/lang/Object;)Z
      //   3135: pop
      //   3136: ldc2_w 51
      //   3139: ldc 53
      //   3141: invokestatic 34	com/tencent/gmtrace/GMTrace:o	(JI)V
      //   3144: return
      //   3145: getstatic 466	com/tencent/mm/plugin/appbrand/h/f$1:hKS	[I
      //   3148: aload 22
      //   3150: getfield 472	com/tencent/mm/plugin/appbrand/e:hyU	Lcom/tencent/mm/plugin/appbrand/b/b;
      //   3153: getfield 478	com/tencent/mm/plugin/appbrand/b/b:hKO	Lcom/tencent/mm/plugin/appbrand/b/c;
      //   3156: invokevirtual 484	com/tencent/mm/plugin/appbrand/b/c:Tc	()Lcom/tencent/mm/plugin/appbrand/b/a;
      //   3159: invokevirtual 489	com/tencent/mm/plugin/appbrand/b/a:ordinal	()I
      //   3162: iaload
      //   3163: istore_2
      //   3164: iload_2
      //   3165: tableswitch	default:+23->3188, 1:+28->3193, 2:+28->3193
      //   3188: iconst_0
      //   3189: istore_2
      //   3190: goto -140 -> 3050
      //   3193: iconst_1
      //   3194: istore_2
      //   3195: goto -145 -> 3050
      //   3198: astore 18
      //   3200: ldc -112
      //   3202: ldc_w 491
      //   3205: iconst_3
      //   3206: anewarray 4	java/lang/Object
      //   3209: dup
      //   3210: iconst_0
      //   3211: aload 18
      //   3213: invokevirtual 492	java/lang/Exception:toString	()Ljava/lang/String;
      //   3216: aastore
      //   3217: dup
      //   3218: iconst_1
      //   3219: aload 30
      //   3221: aastore
      //   3222: dup
      //   3223: iconst_2
      //   3224: aload 31
      //   3226: aastore
      //   3227: invokestatic 344	com/tencent/mm/sdk/platformtools/w:e	(Ljava/lang/String;Ljava/lang/String;[Ljava/lang/Object;)V
      //   3230: goto -114 -> 3116
      //   3233: astore 18
      //   3235: ldc -112
      //   3237: ldc_w 491
      //   3240: iconst_3
      //   3241: anewarray 4	java/lang/Object
      //   3244: dup
      //   3245: iconst_0
      //   3246: aload 18
      //   3248: invokevirtual 493	java/io/IOException:toString	()Ljava/lang/String;
      //   3251: aastore
      //   3252: dup
      //   3253: iconst_1
      //   3254: aload 30
      //   3256: aastore
      //   3257: dup
      //   3258: iconst_2
      //   3259: aload 31
      //   3261: aastore
      //   3262: invokestatic 344	com/tencent/mm/sdk/platformtools/w:e	(Ljava/lang/String;Ljava/lang/String;[Ljava/lang/Object;)V
      //   3265: goto -144 -> 3121
      //   3268: aload 21
      //   3270: aload 20
      //   3272: iconst_0
      //   3273: iload 13
      //   3275: invokevirtual 496	java/io/DataOutputStream:write	([BII)V
      //   3278: iload 13
      //   3280: i2l
      //   3281: lload 14
      //   3283: ladd
      //   3284: lstore 14
      //   3286: lload 16
      //   3288: lconst_0
      //   3289: lcmp
      //   3290: ifle +3833 -> 7123
      //   3293: aload_1
      //   3294: getfield 155	com/tencent/mm/plugin/appbrand/h/g:aDI	Z
      //   3297: ifeq +3826 -> 7123
      //   3300: ldc2_w 497
      //   3303: lload 14
      //   3305: lmul
      //   3306: lload 16
      //   3308: ldiv
      //   3309: l2i
      //   3310: istore_2
      //   3311: aload 32
      //   3313: iload_2
      //   3314: lload 14
      //   3316: lload 16
      //   3318: invokeinterface 502 6 0
      //   3323: ldc -112
      //   3325: ldc_w 504
      //   3328: iconst_3
      //   3329: anewarray 4	java/lang/Object
      //   3332: dup
      //   3333: iconst_0
      //   3334: lload 14
      //   3336: invokestatic 289	java/lang/Long:valueOf	(J)Ljava/lang/Long;
      //   3339: aastore
      //   3340: dup
      //   3341: iconst_1
      //   3342: lload 16
      //   3344: invokestatic 289	java/lang/Long:valueOf	(J)Ljava/lang/Long;
      //   3347: aastore
      //   3348: dup
      //   3349: iconst_2
      //   3350: iload_2
      //   3351: invokestatic 509	java/lang/Integer:valueOf	(I)Ljava/lang/Integer;
      //   3354: aastore
      //   3355: invokestatic 512	com/tencent/mm/sdk/platformtools/w:v	(Ljava/lang/String;Ljava/lang/String;[Ljava/lang/Object;)V
      //   3358: goto -349 -> 3009
      //   3361: aload 21
      //   3363: aload 26
      //   3365: invokevirtual 448	java/io/DataOutputStream:write	([B)V
      //   3368: aload 21
      //   3370: invokevirtual 515	java/io/DataOutputStream:flush	()V
      //   3373: aload 18
      //   3375: invokevirtual 518	java/net/HttpURLConnection:getResponseCode	()I
      //   3378: istore_2
      //   3379: sipush 200
      //   3382: iload_2
      //   3383: if_icmpeq +450 -> 3833
      //   3386: ldc -112
      //   3388: ldc_w 520
      //   3391: iconst_3
      //   3392: anewarray 4	java/lang/Object
      //   3395: dup
      //   3396: iconst_0
      //   3397: aload 18
      //   3399: invokevirtual 518	java/net/HttpURLConnection:getResponseCode	()I
      //   3402: invokestatic 509	java/lang/Integer:valueOf	(I)Ljava/lang/Integer;
      //   3405: aastore
      //   3406: dup
      //   3407: iconst_1
      //   3408: aload 30
      //   3410: aastore
      //   3411: dup
      //   3412: iconst_2
      //   3413: aload 31
      //   3415: aastore
      //   3416: invokestatic 344	com/tencent/mm/sdk/platformtools/w:e	(Ljava/lang/String;Ljava/lang/String;[Ljava/lang/Object;)V
      //   3419: iload_2
      //   3420: invokestatic 524	com/tencent/mm/plugin/appbrand/h/i:jd	(I)Z
      //   3423: ifeq +410 -> 3833
      //   3426: aload 18
      //   3428: invokestatic 527	com/tencent/mm/plugin/appbrand/h/i:c	(Ljava/net/HttpURLConnection;)Ljava/lang/String;
      //   3431: astore 20
      //   3433: aload_1
      //   3434: getfield 530	com/tencent/mm/plugin/appbrand/h/g:itg	I
      //   3437: istore_3
      //   3438: aload 20
      //   3440: invokestatic 535	android/text/TextUtils:isEmpty	(Ljava/lang/CharSequence;)Z
      //   3443: ifne +390 -> 3833
      //   3446: iload_3
      //   3447: ifgt +186 -> 3633
      //   3450: ldc -112
      //   3452: ldc_w 537
      //   3455: iconst_1
      //   3456: anewarray 4	java/lang/Object
      //   3459: dup
      //   3460: iconst_0
      //   3461: bipush 15
      //   3463: invokestatic 509	java/lang/Integer:valueOf	(I)Ljava/lang/Integer;
      //   3466: aastore
      //   3467: invokestatic 540	com/tencent/mm/sdk/platformtools/w:w	(Ljava/lang/String;Ljava/lang/String;[Ljava/lang/Object;)V
      //   3470: aload 32
      //   3472: iconst_0
      //   3473: ldc_w 542
      //   3476: iload_2
      //   3477: invokeinterface 349 4 0
      //   3482: aload_0
      //   3483: getfield 17	com/tencent/mm/plugin/appbrand/h/f$b:itn	Lcom/tencent/mm/plugin/appbrand/h/f;
      //   3486: getfield 128	com/tencent/mm/plugin/appbrand/h/f:hyD	Ljava/lang/String;
      //   3489: aload_1
      //   3490: getfield 131	com/tencent/mm/plugin/appbrand/h/g:itj	Ljava/lang/String;
      //   3493: ldc -123
      //   3495: aload_1
      //   3496: getfield 59	com/tencent/mm/plugin/appbrand/h/g:mUrl	Ljava/lang/String;
      //   3499: lload 14
      //   3501: lconst_0
      //   3502: iload_2
      //   3503: iconst_1
      //   3504: aload_1
      //   3505: invokevirtual 137	com/tencent/mm/plugin/appbrand/h/g:YQ	()I
      //   3508: invokestatic 142	com/tencent/mm/plugin/appbrand/report/a/d:a	(Ljava/lang/String;Ljava/lang/String;Ljava/lang/String;Ljava/lang/String;JJIII)V
      //   3511: aload_1
      //   3512: iconst_0
      //   3513: putfield 155	com/tencent/mm/plugin/appbrand/h/g:aDI	Z
      //   3516: aload_0
      //   3517: getfield 17	com/tencent/mm/plugin/appbrand/h/f$b:itn	Lcom/tencent/mm/plugin/appbrand/h/f;
      //   3520: aload_1
      //   3521: getfield 215	com/tencent/mm/plugin/appbrand/h/g:hXm	Ljava/lang/String;
      //   3524: aload 18
      //   3526: invokevirtual 352	com/tencent/mm/plugin/appbrand/h/f:a	(Ljava/lang/String;Ljava/net/HttpURLConnection;)V
      //   3529: aload 19
      //   3531: invokevirtual 355	java/io/FileInputStream:close	()V
      //   3534: aload 21
      //   3536: invokevirtual 361	java/io/DataOutputStream:close	()V
      //   3539: aload_0
      //   3540: getfield 17	com/tencent/mm/plugin/appbrand/h/f$b:itn	Lcom/tencent/mm/plugin/appbrand/h/f;
      //   3543: getfield 364	com/tencent/mm/plugin/appbrand/h/f:isL	Ljava/util/ArrayList;
      //   3546: aload_1
      //   3547: getfield 215	com/tencent/mm/plugin/appbrand/h/g:hXm	Ljava/lang/String;
      //   3550: invokevirtual 370	java/util/ArrayList:remove	(Ljava/lang/Object;)Z
      //   3553: pop
      //   3554: ldc2_w 51
      //   3557: ldc 53
      //   3559: invokestatic 34	com/tencent/gmtrace/GMTrace:o	(JI)V
      //   3562: return
      //   3563: astore 18
      //   3565: ldc -112
      //   3567: ldc_w 491
      //   3570: iconst_3
      //   3571: anewarray 4	java/lang/Object
      //   3574: dup
      //   3575: iconst_0
      //   3576: aload 18
      //   3578: invokevirtual 492	java/lang/Exception:toString	()Ljava/lang/String;
      //   3581: aastore
      //   3582: dup
      //   3583: iconst_1
      //   3584: aload 30
      //   3586: aastore
      //   3587: dup
      //   3588: iconst_2
      //   3589: aload 31
      //   3591: aastore
      //   3592: invokestatic 344	com/tencent/mm/sdk/platformtools/w:e	(Ljava/lang/String;Ljava/lang/String;[Ljava/lang/Object;)V
      //   3595: goto -61 -> 3534
      //   3598: astore 18
      //   3600: ldc -112
      //   3602: ldc_w 491
      //   3605: iconst_3
      //   3606: anewarray 4	java/lang/Object
      //   3609: dup
      //   3610: iconst_0
      //   3611: aload 18
      //   3613: invokevirtual 493	java/io/IOException:toString	()Ljava/lang/String;
      //   3616: aastore
      //   3617: dup
      //   3618: iconst_1
      //   3619: aload 30
      //   3621: aastore
      //   3622: dup
      //   3623: iconst_2
      //   3624: aload 31
      //   3626: aastore
      //   3627: invokestatic 344	com/tencent/mm/sdk/platformtools/w:e	(Ljava/lang/String;Ljava/lang/String;[Ljava/lang/Object;)V
      //   3630: goto -91 -> 3539
      //   3633: ldc -112
      //   3635: ldc_w 544
      //   3638: iconst_3
      //   3639: anewarray 4	java/lang/Object
      //   3642: dup
      //   3643: iconst_0
      //   3644: iload_3
      //   3645: invokestatic 509	java/lang/Integer:valueOf	(I)Ljava/lang/Integer;
      //   3648: aastore
      //   3649: dup
      //   3650: iconst_1
      //   3651: aload_1
      //   3652: getfield 59	com/tencent/mm/plugin/appbrand/h/g:mUrl	Ljava/lang/String;
      //   3655: aastore
      //   3656: dup
      //   3657: iconst_2
      //   3658: aload 20
      //   3660: aastore
      //   3661: invokestatic 151	com/tencent/mm/sdk/platformtools/w:i	(Ljava/lang/String;Ljava/lang/String;[Ljava/lang/Object;)V
      //   3664: aload_1
      //   3665: aload 20
      //   3667: putfield 59	com/tencent/mm/plugin/appbrand/h/g:mUrl	Ljava/lang/String;
      //   3670: aload_1
      //   3671: iload_3
      //   3672: iconst_1
      //   3673: isub
      //   3674: putfield 530	com/tencent/mm/plugin/appbrand/h/g:itg	I
      //   3677: aload_0
      //   3678: aload_1
      //   3679: invokespecial 546	com/tencent/mm/plugin/appbrand/h/f$b:b	(Lcom/tencent/mm/plugin/appbrand/h/g;)V
      //   3682: aload_0
      //   3683: getfield 17	com/tencent/mm/plugin/appbrand/h/f$b:itn	Lcom/tencent/mm/plugin/appbrand/h/f;
      //   3686: getfield 128	com/tencent/mm/plugin/appbrand/h/f:hyD	Ljava/lang/String;
      //   3689: aload_1
      //   3690: getfield 131	com/tencent/mm/plugin/appbrand/h/g:itj	Ljava/lang/String;
      //   3693: ldc -123
      //   3695: aload_1
      //   3696: getfield 59	com/tencent/mm/plugin/appbrand/h/g:mUrl	Ljava/lang/String;
      //   3699: lload 14
      //   3701: lconst_0
      //   3702: iload_2
      //   3703: iconst_2
      //   3704: aload_1
      //   3705: invokevirtual 137	com/tencent/mm/plugin/appbrand/h/g:YQ	()I
      //   3708: invokestatic 142	com/tencent/mm/plugin/appbrand/report/a/d:a	(Ljava/lang/String;Ljava/lang/String;Ljava/lang/String;Ljava/lang/String;JJIII)V
      //   3711: aload_1
      //   3712: iconst_0
      //   3713: putfield 155	com/tencent/mm/plugin/appbrand/h/g:aDI	Z
      //   3716: aload_0
      //   3717: getfield 17	com/tencent/mm/plugin/appbrand/h/f$b:itn	Lcom/tencent/mm/plugin/appbrand/h/f;
      //   3720: aload_1
      //   3721: getfield 215	com/tencent/mm/plugin/appbrand/h/g:hXm	Ljava/lang/String;
      //   3724: aload 18
      //   3726: invokevirtual 352	com/tencent/mm/plugin/appbrand/h/f:a	(Ljava/lang/String;Ljava/net/HttpURLConnection;)V
      //   3729: aload 19
      //   3731: invokevirtual 355	java/io/FileInputStream:close	()V
      //   3734: aload 21
      //   3736: invokevirtual 361	java/io/DataOutputStream:close	()V
      //   3739: aload_0
      //   3740: getfield 17	com/tencent/mm/plugin/appbrand/h/f$b:itn	Lcom/tencent/mm/plugin/appbrand/h/f;
      //   3743: getfield 364	com/tencent/mm/plugin/appbrand/h/f:isL	Ljava/util/ArrayList;
      //   3746: aload_1
      //   3747: getfield 215	com/tencent/mm/plugin/appbrand/h/g:hXm	Ljava/lang/String;
      //   3750: invokevirtual 370	java/util/ArrayList:remove	(Ljava/lang/Object;)Z
      //   3753: pop
      //   3754: ldc2_w 51
      //   3757: ldc 53
      //   3759: invokestatic 34	com/tencent/gmtrace/GMTrace:o	(JI)V
      //   3762: return
      //   3763: astore 18
      //   3765: ldc -112
      //   3767: ldc_w 491
      //   3770: iconst_3
      //   3771: anewarray 4	java/lang/Object
      //   3774: dup
      //   3775: iconst_0
      //   3776: aload 18
      //   3778: invokevirtual 492	java/lang/Exception:toString	()Ljava/lang/String;
      //   3781: aastore
      //   3782: dup
      //   3783: iconst_1
      //   3784: aload 30
      //   3786: aastore
      //   3787: dup
      //   3788: iconst_2
      //   3789: aload 31
      //   3791: aastore
      //   3792: invokestatic 344	com/tencent/mm/sdk/platformtools/w:e	(Ljava/lang/String;Ljava/lang/String;[Ljava/lang/Object;)V
      //   3795: goto -61 -> 3734
      //   3798: astore 18
      //   3800: ldc -112
      //   3802: ldc_w 491
      //   3805: iconst_3
      //   3806: anewarray 4	java/lang/Object
      //   3809: dup
      //   3810: iconst_0
      //   3811: aload 18
      //   3813: invokevirtual 493	java/io/IOException:toString	()Ljava/lang/String;
      //   3816: aastore
      //   3817: dup
      //   3818: iconst_1
      //   3819: aload 30
      //   3821: aastore
      //   3822: dup
      //   3823: iconst_2
      //   3824: aload 31
      //   3826: aastore
      //   3827: invokestatic 344	com/tencent/mm/sdk/platformtools/w:e	(Ljava/lang/String;Ljava/lang/String;[Ljava/lang/Object;)V
      //   3830: goto -91 -> 3739
      //   3833: ldc -112
      //   3835: ldc_w 548
      //   3838: iconst_1
      //   3839: anewarray 4	java/lang/Object
      //   3842: dup
      //   3843: iconst_0
      //   3844: aload 30
      //   3846: aastore
      //   3847: invokestatic 151	com/tencent/mm/sdk/platformtools/w:i	(Ljava/lang/String;Ljava/lang/String;[Ljava/lang/Object;)V
      //   3850: ldc_w 277
      //   3853: aload 18
      //   3855: invokevirtual 551	java/net/HttpURLConnection:getContentEncoding	()Ljava/lang/String;
      //   3858: invokevirtual 554	java/lang/String:equals	(Ljava/lang/Object;)Z
      //   3861: ifeq +116 -> 3977
      //   3864: new 556	java/util/zip/GZIPInputStream
      //   3867: dup
      //   3868: aload 18
      //   3870: invokevirtual 560	java/net/HttpURLConnection:getInputStream	()Ljava/io/InputStream;
      //   3873: invokespecial 563	java/util/zip/GZIPInputStream:<init>	(Ljava/io/InputStream;)V
      //   3876: astore 20
      //   3878: aload 20
      //   3880: ifnull +3233 -> 7113
      //   3883: new 565	java/io/BufferedReader
      //   3886: dup
      //   3887: new 567	java/io/InputStreamReader
      //   3890: dup
      //   3891: aload 20
      //   3893: invokespecial 568	java/io/InputStreamReader:<init>	(Ljava/io/InputStream;)V
      //   3896: invokespecial 571	java/io/BufferedReader:<init>	(Ljava/io/Reader;)V
      //   3899: astore 22
      //   3901: new 70	java/lang/StringBuilder
      //   3904: dup
      //   3905: invokespecial 393	java/lang/StringBuilder:<init>	()V
      //   3908: astore 23
      //   3910: aload 22
      //   3912: invokevirtual 574	java/io/BufferedReader:readLine	()Ljava/lang/String;
      //   3915: astore 24
      //   3917: aload 24
      //   3919: ifnull +156 -> 4075
      //   3922: aload_1
      //   3923: getfield 155	com/tencent/mm/plugin/appbrand/h/g:aDI	Z
      //   3926: ifeq +149 -> 4075
      //   3929: aload 23
      //   3931: aload 24
      //   3933: invokevirtual 93	java/lang/StringBuilder:append	(Ljava/lang/String;)Ljava/lang/StringBuilder;
      //   3936: pop
      //   3937: goto -27 -> 3910
      //   3940: astore 22
      //   3942: iload_2
      //   3943: istore_3
      //   3944: iconst_0
      //   3945: istore_2
      //   3946: aload 21
      //   3948: astore 23
      //   3950: aload 18
      //   3952: astore 24
      //   3954: aload 22
      //   3956: astore 21
      //   3958: aload 19
      //   3960: astore 18
      //   3962: aload 20
      //   3964: astore 19
      //   3966: aload 23
      //   3968: astore 22
      //   3970: aload 24
      //   3972: astore 20
      //   3974: goto -2713 -> 1261
      //   3977: aload 18
      //   3979: invokevirtual 560	java/net/HttpURLConnection:getInputStream	()Ljava/io/InputStream;
      //   3982: astore 20
      //   3984: goto -106 -> 3878
      //   3987: astore 20
      //   3989: ldc -112
      //   3991: ldc_w 576
      //   3994: iconst_1
      //   3995: anewarray 4	java/lang/Object
      //   3998: dup
      //   3999: iconst_0
      //   4000: aload 20
      //   4002: aastore
      //   4003: invokestatic 344	com/tencent/mm/sdk/platformtools/w:e	(Ljava/lang/String;Ljava/lang/String;[Ljava/lang/Object;)V
      //   4006: ldc_w 277
      //   4009: aload 18
      //   4011: invokevirtual 551	java/net/HttpURLConnection:getContentEncoding	()Ljava/lang/String;
      //   4014: invokevirtual 554	java/lang/String:equals	(Ljava/lang/Object;)Z
      //   4017: ifeq +48 -> 4065
      //   4020: new 556	java/util/zip/GZIPInputStream
      //   4023: dup
      //   4024: aload 18
      //   4026: invokevirtual 579	java/net/HttpURLConnection:getErrorStream	()Ljava/io/InputStream;
      //   4029: invokespecial 563	java/util/zip/GZIPInputStream:<init>	(Ljava/io/InputStream;)V
      //   4032: astore 20
      //   4034: goto -156 -> 3878
      //   4037: astore 20
      //   4039: ldc -112
      //   4041: ldc_w 581
      //   4044: iconst_1
      //   4045: anewarray 4	java/lang/Object
      //   4048: dup
      //   4049: iconst_0
      //   4050: aload 20
      //   4052: invokevirtual 492	java/lang/Exception:toString	()Ljava/lang/String;
      //   4055: aastore
      //   4056: invokestatic 344	com/tencent/mm/sdk/platformtools/w:e	(Ljava/lang/String;Ljava/lang/String;[Ljava/lang/Object;)V
      //   4059: aconst_null
      //   4060: astore 20
      //   4062: goto -184 -> 3878
      //   4065: aload 18
      //   4067: invokevirtual 579	java/net/HttpURLConnection:getErrorStream	()Ljava/io/InputStream;
      //   4070: astore 20
      //   4072: goto -194 -> 3878
      //   4075: aload 23
      //   4077: invokevirtual 97	java/lang/StringBuilder:toString	()Ljava/lang/String;
      //   4080: astore 22
      //   4082: aload 22
      //   4084: ldc_w 427
      //   4087: invokestatic 587	java/nio/charset/Charset:forName	(Ljava/lang/String;)Ljava/nio/charset/Charset;
      //   4090: invokevirtual 590	java/lang/String:getBytes	(Ljava/nio/charset/Charset;)[B
      //   4093: arraylength
      //   4094: istore_3
      //   4095: ldc -112
      //   4097: ldc_w 592
      //   4100: iconst_3
      //   4101: anewarray 4	java/lang/Object
      //   4104: dup
      //   4105: iconst_0
      //   4106: aload 33
      //   4108: aastore
      //   4109: dup
      //   4110: iconst_1
      //   4111: aload 22
      //   4113: aastore
      //   4114: dup
      //   4115: iconst_2
      //   4116: iload_2
      //   4117: invokestatic 509	java/lang/Integer:valueOf	(I)Ljava/lang/Integer;
      //   4120: aastore
      //   4121: invokestatic 151	com/tencent/mm/sdk/platformtools/w:i	(Ljava/lang/String;Ljava/lang/String;[Ljava/lang/Object;)V
      //   4124: aload_1
      //   4125: getfield 155	com/tencent/mm/plugin/appbrand/h/g:aDI	Z
      //   4128: ifeq +136 -> 4264
      //   4131: aload 32
      //   4133: iconst_0
      //   4134: aload 22
      //   4136: iload_2
      //   4137: invokeinterface 349 4 0
      //   4142: ldc -112
      //   4144: ldc_w 594
      //   4147: iconst_2
      //   4148: anewarray 4	java/lang/Object
      //   4151: dup
      //   4152: iconst_0
      //   4153: aload 30
      //   4155: aastore
      //   4156: dup
      //   4157: iconst_1
      //   4158: aload 31
      //   4160: aastore
      //   4161: invokestatic 151	com/tencent/mm/sdk/platformtools/w:i	(Ljava/lang/String;Ljava/lang/String;[Ljava/lang/Object;)V
      //   4164: iconst_1
      //   4165: istore 4
      //   4167: iload 4
      //   4169: ifeq +119 -> 4288
      //   4172: aload_0
      //   4173: getfield 17	com/tencent/mm/plugin/appbrand/h/f$b:itn	Lcom/tencent/mm/plugin/appbrand/h/f;
      //   4176: getfield 128	com/tencent/mm/plugin/appbrand/h/f:hyD	Ljava/lang/String;
      //   4179: aload_1
      //   4180: getfield 131	com/tencent/mm/plugin/appbrand/h/g:itj	Ljava/lang/String;
      //   4183: ldc -123
      //   4185: aload_1
      //   4186: getfield 59	com/tencent/mm/plugin/appbrand/h/g:mUrl	Ljava/lang/String;
      //   4189: lload 14
      //   4191: iload_3
      //   4192: i2l
      //   4193: iload_2
      //   4194: iconst_1
      //   4195: aload_1
      //   4196: invokevirtual 137	com/tencent/mm/plugin/appbrand/h/g:YQ	()I
      //   4199: invokestatic 142	com/tencent/mm/plugin/appbrand/report/a/d:a	(Ljava/lang/String;Ljava/lang/String;Ljava/lang/String;Ljava/lang/String;JJIII)V
      //   4202: aload_1
      //   4203: iconst_0
      //   4204: putfield 155	com/tencent/mm/plugin/appbrand/h/g:aDI	Z
      //   4207: aload_0
      //   4208: getfield 17	com/tencent/mm/plugin/appbrand/h/f$b:itn	Lcom/tencent/mm/plugin/appbrand/h/f;
      //   4211: aload_1
      //   4212: getfield 215	com/tencent/mm/plugin/appbrand/h/g:hXm	Ljava/lang/String;
      //   4215: aload 18
      //   4217: invokevirtual 352	com/tencent/mm/plugin/appbrand/h/f:a	(Ljava/lang/String;Ljava/net/HttpURLConnection;)V
      //   4220: aload 19
      //   4222: invokevirtual 355	java/io/FileInputStream:close	()V
      //   4225: aload 20
      //   4227: ifnull +8 -> 4235
      //   4230: aload 20
      //   4232: invokevirtual 358	java/io/InputStream:close	()V
      //   4235: aload 21
      //   4237: invokevirtual 361	java/io/DataOutputStream:close	()V
      //   4240: aload_0
      //   4241: getfield 17	com/tencent/mm/plugin/appbrand/h/f$b:itn	Lcom/tencent/mm/plugin/appbrand/h/f;
      //   4244: getfield 364	com/tencent/mm/plugin/appbrand/h/f:isL	Ljava/util/ArrayList;
      //   4247: aload_1
      //   4248: getfield 215	com/tencent/mm/plugin/appbrand/h/g:hXm	Ljava/lang/String;
      //   4251: invokevirtual 370	java/util/ArrayList:remove	(Ljava/lang/Object;)Z
      //   4254: pop
      //   4255: ldc2_w 51
      //   4258: ldc 53
      //   4260: invokestatic 34	com/tencent/gmtrace/GMTrace:o	(JI)V
      //   4263: return
      //   4264: aload 32
      //   4266: iconst_0
      //   4267: ldc -99
      //   4269: iload_2
      //   4270: invokeinterface 349 4 0
      //   4275: ldc -112
      //   4277: ldc -97
      //   4279: invokestatic 163	com/tencent/mm/sdk/platformtools/w:e	(Ljava/lang/String;Ljava/lang/String;)V
      //   4282: iconst_0
      //   4283: istore 4
      //   4285: goto -118 -> 4167
      //   4288: aload_0
      //   4289: getfield 17	com/tencent/mm/plugin/appbrand/h/f$b:itn	Lcom/tencent/mm/plugin/appbrand/h/f;
      //   4292: getfield 128	com/tencent/mm/plugin/appbrand/h/f:hyD	Ljava/lang/String;
      //   4295: aload_1
      //   4296: getfield 131	com/tencent/mm/plugin/appbrand/h/g:itj	Ljava/lang/String;
      //   4299: ldc -123
      //   4301: aload_1
      //   4302: getfield 59	com/tencent/mm/plugin/appbrand/h/g:mUrl	Ljava/lang/String;
      //   4305: lload 14
      //   4307: iload_3
      //   4308: i2l
      //   4309: iload_2
      //   4310: iconst_2
      //   4311: aload_1
      //   4312: invokevirtual 137	com/tencent/mm/plugin/appbrand/h/g:YQ	()I
      //   4315: invokestatic 142	com/tencent/mm/plugin/appbrand/report/a/d:a	(Ljava/lang/String;Ljava/lang/String;Ljava/lang/String;Ljava/lang/String;JJIII)V
      //   4318: goto -116 -> 4202
      //   4321: astore 18
      //   4323: ldc -112
      //   4325: ldc_w 491
      //   4328: iconst_3
      //   4329: anewarray 4	java/lang/Object
      //   4332: dup
      //   4333: iconst_0
      //   4334: aload 18
      //   4336: invokevirtual 492	java/lang/Exception:toString	()Ljava/lang/String;
      //   4339: aastore
      //   4340: dup
      //   4341: iconst_1
      //   4342: aload 30
      //   4344: aastore
      //   4345: dup
      //   4346: iconst_2
      //   4347: aload 31
      //   4349: aastore
      //   4350: invokestatic 344	com/tencent/mm/sdk/platformtools/w:e	(Ljava/lang/String;Ljava/lang/String;[Ljava/lang/Object;)V
      //   4353: goto -128 -> 4225
      //   4356: astore 18
      //   4358: ldc -112
      //   4360: ldc_w 596
      //   4363: iconst_3
      //   4364: anewarray 4	java/lang/Object
      //   4367: dup
      //   4368: iconst_0
      //   4369: aload 18
      //   4371: invokevirtual 493	java/io/IOException:toString	()Ljava/lang/String;
      //   4374: aastore
      //   4375: dup
      //   4376: iconst_1
      //   4377: aload 30
      //   4379: aastore
      //   4380: dup
      //   4381: iconst_2
      //   4382: aload 31
      //   4384: aastore
      //   4385: invokestatic 344	com/tencent/mm/sdk/platformtools/w:e	(Ljava/lang/String;Ljava/lang/String;[Ljava/lang/Object;)V
      //   4388: goto -153 -> 4235
      //   4391: astore 18
      //   4393: ldc -112
      //   4395: aload 18
      //   4397: ldc_w 598
      //   4400: iconst_0
      //   4401: anewarray 4	java/lang/Object
      //   4404: invokestatic 602	com/tencent/mm/sdk/platformtools/w:printErrStackTrace	(Ljava/lang/String;Ljava/lang/Throwable;Ljava/lang/String;[Ljava/lang/Object;)V
      //   4407: goto -172 -> 4235
      //   4410: astore 18
      //   4412: ldc -112
      //   4414: ldc_w 491
      //   4417: iconst_3
      //   4418: anewarray 4	java/lang/Object
      //   4421: dup
      //   4422: iconst_0
      //   4423: aload 18
      //   4425: invokevirtual 493	java/io/IOException:toString	()Ljava/lang/String;
      //   4428: aastore
      //   4429: dup
      //   4430: iconst_1
      //   4431: aload 30
      //   4433: aastore
      //   4434: dup
      //   4435: iconst_2
      //   4436: aload 31
      //   4438: aastore
      //   4439: invokestatic 344	com/tencent/mm/sdk/platformtools/w:e	(Ljava/lang/String;Ljava/lang/String;[Ljava/lang/Object;)V
      //   4442: goto -202 -> 4240
      //   4445: astore 18
      //   4447: ldc -112
      //   4449: ldc_w 491
      //   4452: iconst_3
      //   4453: anewarray 4	java/lang/Object
      //   4456: dup
      //   4457: iconst_0
      //   4458: aload 18
      //   4460: invokevirtual 492	java/lang/Exception:toString	()Ljava/lang/String;
      //   4463: aastore
      //   4464: dup
      //   4465: iconst_1
      //   4466: aload 30
      //   4468: aastore
      //   4469: dup
      //   4470: iconst_2
      //   4471: aload 31
      //   4473: aastore
      //   4474: invokestatic 344	com/tencent/mm/sdk/platformtools/w:e	(Ljava/lang/String;Ljava/lang/String;[Ljava/lang/Object;)V
      //   4477: goto -3104 -> 1373
      //   4480: astore 18
      //   4482: ldc -112
      //   4484: ldc_w 596
      //   4487: iconst_3
      //   4488: anewarray 4	java/lang/Object
      //   4491: dup
      //   4492: iconst_0
      //   4493: aload 18
      //   4495: invokevirtual 493	java/io/IOException:toString	()Ljava/lang/String;
      //   4498: aastore
      //   4499: dup
      //   4500: iconst_1
      //   4501: aload 30
      //   4503: aastore
      //   4504: dup
      //   4505: iconst_2
      //   4506: aload 31
      //   4508: aastore
      //   4509: invokestatic 344	com/tencent/mm/sdk/platformtools/w:e	(Ljava/lang/String;Ljava/lang/String;[Ljava/lang/Object;)V
      //   4512: goto -3129 -> 1383
      //   4515: astore 18
      //   4517: ldc -112
      //   4519: aload 18
      //   4521: ldc_w 598
      //   4524: iconst_0
      //   4525: anewarray 4	java/lang/Object
      //   4528: invokestatic 602	com/tencent/mm/sdk/platformtools/w:printErrStackTrace	(Ljava/lang/String;Ljava/lang/Throwable;Ljava/lang/String;[Ljava/lang/Object;)V
      //   4531: goto -3148 -> 1383
      //   4534: astore 18
      //   4536: ldc -112
      //   4538: ldc_w 491
      //   4541: iconst_3
      //   4542: anewarray 4	java/lang/Object
      //   4545: dup
      //   4546: iconst_0
      //   4547: aload 18
      //   4549: invokevirtual 493	java/io/IOException:toString	()Ljava/lang/String;
      //   4552: aastore
      //   4553: dup
      //   4554: iconst_1
      //   4555: aload 30
      //   4557: aastore
      //   4558: dup
      //   4559: iconst_2
      //   4560: aload 31
      //   4562: aastore
      //   4563: invokestatic 344	com/tencent/mm/sdk/platformtools/w:e	(Ljava/lang/String;Ljava/lang/String;[Ljava/lang/Object;)V
      //   4566: goto -3173 -> 1393
      //   4569: astore 18
      //   4571: ldc -112
      //   4573: ldc_w 491
      //   4576: iconst_3
      //   4577: anewarray 4	java/lang/Object
      //   4580: dup
      //   4581: iconst_0
      //   4582: aload 18
      //   4584: invokevirtual 492	java/lang/Exception:toString	()Ljava/lang/String;
      //   4587: aastore
      //   4588: dup
      //   4589: iconst_1
      //   4590: aload 30
      //   4592: aastore
      //   4593: dup
      //   4594: iconst_2
      //   4595: aload 31
      //   4597: aastore
      //   4598: invokestatic 344	com/tencent/mm/sdk/platformtools/w:e	(Ljava/lang/String;Ljava/lang/String;[Ljava/lang/Object;)V
      //   4601: goto -2932 -> 1669
      //   4604: astore 18
      //   4606: ldc -112
      //   4608: ldc_w 596
      //   4611: iconst_3
      //   4612: anewarray 4	java/lang/Object
      //   4615: dup
      //   4616: iconst_0
      //   4617: aload 18
      //   4619: invokevirtual 493	java/io/IOException:toString	()Ljava/lang/String;
      //   4622: aastore
      //   4623: dup
      //   4624: iconst_1
      //   4625: aload 30
      //   4627: aastore
      //   4628: dup
      //   4629: iconst_2
      //   4630: aload 31
      //   4632: aastore
      //   4633: invokestatic 344	com/tencent/mm/sdk/platformtools/w:e	(Ljava/lang/String;Ljava/lang/String;[Ljava/lang/Object;)V
      //   4636: goto -2957 -> 1679
      //   4639: astore 18
      //   4641: ldc -112
      //   4643: aload 18
      //   4645: ldc_w 598
      //   4648: iconst_0
      //   4649: anewarray 4	java/lang/Object
      //   4652: invokestatic 602	com/tencent/mm/sdk/platformtools/w:printErrStackTrace	(Ljava/lang/String;Ljava/lang/Throwable;Ljava/lang/String;[Ljava/lang/Object;)V
      //   4655: goto -2976 -> 1679
      //   4658: astore 18
      //   4660: ldc -112
      //   4662: ldc_w 491
      //   4665: iconst_3
      //   4666: anewarray 4	java/lang/Object
      //   4669: dup
      //   4670: iconst_0
      //   4671: aload 18
      //   4673: invokevirtual 493	java/io/IOException:toString	()Ljava/lang/String;
      //   4676: aastore
      //   4677: dup
      //   4678: iconst_1
      //   4679: aload 30
      //   4681: aastore
      //   4682: dup
      //   4683: iconst_2
      //   4684: aload 31
      //   4686: aastore
      //   4687: invokestatic 344	com/tencent/mm/sdk/platformtools/w:e	(Ljava/lang/String;Ljava/lang/String;[Ljava/lang/Object;)V
      //   4690: goto -3001 -> 1689
      //   4693: astore 18
      //   4695: ldc -112
      //   4697: ldc_w 491
      //   4700: iconst_3
      //   4701: anewarray 4	java/lang/Object
      //   4704: dup
      //   4705: iconst_0
      //   4706: aload 18
      //   4708: invokevirtual 492	java/lang/Exception:toString	()Ljava/lang/String;
      //   4711: aastore
      //   4712: dup
      //   4713: iconst_1
      //   4714: aload 30
      //   4716: aastore
      //   4717: dup
      //   4718: iconst_2
      //   4719: aload 31
      //   4721: aastore
      //   4722: invokestatic 344	com/tencent/mm/sdk/platformtools/w:e	(Ljava/lang/String;Ljava/lang/String;[Ljava/lang/Object;)V
      //   4725: goto -2286 -> 2439
      //   4728: astore 18
      //   4730: ldc -112
      //   4732: ldc_w 596
      //   4735: iconst_3
      //   4736: anewarray 4	java/lang/Object
      //   4739: dup
      //   4740: iconst_0
      //   4741: aload 18
      //   4743: invokevirtual 493	java/io/IOException:toString	()Ljava/lang/String;
      //   4746: aastore
      //   4747: dup
      //   4748: iconst_1
      //   4749: aload 30
      //   4751: aastore
      //   4752: dup
      //   4753: iconst_2
      //   4754: aload 31
      //   4756: aastore
      //   4757: invokestatic 344	com/tencent/mm/sdk/platformtools/w:e	(Ljava/lang/String;Ljava/lang/String;[Ljava/lang/Object;)V
      //   4760: goto -2311 -> 2449
      //   4763: astore 18
      //   4765: ldc -112
      //   4767: aload 18
      //   4769: ldc_w 598
      //   4772: iconst_0
      //   4773: anewarray 4	java/lang/Object
      //   4776: invokestatic 602	com/tencent/mm/sdk/platformtools/w:printErrStackTrace	(Ljava/lang/String;Ljava/lang/Throwable;Ljava/lang/String;[Ljava/lang/Object;)V
      //   4779: goto -2330 -> 2449
      //   4782: astore 18
      //   4784: ldc -112
      //   4786: ldc_w 491
      //   4789: iconst_3
      //   4790: anewarray 4	java/lang/Object
      //   4793: dup
      //   4794: iconst_0
      //   4795: aload 18
      //   4797: invokevirtual 493	java/io/IOException:toString	()Ljava/lang/String;
      //   4800: aastore
      //   4801: dup
      //   4802: iconst_1
      //   4803: aload 30
      //   4805: aastore
      //   4806: dup
      //   4807: iconst_2
      //   4808: aload 31
      //   4810: aastore
      //   4811: invokestatic 344	com/tencent/mm/sdk/platformtools/w:e	(Ljava/lang/String;Ljava/lang/String;[Ljava/lang/Object;)V
      //   4814: goto -2355 -> 2459
      //   4817: astore 22
      //   4819: aconst_null
      //   4820: astore 26
      //   4822: aconst_null
      //   4823: astore 25
      //   4825: aconst_null
      //   4826: astore 20
      //   4828: iload 7
      //   4830: istore 5
      //   4832: iload 11
      //   4834: istore_2
      //   4835: aload 24
      //   4837: astore 18
      //   4839: aload 26
      //   4841: astore 23
      //   4843: aload 20
      //   4845: astore 19
      //   4847: aload 25
      //   4849: astore 21
      //   4851: iload_2
      //   4852: istore 4
      //   4854: lload 14
      //   4856: lstore 16
      //   4858: iload 5
      //   4860: istore_3
      //   4861: getstatic 190	com/tencent/mm/plugin/report/service/g:ork	Lcom/tencent/mm/plugin/report/service/g;
      //   4864: ldc2_w 191
      //   4867: ldc2_w 603
      //   4870: lconst_1
      //   4871: iconst_0
      //   4872: invokevirtual 195	com/tencent/mm/plugin/report/service/g:a	(JJJZ)V
      //   4875: aload 24
      //   4877: astore 18
      //   4879: aload 26
      //   4881: astore 23
      //   4883: aload 20
      //   4885: astore 19
      //   4887: aload 25
      //   4889: astore 21
      //   4891: iload_2
      //   4892: istore 4
      //   4894: lload 14
      //   4896: lstore 16
      //   4898: iload 5
      //   4900: istore_3
      //   4901: ldc -112
      //   4903: ldc_w 606
      //   4906: iconst_3
      //   4907: anewarray 4	java/lang/Object
      //   4910: dup
      //   4911: iconst_0
      //   4912: aload 22
      //   4914: invokevirtual 607	java/net/SocketTimeoutException:toString	()Ljava/lang/String;
      //   4917: aastore
      //   4918: dup
      //   4919: iconst_1
      //   4920: aload 30
      //   4922: aastore
      //   4923: dup
      //   4924: iconst_2
      //   4925: aload 31
      //   4927: aastore
      //   4928: invokestatic 344	com/tencent/mm/sdk/platformtools/w:e	(Ljava/lang/String;Ljava/lang/String;[Ljava/lang/Object;)V
      //   4931: aload 24
      //   4933: astore 18
      //   4935: aload 26
      //   4937: astore 23
      //   4939: aload 20
      //   4941: astore 19
      //   4943: aload 25
      //   4945: astore 21
      //   4947: iload_2
      //   4948: istore 4
      //   4950: lload 14
      //   4952: lstore 16
      //   4954: iload 5
      //   4956: istore_3
      //   4957: aload 32
      //   4959: iconst_m1
      //   4960: ldc_w 609
      //   4963: iload_2
      //   4964: invokeinterface 349 4 0
      //   4969: aload_0
      //   4970: getfield 17	com/tencent/mm/plugin/appbrand/h/f$b:itn	Lcom/tencent/mm/plugin/appbrand/h/f;
      //   4973: getfield 128	com/tencent/mm/plugin/appbrand/h/f:hyD	Ljava/lang/String;
      //   4976: aload_1
      //   4977: getfield 131	com/tencent/mm/plugin/appbrand/h/g:itj	Ljava/lang/String;
      //   4980: ldc -123
      //   4982: aload_1
      //   4983: getfield 59	com/tencent/mm/plugin/appbrand/h/g:mUrl	Ljava/lang/String;
      //   4986: lload 14
      //   4988: iload 5
      //   4990: i2l
      //   4991: iload_2
      //   4992: iconst_2
      //   4993: aload_1
      //   4994: invokevirtual 137	com/tencent/mm/plugin/appbrand/h/g:YQ	()I
      //   4997: invokestatic 142	com/tencent/mm/plugin/appbrand/report/a/d:a	(Ljava/lang/String;Ljava/lang/String;Ljava/lang/String;Ljava/lang/String;JJIII)V
      //   5000: aload_1
      //   5001: iconst_0
      //   5002: putfield 155	com/tencent/mm/plugin/appbrand/h/g:aDI	Z
      //   5005: aload_0
      //   5006: getfield 17	com/tencent/mm/plugin/appbrand/h/f$b:itn	Lcom/tencent/mm/plugin/appbrand/h/f;
      //   5009: aload_1
      //   5010: getfield 215	com/tencent/mm/plugin/appbrand/h/g:hXm	Ljava/lang/String;
      //   5013: aload 24
      //   5015: invokevirtual 352	com/tencent/mm/plugin/appbrand/h/f:a	(Ljava/lang/String;Ljava/net/HttpURLConnection;)V
      //   5018: aload 26
      //   5020: ifnull +8 -> 5028
      //   5023: aload 26
      //   5025: invokevirtual 355	java/io/FileInputStream:close	()V
      //   5028: aload 20
      //   5030: ifnull +8 -> 5038
      //   5033: aload 20
      //   5035: invokevirtual 358	java/io/InputStream:close	()V
      //   5038: aload 25
      //   5040: ifnull +8 -> 5048
      //   5043: aload 25
      //   5045: invokevirtual 361	java/io/DataOutputStream:close	()V
      //   5048: aload_0
      //   5049: getfield 17	com/tencent/mm/plugin/appbrand/h/f$b:itn	Lcom/tencent/mm/plugin/appbrand/h/f;
      //   5052: getfield 364	com/tencent/mm/plugin/appbrand/h/f:isL	Ljava/util/ArrayList;
      //   5055: aload_1
      //   5056: getfield 215	com/tencent/mm/plugin/appbrand/h/g:hXm	Ljava/lang/String;
      //   5059: invokevirtual 370	java/util/ArrayList:remove	(Ljava/lang/Object;)Z
      //   5062: pop
      //   5063: ldc2_w 51
      //   5066: ldc 53
      //   5068: invokestatic 34	com/tencent/gmtrace/GMTrace:o	(JI)V
      //   5071: return
      //   5072: astore 18
      //   5074: ldc -112
      //   5076: ldc_w 491
      //   5079: iconst_3
      //   5080: anewarray 4	java/lang/Object
      //   5083: dup
      //   5084: iconst_0
      //   5085: aload 18
      //   5087: invokevirtual 492	java/lang/Exception:toString	()Ljava/lang/String;
      //   5090: aastore
      //   5091: dup
      //   5092: iconst_1
      //   5093: aload 30
      //   5095: aastore
      //   5096: dup
      //   5097: iconst_2
      //   5098: aload 31
      //   5100: aastore
      //   5101: invokestatic 344	com/tencent/mm/sdk/platformtools/w:e	(Ljava/lang/String;Ljava/lang/String;[Ljava/lang/Object;)V
      //   5104: goto -76 -> 5028
      //   5107: astore 18
      //   5109: ldc -112
      //   5111: ldc_w 596
      //   5114: iconst_3
      //   5115: anewarray 4	java/lang/Object
      //   5118: dup
      //   5119: iconst_0
      //   5120: aload 18
      //   5122: invokevirtual 493	java/io/IOException:toString	()Ljava/lang/String;
      //   5125: aastore
      //   5126: dup
      //   5127: iconst_1
      //   5128: aload 30
      //   5130: aastore
      //   5131: dup
      //   5132: iconst_2
      //   5133: aload 31
      //   5135: aastore
      //   5136: invokestatic 344	com/tencent/mm/sdk/platformtools/w:e	(Ljava/lang/String;Ljava/lang/String;[Ljava/lang/Object;)V
      //   5139: goto -101 -> 5038
      //   5142: astore 18
      //   5144: ldc -112
      //   5146: aload 18
      //   5148: ldc_w 598
      //   5151: iconst_0
      //   5152: anewarray 4	java/lang/Object
      //   5155: invokestatic 602	com/tencent/mm/sdk/platformtools/w:printErrStackTrace	(Ljava/lang/String;Ljava/lang/Throwable;Ljava/lang/String;[Ljava/lang/Object;)V
      //   5158: goto -120 -> 5038
      //   5161: astore 18
      //   5163: ldc -112
      //   5165: ldc_w 491
      //   5168: iconst_3
      //   5169: anewarray 4	java/lang/Object
      //   5172: dup
      //   5173: iconst_0
      //   5174: aload 18
      //   5176: invokevirtual 493	java/io/IOException:toString	()Ljava/lang/String;
      //   5179: aastore
      //   5180: dup
      //   5181: iconst_1
      //   5182: aload 30
      //   5184: aastore
      //   5185: dup
      //   5186: iconst_2
      //   5187: aload 31
      //   5189: aastore
      //   5190: invokestatic 344	com/tencent/mm/sdk/platformtools/w:e	(Ljava/lang/String;Ljava/lang/String;[Ljava/lang/Object;)V
      //   5193: goto -145 -> 5048
      //   5196: astore 22
      //   5198: aconst_null
      //   5199: astore 26
      //   5201: aconst_null
      //   5202: astore 25
      //   5204: aconst_null
      //   5205: astore 20
      //   5207: iload 8
      //   5209: istore 5
      //   5211: iload 12
      //   5213: istore_2
      //   5214: aload 18
      //   5216: astore 24
      //   5218: aload 24
      //   5220: astore 18
      //   5222: aload 26
      //   5224: astore 23
      //   5226: aload 20
      //   5228: astore 19
      //   5230: aload 25
      //   5232: astore 21
      //   5234: iload_2
      //   5235: istore 4
      //   5237: lload 14
      //   5239: lstore 16
      //   5241: iload 5
      //   5243: istore_3
      //   5244: getstatic 190	com/tencent/mm/plugin/report/service/g:ork	Lcom/tencent/mm/plugin/report/service/g;
      //   5247: ldc2_w 191
      //   5250: ldc2_w 610
      //   5253: lconst_1
      //   5254: iconst_0
      //   5255: invokevirtual 195	com/tencent/mm/plugin/report/service/g:a	(JJJZ)V
      //   5258: aload 24
      //   5260: astore 18
      //   5262: aload 26
      //   5264: astore 23
      //   5266: aload 20
      //   5268: astore 19
      //   5270: aload 25
      //   5272: astore 21
      //   5274: iload_2
      //   5275: istore 4
      //   5277: lload 14
      //   5279: lstore 16
      //   5281: iload 5
      //   5283: istore_3
      //   5284: ldc -112
      //   5286: ldc_w 491
      //   5289: iconst_3
      //   5290: anewarray 4	java/lang/Object
      //   5293: dup
      //   5294: iconst_0
      //   5295: aload 22
      //   5297: invokevirtual 492	java/lang/Exception:toString	()Ljava/lang/String;
      //   5300: aastore
      //   5301: dup
      //   5302: iconst_1
      //   5303: aload 30
      //   5305: aastore
      //   5306: dup
      //   5307: iconst_2
      //   5308: aload 31
      //   5310: aastore
      //   5311: invokestatic 344	com/tencent/mm/sdk/platformtools/w:e	(Ljava/lang/String;Ljava/lang/String;[Ljava/lang/Object;)V
      //   5314: aload 24
      //   5316: astore 18
      //   5318: aload 26
      //   5320: astore 23
      //   5322: aload 20
      //   5324: astore 19
      //   5326: aload 25
      //   5328: astore 21
      //   5330: iload_2
      //   5331: istore 4
      //   5333: lload 14
      //   5335: lstore 16
      //   5337: iload 5
      //   5339: istore_3
      //   5340: aload 32
      //   5342: iconst_m1
      //   5343: ldc_w 613
      //   5346: iload_2
      //   5347: invokeinterface 349 4 0
      //   5352: aload_0
      //   5353: getfield 17	com/tencent/mm/plugin/appbrand/h/f$b:itn	Lcom/tencent/mm/plugin/appbrand/h/f;
      //   5356: getfield 128	com/tencent/mm/plugin/appbrand/h/f:hyD	Ljava/lang/String;
      //   5359: aload_1
      //   5360: getfield 131	com/tencent/mm/plugin/appbrand/h/g:itj	Ljava/lang/String;
      //   5363: ldc -123
      //   5365: aload_1
      //   5366: getfield 59	com/tencent/mm/plugin/appbrand/h/g:mUrl	Ljava/lang/String;
      //   5369: lload 14
      //   5371: iload 5
      //   5373: i2l
      //   5374: iload_2
      //   5375: iconst_2
      //   5376: aload_1
      //   5377: invokevirtual 137	com/tencent/mm/plugin/appbrand/h/g:YQ	()I
      //   5380: invokestatic 142	com/tencent/mm/plugin/appbrand/report/a/d:a	(Ljava/lang/String;Ljava/lang/String;Ljava/lang/String;Ljava/lang/String;JJIII)V
      //   5383: aload_1
      //   5384: iconst_0
      //   5385: putfield 155	com/tencent/mm/plugin/appbrand/h/g:aDI	Z
      //   5388: aload_0
      //   5389: getfield 17	com/tencent/mm/plugin/appbrand/h/f$b:itn	Lcom/tencent/mm/plugin/appbrand/h/f;
      //   5392: aload_1
      //   5393: getfield 215	com/tencent/mm/plugin/appbrand/h/g:hXm	Ljava/lang/String;
      //   5396: aload 24
      //   5398: invokevirtual 352	com/tencent/mm/plugin/appbrand/h/f:a	(Ljava/lang/String;Ljava/net/HttpURLConnection;)V
      //   5401: aload 26
      //   5403: ifnull +8 -> 5411
      //   5406: aload 26
      //   5408: invokevirtual 355	java/io/FileInputStream:close	()V
      //   5411: aload 20
      //   5413: ifnull +8 -> 5421
      //   5416: aload 20
      //   5418: invokevirtual 358	java/io/InputStream:close	()V
      //   5421: aload 25
      //   5423: ifnull +8 -> 5431
      //   5426: aload 25
      //   5428: invokevirtual 361	java/io/DataOutputStream:close	()V
      //   5431: aload_0
      //   5432: getfield 17	com/tencent/mm/plugin/appbrand/h/f$b:itn	Lcom/tencent/mm/plugin/appbrand/h/f;
      //   5435: getfield 364	com/tencent/mm/plugin/appbrand/h/f:isL	Ljava/util/ArrayList;
      //   5438: aload_1
      //   5439: getfield 215	com/tencent/mm/plugin/appbrand/h/g:hXm	Ljava/lang/String;
      //   5442: invokevirtual 370	java/util/ArrayList:remove	(Ljava/lang/Object;)Z
      //   5445: pop
      //   5446: ldc2_w 51
      //   5449: ldc 53
      //   5451: invokestatic 34	com/tencent/gmtrace/GMTrace:o	(JI)V
      //   5454: return
      //   5455: astore 18
      //   5457: ldc -112
      //   5459: ldc_w 491
      //   5462: iconst_3
      //   5463: anewarray 4	java/lang/Object
      //   5466: dup
      //   5467: iconst_0
      //   5468: aload 18
      //   5470: invokevirtual 492	java/lang/Exception:toString	()Ljava/lang/String;
      //   5473: aastore
      //   5474: dup
      //   5475: iconst_1
      //   5476: aload 30
      //   5478: aastore
      //   5479: dup
      //   5480: iconst_2
      //   5481: aload 31
      //   5483: aastore
      //   5484: invokestatic 344	com/tencent/mm/sdk/platformtools/w:e	(Ljava/lang/String;Ljava/lang/String;[Ljava/lang/Object;)V
      //   5487: goto -76 -> 5411
      //   5490: astore 18
      //   5492: ldc -112
      //   5494: ldc_w 596
      //   5497: iconst_3
      //   5498: anewarray 4	java/lang/Object
      //   5501: dup
      //   5502: iconst_0
      //   5503: aload 18
      //   5505: invokevirtual 493	java/io/IOException:toString	()Ljava/lang/String;
      //   5508: aastore
      //   5509: dup
      //   5510: iconst_1
      //   5511: aload 30
      //   5513: aastore
      //   5514: dup
      //   5515: iconst_2
      //   5516: aload 31
      //   5518: aastore
      //   5519: invokestatic 344	com/tencent/mm/sdk/platformtools/w:e	(Ljava/lang/String;Ljava/lang/String;[Ljava/lang/Object;)V
      //   5522: goto -101 -> 5421
      //   5525: astore 18
      //   5527: ldc -112
      //   5529: aload 18
      //   5531: ldc_w 598
      //   5534: iconst_0
      //   5535: anewarray 4	java/lang/Object
      //   5538: invokestatic 602	com/tencent/mm/sdk/platformtools/w:printErrStackTrace	(Ljava/lang/String;Ljava/lang/Throwable;Ljava/lang/String;[Ljava/lang/Object;)V
      //   5541: goto -120 -> 5421
      //   5544: astore 18
      //   5546: ldc -112
      //   5548: ldc_w 491
      //   5551: iconst_3
      //   5552: anewarray 4	java/lang/Object
      //   5555: dup
      //   5556: iconst_0
      //   5557: aload 18
      //   5559: invokevirtual 493	java/io/IOException:toString	()Ljava/lang/String;
      //   5562: aastore
      //   5563: dup
      //   5564: iconst_1
      //   5565: aload 30
      //   5567: aastore
      //   5568: dup
      //   5569: iconst_2
      //   5570: aload 31
      //   5572: aastore
      //   5573: invokestatic 344	com/tencent/mm/sdk/platformtools/w:e	(Ljava/lang/String;Ljava/lang/String;[Ljava/lang/Object;)V
      //   5576: goto -145 -> 5431
      //   5579: astore 18
      //   5581: aconst_null
      //   5582: astore 23
      //   5584: aconst_null
      //   5585: astore 21
      //   5587: lconst_0
      //   5588: lstore 14
      //   5590: iconst_0
      //   5591: istore_2
      //   5592: aconst_null
      //   5593: astore 19
      //   5595: aconst_null
      //   5596: astore 20
      //   5598: iload 4
      //   5600: istore_3
      //   5601: aload_0
      //   5602: getfield 17	com/tencent/mm/plugin/appbrand/h/f$b:itn	Lcom/tencent/mm/plugin/appbrand/h/f;
      //   5605: getfield 128	com/tencent/mm/plugin/appbrand/h/f:hyD	Ljava/lang/String;
      //   5608: aload_1
      //   5609: getfield 131	com/tencent/mm/plugin/appbrand/h/g:itj	Ljava/lang/String;
      //   5612: ldc -123
      //   5614: aload_1
      //   5615: getfield 59	com/tencent/mm/plugin/appbrand/h/g:mUrl	Ljava/lang/String;
      //   5618: lload 14
      //   5620: iload_3
      //   5621: i2l
      //   5622: iload_2
      //   5623: iconst_2
      //   5624: aload_1
      //   5625: invokevirtual 137	com/tencent/mm/plugin/appbrand/h/g:YQ	()I
      //   5628: invokestatic 142	com/tencent/mm/plugin/appbrand/report/a/d:a	(Ljava/lang/String;Ljava/lang/String;Ljava/lang/String;Ljava/lang/String;JJIII)V
      //   5631: aload_1
      //   5632: iconst_0
      //   5633: putfield 155	com/tencent/mm/plugin/appbrand/h/g:aDI	Z
      //   5636: aload_0
      //   5637: getfield 17	com/tencent/mm/plugin/appbrand/h/f$b:itn	Lcom/tencent/mm/plugin/appbrand/h/f;
      //   5640: aload_1
      //   5641: getfield 215	com/tencent/mm/plugin/appbrand/h/g:hXm	Ljava/lang/String;
      //   5644: aload 19
      //   5646: invokevirtual 352	com/tencent/mm/plugin/appbrand/h/f:a	(Ljava/lang/String;Ljava/net/HttpURLConnection;)V
      //   5649: aload 23
      //   5651: ifnull +8 -> 5659
      //   5654: aload 23
      //   5656: invokevirtual 355	java/io/FileInputStream:close	()V
      //   5659: aload 20
      //   5661: ifnull +8 -> 5669
      //   5664: aload 20
      //   5666: invokevirtual 358	java/io/InputStream:close	()V
      //   5669: aload 21
      //   5671: ifnull +8 -> 5679
      //   5674: aload 21
      //   5676: invokevirtual 361	java/io/DataOutputStream:close	()V
      //   5679: aload_0
      //   5680: getfield 17	com/tencent/mm/plugin/appbrand/h/f$b:itn	Lcom/tencent/mm/plugin/appbrand/h/f;
      //   5683: getfield 364	com/tencent/mm/plugin/appbrand/h/f:isL	Ljava/util/ArrayList;
      //   5686: aload_1
      //   5687: getfield 215	com/tencent/mm/plugin/appbrand/h/g:hXm	Ljava/lang/String;
      //   5690: invokevirtual 370	java/util/ArrayList:remove	(Ljava/lang/Object;)Z
      //   5693: pop
      //   5694: aload 18
      //   5696: athrow
      //   5697: astore 19
      //   5699: ldc -112
      //   5701: ldc_w 491
      //   5704: iconst_3
      //   5705: anewarray 4	java/lang/Object
      //   5708: dup
      //   5709: iconst_0
      //   5710: aload 19
      //   5712: invokevirtual 492	java/lang/Exception:toString	()Ljava/lang/String;
      //   5715: aastore
      //   5716: dup
      //   5717: iconst_1
      //   5718: aload 30
      //   5720: aastore
      //   5721: dup
      //   5722: iconst_2
      //   5723: aload 31
      //   5725: aastore
      //   5726: invokestatic 344	com/tencent/mm/sdk/platformtools/w:e	(Ljava/lang/String;Ljava/lang/String;[Ljava/lang/Object;)V
      //   5729: goto -70 -> 5659
      //   5732: astore 19
      //   5734: ldc -112
      //   5736: ldc_w 596
      //   5739: iconst_3
      //   5740: anewarray 4	java/lang/Object
      //   5743: dup
      //   5744: iconst_0
      //   5745: aload 19
      //   5747: invokevirtual 493	java/io/IOException:toString	()Ljava/lang/String;
      //   5750: aastore
      //   5751: dup
      //   5752: iconst_1
      //   5753: aload 30
      //   5755: aastore
      //   5756: dup
      //   5757: iconst_2
      //   5758: aload 31
      //   5760: aastore
      //   5761: invokestatic 344	com/tencent/mm/sdk/platformtools/w:e	(Ljava/lang/String;Ljava/lang/String;[Ljava/lang/Object;)V
      //   5764: goto -95 -> 5669
      //   5767: astore 19
      //   5769: ldc -112
      //   5771: aload 19
      //   5773: ldc_w 598
      //   5776: iconst_0
      //   5777: anewarray 4	java/lang/Object
      //   5780: invokestatic 602	com/tencent/mm/sdk/platformtools/w:printErrStackTrace	(Ljava/lang/String;Ljava/lang/Throwable;Ljava/lang/String;[Ljava/lang/Object;)V
      //   5783: goto -114 -> 5669
      //   5786: astore 19
      //   5788: ldc -112
      //   5790: ldc_w 491
      //   5793: iconst_3
      //   5794: anewarray 4	java/lang/Object
      //   5797: dup
      //   5798: iconst_0
      //   5799: aload 19
      //   5801: invokevirtual 493	java/io/IOException:toString	()Ljava/lang/String;
      //   5804: aastore
      //   5805: dup
      //   5806: iconst_1
      //   5807: aload 30
      //   5809: aastore
      //   5810: dup
      //   5811: iconst_2
      //   5812: aload 31
      //   5814: aastore
      //   5815: invokestatic 344	com/tencent/mm/sdk/platformtools/w:e	(Ljava/lang/String;Ljava/lang/String;[Ljava/lang/Object;)V
      //   5818: goto -139 -> 5679
      //   5821: astore 18
      //   5823: aconst_null
      //   5824: astore 21
      //   5826: lconst_0
      //   5827: lstore 14
      //   5829: iconst_0
      //   5830: istore_2
      //   5831: aconst_null
      //   5832: astore 22
      //   5834: aconst_null
      //   5835: astore 20
      //   5837: aload 19
      //   5839: astore 23
      //   5841: aload 22
      //   5843: astore 19
      //   5845: iload 4
      //   5847: istore_3
      //   5848: goto -247 -> 5601
      //   5851: astore 23
      //   5853: aconst_null
      //   5854: astore 21
      //   5856: lconst_0
      //   5857: lstore 14
      //   5859: iconst_0
      //   5860: istore_2
      //   5861: aload 18
      //   5863: astore 22
      //   5865: aconst_null
      //   5866: astore 20
      //   5868: aload 23
      //   5870: astore 18
      //   5872: aload 19
      //   5874: astore 23
      //   5876: aload 22
      //   5878: astore 19
      //   5880: iload 4
      //   5882: istore_3
      //   5883: goto -282 -> 5601
      //   5886: astore 23
      //   5888: aconst_null
      //   5889: astore 20
      //   5891: lconst_0
      //   5892: lstore 14
      //   5894: iconst_0
      //   5895: istore_2
      //   5896: aload 18
      //   5898: astore 22
      //   5900: aload 23
      //   5902: astore 18
      //   5904: aload 19
      //   5906: astore 23
      //   5908: aload 22
      //   5910: astore 19
      //   5912: iload 4
      //   5914: istore_3
      //   5915: goto -314 -> 5601
      //   5918: astore 23
      //   5920: aconst_null
      //   5921: astore 20
      //   5923: iconst_0
      //   5924: istore_2
      //   5925: aload 18
      //   5927: astore 22
      //   5929: aload 23
      //   5931: astore 18
      //   5933: aload 19
      //   5935: astore 23
      //   5937: aload 22
      //   5939: astore 19
      //   5941: iload 4
      //   5943: istore_3
      //   5944: goto -343 -> 5601
      //   5947: astore 23
      //   5949: aconst_null
      //   5950: astore 20
      //   5952: iconst_0
      //   5953: istore_2
      //   5954: aload 18
      //   5956: astore 22
      //   5958: aload 23
      //   5960: astore 18
      //   5962: aload 19
      //   5964: astore 23
      //   5966: aload 22
      //   5968: astore 19
      //   5970: iload 4
      //   5972: istore_3
      //   5973: goto -372 -> 5601
      //   5976: astore 23
      //   5978: aconst_null
      //   5979: astore 20
      //   5981: aload 18
      //   5983: astore 22
      //   5985: aload 23
      //   5987: astore 18
      //   5989: aload 19
      //   5991: astore 23
      //   5993: aload 22
      //   5995: astore 19
      //   5997: iload 4
      //   5999: istore_3
      //   6000: goto -399 -> 5601
      //   6003: astore 23
      //   6005: aload 18
      //   6007: astore 22
      //   6009: aload 23
      //   6011: astore 18
      //   6013: aload 19
      //   6015: astore 23
      //   6017: aload 22
      //   6019: astore 19
      //   6021: iload 4
      //   6023: istore_3
      //   6024: goto -423 -> 5601
      //   6027: astore 23
      //   6029: aload 18
      //   6031: astore 22
      //   6033: aload 23
      //   6035: astore 18
      //   6037: aload 19
      //   6039: astore 23
      //   6041: aload 22
      //   6043: astore 19
      //   6045: goto -444 -> 5601
      //   6048: astore 23
      //   6050: aload 18
      //   6052: astore 22
      //   6054: aload 23
      //   6056: astore 18
      //   6058: aload 19
      //   6060: astore 23
      //   6062: aload 22
      //   6064: astore 19
      //   6066: goto -465 -> 5601
      //   6069: astore 25
      //   6071: iload_2
      //   6072: istore 4
      //   6074: aload 20
      //   6076: astore 24
      //   6078: aload 22
      //   6080: astore 21
      //   6082: aload 18
      //   6084: astore 23
      //   6086: aload 25
      //   6088: astore 18
      //   6090: iload_3
      //   6091: istore_2
      //   6092: aload 19
      //   6094: astore 20
      //   6096: aload 24
      //   6098: astore 19
      //   6100: iload 4
      //   6102: istore_3
      //   6103: goto -502 -> 5601
      //   6106: astore 20
      //   6108: lload 16
      //   6110: lstore 14
      //   6112: iload 4
      //   6114: istore_2
      //   6115: aload 18
      //   6117: astore 22
      //   6119: aload 20
      //   6121: astore 18
      //   6123: aload 19
      //   6125: astore 20
      //   6127: aload 22
      //   6129: astore 19
      //   6131: goto -530 -> 5601
      //   6134: astore 22
      //   6136: aconst_null
      //   6137: astore 25
      //   6139: aconst_null
      //   6140: astore 18
      //   6142: aload 20
      //   6144: astore 24
      //   6146: aload 19
      //   6148: astore 26
      //   6150: aload 18
      //   6152: astore 20
      //   6154: iload 12
      //   6156: istore_2
      //   6157: iload 8
      //   6159: istore 5
      //   6161: goto -943 -> 5218
      //   6164: astore 22
      //   6166: aconst_null
      //   6167: astore 20
      //   6169: aload 18
      //   6171: astore 24
      //   6173: aload 19
      //   6175: astore 26
      //   6177: aload 21
      //   6179: astore 25
      //   6181: iload 12
      //   6183: istore_2
      //   6184: iload 8
      //   6186: istore 5
      //   6188: goto -970 -> 5218
      //   6191: astore 22
      //   6193: aconst_null
      //   6194: astore 20
      //   6196: aload 18
      //   6198: astore 24
      //   6200: aload 19
      //   6202: astore 26
      //   6204: aload 21
      //   6206: astore 25
      //   6208: iload 12
      //   6210: istore_2
      //   6211: iload 8
      //   6213: istore 5
      //   6215: goto -997 -> 5218
      //   6218: astore 22
      //   6220: aconst_null
      //   6221: astore 20
      //   6223: aload 18
      //   6225: astore 24
      //   6227: aload 19
      //   6229: astore 26
      //   6231: aload 21
      //   6233: astore 25
      //   6235: iload 12
      //   6237: istore_2
      //   6238: iload 8
      //   6240: istore 5
      //   6242: goto -1024 -> 5218
      //   6245: astore 22
      //   6247: aconst_null
      //   6248: astore 20
      //   6250: aload 18
      //   6252: astore 24
      //   6254: aload 19
      //   6256: astore 26
      //   6258: aload 21
      //   6260: astore 25
      //   6262: iload 8
      //   6264: istore 5
      //   6266: goto -1048 -> 5218
      //   6269: astore 22
      //   6271: aload 18
      //   6273: astore 24
      //   6275: aload 19
      //   6277: astore 26
      //   6279: aload 21
      //   6281: astore 25
      //   6283: iload 8
      //   6285: istore 5
      //   6287: goto -1069 -> 5218
      //   6290: astore 22
      //   6292: aload 18
      //   6294: astore 24
      //   6296: aload 19
      //   6298: astore 26
      //   6300: aload 21
      //   6302: astore 25
      //   6304: iload_3
      //   6305: istore 5
      //   6307: goto -1089 -> 5218
      //   6310: astore 22
      //   6312: aload 18
      //   6314: astore 24
      //   6316: aload 19
      //   6318: astore 26
      //   6320: aload 21
      //   6322: astore 25
      //   6324: iload_3
      //   6325: istore 5
      //   6327: goto -1109 -> 5218
      //   6330: astore 22
      //   6332: aconst_null
      //   6333: astore 25
      //   6335: aconst_null
      //   6336: astore 20
      //   6338: aload 23
      //   6340: astore 24
      //   6342: aload 19
      //   6344: astore 26
      //   6346: iload 11
      //   6348: istore_2
      //   6349: iload 7
      //   6351: istore 5
      //   6353: goto -1518 -> 4835
      //   6356: astore 22
      //   6358: aconst_null
      //   6359: astore 20
      //   6361: aload 18
      //   6363: astore 24
      //   6365: aload 19
      //   6367: astore 26
      //   6369: aload 21
      //   6371: astore 25
      //   6373: iload 11
      //   6375: istore_2
      //   6376: iload 7
      //   6378: istore 5
      //   6380: goto -1545 -> 4835
      //   6383: astore 22
      //   6385: aconst_null
      //   6386: astore 20
      //   6388: aload 18
      //   6390: astore 24
      //   6392: aload 19
      //   6394: astore 26
      //   6396: aload 21
      //   6398: astore 25
      //   6400: iload 11
      //   6402: istore_2
      //   6403: iload 7
      //   6405: istore 5
      //   6407: goto -1572 -> 4835
      //   6410: astore 22
      //   6412: aconst_null
      //   6413: astore 20
      //   6415: aload 18
      //   6417: astore 24
      //   6419: aload 19
      //   6421: astore 26
      //   6423: aload 21
      //   6425: astore 25
      //   6427: iload 11
      //   6429: istore_2
      //   6430: iload 7
      //   6432: istore 5
      //   6434: goto -1599 -> 4835
      //   6437: astore 22
      //   6439: aconst_null
      //   6440: astore 20
      //   6442: aload 18
      //   6444: astore 24
      //   6446: aload 19
      //   6448: astore 26
      //   6450: aload 21
      //   6452: astore 25
      //   6454: iload 7
      //   6456: istore 5
      //   6458: goto -1623 -> 4835
      //   6461: astore 22
      //   6463: aload 18
      //   6465: astore 24
      //   6467: aload 19
      //   6469: astore 26
      //   6471: aload 21
      //   6473: astore 25
      //   6475: iload 7
      //   6477: istore 5
      //   6479: goto -1644 -> 4835
      //   6482: astore 22
      //   6484: aload 18
      //   6486: astore 24
      //   6488: aload 19
      //   6490: astore 26
      //   6492: aload 21
      //   6494: astore 25
      //   6496: iload_3
      //   6497: istore 5
      //   6499: goto -1664 -> 4835
      //   6502: astore 22
      //   6504: aload 18
      //   6506: astore 24
      //   6508: aload 19
      //   6510: astore 26
      //   6512: aload 21
      //   6514: astore 25
      //   6516: iload_3
      //   6517: istore 5
      //   6519: goto -1684 -> 4835
      //   6522: astore 22
      //   6524: aconst_null
      //   6525: astore 26
      //   6527: aconst_null
      //   6528: astore 25
      //   6530: aconst_null
      //   6531: astore 20
      //   6533: aload 21
      //   6535: astore 24
      //   6537: iload 10
      //   6539: istore_2
      //   6540: iload 6
      //   6542: istore 5
      //   6544: goto -4298 -> 2246
      //   6547: astore 22
      //   6549: aconst_null
      //   6550: astore 20
      //   6552: aload 18
      //   6554: astore 24
      //   6556: aload 19
      //   6558: astore 26
      //   6560: aload 21
      //   6562: astore 25
      //   6564: iload 10
      //   6566: istore_2
      //   6567: iload 6
      //   6569: istore 5
      //   6571: goto -4325 -> 2246
      //   6574: astore 22
      //   6576: aconst_null
      //   6577: astore 20
      //   6579: aload 18
      //   6581: astore 24
      //   6583: aload 19
      //   6585: astore 26
      //   6587: aload 21
      //   6589: astore 25
      //   6591: iload 10
      //   6593: istore_2
      //   6594: iload 6
      //   6596: istore 5
      //   6598: goto -4352 -> 2246
      //   6601: astore 22
      //   6603: aconst_null
      //   6604: astore 20
      //   6606: aload 18
      //   6608: astore 24
      //   6610: aload 19
      //   6612: astore 26
      //   6614: aload 21
      //   6616: astore 25
      //   6618: iload 10
      //   6620: istore_2
      //   6621: iload 6
      //   6623: istore 5
      //   6625: goto -4379 -> 2246
      //   6628: astore 22
      //   6630: aconst_null
      //   6631: astore 20
      //   6633: aload 18
      //   6635: astore 24
      //   6637: aload 19
      //   6639: astore 26
      //   6641: aload 21
      //   6643: astore 25
      //   6645: iload 6
      //   6647: istore 5
      //   6649: goto -4403 -> 2246
      //   6652: astore 22
      //   6654: aload 18
      //   6656: astore 24
      //   6658: aload 19
      //   6660: astore 26
      //   6662: aload 21
      //   6664: astore 25
      //   6666: iload 6
      //   6668: istore 5
      //   6670: goto -4424 -> 2246
      //   6673: astore 22
      //   6675: aload 18
      //   6677: astore 24
      //   6679: aload 19
      //   6681: astore 26
      //   6683: aload 21
      //   6685: astore 25
      //   6687: iload_3
      //   6688: istore 5
      //   6690: goto -4444 -> 2246
      //   6693: astore 22
      //   6695: aload 18
      //   6697: astore 24
      //   6699: aload 19
      //   6701: astore 26
      //   6703: aload 21
      //   6705: astore 25
      //   6707: iload_3
      //   6708: istore 5
      //   6710: goto -4464 -> 2246
      //   6713: astore 22
      //   6715: aconst_null
      //   6716: astore 26
      //   6718: aconst_null
      //   6719: astore 25
      //   6721: aconst_null
      //   6722: astore 18
      //   6724: aload 20
      //   6726: astore 24
      //   6728: aload 18
      //   6730: astore 20
      //   6732: iload 9
      //   6734: istore_2
      //   6735: goto -5259 -> 1476
      //   6738: astore 22
      //   6740: aconst_null
      //   6741: astore 20
      //   6743: aload 18
      //   6745: astore 24
      //   6747: aload 19
      //   6749: astore 26
      //   6751: aload 21
      //   6753: astore 25
      //   6755: iload 9
      //   6757: istore_2
      //   6758: goto -5282 -> 1476
      //   6761: astore 22
      //   6763: aconst_null
      //   6764: astore 20
      //   6766: aload 18
      //   6768: astore 24
      //   6770: aload 19
      //   6772: astore 26
      //   6774: aload 21
      //   6776: astore 25
      //   6778: iload 9
      //   6780: istore_2
      //   6781: goto -5305 -> 1476
      //   6784: astore 22
      //   6786: aconst_null
      //   6787: astore 20
      //   6789: aload 18
      //   6791: astore 24
      //   6793: aload 19
      //   6795: astore 26
      //   6797: aload 21
      //   6799: astore 25
      //   6801: iload 9
      //   6803: istore_2
      //   6804: goto -5328 -> 1476
      //   6807: astore 22
      //   6809: aconst_null
      //   6810: astore 20
      //   6812: aload 18
      //   6814: astore 24
      //   6816: aload 19
      //   6818: astore 26
      //   6820: aload 21
      //   6822: astore 25
      //   6824: goto -5348 -> 1476
      //   6827: astore 22
      //   6829: aload 18
      //   6831: astore 24
      //   6833: aload 19
      //   6835: astore 26
      //   6837: aload 21
      //   6839: astore 25
      //   6841: goto -5365 -> 1476
      //   6844: astore 22
      //   6846: aload 18
      //   6848: astore 24
      //   6850: aload 19
      //   6852: astore 26
      //   6854: aload 21
      //   6856: astore 25
      //   6858: iload_3
      //   6859: istore 5
      //   6861: goto -5385 -> 1476
      //   6864: astore 22
      //   6866: aload 18
      //   6868: astore 24
      //   6870: aload 19
      //   6872: astore 26
      //   6874: aload 21
      //   6876: astore 25
      //   6878: iload_3
      //   6879: istore 5
      //   6881: goto -5405 -> 1476
      //   6884: astore 21
      //   6886: aconst_null
      //   6887: astore 19
      //   6889: aconst_null
      //   6890: astore 20
      //   6892: aconst_null
      //   6893: astore 18
      //   6895: iconst_0
      //   6896: istore_2
      //   6897: aload 27
      //   6899: astore 22
      //   6901: goto -5640 -> 1261
      //   6904: astore 21
      //   6906: aconst_null
      //   6907: astore 20
      //   6909: aload 19
      //   6911: astore 18
      //   6913: aconst_null
      //   6914: astore 19
      //   6916: iconst_0
      //   6917: istore_2
      //   6918: aload 27
      //   6920: astore 22
      //   6922: goto -5661 -> 1261
      //   6925: astore 23
      //   6927: aload 21
      //   6929: astore 22
      //   6931: aload 18
      //   6933: astore 20
      //   6935: aload 19
      //   6937: astore 18
      //   6939: aconst_null
      //   6940: astore 19
      //   6942: iconst_0
      //   6943: istore_2
      //   6944: aload 23
      //   6946: astore 21
      //   6948: goto -5687 -> 1261
      //   6951: astore 23
      //   6953: aload 21
      //   6955: astore 22
      //   6957: aload 18
      //   6959: astore 20
      //   6961: aload 19
      //   6963: astore 18
      //   6965: aconst_null
      //   6966: astore 19
      //   6968: iconst_0
      //   6969: istore_2
      //   6970: aload 23
      //   6972: astore 21
      //   6974: goto -5713 -> 1261
      //   6977: astore 23
      //   6979: aload 21
      //   6981: astore 22
      //   6983: aload 18
      //   6985: astore 20
      //   6987: aload 19
      //   6989: astore 18
      //   6991: aconst_null
      //   6992: astore 19
      //   6994: iconst_0
      //   6995: istore_2
      //   6996: aload 23
      //   6998: astore 21
      //   7000: goto -5739 -> 1261
      //   7003: astore 23
      //   7005: aload 21
      //   7007: astore 22
      //   7009: iload_2
      //   7010: istore_3
      //   7011: aload 18
      //   7013: astore 20
      //   7015: aload 19
      //   7017: astore 18
      //   7019: aconst_null
      //   7020: astore 19
      //   7022: iconst_0
      //   7023: istore_2
      //   7024: aload 23
      //   7026: astore 21
      //   7028: goto -5767 -> 1261
      //   7031: astore 22
      //   7033: iload_2
      //   7034: istore 4
      //   7036: iload_3
      //   7037: istore_2
      //   7038: aload 21
      //   7040: astore 23
      //   7042: aload 18
      //   7044: astore 24
      //   7046: aload 22
      //   7048: astore 21
      //   7050: aload 19
      //   7052: astore 18
      //   7054: aload 20
      //   7056: astore 19
      //   7058: aload 23
      //   7060: astore 22
      //   7062: aload 24
      //   7064: astore 20
      //   7066: iload 4
      //   7068: istore_3
      //   7069: goto -5808 -> 1261
      //   7072: astore 22
      //   7074: iload_2
      //   7075: istore 4
      //   7077: iload_3
      //   7078: istore_2
      //   7079: aload 21
      //   7081: astore 23
      //   7083: aload 18
      //   7085: astore 24
      //   7087: aload 22
      //   7089: astore 21
      //   7091: aload 19
      //   7093: astore 18
      //   7095: aload 20
      //   7097: astore 19
      //   7099: aload 23
      //   7101: astore 22
      //   7103: aload 24
      //   7105: astore 20
      //   7107: iload 4
      //   7109: istore_3
      //   7110: goto -5849 -> 1261
      //   7113: ldc_w 598
      //   7116: astore 22
      //   7118: iconst_0
      //   7119: istore_3
      //   7120: goto -2996 -> 4124
      //   7123: goto -4114 -> 3009
      //   7126: goto -4266 -> 2860
      // Local variable table:
      //   start	length	slot	name	signature
      //   0	7129	0	this	b
      //   0	7129	1	paramg	g
      //   1256	5823	2	i	int
      //   118	7002	3	j	int
      //   100	7008	4	k	int
      //   103	6777	5	m	int
      //   91	6576	6	n	int
      //   94	6382	7	i1	int
      //   97	6187	8	i2	int
      //   106	6696	9	i3	int
      //   109	6510	10	i4	int
      //   112	6316	11	i5	int
      //   115	6121	12	i6	int
      //   3016	263	13	i7	int
      //   120	5991	14	l1	long
      //   1497	4612	16	l2	long
      //   48	2156	18	localObject1	Object
      //   2219	24	18	localSSLHandshakeException1	javax.net.ssl.SSLHandshakeException
      //   2248	859	18	localObject2	Object
      //   3198	14	18	localException1	Exception
      //   3233	292	18	localIOException1	java.io.IOException
      //   3563	14	18	localException2	Exception
      //   3598	127	18	localIOException2	java.io.IOException
      //   3763	14	18	localException3	Exception
      //   3798	153	18	localIOException3	java.io.IOException
      //   3960	256	18	localObject3	Object
      //   4321	14	18	localException4	Exception
      //   4356	14	18	localIOException4	java.io.IOException
      //   4391	5	18	localArrayIndexOutOfBoundsException1	ArrayIndexOutOfBoundsException
      //   4410	14	18	localIOException5	java.io.IOException
      //   4445	14	18	localException5	Exception
      //   4480	14	18	localIOException6	java.io.IOException
      //   4515	5	18	localArrayIndexOutOfBoundsException2	ArrayIndexOutOfBoundsException
      //   4534	14	18	localIOException7	java.io.IOException
      //   4569	14	18	localException6	Exception
      //   4604	14	18	localIOException8	java.io.IOException
      //   4639	5	18	localArrayIndexOutOfBoundsException3	ArrayIndexOutOfBoundsException
      //   4658	14	18	localIOException9	java.io.IOException
      //   4693	14	18	localException7	Exception
      //   4728	14	18	localIOException10	java.io.IOException
      //   4763	5	18	localArrayIndexOutOfBoundsException4	ArrayIndexOutOfBoundsException
      //   4782	14	18	localIOException11	java.io.IOException
      //   4837	97	18	localObject4	Object
      //   5072	14	18	localException8	Exception
      //   5107	14	18	localIOException12	java.io.IOException
      //   5142	5	18	localArrayIndexOutOfBoundsException5	ArrayIndexOutOfBoundsException
      //   5161	54	18	localIOException13	java.io.IOException
      //   5220	97	18	localObject5	Object
      //   5455	14	18	localException9	Exception
      //   5490	14	18	localIOException14	java.io.IOException
      //   5525	5	18	localArrayIndexOutOfBoundsException6	ArrayIndexOutOfBoundsException
      //   5544	14	18	localIOException15	java.io.IOException
      //   5579	116	18	localObject6	Object
      //   5821	41	18	localObject7	Object
      //   5870	1224	18	localObject8	Object
      //   52	5593	19	localObject9	Object
      //   5697	14	19	localException10	Exception
      //   5732	14	19	localIOException16	java.io.IOException
      //   5767	5	19	localArrayIndexOutOfBoundsException7	ArrayIndexOutOfBoundsException
      //   5786	52	19	localIOException17	java.io.IOException
      //   5843	1255	19	localObject10	Object
      //   41	3942	20	localObject11	Object
      //   3987	14	20	localException11	Exception
      //   4032	1	20	localGZIPInputStream	java.util.zip.GZIPInputStream
      //   4037	14	20	localException12	Exception
      //   4060	2035	20	localObject12	Object
      //   6106	14	20	localObject13	Object
      //   6125	981	20	localObject14	Object
      //   221	828	21	localIterator	Iterator
      //   1242	43	21	localUnsupportedEncodingException1	java.io.UnsupportedEncodingException
      //   1490	5385	21	localObject15	Object
      //   6884	1	21	localUnsupportedEncodingException2	java.io.UnsupportedEncodingException
      //   6904	24	21	localUnsupportedEncodingException3	java.io.UnsupportedEncodingException
      //   6946	144	21	localObject16	Object
      //   415	1009	22	localObject17	Object
      //   1461	93	22	localFileNotFoundException1	java.io.FileNotFoundException
      //   1719	2192	22	localObject18	Object
      //   3940	15	22	localUnsupportedEncodingException4	java.io.UnsupportedEncodingException
      //   3968	167	22	localObject19	Object
      //   4817	96	22	localSocketTimeoutException1	java.net.SocketTimeoutException
      //   5196	100	22	localException13	Exception
      //   5832	296	22	localObject20	Object
      //   6134	1	22	localException14	Exception
      //   6164	1	22	localException15	Exception
      //   6191	1	22	localException16	Exception
      //   6218	1	22	localException17	Exception
      //   6245	1	22	localException18	Exception
      //   6269	1	22	localException19	Exception
      //   6290	1	22	localException20	Exception
      //   6310	1	22	localException21	Exception
      //   6330	1	22	localSocketTimeoutException2	java.net.SocketTimeoutException
      //   6356	1	22	localSocketTimeoutException3	java.net.SocketTimeoutException
      //   6383	1	22	localSocketTimeoutException4	java.net.SocketTimeoutException
      //   6410	1	22	localSocketTimeoutException5	java.net.SocketTimeoutException
      //   6437	1	22	localSocketTimeoutException6	java.net.SocketTimeoutException
      //   6461	1	22	localSocketTimeoutException7	java.net.SocketTimeoutException
      //   6482	1	22	localSocketTimeoutException8	java.net.SocketTimeoutException
      //   6502	1	22	localSocketTimeoutException9	java.net.SocketTimeoutException
      //   6522	1	22	localSSLHandshakeException2	javax.net.ssl.SSLHandshakeException
      //   6547	1	22	localSSLHandshakeException3	javax.net.ssl.SSLHandshakeException
      //   6574	1	22	localSSLHandshakeException4	javax.net.ssl.SSLHandshakeException
      //   6601	1	22	localSSLHandshakeException5	javax.net.ssl.SSLHandshakeException
      //   6628	1	22	localSSLHandshakeException6	javax.net.ssl.SSLHandshakeException
      //   6652	1	22	localSSLHandshakeException7	javax.net.ssl.SSLHandshakeException
      //   6673	1	22	localSSLHandshakeException8	javax.net.ssl.SSLHandshakeException
      //   6693	1	22	localSSLHandshakeException9	javax.net.ssl.SSLHandshakeException
      //   6713	1	22	localFileNotFoundException2	java.io.FileNotFoundException
      //   6738	1	22	localFileNotFoundException3	java.io.FileNotFoundException
      //   6761	1	22	localFileNotFoundException4	java.io.FileNotFoundException
      //   6784	1	22	localFileNotFoundException5	java.io.FileNotFoundException
      //   6807	1	22	localFileNotFoundException6	java.io.FileNotFoundException
      //   6827	1	22	localFileNotFoundException7	java.io.FileNotFoundException
      //   6844	1	22	localFileNotFoundException8	java.io.FileNotFoundException
      //   6864	1	22	localFileNotFoundException9	java.io.FileNotFoundException
      //   6899	109	22	localObject21	Object
      //   7031	16	22	localUnsupportedEncodingException5	java.io.UnsupportedEncodingException
      //   7060	1	22	localObject22	Object
      //   7072	16	22	localUnsupportedEncodingException6	java.io.UnsupportedEncodingException
      //   7101	16	22	localObject23	Object
      //   423	5417	23	localObject24	Object
      //   5851	18	23	localObject25	Object
      //   5874	1	23	localObject26	Object
      //   5886	15	23	localObject27	Object
      //   5906	1	23	localObject28	Object
      //   5918	12	23	localObject29	Object
      //   5935	1	23	localObject30	Object
      //   5947	12	23	localObject31	Object
      //   5964	1	23	localObject32	Object
      //   5976	10	23	localObject33	Object
      //   5991	1	23	localObject34	Object
      //   6003	7	23	localObject35	Object
      //   6015	1	23	localObject36	Object
      //   6027	7	23	localObject37	Object
      //   6039	1	23	localObject38	Object
      //   6048	7	23	localObject39	Object
      //   6060	279	23	localObject40	Object
      //   6925	20	23	localUnsupportedEncodingException7	java.io.UnsupportedEncodingException
      //   6951	20	23	localUnsupportedEncodingException8	java.io.UnsupportedEncodingException
      //   6977	20	23	localUnsupportedEncodingException9	java.io.UnsupportedEncodingException
      //   7003	22	23	localUnsupportedEncodingException10	java.io.UnsupportedEncodingException
      //   7040	60	23	localObject41	Object
      //   224	6880	24	localObject42	Object
      //   236	5191	25	localObject43	Object
      //   6069	18	25	localObject44	Object
      //   6137	740	25	localObject45	Object
      //   218	6655	26	localObject46	Object
      //   239	6680	27	localObject47	Object
      //   230	1870	28	str1	String
      //   233	1953	29	str2	String
      //   12	5796	30	str3	String
      //   18	5795	31	str4	String
      //   126	5215	32	locala	f.a
      //   434	3673	33	localURL	java.net.URL
      //   396	2604	34	localFile	java.io.File
      //   24	2537	35	str5	String
      //   30	2594	36	str6	String
      //   76	2496	37	str7	String
      //   82	1889	38	localMap1	Map
      //   373	2350	39	str8	String
      //   88	905	40	localMap2	Map
      //   132	540	41	localArrayList	ArrayList
      // Exception table:
      //   from	to	target	type
      //   478	488	1242	java/io/UnsupportedEncodingException
      //   504	510	1242	java/io/UnsupportedEncodingException
      //   526	534	1242	java/io/UnsupportedEncodingException
      //   550	560	1242	java/io/UnsupportedEncodingException
      //   576	593	1242	java/io/UnsupportedEncodingException
      //   609	619	1242	java/io/UnsupportedEncodingException
      //   635	653	1242	java/io/UnsupportedEncodingException
      //   669	676	1242	java/io/UnsupportedEncodingException
      //   692	698	1242	java/io/UnsupportedEncodingException
      //   714	720	1242	java/io/UnsupportedEncodingException
      //   736	742	1242	java/io/UnsupportedEncodingException
      //   758	767	1242	java/io/UnsupportedEncodingException
      //   783	792	1242	java/io/UnsupportedEncodingException
      //   808	815	1242	java/io/UnsupportedEncodingException
      //   831	842	1242	java/io/UnsupportedEncodingException
      //   858	869	1242	java/io/UnsupportedEncodingException
      //   885	916	1242	java/io/UnsupportedEncodingException
      //   932	938	1242	java/io/UnsupportedEncodingException
      //   959	976	1242	java/io/UnsupportedEncodingException
      //   992	1006	1242	java/io/UnsupportedEncodingException
      //   1022	1032	1242	java/io/UnsupportedEncodingException
      //   1048	1060	1242	java/io/UnsupportedEncodingException
      //   1076	1113	1242	java/io/UnsupportedEncodingException
      //   1129	1145	1242	java/io/UnsupportedEncodingException
      //   1161	1177	1242	java/io/UnsupportedEncodingException
      //   1193	1215	1242	java/io/UnsupportedEncodingException
      //   1231	1239	1242	java/io/UnsupportedEncodingException
      //   1433	1458	1242	java/io/UnsupportedEncodingException
      //   1729	1750	1242	java/io/UnsupportedEncodingException
      //   1766	1773	1242	java/io/UnsupportedEncodingException
      //   1789	1798	1242	java/io/UnsupportedEncodingException
      //   1814	1823	1242	java/io/UnsupportedEncodingException
      //   1844	1870	1242	java/io/UnsupportedEncodingException
      //   1886	1900	1242	java/io/UnsupportedEncodingException
      //   1916	1926	1242	java/io/UnsupportedEncodingException
      //   1942	1954	1242	java/io/UnsupportedEncodingException
      //   1970	1984	1242	java/io/UnsupportedEncodingException
      //   2000	2022	1242	java/io/UnsupportedEncodingException
      //   2038	2071	1242	java/io/UnsupportedEncodingException
      //   2087	2117	1242	java/io/UnsupportedEncodingException
      //   2133	2142	1242	java/io/UnsupportedEncodingException
      //   2158	2167	1242	java/io/UnsupportedEncodingException
      //   2183	2191	1242	java/io/UnsupportedEncodingException
      //   2207	2216	1242	java/io/UnsupportedEncodingException
      //   2499	2532	1242	java/io/UnsupportedEncodingException
      //   2548	2595	1242	java/io/UnsupportedEncodingException
      //   2611	2635	1242	java/io/UnsupportedEncodingException
      //   2651	2660	1242	java/io/UnsupportedEncodingException
      //   2676	2685	1242	java/io/UnsupportedEncodingException
      //   2701	2746	1242	java/io/UnsupportedEncodingException
      //   2762	2775	1242	java/io/UnsupportedEncodingException
      //   2791	2804	1242	java/io/UnsupportedEncodingException
      //   2829	2834	1242	java/io/UnsupportedEncodingException
      //   2855	2860	1242	java/io/UnsupportedEncodingException
      //   2876	2890	1242	java/io/UnsupportedEncodingException
      //   2906	2926	1242	java/io/UnsupportedEncodingException
      //   2942	2955	1242	java/io/UnsupportedEncodingException
      //   2971	2985	1242	java/io/UnsupportedEncodingException
      //   425	436	1461	java/io/FileNotFoundException
      //   452	462	1461	java/io/FileNotFoundException
      //   478	488	1461	java/io/FileNotFoundException
      //   504	510	1461	java/io/FileNotFoundException
      //   526	534	1461	java/io/FileNotFoundException
      //   550	560	1461	java/io/FileNotFoundException
      //   576	593	1461	java/io/FileNotFoundException
      //   609	619	1461	java/io/FileNotFoundException
      //   635	653	1461	java/io/FileNotFoundException
      //   669	676	1461	java/io/FileNotFoundException
      //   692	698	1461	java/io/FileNotFoundException
      //   714	720	1461	java/io/FileNotFoundException
      //   736	742	1461	java/io/FileNotFoundException
      //   758	767	1461	java/io/FileNotFoundException
      //   783	792	1461	java/io/FileNotFoundException
      //   808	815	1461	java/io/FileNotFoundException
      //   831	842	1461	java/io/FileNotFoundException
      //   858	869	1461	java/io/FileNotFoundException
      //   885	916	1461	java/io/FileNotFoundException
      //   932	938	1461	java/io/FileNotFoundException
      //   959	976	1461	java/io/FileNotFoundException
      //   992	1006	1461	java/io/FileNotFoundException
      //   1022	1032	1461	java/io/FileNotFoundException
      //   1048	1060	1461	java/io/FileNotFoundException
      //   1076	1113	1461	java/io/FileNotFoundException
      //   1129	1145	1461	java/io/FileNotFoundException
      //   1161	1177	1461	java/io/FileNotFoundException
      //   1193	1215	1461	java/io/FileNotFoundException
      //   1231	1239	1461	java/io/FileNotFoundException
      //   1433	1458	1461	java/io/FileNotFoundException
      //   1729	1750	1461	java/io/FileNotFoundException
      //   1766	1773	1461	java/io/FileNotFoundException
      //   1789	1798	1461	java/io/FileNotFoundException
      //   1814	1823	1461	java/io/FileNotFoundException
      //   1844	1870	1461	java/io/FileNotFoundException
      //   1886	1900	1461	java/io/FileNotFoundException
      //   1916	1926	1461	java/io/FileNotFoundException
      //   1942	1954	1461	java/io/FileNotFoundException
      //   1970	1984	1461	java/io/FileNotFoundException
      //   2000	2022	1461	java/io/FileNotFoundException
      //   2038	2071	1461	java/io/FileNotFoundException
      //   2087	2117	1461	java/io/FileNotFoundException
      //   2133	2142	1461	java/io/FileNotFoundException
      //   2158	2167	1461	java/io/FileNotFoundException
      //   2183	2191	1461	java/io/FileNotFoundException
      //   2207	2216	1461	java/io/FileNotFoundException
      //   2499	2532	1461	java/io/FileNotFoundException
      //   2548	2595	1461	java/io/FileNotFoundException
      //   2611	2635	1461	java/io/FileNotFoundException
      //   2651	2660	1461	java/io/FileNotFoundException
      //   2676	2685	1461	java/io/FileNotFoundException
      //   2701	2746	1461	java/io/FileNotFoundException
      //   2762	2775	1461	java/io/FileNotFoundException
      //   2791	2804	1461	java/io/FileNotFoundException
      //   2829	2834	1461	java/io/FileNotFoundException
      //   2855	2860	1461	java/io/FileNotFoundException
      //   2876	2890	1461	java/io/FileNotFoundException
      //   2906	2926	1461	java/io/FileNotFoundException
      //   2942	2955	1461	java/io/FileNotFoundException
      //   2971	2985	1461	java/io/FileNotFoundException
      //   425	436	2219	javax/net/ssl/SSLHandshakeException
      //   452	462	2219	javax/net/ssl/SSLHandshakeException
      //   478	488	2219	javax/net/ssl/SSLHandshakeException
      //   504	510	2219	javax/net/ssl/SSLHandshakeException
      //   526	534	2219	javax/net/ssl/SSLHandshakeException
      //   550	560	2219	javax/net/ssl/SSLHandshakeException
      //   576	593	2219	javax/net/ssl/SSLHandshakeException
      //   609	619	2219	javax/net/ssl/SSLHandshakeException
      //   635	653	2219	javax/net/ssl/SSLHandshakeException
      //   669	676	2219	javax/net/ssl/SSLHandshakeException
      //   692	698	2219	javax/net/ssl/SSLHandshakeException
      //   714	720	2219	javax/net/ssl/SSLHandshakeException
      //   736	742	2219	javax/net/ssl/SSLHandshakeException
      //   758	767	2219	javax/net/ssl/SSLHandshakeException
      //   783	792	2219	javax/net/ssl/SSLHandshakeException
      //   808	815	2219	javax/net/ssl/SSLHandshakeException
      //   831	842	2219	javax/net/ssl/SSLHandshakeException
      //   858	869	2219	javax/net/ssl/SSLHandshakeException
      //   885	916	2219	javax/net/ssl/SSLHandshakeException
      //   932	938	2219	javax/net/ssl/SSLHandshakeException
      //   959	976	2219	javax/net/ssl/SSLHandshakeException
      //   992	1006	2219	javax/net/ssl/SSLHandshakeException
      //   1022	1032	2219	javax/net/ssl/SSLHandshakeException
      //   1048	1060	2219	javax/net/ssl/SSLHandshakeException
      //   1076	1113	2219	javax/net/ssl/SSLHandshakeException
      //   1129	1145	2219	javax/net/ssl/SSLHandshakeException
      //   1161	1177	2219	javax/net/ssl/SSLHandshakeException
      //   1193	1215	2219	javax/net/ssl/SSLHandshakeException
      //   1231	1239	2219	javax/net/ssl/SSLHandshakeException
      //   1433	1458	2219	javax/net/ssl/SSLHandshakeException
      //   1729	1750	2219	javax/net/ssl/SSLHandshakeException
      //   1766	1773	2219	javax/net/ssl/SSLHandshakeException
      //   1789	1798	2219	javax/net/ssl/SSLHandshakeException
      //   1814	1823	2219	javax/net/ssl/SSLHandshakeException
      //   1844	1870	2219	javax/net/ssl/SSLHandshakeException
      //   1886	1900	2219	javax/net/ssl/SSLHandshakeException
      //   1916	1926	2219	javax/net/ssl/SSLHandshakeException
      //   1942	1954	2219	javax/net/ssl/SSLHandshakeException
      //   1970	1984	2219	javax/net/ssl/SSLHandshakeException
      //   2000	2022	2219	javax/net/ssl/SSLHandshakeException
      //   2038	2071	2219	javax/net/ssl/SSLHandshakeException
      //   2087	2117	2219	javax/net/ssl/SSLHandshakeException
      //   2133	2142	2219	javax/net/ssl/SSLHandshakeException
      //   2158	2167	2219	javax/net/ssl/SSLHandshakeException
      //   2183	2191	2219	javax/net/ssl/SSLHandshakeException
      //   2207	2216	2219	javax/net/ssl/SSLHandshakeException
      //   2499	2532	2219	javax/net/ssl/SSLHandshakeException
      //   2548	2595	2219	javax/net/ssl/SSLHandshakeException
      //   2611	2635	2219	javax/net/ssl/SSLHandshakeException
      //   2651	2660	2219	javax/net/ssl/SSLHandshakeException
      //   2676	2685	2219	javax/net/ssl/SSLHandshakeException
      //   2701	2746	2219	javax/net/ssl/SSLHandshakeException
      //   2762	2775	2219	javax/net/ssl/SSLHandshakeException
      //   2791	2804	2219	javax/net/ssl/SSLHandshakeException
      //   2829	2834	2219	javax/net/ssl/SSLHandshakeException
      //   2855	2860	2219	javax/net/ssl/SSLHandshakeException
      //   2876	2890	2219	javax/net/ssl/SSLHandshakeException
      //   2906	2926	2219	javax/net/ssl/SSLHandshakeException
      //   2942	2955	2219	javax/net/ssl/SSLHandshakeException
      //   2971	2985	2219	javax/net/ssl/SSLHandshakeException
      //   3111	3116	3198	java/lang/Exception
      //   3116	3121	3233	java/io/IOException
      //   3529	3534	3563	java/lang/Exception
      //   3534	3539	3598	java/io/IOException
      //   3729	3734	3763	java/lang/Exception
      //   3734	3739	3798	java/io/IOException
      //   3883	3910	3940	java/io/UnsupportedEncodingException
      //   3910	3917	3940	java/io/UnsupportedEncodingException
      //   3922	3937	3940	java/io/UnsupportedEncodingException
      //   4075	4095	3940	java/io/UnsupportedEncodingException
      //   3850	3878	3987	java/lang/Exception
      //   3977	3984	3987	java/lang/Exception
      //   4006	4034	4037	java/lang/Exception
      //   4065	4072	4037	java/lang/Exception
      //   4220	4225	4321	java/lang/Exception
      //   4230	4235	4356	java/io/IOException
      //   4230	4235	4391	java/lang/ArrayIndexOutOfBoundsException
      //   4235	4240	4410	java/io/IOException
      //   1368	1373	4445	java/lang/Exception
      //   1378	1383	4480	java/io/IOException
      //   1378	1383	4515	java/lang/ArrayIndexOutOfBoundsException
      //   1388	1393	4534	java/io/IOException
      //   1664	1669	4569	java/lang/Exception
      //   1674	1679	4604	java/io/IOException
      //   1674	1679	4639	java/lang/ArrayIndexOutOfBoundsException
      //   1684	1689	4658	java/io/IOException
      //   2434	2439	4693	java/lang/Exception
      //   2444	2449	4728	java/io/IOException
      //   2444	2449	4763	java/lang/ArrayIndexOutOfBoundsException
      //   2454	2459	4782	java/io/IOException
      //   375	409	4817	java/net/SocketTimeoutException
      //   5023	5028	5072	java/lang/Exception
      //   5033	5038	5107	java/io/IOException
      //   5033	5038	5142	java/lang/ArrayIndexOutOfBoundsException
      //   5043	5048	5161	java/io/IOException
      //   375	409	5196	java/lang/Exception
      //   5406	5411	5455	java/lang/Exception
      //   5416	5421	5490	java/io/IOException
      //   5416	5421	5525	java/lang/ArrayIndexOutOfBoundsException
      //   5426	5431	5544	java/io/IOException
      //   375	409	5579	finally
      //   5654	5659	5697	java/lang/Exception
      //   5664	5669	5732	java/io/IOException
      //   5664	5669	5767	java/lang/ArrayIndexOutOfBoundsException
      //   5674	5679	5786	java/io/IOException
      //   425	436	5821	finally
      //   452	462	5821	finally
      //   478	488	5851	finally
      //   504	510	5851	finally
      //   526	534	5851	finally
      //   550	560	5851	finally
      //   576	593	5851	finally
      //   609	619	5851	finally
      //   635	653	5851	finally
      //   669	676	5851	finally
      //   692	698	5851	finally
      //   714	720	5851	finally
      //   736	742	5851	finally
      //   758	767	5851	finally
      //   783	792	5851	finally
      //   808	815	5851	finally
      //   831	842	5851	finally
      //   858	869	5851	finally
      //   885	916	5851	finally
      //   932	938	5851	finally
      //   959	976	5851	finally
      //   992	1006	5851	finally
      //   1022	1032	5851	finally
      //   1048	1060	5851	finally
      //   1076	1113	5851	finally
      //   1129	1145	5851	finally
      //   1161	1177	5851	finally
      //   1193	1215	5851	finally
      //   1231	1239	5851	finally
      //   1433	1458	5851	finally
      //   1729	1750	5851	finally
      //   1766	1773	5851	finally
      //   1789	1798	5851	finally
      //   1814	1823	5851	finally
      //   1844	1870	5851	finally
      //   1886	1900	5851	finally
      //   1916	1926	5851	finally
      //   1942	1954	5851	finally
      //   1970	1984	5851	finally
      //   2000	2022	5851	finally
      //   2038	2071	5851	finally
      //   2087	2117	5851	finally
      //   2133	2142	5851	finally
      //   2158	2167	5851	finally
      //   2183	2191	5851	finally
      //   2207	2216	5851	finally
      //   2499	2532	5851	finally
      //   2548	2595	5851	finally
      //   2611	2635	5851	finally
      //   2651	2660	5851	finally
      //   2676	2685	5851	finally
      //   2701	2746	5851	finally
      //   2762	2775	5851	finally
      //   2791	2804	5851	finally
      //   2829	2834	5851	finally
      //   2855	2860	5851	finally
      //   2876	2890	5851	finally
      //   2906	2926	5851	finally
      //   2942	2955	5851	finally
      //   2971	2985	5851	finally
      //   2985	3006	5886	finally
      //   3009	3018	5918	finally
      //   3024	3043	5918	finally
      //   3054	3064	5918	finally
      //   3145	3164	5918	finally
      //   3268	3278	5918	finally
      //   3361	3379	5918	finally
      //   3293	3358	5947	finally
      //   3386	3446	5976	finally
      //   3450	3482	5976	finally
      //   3633	3682	5976	finally
      //   3833	3850	5976	finally
      //   3850	3878	5976	finally
      //   3977	3984	5976	finally
      //   3989	4006	5976	finally
      //   4006	4034	5976	finally
      //   4039	4059	5976	finally
      //   4065	4072	5976	finally
      //   3883	3910	6003	finally
      //   3910	3917	6003	finally
      //   3922	3937	6003	finally
      //   4075	4095	6003	finally
      //   4095	4124	6027	finally
      //   4124	4164	6048	finally
      //   4264	4282	6048	finally
      //   1261	1315	6069	finally
      //   1502	1516	6106	finally
      //   1542	1572	6106	finally
      //   1598	1610	6106	finally
      //   2272	2286	6106	finally
      //   2312	2342	6106	finally
      //   2368	2380	6106	finally
      //   4861	4875	6106	finally
      //   4901	4931	6106	finally
      //   4957	4969	6106	finally
      //   5244	5258	6106	finally
      //   5284	5314	6106	finally
      //   5340	5352	6106	finally
      //   425	436	6134	java/lang/Exception
      //   452	462	6134	java/lang/Exception
      //   478	488	6134	java/lang/Exception
      //   504	510	6134	java/lang/Exception
      //   526	534	6134	java/lang/Exception
      //   550	560	6134	java/lang/Exception
      //   576	593	6134	java/lang/Exception
      //   609	619	6134	java/lang/Exception
      //   635	653	6134	java/lang/Exception
      //   669	676	6134	java/lang/Exception
      //   692	698	6134	java/lang/Exception
      //   714	720	6134	java/lang/Exception
      //   736	742	6134	java/lang/Exception
      //   758	767	6134	java/lang/Exception
      //   783	792	6134	java/lang/Exception
      //   808	815	6134	java/lang/Exception
      //   831	842	6134	java/lang/Exception
      //   858	869	6134	java/lang/Exception
      //   885	916	6134	java/lang/Exception
      //   932	938	6134	java/lang/Exception
      //   959	976	6134	java/lang/Exception
      //   992	1006	6134	java/lang/Exception
      //   1022	1032	6134	java/lang/Exception
      //   1048	1060	6134	java/lang/Exception
      //   1076	1113	6134	java/lang/Exception
      //   1129	1145	6134	java/lang/Exception
      //   1161	1177	6134	java/lang/Exception
      //   1193	1215	6134	java/lang/Exception
      //   1231	1239	6134	java/lang/Exception
      //   1433	1458	6134	java/lang/Exception
      //   1729	1750	6134	java/lang/Exception
      //   1766	1773	6134	java/lang/Exception
      //   1789	1798	6134	java/lang/Exception
      //   1814	1823	6134	java/lang/Exception
      //   1844	1870	6134	java/lang/Exception
      //   1886	1900	6134	java/lang/Exception
      //   1916	1926	6134	java/lang/Exception
      //   1942	1954	6134	java/lang/Exception
      //   1970	1984	6134	java/lang/Exception
      //   2000	2022	6134	java/lang/Exception
      //   2038	2071	6134	java/lang/Exception
      //   2087	2117	6134	java/lang/Exception
      //   2133	2142	6134	java/lang/Exception
      //   2158	2167	6134	java/lang/Exception
      //   2183	2191	6134	java/lang/Exception
      //   2207	2216	6134	java/lang/Exception
      //   2499	2532	6134	java/lang/Exception
      //   2548	2595	6134	java/lang/Exception
      //   2611	2635	6134	java/lang/Exception
      //   2651	2660	6134	java/lang/Exception
      //   2676	2685	6134	java/lang/Exception
      //   2701	2746	6134	java/lang/Exception
      //   2762	2775	6134	java/lang/Exception
      //   2791	2804	6134	java/lang/Exception
      //   2829	2834	6134	java/lang/Exception
      //   2855	2860	6134	java/lang/Exception
      //   2876	2890	6134	java/lang/Exception
      //   2906	2926	6134	java/lang/Exception
      //   2942	2955	6134	java/lang/Exception
      //   2971	2985	6134	java/lang/Exception
      //   2985	3006	6164	java/lang/Exception
      //   3009	3018	6191	java/lang/Exception
      //   3024	3043	6191	java/lang/Exception
      //   3054	3064	6191	java/lang/Exception
      //   3145	3164	6191	java/lang/Exception
      //   3268	3278	6191	java/lang/Exception
      //   3361	3379	6191	java/lang/Exception
      //   3293	3358	6218	java/lang/Exception
      //   3386	3446	6245	java/lang/Exception
      //   3450	3482	6245	java/lang/Exception
      //   3633	3682	6245	java/lang/Exception
      //   3833	3850	6245	java/lang/Exception
      //   3989	4006	6245	java/lang/Exception
      //   4039	4059	6245	java/lang/Exception
      //   3883	3910	6269	java/lang/Exception
      //   3910	3917	6269	java/lang/Exception
      //   3922	3937	6269	java/lang/Exception
      //   4075	4095	6269	java/lang/Exception
      //   4095	4124	6290	java/lang/Exception
      //   4124	4164	6310	java/lang/Exception
      //   4264	4282	6310	java/lang/Exception
      //   425	436	6330	java/net/SocketTimeoutException
      //   452	462	6330	java/net/SocketTimeoutException
      //   478	488	6330	java/net/SocketTimeoutException
      //   504	510	6330	java/net/SocketTimeoutException
      //   526	534	6330	java/net/SocketTimeoutException
      //   550	560	6330	java/net/SocketTimeoutException
      //   576	593	6330	java/net/SocketTimeoutException
      //   609	619	6330	java/net/SocketTimeoutException
      //   635	653	6330	java/net/SocketTimeoutException
      //   669	676	6330	java/net/SocketTimeoutException
      //   692	698	6330	java/net/SocketTimeoutException
      //   714	720	6330	java/net/SocketTimeoutException
      //   736	742	6330	java/net/SocketTimeoutException
      //   758	767	6330	java/net/SocketTimeoutException
      //   783	792	6330	java/net/SocketTimeoutException
      //   808	815	6330	java/net/SocketTimeoutException
      //   831	842	6330	java/net/SocketTimeoutException
      //   858	869	6330	java/net/SocketTimeoutException
      //   885	916	6330	java/net/SocketTimeoutException
      //   932	938	6330	java/net/SocketTimeoutException
      //   959	976	6330	java/net/SocketTimeoutException
      //   992	1006	6330	java/net/SocketTimeoutException
      //   1022	1032	6330	java/net/SocketTimeoutException
      //   1048	1060	6330	java/net/SocketTimeoutException
      //   1076	1113	6330	java/net/SocketTimeoutException
      //   1129	1145	6330	java/net/SocketTimeoutException
      //   1161	1177	6330	java/net/SocketTimeoutException
      //   1193	1215	6330	java/net/SocketTimeoutException
      //   1231	1239	6330	java/net/SocketTimeoutException
      //   1433	1458	6330	java/net/SocketTimeoutException
      //   1729	1750	6330	java/net/SocketTimeoutException
      //   1766	1773	6330	java/net/SocketTimeoutException
      //   1789	1798	6330	java/net/SocketTimeoutException
      //   1814	1823	6330	java/net/SocketTimeoutException
      //   1844	1870	6330	java/net/SocketTimeoutException
      //   1886	1900	6330	java/net/SocketTimeoutException
      //   1916	1926	6330	java/net/SocketTimeoutException
      //   1942	1954	6330	java/net/SocketTimeoutException
      //   1970	1984	6330	java/net/SocketTimeoutException
      //   2000	2022	6330	java/net/SocketTimeoutException
      //   2038	2071	6330	java/net/SocketTimeoutException
      //   2087	2117	6330	java/net/SocketTimeoutException
      //   2133	2142	6330	java/net/SocketTimeoutException
      //   2158	2167	6330	java/net/SocketTimeoutException
      //   2183	2191	6330	java/net/SocketTimeoutException
      //   2207	2216	6330	java/net/SocketTimeoutException
      //   2499	2532	6330	java/net/SocketTimeoutException
      //   2548	2595	6330	java/net/SocketTimeoutException
      //   2611	2635	6330	java/net/SocketTimeoutException
      //   2651	2660	6330	java/net/SocketTimeoutException
      //   2676	2685	6330	java/net/SocketTimeoutException
      //   2701	2746	6330	java/net/SocketTimeoutException
      //   2762	2775	6330	java/net/SocketTimeoutException
      //   2791	2804	6330	java/net/SocketTimeoutException
      //   2829	2834	6330	java/net/SocketTimeoutException
      //   2855	2860	6330	java/net/SocketTimeoutException
      //   2876	2890	6330	java/net/SocketTimeoutException
      //   2906	2926	6330	java/net/SocketTimeoutException
      //   2942	2955	6330	java/net/SocketTimeoutException
      //   2971	2985	6330	java/net/SocketTimeoutException
      //   2985	3006	6356	java/net/SocketTimeoutException
      //   3009	3018	6383	java/net/SocketTimeoutException
      //   3024	3043	6383	java/net/SocketTimeoutException
      //   3054	3064	6383	java/net/SocketTimeoutException
      //   3145	3164	6383	java/net/SocketTimeoutException
      //   3268	3278	6383	java/net/SocketTimeoutException
      //   3361	3379	6383	java/net/SocketTimeoutException
      //   3293	3358	6410	java/net/SocketTimeoutException
      //   3386	3446	6437	java/net/SocketTimeoutException
      //   3450	3482	6437	java/net/SocketTimeoutException
      //   3633	3682	6437	java/net/SocketTimeoutException
      //   3833	3850	6437	java/net/SocketTimeoutException
      //   3850	3878	6437	java/net/SocketTimeoutException
      //   3977	3984	6437	java/net/SocketTimeoutException
      //   3989	4006	6437	java/net/SocketTimeoutException
      //   4006	4034	6437	java/net/SocketTimeoutException
      //   4039	4059	6437	java/net/SocketTimeoutException
      //   4065	4072	6437	java/net/SocketTimeoutException
      //   3883	3910	6461	java/net/SocketTimeoutException
      //   3910	3917	6461	java/net/SocketTimeoutException
      //   3922	3937	6461	java/net/SocketTimeoutException
      //   4075	4095	6461	java/net/SocketTimeoutException
      //   4095	4124	6482	java/net/SocketTimeoutException
      //   4124	4164	6502	java/net/SocketTimeoutException
      //   4264	4282	6502	java/net/SocketTimeoutException
      //   375	409	6522	javax/net/ssl/SSLHandshakeException
      //   2985	3006	6547	javax/net/ssl/SSLHandshakeException
      //   3009	3018	6574	javax/net/ssl/SSLHandshakeException
      //   3024	3043	6574	javax/net/ssl/SSLHandshakeException
      //   3054	3064	6574	javax/net/ssl/SSLHandshakeException
      //   3145	3164	6574	javax/net/ssl/SSLHandshakeException
      //   3268	3278	6574	javax/net/ssl/SSLHandshakeException
      //   3361	3379	6574	javax/net/ssl/SSLHandshakeException
      //   3293	3358	6601	javax/net/ssl/SSLHandshakeException
      //   3386	3446	6628	javax/net/ssl/SSLHandshakeException
      //   3450	3482	6628	javax/net/ssl/SSLHandshakeException
      //   3633	3682	6628	javax/net/ssl/SSLHandshakeException
      //   3833	3850	6628	javax/net/ssl/SSLHandshakeException
      //   3850	3878	6628	javax/net/ssl/SSLHandshakeException
      //   3977	3984	6628	javax/net/ssl/SSLHandshakeException
      //   3989	4006	6628	javax/net/ssl/SSLHandshakeException
      //   4006	4034	6628	javax/net/ssl/SSLHandshakeException
      //   4039	4059	6628	javax/net/ssl/SSLHandshakeException
      //   4065	4072	6628	javax/net/ssl/SSLHandshakeException
      //   3883	3910	6652	javax/net/ssl/SSLHandshakeException
      //   3910	3917	6652	javax/net/ssl/SSLHandshakeException
      //   3922	3937	6652	javax/net/ssl/SSLHandshakeException
      //   4075	4095	6652	javax/net/ssl/SSLHandshakeException
      //   4095	4124	6673	javax/net/ssl/SSLHandshakeException
      //   4124	4164	6693	javax/net/ssl/SSLHandshakeException
      //   4264	4282	6693	javax/net/ssl/SSLHandshakeException
      //   375	409	6713	java/io/FileNotFoundException
      //   2985	3006	6738	java/io/FileNotFoundException
      //   3009	3018	6761	java/io/FileNotFoundException
      //   3024	3043	6761	java/io/FileNotFoundException
      //   3054	3064	6761	java/io/FileNotFoundException
      //   3145	3164	6761	java/io/FileNotFoundException
      //   3268	3278	6761	java/io/FileNotFoundException
      //   3361	3379	6761	java/io/FileNotFoundException
      //   3293	3358	6784	java/io/FileNotFoundException
      //   3386	3446	6807	java/io/FileNotFoundException
      //   3450	3482	6807	java/io/FileNotFoundException
      //   3633	3682	6807	java/io/FileNotFoundException
      //   3833	3850	6807	java/io/FileNotFoundException
      //   3850	3878	6807	java/io/FileNotFoundException
      //   3977	3984	6807	java/io/FileNotFoundException
      //   3989	4006	6807	java/io/FileNotFoundException
      //   4006	4034	6807	java/io/FileNotFoundException
      //   4039	4059	6807	java/io/FileNotFoundException
      //   4065	4072	6807	java/io/FileNotFoundException
      //   3883	3910	6827	java/io/FileNotFoundException
      //   3910	3917	6827	java/io/FileNotFoundException
      //   3922	3937	6827	java/io/FileNotFoundException
      //   4075	4095	6827	java/io/FileNotFoundException
      //   4095	4124	6844	java/io/FileNotFoundException
      //   4124	4164	6864	java/io/FileNotFoundException
      //   4264	4282	6864	java/io/FileNotFoundException
      //   375	409	6884	java/io/UnsupportedEncodingException
      //   425	436	6904	java/io/UnsupportedEncodingException
      //   452	462	6904	java/io/UnsupportedEncodingException
      //   2985	3006	6925	java/io/UnsupportedEncodingException
      //   3009	3018	6951	java/io/UnsupportedEncodingException
      //   3024	3043	6951	java/io/UnsupportedEncodingException
      //   3054	3064	6951	java/io/UnsupportedEncodingException
      //   3145	3164	6951	java/io/UnsupportedEncodingException
      //   3268	3278	6951	java/io/UnsupportedEncodingException
      //   3361	3379	6951	java/io/UnsupportedEncodingException
      //   3293	3358	6977	java/io/UnsupportedEncodingException
      //   3386	3446	7003	java/io/UnsupportedEncodingException
      //   3450	3482	7003	java/io/UnsupportedEncodingException
      //   3633	3682	7003	java/io/UnsupportedEncodingException
      //   3833	3850	7003	java/io/UnsupportedEncodingException
      //   3850	3878	7003	java/io/UnsupportedEncodingException
      //   3977	3984	7003	java/io/UnsupportedEncodingException
      //   3989	4006	7003	java/io/UnsupportedEncodingException
      //   4006	4034	7003	java/io/UnsupportedEncodingException
      //   4039	4059	7003	java/io/UnsupportedEncodingException
      //   4065	4072	7003	java/io/UnsupportedEncodingException
      //   4095	4124	7031	java/io/UnsupportedEncodingException
      //   4124	4164	7072	java/io/UnsupportedEncodingException
      //   4264	4282	7072	java/io/UnsupportedEncodingException
    }
    
    public final void run()
    {
      GMTrace.i(10676483391488L, 79546);
      b(this.itm);
      GMTrace.o(10676483391488L, 79546);
    }
  }
}


/* Location:              D:\tools\apktool\weixin6519android1140\jar\classes2-dex2jar.jar!\com\tencent\mm\plugin\appbrand\h\f.class
 * Java compiler version: 6 (50.0)
 * JD-Core Version:       0.7.1
 */