package com.tencent.mm.opensdk.diffdev.a;

import android.os.AsyncTask;
import android.os.Environment;
import com.tencent.gmtrace.GMTrace;
import com.tencent.mm.opensdk.diffdev.OAuthErrCode;
import com.tencent.mm.opensdk.diffdev.OAuthListener;
import com.tencent.mm.opensdk.utils.Log;
import java.io.File;

public final class d
  extends AsyncTask<Void, Void, a>
{
  private static final boolean h;
  private static final String i;
  private static String j;
  private String appId;
  private String k;
  private String l;
  private OAuthListener m;
  private f n;
  private String scope;
  private String signature;
  
  static
  {
    GMTrace.i(6576668672L, 49);
    if ((Environment.getExternalStorageState().equals("mounted")) && (new File(Environment.getExternalStorageDirectory().getAbsolutePath()).canWrite())) {}
    for (boolean bool = true;; bool = false)
    {
      h = bool;
      i = Environment.getExternalStorageDirectory().getAbsolutePath() + "/tencent/MicroMsg/oauth_qrcode.png";
      j = null;
      j = "http://open.weixin.qq.com/connect/sdk/qrconnect?appid=%s&noncestr=%s&timestamp=%s&scope=%s&signature=%s";
      GMTrace.o(6576668672L, 49);
      return;
    }
  }
  
  public d(String paramString1, String paramString2, String paramString3, String paramString4, String paramString5, OAuthListener paramOAuthListener)
  {
    GMTrace.i(5771362304L, 43);
    this.appId = paramString1;
    this.scope = paramString2;
    this.k = paramString3;
    this.l = paramString4;
    this.signature = paramString5;
    this.m = paramOAuthListener;
    GMTrace.o(5771362304L, 43);
  }
  
  public final boolean a()
  {
    GMTrace.i(5905580032L, 44);
    Log.i("MicroMsg.SDK.GetQRCodeTask", "cancelTask");
    if (this.n == null)
    {
      bool = cancel(true);
      GMTrace.o(5905580032L, 44);
      return bool;
    }
    boolean bool = this.n.cancel(true);
    GMTrace.o(5905580032L, 44);
    return bool;
  }
  
  static final class a
  {
    public OAuthErrCode o;
    public String p;
    public String q;
    public String r;
    public int s;
    public String t;
    public byte[] u;
    
    private a()
    {
      GMTrace.i(5368709120L, 40);
      GMTrace.o(5368709120L, 40);
    }
    
    /* Error */
    public static a a(byte[] paramArrayOfByte)
    {
      // Byte code:
      //   0: ldc2_w 37
      //   3: bipush 41
      //   5: invokestatic 30	com/tencent/gmtrace/GMTrace:i	(JI)V
      //   8: new 2	com/tencent/mm/opensdk/diffdev/a/d$a
      //   11: dup
      //   12: invokespecial 39	com/tencent/mm/opensdk/diffdev/a/d$a:<init>	()V
      //   15: astore_2
      //   16: aload_0
      //   17: ifnull +8 -> 25
      //   20: aload_0
      //   21: arraylength
      //   22: ifne +27 -> 49
      //   25: ldc 41
      //   27: ldc 43
      //   29: invokestatic 49	com/tencent/mm/opensdk/utils/Log:e	(Ljava/lang/String;Ljava/lang/String;)V
      //   32: aload_2
      //   33: getstatic 54	com/tencent/mm/opensdk/diffdev/OAuthErrCode:WechatAuth_Err_NetworkErr	Lcom/tencent/mm/opensdk/diffdev/OAuthErrCode;
      //   36: putfield 56	com/tencent/mm/opensdk/diffdev/a/d$a:o	Lcom/tencent/mm/opensdk/diffdev/OAuthErrCode;
      //   39: ldc2_w 37
      //   42: bipush 41
      //   44: invokestatic 32	com/tencent/gmtrace/GMTrace:o	(JI)V
      //   47: aload_2
      //   48: areturn
      //   49: new 58	java/lang/String
      //   52: dup
      //   53: aload_0
      //   54: ldc 60
      //   56: invokespecial 63	java/lang/String:<init>	([BLjava/lang/String;)V
      //   59: astore_0
      //   60: new 65	org/json/JSONObject
      //   63: dup
      //   64: aload_0
      //   65: invokespecial 68	org/json/JSONObject:<init>	(Ljava/lang/String;)V
      //   68: astore_0
      //   69: aload_0
      //   70: ldc 70
      //   72: invokevirtual 74	org/json/JSONObject:getInt	(Ljava/lang/String;)I
      //   75: istore_1
      //   76: iload_1
      //   77: ifeq +95 -> 172
      //   80: ldc 41
      //   82: ldc 76
      //   84: iconst_1
      //   85: anewarray 4	java/lang/Object
      //   88: dup
      //   89: iconst_0
      //   90: iload_1
      //   91: invokestatic 82	java/lang/Integer:valueOf	(I)Ljava/lang/Integer;
      //   94: aastore
      //   95: invokestatic 86	java/lang/String:format	(Ljava/lang/String;[Ljava/lang/Object;)Ljava/lang/String;
      //   98: invokestatic 49	com/tencent/mm/opensdk/utils/Log:e	(Ljava/lang/String;Ljava/lang/String;)V
      //   101: aload_2
      //   102: getstatic 89	com/tencent/mm/opensdk/diffdev/OAuthErrCode:WechatAuth_Err_NormalErr	Lcom/tencent/mm/opensdk/diffdev/OAuthErrCode;
      //   105: putfield 56	com/tencent/mm/opensdk/diffdev/a/d$a:o	Lcom/tencent/mm/opensdk/diffdev/OAuthErrCode;
      //   108: aload_2
      //   109: iload_1
      //   110: putfield 91	com/tencent/mm/opensdk/diffdev/a/d$a:s	I
      //   113: aload_2
      //   114: aload_0
      //   115: ldc 93
      //   117: invokevirtual 97	org/json/JSONObject:optString	(Ljava/lang/String;)Ljava/lang/String;
      //   120: putfield 99	com/tencent/mm/opensdk/diffdev/a/d$a:t	Ljava/lang/String;
      //   123: ldc2_w 37
      //   126: bipush 41
      //   128: invokestatic 32	com/tencent/gmtrace/GMTrace:o	(JI)V
      //   131: aload_2
      //   132: areturn
      //   133: astore_0
      //   134: ldc 41
      //   136: ldc 101
      //   138: iconst_1
      //   139: anewarray 4	java/lang/Object
      //   142: dup
      //   143: iconst_0
      //   144: aload_0
      //   145: invokevirtual 105	java/lang/Exception:getMessage	()Ljava/lang/String;
      //   148: aastore
      //   149: invokestatic 86	java/lang/String:format	(Ljava/lang/String;[Ljava/lang/Object;)Ljava/lang/String;
      //   152: invokestatic 49	com/tencent/mm/opensdk/utils/Log:e	(Ljava/lang/String;Ljava/lang/String;)V
      //   155: aload_2
      //   156: getstatic 89	com/tencent/mm/opensdk/diffdev/OAuthErrCode:WechatAuth_Err_NormalErr	Lcom/tencent/mm/opensdk/diffdev/OAuthErrCode;
      //   159: putfield 56	com/tencent/mm/opensdk/diffdev/a/d$a:o	Lcom/tencent/mm/opensdk/diffdev/OAuthErrCode;
      //   162: ldc2_w 37
      //   165: bipush 41
      //   167: invokestatic 32	com/tencent/gmtrace/GMTrace:o	(JI)V
      //   170: aload_2
      //   171: areturn
      //   172: aload_0
      //   173: ldc 107
      //   175: invokevirtual 111	org/json/JSONObject:getJSONObject	(Ljava/lang/String;)Lorg/json/JSONObject;
      //   178: ldc 113
      //   180: invokevirtual 116	org/json/JSONObject:getString	(Ljava/lang/String;)Ljava/lang/String;
      //   183: astore_3
      //   184: aload_3
      //   185: ifnull +10 -> 195
      //   188: aload_3
      //   189: invokevirtual 120	java/lang/String:length	()I
      //   192: ifne +27 -> 219
      //   195: ldc 41
      //   197: ldc 122
      //   199: invokestatic 49	com/tencent/mm/opensdk/utils/Log:e	(Ljava/lang/String;Ljava/lang/String;)V
      //   202: aload_2
      //   203: getstatic 125	com/tencent/mm/opensdk/diffdev/OAuthErrCode:WechatAuth_Err_JsonDecodeErr	Lcom/tencent/mm/opensdk/diffdev/OAuthErrCode;
      //   206: putfield 56	com/tencent/mm/opensdk/diffdev/a/d$a:o	Lcom/tencent/mm/opensdk/diffdev/OAuthErrCode;
      //   209: ldc2_w 37
      //   212: bipush 41
      //   214: invokestatic 32	com/tencent/gmtrace/GMTrace:o	(JI)V
      //   217: aload_2
      //   218: areturn
      //   219: aload_3
      //   220: iconst_0
      //   221: invokestatic 131	android/util/Base64:decode	(Ljava/lang/String;I)[B
      //   224: astore_3
      //   225: aload_3
      //   226: ifnull +8 -> 234
      //   229: aload_3
      //   230: arraylength
      //   231: ifne +27 -> 258
      //   234: ldc 41
      //   236: ldc -123
      //   238: invokestatic 49	com/tencent/mm/opensdk/utils/Log:e	(Ljava/lang/String;Ljava/lang/String;)V
      //   241: aload_2
      //   242: getstatic 125	com/tencent/mm/opensdk/diffdev/OAuthErrCode:WechatAuth_Err_JsonDecodeErr	Lcom/tencent/mm/opensdk/diffdev/OAuthErrCode;
      //   245: putfield 56	com/tencent/mm/opensdk/diffdev/a/d$a:o	Lcom/tencent/mm/opensdk/diffdev/OAuthErrCode;
      //   248: ldc2_w 37
      //   251: bipush 41
      //   253: invokestatic 32	com/tencent/gmtrace/GMTrace:o	(JI)V
      //   256: aload_2
      //   257: areturn
      //   258: invokestatic 137	com/tencent/mm/opensdk/diffdev/a/d:b	()Z
      //   261: ifeq +163 -> 424
      //   264: new 139	java/io/File
      //   267: dup
      //   268: invokestatic 142	com/tencent/mm/opensdk/diffdev/a/d:c	()Ljava/lang/String;
      //   271: invokespecial 143	java/io/File:<init>	(Ljava/lang/String;)V
      //   274: astore 4
      //   276: aload 4
      //   278: invokevirtual 146	java/io/File:mkdirs	()Z
      //   281: pop
      //   282: aload 4
      //   284: invokevirtual 149	java/io/File:exists	()Z
      //   287: ifeq +9 -> 296
      //   290: aload 4
      //   292: invokevirtual 152	java/io/File:delete	()Z
      //   295: pop
      //   296: invokestatic 142	com/tencent/mm/opensdk/diffdev/a/d:c	()Ljava/lang/String;
      //   299: aload_3
      //   300: invokestatic 155	com/tencent/mm/opensdk/diffdev/a/d$a:a	(Ljava/lang/String;[B)Z
      //   303: ifne +42 -> 345
      //   306: ldc 41
      //   308: ldc -99
      //   310: iconst_1
      //   311: anewarray 4	java/lang/Object
      //   314: dup
      //   315: iconst_0
      //   316: aload_3
      //   317: arraylength
      //   318: invokestatic 82	java/lang/Integer:valueOf	(I)Ljava/lang/Integer;
      //   321: aastore
      //   322: invokestatic 86	java/lang/String:format	(Ljava/lang/String;[Ljava/lang/Object;)Ljava/lang/String;
      //   325: invokestatic 49	com/tencent/mm/opensdk/utils/Log:e	(Ljava/lang/String;Ljava/lang/String;)V
      //   328: aload_2
      //   329: getstatic 89	com/tencent/mm/opensdk/diffdev/OAuthErrCode:WechatAuth_Err_NormalErr	Lcom/tencent/mm/opensdk/diffdev/OAuthErrCode;
      //   332: putfield 56	com/tencent/mm/opensdk/diffdev/a/d$a:o	Lcom/tencent/mm/opensdk/diffdev/OAuthErrCode;
      //   335: ldc2_w 37
      //   338: bipush 41
      //   340: invokestatic 32	com/tencent/gmtrace/GMTrace:o	(JI)V
      //   343: aload_2
      //   344: areturn
      //   345: aload_2
      //   346: getstatic 160	com/tencent/mm/opensdk/diffdev/OAuthErrCode:WechatAuth_Err_OK	Lcom/tencent/mm/opensdk/diffdev/OAuthErrCode;
      //   349: putfield 56	com/tencent/mm/opensdk/diffdev/a/d$a:o	Lcom/tencent/mm/opensdk/diffdev/OAuthErrCode;
      //   352: aload_2
      //   353: invokestatic 142	com/tencent/mm/opensdk/diffdev/a/d:c	()Ljava/lang/String;
      //   356: putfield 162	com/tencent/mm/opensdk/diffdev/a/d$a:r	Ljava/lang/String;
      //   359: aload_2
      //   360: aload_0
      //   361: ldc -92
      //   363: invokevirtual 116	org/json/JSONObject:getString	(Ljava/lang/String;)Ljava/lang/String;
      //   366: putfield 166	com/tencent/mm/opensdk/diffdev/a/d$a:p	Ljava/lang/String;
      //   369: aload_2
      //   370: aload_0
      //   371: ldc -88
      //   373: invokevirtual 116	org/json/JSONObject:getString	(Ljava/lang/String;)Ljava/lang/String;
      //   376: putfield 170	com/tencent/mm/opensdk/diffdev/a/d$a:q	Ljava/lang/String;
      //   379: ldc 41
      //   381: ldc -84
      //   383: iconst_3
      //   384: anewarray 4	java/lang/Object
      //   387: dup
      //   388: iconst_0
      //   389: aload_2
      //   390: getfield 166	com/tencent/mm/opensdk/diffdev/a/d$a:p	Ljava/lang/String;
      //   393: aastore
      //   394: dup
      //   395: iconst_1
      //   396: aload_2
      //   397: getfield 170	com/tencent/mm/opensdk/diffdev/a/d$a:q	Ljava/lang/String;
      //   400: aastore
      //   401: dup
      //   402: iconst_2
      //   403: aload_2
      //   404: getfield 162	com/tencent/mm/opensdk/diffdev/a/d$a:r	Ljava/lang/String;
      //   407: aastore
      //   408: invokestatic 86	java/lang/String:format	(Ljava/lang/String;[Ljava/lang/Object;)Ljava/lang/String;
      //   411: invokestatic 175	com/tencent/mm/opensdk/utils/Log:d	(Ljava/lang/String;Ljava/lang/String;)V
      //   414: ldc2_w 37
      //   417: bipush 41
      //   419: invokestatic 32	com/tencent/gmtrace/GMTrace:o	(JI)V
      //   422: aload_2
      //   423: areturn
      //   424: aload_2
      //   425: getstatic 160	com/tencent/mm/opensdk/diffdev/OAuthErrCode:WechatAuth_Err_OK	Lcom/tencent/mm/opensdk/diffdev/OAuthErrCode;
      //   428: putfield 56	com/tencent/mm/opensdk/diffdev/a/d$a:o	Lcom/tencent/mm/opensdk/diffdev/OAuthErrCode;
      //   431: aload_2
      //   432: aload_3
      //   433: putfield 177	com/tencent/mm/opensdk/diffdev/a/d$a:u	[B
      //   436: aload_2
      //   437: aload_0
      //   438: ldc -92
      //   440: invokevirtual 116	org/json/JSONObject:getString	(Ljava/lang/String;)Ljava/lang/String;
      //   443: putfield 166	com/tencent/mm/opensdk/diffdev/a/d$a:p	Ljava/lang/String;
      //   446: aload_2
      //   447: aload_0
      //   448: ldc -88
      //   450: invokevirtual 116	org/json/JSONObject:getString	(Ljava/lang/String;)Ljava/lang/String;
      //   453: putfield 170	com/tencent/mm/opensdk/diffdev/a/d$a:q	Ljava/lang/String;
      //   456: ldc 41
      //   458: ldc -77
      //   460: iconst_3
      //   461: anewarray 4	java/lang/Object
      //   464: dup
      //   465: iconst_0
      //   466: aload_2
      //   467: getfield 166	com/tencent/mm/opensdk/diffdev/a/d$a:p	Ljava/lang/String;
      //   470: aastore
      //   471: dup
      //   472: iconst_1
      //   473: aload_2
      //   474: getfield 170	com/tencent/mm/opensdk/diffdev/a/d$a:q	Ljava/lang/String;
      //   477: aastore
      //   478: dup
      //   479: iconst_2
      //   480: aload_2
      //   481: getfield 177	com/tencent/mm/opensdk/diffdev/a/d$a:u	[B
      //   484: arraylength
      //   485: invokestatic 82	java/lang/Integer:valueOf	(I)Ljava/lang/Integer;
      //   488: aastore
      //   489: invokestatic 86	java/lang/String:format	(Ljava/lang/String;[Ljava/lang/Object;)Ljava/lang/String;
      //   492: invokestatic 175	com/tencent/mm/opensdk/utils/Log:d	(Ljava/lang/String;Ljava/lang/String;)V
      //   495: ldc2_w 37
      //   498: bipush 41
      //   500: invokestatic 32	com/tencent/gmtrace/GMTrace:o	(JI)V
      //   503: aload_2
      //   504: areturn
      //   505: astore_0
      //   506: ldc 41
      //   508: ldc -75
      //   510: iconst_1
      //   511: anewarray 4	java/lang/Object
      //   514: dup
      //   515: iconst_0
      //   516: aload_0
      //   517: invokevirtual 105	java/lang/Exception:getMessage	()Ljava/lang/String;
      //   520: aastore
      //   521: invokestatic 86	java/lang/String:format	(Ljava/lang/String;[Ljava/lang/Object;)Ljava/lang/String;
      //   524: invokestatic 49	com/tencent/mm/opensdk/utils/Log:e	(Ljava/lang/String;Ljava/lang/String;)V
      //   527: aload_2
      //   528: getstatic 89	com/tencent/mm/opensdk/diffdev/OAuthErrCode:WechatAuth_Err_NormalErr	Lcom/tencent/mm/opensdk/diffdev/OAuthErrCode;
      //   531: putfield 56	com/tencent/mm/opensdk/diffdev/a/d$a:o	Lcom/tencent/mm/opensdk/diffdev/OAuthErrCode;
      //   534: ldc2_w 37
      //   537: bipush 41
      //   539: invokestatic 32	com/tencent/gmtrace/GMTrace:o	(JI)V
      //   542: aload_2
      //   543: areturn
      // Local variable table:
      //   start	length	slot	name	signature
      //   0	544	0	paramArrayOfByte	byte[]
      //   75	35	1	i	int
      //   15	528	2	locala	a
      //   183	250	3	localObject	Object
      //   274	17	4	localFile	File
      // Exception table:
      //   from	to	target	type
      //   49	60	133	java/lang/Exception
      //   60	76	505	java/lang/Exception
      //   80	123	505	java/lang/Exception
      //   172	184	505	java/lang/Exception
      //   188	195	505	java/lang/Exception
      //   195	209	505	java/lang/Exception
      //   219	225	505	java/lang/Exception
      //   229	234	505	java/lang/Exception
      //   234	248	505	java/lang/Exception
      //   258	296	505	java/lang/Exception
      //   296	335	505	java/lang/Exception
      //   345	414	505	java/lang/Exception
      //   424	495	505	java/lang/Exception
    }
    
    /* Error */
    private static boolean a(String paramString, byte[] paramArrayOfByte)
    {
      // Byte code:
      //   0: ldc2_w 184
      //   3: bipush 42
      //   5: invokestatic 30	com/tencent/gmtrace/GMTrace:i	(JI)V
      //   8: new 187	java/io/FileOutputStream
      //   11: dup
      //   12: aload_0
      //   13: invokespecial 188	java/io/FileOutputStream:<init>	(Ljava/lang/String;)V
      //   16: astore_2
      //   17: aload_2
      //   18: astore_0
      //   19: aload_2
      //   20: aload_1
      //   21: invokevirtual 192	java/io/FileOutputStream:write	([B)V
      //   24: aload_2
      //   25: astore_0
      //   26: aload_2
      //   27: invokevirtual 195	java/io/FileOutputStream:flush	()V
      //   30: aload_2
      //   31: invokevirtual 198	java/io/FileOutputStream:close	()V
      //   34: ldc 41
      //   36: ldc -56
      //   38: invokestatic 175	com/tencent/mm/opensdk/utils/Log:d	(Ljava/lang/String;Ljava/lang/String;)V
      //   41: ldc2_w 184
      //   44: bipush 42
      //   46: invokestatic 32	com/tencent/gmtrace/GMTrace:o	(JI)V
      //   49: iconst_1
      //   50: ireturn
      //   51: astore_0
      //   52: ldc 41
      //   54: new 202	java/lang/StringBuilder
      //   57: dup
      //   58: ldc -52
      //   60: invokespecial 205	java/lang/StringBuilder:<init>	(Ljava/lang/String;)V
      //   63: aload_0
      //   64: invokevirtual 206	java/io/IOException:getMessage	()Ljava/lang/String;
      //   67: invokevirtual 210	java/lang/StringBuilder:append	(Ljava/lang/String;)Ljava/lang/StringBuilder;
      //   70: invokevirtual 213	java/lang/StringBuilder:toString	()Ljava/lang/String;
      //   73: invokestatic 49	com/tencent/mm/opensdk/utils/Log:e	(Ljava/lang/String;Ljava/lang/String;)V
      //   76: goto -42 -> 34
      //   79: astore_3
      //   80: aconst_null
      //   81: astore_1
      //   82: aload_1
      //   83: astore_0
      //   84: ldc 41
      //   86: new 202	java/lang/StringBuilder
      //   89: dup
      //   90: ldc -41
      //   92: invokespecial 205	java/lang/StringBuilder:<init>	(Ljava/lang/String;)V
      //   95: aload_3
      //   96: invokevirtual 105	java/lang/Exception:getMessage	()Ljava/lang/String;
      //   99: invokevirtual 210	java/lang/StringBuilder:append	(Ljava/lang/String;)Ljava/lang/StringBuilder;
      //   102: invokevirtual 213	java/lang/StringBuilder:toString	()Ljava/lang/String;
      //   105: invokestatic 218	com/tencent/mm/opensdk/utils/Log:w	(Ljava/lang/String;Ljava/lang/String;)V
      //   108: aload_1
      //   109: ifnull +7 -> 116
      //   112: aload_1
      //   113: invokevirtual 198	java/io/FileOutputStream:close	()V
      //   116: ldc2_w 184
      //   119: bipush 42
      //   121: invokestatic 32	com/tencent/gmtrace/GMTrace:o	(JI)V
      //   124: iconst_0
      //   125: ireturn
      //   126: astore_0
      //   127: ldc 41
      //   129: new 202	java/lang/StringBuilder
      //   132: dup
      //   133: ldc -52
      //   135: invokespecial 205	java/lang/StringBuilder:<init>	(Ljava/lang/String;)V
      //   138: aload_0
      //   139: invokevirtual 206	java/io/IOException:getMessage	()Ljava/lang/String;
      //   142: invokevirtual 210	java/lang/StringBuilder:append	(Ljava/lang/String;)Ljava/lang/StringBuilder;
      //   145: invokevirtual 213	java/lang/StringBuilder:toString	()Ljava/lang/String;
      //   148: invokestatic 49	com/tencent/mm/opensdk/utils/Log:e	(Ljava/lang/String;Ljava/lang/String;)V
      //   151: goto -35 -> 116
      //   154: astore_1
      //   155: aconst_null
      //   156: astore_0
      //   157: aload_0
      //   158: ifnull +7 -> 165
      //   161: aload_0
      //   162: invokevirtual 198	java/io/FileOutputStream:close	()V
      //   165: aload_1
      //   166: athrow
      //   167: astore_0
      //   168: ldc 41
      //   170: new 202	java/lang/StringBuilder
      //   173: dup
      //   174: ldc -52
      //   176: invokespecial 205	java/lang/StringBuilder:<init>	(Ljava/lang/String;)V
      //   179: aload_0
      //   180: invokevirtual 206	java/io/IOException:getMessage	()Ljava/lang/String;
      //   183: invokevirtual 210	java/lang/StringBuilder:append	(Ljava/lang/String;)Ljava/lang/StringBuilder;
      //   186: invokevirtual 213	java/lang/StringBuilder:toString	()Ljava/lang/String;
      //   189: invokestatic 49	com/tencent/mm/opensdk/utils/Log:e	(Ljava/lang/String;Ljava/lang/String;)V
      //   192: goto -27 -> 165
      //   195: astore_1
      //   196: goto -39 -> 157
      //   199: astore_3
      //   200: aload_2
      //   201: astore_1
      //   202: goto -120 -> 82
      // Local variable table:
      //   start	length	slot	name	signature
      //   0	205	0	paramString	String
      //   0	205	1	paramArrayOfByte	byte[]
      //   16	185	2	localFileOutputStream	java.io.FileOutputStream
      //   79	17	3	localException1	Exception
      //   199	1	3	localException2	Exception
      // Exception table:
      //   from	to	target	type
      //   30	34	51	java/io/IOException
      //   8	17	79	java/lang/Exception
      //   112	116	126	java/io/IOException
      //   8	17	154	finally
      //   161	165	167	java/io/IOException
      //   19	24	195	finally
      //   26	30	195	finally
      //   84	108	195	finally
      //   19	24	199	java/lang/Exception
      //   26	30	199	java/lang/Exception
    }
  }
}


/* Location:              D:\tools\apktool\weixin6519android1140\jar\classes3-dex2jar.jar!\com\tencent\mm\opensdk\diffdev\a\d.class
 * Java compiler version: 6 (50.0)
 * JD-Core Version:       0.7.1
 */