package com.tencent.mm.plugin.wenote.a;

import com.tencent.gmtrace.GMTrace;
import com.tencent.mm.g.a.kl;
import com.tencent.mm.sdk.b.c;

public final class a
  extends c<kl>
{
  public a()
  {
    GMTrace.i(5663988121600L, 42200);
    this.vhf = kl.class.getName().hashCode();
    GMTrace.o(5663988121600L, 42200);
  }
  
  /* Error */
  private static boolean a(kl paramkl)
  {
    // Byte code:
    //   0: ldc2_w 45
    //   3: ldc 47
    //   5: invokestatic 18	com/tencent/gmtrace/GMTrace:i	(JI)V
    //   8: aload_0
    //   9: getfield 51	com/tencent/mm/g/a/kl:eOD	Lcom/tencent/mm/g/a/kl$a;
    //   12: getfield 56	com/tencent/mm/g/a/kl$a:field_status	I
    //   15: iconst_3
    //   16: if_icmpeq +14 -> 30
    //   19: aload_0
    //   20: getfield 51	com/tencent/mm/g/a/kl:eOD	Lcom/tencent/mm/g/a/kl$a;
    //   23: getfield 56	com/tencent/mm/g/a/kl$a:field_status	I
    //   26: iconst_2
    //   27: if_icmpne +48 -> 75
    //   30: aload_0
    //   31: getfield 51	com/tencent/mm/g/a/kl:eOD	Lcom/tencent/mm/g/a/kl$a;
    //   34: getfield 60	com/tencent/mm/g/a/kl$a:field_path	Ljava/lang/String;
    //   37: invokestatic 66	com/tencent/mm/a/e:aZ	(Ljava/lang/String;)Z
    //   40: ifeq +35 -> 75
    //   43: aload_0
    //   44: getfield 51	com/tencent/mm/g/a/kl:eOD	Lcom/tencent/mm/g/a/kl$a;
    //   47: getfield 60	com/tencent/mm/g/a/kl$a:field_path	Ljava/lang/String;
    //   50: ldc 68
    //   52: invokevirtual 71	java/lang/String:endsWith	(Ljava/lang/String;)Z
    //   55: ifeq +20 -> 75
    //   58: aload_0
    //   59: getfield 51	com/tencent/mm/g/a/kl:eOD	Lcom/tencent/mm/g/a/kl$a;
    //   62: getfield 75	com/tencent/mm/g/a/kl$a:field_favLocalId	J
    //   65: aload_0
    //   66: getfield 51	com/tencent/mm/g/a/kl:eOD	Lcom/tencent/mm/g/a/kl$a;
    //   69: getfield 60	com/tencent/mm/g/a/kl$a:field_path	Ljava/lang/String;
    //   72: invokestatic 81	com/tencent/mm/plugin/wenote/model/f:s	(JLjava/lang/String;)V
    //   75: invokestatic 87	com/tencent/mm/plugin/wenote/model/b:bGM	()Lcom/tencent/mm/plugin/wenote/model/b;
    //   78: getfield 91	com/tencent/mm/plugin/wenote/model/b:sbA	Lcom/tencent/mm/plugin/wenote/model/c;
    //   81: astore 4
    //   83: aload 4
    //   85: ifnonnull +13 -> 98
    //   88: ldc2_w 45
    //   91: ldc 47
    //   93: invokestatic 39	com/tencent/gmtrace/GMTrace:o	(JI)V
    //   96: iconst_0
    //   97: ireturn
    //   98: new 93	com/tencent/mm/plugin/wenote/model/d
    //   101: dup
    //   102: invokespecial 94	com/tencent/mm/plugin/wenote/model/d:<init>	()V
    //   105: astore 5
    //   107: aload 5
    //   109: aload_0
    //   110: getfield 51	com/tencent/mm/g/a/kl:eOD	Lcom/tencent/mm/g/a/kl$a;
    //   113: getfield 97	com/tencent/mm/g/a/kl$a:field_dataId	Ljava/lang/String;
    //   116: putfield 98	com/tencent/mm/plugin/wenote/model/d:field_dataId	Ljava/lang/String;
    //   119: aload 5
    //   121: aload_0
    //   122: getfield 51	com/tencent/mm/g/a/kl:eOD	Lcom/tencent/mm/g/a/kl$a;
    //   125: getfield 75	com/tencent/mm/g/a/kl$a:field_favLocalId	J
    //   128: putfield 99	com/tencent/mm/plugin/wenote/model/d:field_favLocalId	J
    //   131: aload 5
    //   133: aload_0
    //   134: getfield 51	com/tencent/mm/g/a/kl:eOD	Lcom/tencent/mm/g/a/kl$a;
    //   137: getfield 102	com/tencent/mm/g/a/kl$a:field_offset	I
    //   140: putfield 103	com/tencent/mm/plugin/wenote/model/d:field_offset	I
    //   143: aload 5
    //   145: aload_0
    //   146: getfield 51	com/tencent/mm/g/a/kl:eOD	Lcom/tencent/mm/g/a/kl$a;
    //   149: getfield 106	com/tencent/mm/g/a/kl$a:field_totalLen	I
    //   152: putfield 107	com/tencent/mm/plugin/wenote/model/d:field_totalLen	I
    //   155: aload 5
    //   157: aload_0
    //   158: getfield 51	com/tencent/mm/g/a/kl:eOD	Lcom/tencent/mm/g/a/kl$a;
    //   161: getfield 56	com/tencent/mm/g/a/kl$a:field_status	I
    //   164: putfield 108	com/tencent/mm/plugin/wenote/model/d:field_status	I
    //   167: aload 5
    //   169: aload_0
    //   170: getfield 51	com/tencent/mm/g/a/kl:eOD	Lcom/tencent/mm/g/a/kl$a;
    //   173: getfield 60	com/tencent/mm/g/a/kl$a:field_path	Ljava/lang/String;
    //   176: putfield 109	com/tencent/mm/plugin/wenote/model/d:field_path	Ljava/lang/String;
    //   179: aload 5
    //   181: aload_0
    //   182: getfield 51	com/tencent/mm/g/a/kl:eOD	Lcom/tencent/mm/g/a/kl$a;
    //   185: getfield 112	com/tencent/mm/g/a/kl$a:field_localId	I
    //   188: putfield 113	com/tencent/mm/plugin/wenote/model/d:field_localId	I
    //   191: aload 5
    //   193: getfield 108	com/tencent/mm/plugin/wenote/model/d:field_status	I
    //   196: iconst_3
    //   197: if_icmpeq +12 -> 209
    //   200: aload 5
    //   202: getfield 108	com/tencent/mm/plugin/wenote/model/d:field_status	I
    //   205: iconst_2
    //   206: if_icmpne +30 -> 236
    //   209: iconst_1
    //   210: istore_1
    //   211: iload_1
    //   212: ifeq +565 -> 777
    //   215: aload 5
    //   217: getfield 109	com/tencent/mm/plugin/wenote/model/d:field_path	Ljava/lang/String;
    //   220: invokestatic 66	com/tencent/mm/a/e:aZ	(Ljava/lang/String;)Z
    //   223: ifne +18 -> 241
    //   226: ldc2_w 45
    //   229: ldc 47
    //   231: invokestatic 39	com/tencent/gmtrace/GMTrace:o	(JI)V
    //   234: iconst_0
    //   235: ireturn
    //   236: iconst_0
    //   237: istore_1
    //   238: goto -27 -> 211
    //   241: aload 4
    //   243: getfield 119	com/tencent/mm/plugin/wenote/model/c:sbF	Ljava/util/HashMap;
    //   246: aload 5
    //   248: getfield 98	com/tencent/mm/plugin/wenote/model/d:field_dataId	Ljava/lang/String;
    //   251: invokevirtual 125	java/util/HashMap:get	(Ljava/lang/Object;)Ljava/lang/Object;
    //   254: checkcast 28	java/lang/String
    //   257: astore 6
    //   259: aload 6
    //   261: invokestatic 130	com/tencent/mm/sdk/platformtools/bg:nm	(Ljava/lang/String;)Z
    //   264: ifne +513 -> 777
    //   267: ldc -124
    //   269: ldc -122
    //   271: iconst_1
    //   272: anewarray 136	java/lang/Object
    //   275: dup
    //   276: iconst_0
    //   277: aload 6
    //   279: aastore
    //   280: invokestatic 142	com/tencent/mm/sdk/platformtools/w:d	(Ljava/lang/String;Ljava/lang/String;[Ljava/lang/Object;)V
    //   283: aload 5
    //   285: getfield 98	com/tencent/mm/plugin/wenote/model/d:field_dataId	Ljava/lang/String;
    //   288: ldc -112
    //   290: invokevirtual 71	java/lang/String:endsWith	(Ljava/lang/String;)Z
    //   293: ifeq +102 -> 395
    //   296: aload 4
    //   298: getfield 147	com/tencent/mm/plugin/wenote/model/c:sbG	Ljava/util/HashMap;
    //   301: aload 6
    //   303: invokevirtual 125	java/util/HashMap:get	(Ljava/lang/Object;)Ljava/lang/Object;
    //   306: ifnull +89 -> 395
    //   309: aload 4
    //   311: getfield 147	com/tencent/mm/plugin/wenote/model/c:sbG	Ljava/util/HashMap;
    //   314: aload 6
    //   316: invokevirtual 125	java/util/HashMap:get	(Ljava/lang/Object;)Ljava/lang/Object;
    //   319: checkcast 149	com/tencent/mm/plugin/wenote/model/a/n
    //   322: invokevirtual 152	com/tencent/mm/plugin/wenote/model/a/n:getType	()I
    //   325: iconst_2
    //   326: if_icmpne +24 -> 350
    //   329: aload 4
    //   331: getfield 147	com/tencent/mm/plugin/wenote/model/c:sbG	Ljava/util/HashMap;
    //   334: aload 6
    //   336: invokevirtual 125	java/util/HashMap:get	(Ljava/lang/Object;)Ljava/lang/Object;
    //   339: checkcast 149	com/tencent/mm/plugin/wenote/model/a/n
    //   342: aload 5
    //   344: getfield 109	com/tencent/mm/plugin/wenote/model/d:field_path	Ljava/lang/String;
    //   347: putfield 155	com/tencent/mm/plugin/wenote/model/a/n:eOR	Ljava/lang/String;
    //   350: invokestatic 161	com/tencent/mm/plugin/wenote/model/nativenote/manager/c:bHo	()Lcom/tencent/mm/plugin/wenote/model/nativenote/manager/c;
    //   353: aload 6
    //   355: aload 4
    //   357: getfield 147	com/tencent/mm/plugin/wenote/model/c:sbG	Ljava/util/HashMap;
    //   360: aload 6
    //   362: invokevirtual 125	java/util/HashMap:get	(Ljava/lang/Object;)Ljava/lang/Object;
    //   365: checkcast 163	com/tencent/mm/plugin/wenote/model/a/b
    //   368: invokevirtual 166	com/tencent/mm/plugin/wenote/model/nativenote/manager/c:a	(Ljava/lang/String;Lcom/tencent/mm/plugin/wenote/model/a/b;)V
    //   371: aload 4
    //   373: getfield 119	com/tencent/mm/plugin/wenote/model/c:sbF	Ljava/util/HashMap;
    //   376: aload 5
    //   378: getfield 98	com/tencent/mm/plugin/wenote/model/d:field_dataId	Ljava/lang/String;
    //   381: invokevirtual 169	java/util/HashMap:remove	(Ljava/lang/Object;)Ljava/lang/Object;
    //   384: pop
    //   385: ldc2_w 45
    //   388: ldc 47
    //   390: invokestatic 39	com/tencent/gmtrace/GMTrace:o	(JI)V
    //   393: iconst_0
    //   394: ireturn
    //   395: aload 6
    //   397: ldc -85
    //   399: invokevirtual 175	java/lang/String:equals	(Ljava/lang/Object;)Z
    //   402: ifne +670 -> 1072
    //   405: aload 4
    //   407: getfield 119	com/tencent/mm/plugin/wenote/model/c:sbF	Ljava/util/HashMap;
    //   410: ldc -85
    //   412: invokevirtual 178	java/util/HashMap:containsValue	(Ljava/lang/Object;)Z
    //   415: ifne +381 -> 796
    //   418: new 180	com/tencent/mm/g/a/kn
    //   421: dup
    //   422: invokespecial 181	com/tencent/mm/g/a/kn:<init>	()V
    //   425: astore_0
    //   426: aload_0
    //   427: getfield 185	com/tencent/mm/g/a/kn:eOO	Lcom/tencent/mm/g/a/kn$a;
    //   430: aload 6
    //   432: putfield 190	com/tencent/mm/g/a/kn$a:eOG	Ljava/lang/String;
    //   435: aload_0
    //   436: getfield 185	com/tencent/mm/g/a/kn:eOO	Lcom/tencent/mm/g/a/kn$a;
    //   439: aload 5
    //   441: getfield 109	com/tencent/mm/plugin/wenote/model/d:field_path	Ljava/lang/String;
    //   444: putfield 191	com/tencent/mm/g/a/kn$a:eOR	Ljava/lang/String;
    //   447: aload_0
    //   448: getfield 185	com/tencent/mm/g/a/kn:eOO	Lcom/tencent/mm/g/a/kn$a;
    //   451: iconst_1
    //   452: putfield 194	com/tencent/mm/g/a/kn$a:type	I
    //   455: aload_0
    //   456: getfield 185	com/tencent/mm/g/a/kn:eOO	Lcom/tencent/mm/g/a/kn$a;
    //   459: aload 4
    //   461: getfield 147	com/tencent/mm/plugin/wenote/model/c:sbG	Ljava/util/HashMap;
    //   464: aload 6
    //   466: invokevirtual 125	java/util/HashMap:get	(Ljava/lang/Object;)Ljava/lang/Object;
    //   469: checkcast 149	com/tencent/mm/plugin/wenote/model/a/n
    //   472: getfield 195	com/tencent/mm/plugin/wenote/model/a/n:type	I
    //   475: putfield 198	com/tencent/mm/g/a/kn$a:eOK	I
    //   478: getstatic 204	com/tencent/mm/pluginsdk/model/c:tmH	Z
    //   481: ifeq +84 -> 565
    //   484: aload_0
    //   485: getfield 185	com/tencent/mm/g/a/kn:eOO	Lcom/tencent/mm/g/a/kn$a;
    //   488: getfield 198	com/tencent/mm/g/a/kn$a:eOK	I
    //   491: iconst_4
    //   492: if_icmpeq +73 -> 565
    //   495: aload_0
    //   496: getfield 185	com/tencent/mm/g/a/kn:eOO	Lcom/tencent/mm/g/a/kn$a;
    //   499: getfield 198	com/tencent/mm/g/a/kn$a:eOK	I
    //   502: iconst_2
    //   503: if_icmpeq +83 -> 586
    //   506: aload 4
    //   508: getfield 147	com/tencent/mm/plugin/wenote/model/c:sbG	Ljava/util/HashMap;
    //   511: aload 6
    //   513: invokevirtual 125	java/util/HashMap:get	(Ljava/lang/Object;)Ljava/lang/Object;
    //   516: checkcast 149	com/tencent/mm/plugin/wenote/model/a/n
    //   519: aload 5
    //   521: getfield 109	com/tencent/mm/plugin/wenote/model/d:field_path	Ljava/lang/String;
    //   524: putfield 155	com/tencent/mm/plugin/wenote/model/a/n:eOR	Ljava/lang/String;
    //   527: aload 4
    //   529: getfield 147	com/tencent/mm/plugin/wenote/model/c:sbG	Ljava/util/HashMap;
    //   532: aload 6
    //   534: invokevirtual 125	java/util/HashMap:get	(Ljava/lang/Object;)Ljava/lang/Object;
    //   537: checkcast 149	com/tencent/mm/plugin/wenote/model/a/n
    //   540: iconst_1
    //   541: putfield 207	com/tencent/mm/plugin/wenote/model/a/n:sdf	Z
    //   544: invokestatic 161	com/tencent/mm/plugin/wenote/model/nativenote/manager/c:bHo	()Lcom/tencent/mm/plugin/wenote/model/nativenote/manager/c;
    //   547: aload 6
    //   549: aload 4
    //   551: getfield 147	com/tencent/mm/plugin/wenote/model/c:sbG	Ljava/util/HashMap;
    //   554: aload 6
    //   556: invokevirtual 125	java/util/HashMap:get	(Ljava/lang/Object;)Ljava/lang/Object;
    //   559: checkcast 163	com/tencent/mm/plugin/wenote/model/a/b
    //   562: invokevirtual 166	com/tencent/mm/plugin/wenote/model/nativenote/manager/c:a	(Ljava/lang/String;Lcom/tencent/mm/plugin/wenote/model/a/b;)V
    //   565: iconst_5
    //   566: aload_0
    //   567: getfield 185	com/tencent/mm/g/a/kn:eOO	Lcom/tencent/mm/g/a/kn$a;
    //   570: getfield 198	com/tencent/mm/g/a/kn$a:eOK	I
    //   573: if_icmpne +41 -> 614
    //   576: ldc2_w 45
    //   579: ldc 47
    //   581: invokestatic 39	com/tencent/gmtrace/GMTrace:o	(JI)V
    //   584: iconst_0
    //   585: ireturn
    //   586: aload 5
    //   588: getfield 109	com/tencent/mm/plugin/wenote/model/d:field_path	Ljava/lang/String;
    //   591: aload 4
    //   593: getfield 147	com/tencent/mm/plugin/wenote/model/c:sbG	Ljava/util/HashMap;
    //   596: aload 6
    //   598: invokevirtual 125	java/util/HashMap:get	(Ljava/lang/Object;)Ljava/lang/Object;
    //   601: checkcast 149	com/tencent/mm/plugin/wenote/model/a/n
    //   604: getfield 155	com/tencent/mm/plugin/wenote/model/a/n:eOR	Ljava/lang/String;
    //   607: invokestatic 213	com/tencent/mm/plugin/wenote/b/b:eA	(Ljava/lang/String;Ljava/lang/String;)Ljava/lang/String;
    //   610: pop
    //   611: goto -84 -> 527
    //   614: aload_0
    //   615: getfield 185	com/tencent/mm/g/a/kn:eOO	Lcom/tencent/mm/g/a/kn$a;
    //   618: getfield 198	com/tencent/mm/g/a/kn$a:eOK	I
    //   621: iconst_4
    //   622: if_icmpne +96 -> 718
    //   625: aload 4
    //   627: aload 5
    //   629: getfield 98	com/tencent/mm/plugin/wenote/model/d:field_dataId	Ljava/lang/String;
    //   632: invokevirtual 217	com/tencent/mm/plugin/wenote/model/c:Nz	(Ljava/lang/String;)Lcom/tencent/mm/protocal/c/th;
    //   635: astore 7
    //   637: iconst_0
    //   638: istore_1
    //   639: aload 7
    //   641: ifnonnull +146 -> 787
    //   644: ldc -124
    //   646: ldc -37
    //   648: invokestatic 223	com/tencent/mm/sdk/platformtools/w:e	(Ljava/lang/String;Ljava/lang/String;)V
    //   651: aload_0
    //   652: getfield 185	com/tencent/mm/g/a/kn:eOO	Lcom/tencent/mm/g/a/kn$a;
    //   655: iload_1
    //   656: putfield 226	com/tencent/mm/g/a/kn$a:eIw	I
    //   659: aload 4
    //   661: getfield 147	com/tencent/mm/plugin/wenote/model/c:sbG	Ljava/util/HashMap;
    //   664: aload 6
    //   666: invokevirtual 125	java/util/HashMap:get	(Ljava/lang/Object;)Ljava/lang/Object;
    //   669: checkcast 149	com/tencent/mm/plugin/wenote/model/a/n
    //   672: aload 5
    //   674: getfield 109	com/tencent/mm/plugin/wenote/model/d:field_path	Ljava/lang/String;
    //   677: putfield 155	com/tencent/mm/plugin/wenote/model/a/n:eOR	Ljava/lang/String;
    //   680: aload 4
    //   682: getfield 147	com/tencent/mm/plugin/wenote/model/c:sbG	Ljava/util/HashMap;
    //   685: aload 6
    //   687: invokevirtual 125	java/util/HashMap:get	(Ljava/lang/Object;)Ljava/lang/Object;
    //   690: checkcast 149	com/tencent/mm/plugin/wenote/model/a/n
    //   693: iconst_1
    //   694: putfield 207	com/tencent/mm/plugin/wenote/model/a/n:sdf	Z
    //   697: invokestatic 161	com/tencent/mm/plugin/wenote/model/nativenote/manager/c:bHo	()Lcom/tencent/mm/plugin/wenote/model/nativenote/manager/c;
    //   700: aload 6
    //   702: aload 4
    //   704: getfield 147	com/tencent/mm/plugin/wenote/model/c:sbG	Ljava/util/HashMap;
    //   707: aload 6
    //   709: invokevirtual 125	java/util/HashMap:get	(Ljava/lang/Object;)Ljava/lang/Object;
    //   712: checkcast 163	com/tencent/mm/plugin/wenote/model/a/b
    //   715: invokevirtual 166	com/tencent/mm/plugin/wenote/model/nativenote/manager/c:a	(Ljava/lang/String;Lcom/tencent/mm/plugin/wenote/model/a/b;)V
    //   718: ldc -124
    //   720: ldc -28
    //   722: iconst_2
    //   723: anewarray 136	java/lang/Object
    //   726: dup
    //   727: iconst_0
    //   728: aload_0
    //   729: getfield 185	com/tencent/mm/g/a/kn:eOO	Lcom/tencent/mm/g/a/kn$a;
    //   732: getfield 190	com/tencent/mm/g/a/kn$a:eOG	Ljava/lang/String;
    //   735: aastore
    //   736: dup
    //   737: iconst_1
    //   738: aload_0
    //   739: getfield 185	com/tencent/mm/g/a/kn:eOO	Lcom/tencent/mm/g/a/kn$a;
    //   742: getfield 191	com/tencent/mm/g/a/kn$a:eOR	Ljava/lang/String;
    //   745: aastore
    //   746: invokestatic 230	com/tencent/mm/sdk/platformtools/w:i	(Ljava/lang/String;Ljava/lang/String;[Ljava/lang/Object;)V
    //   749: getstatic 204	com/tencent/mm/pluginsdk/model/c:tmH	Z
    //   752: ifne +11 -> 763
    //   755: getstatic 236	com/tencent/mm/sdk/b/a:vgX	Lcom/tencent/mm/sdk/b/a;
    //   758: aload_0
    //   759: invokevirtual 240	com/tencent/mm/sdk/b/a:m	(Lcom/tencent/mm/sdk/b/b;)Z
    //   762: pop
    //   763: aload 4
    //   765: getfield 119	com/tencent/mm/plugin/wenote/model/c:sbF	Ljava/util/HashMap;
    //   768: aload 5
    //   770: getfield 98	com/tencent/mm/plugin/wenote/model/d:field_dataId	Ljava/lang/String;
    //   773: invokevirtual 169	java/util/HashMap:remove	(Ljava/lang/Object;)Ljava/lang/Object;
    //   776: pop
    //   777: ldc2_w 45
    //   780: ldc 47
    //   782: invokestatic 39	com/tencent/gmtrace/GMTrace:o	(JI)V
    //   785: iconst_0
    //   786: ireturn
    //   787: aload 7
    //   789: getfield 245	com/tencent/mm/protocal/c/th:duration	I
    //   792: istore_1
    //   793: goto -142 -> 651
    //   796: aload 4
    //   798: getfield 249	com/tencent/mm/plugin/wenote/model/c:sbC	Lcom/tencent/mm/plugin/wenote/model/a/l;
    //   801: getfield 254	com/tencent/mm/plugin/wenote/model/a/l:eOS	J
    //   804: ldc2_w 255
    //   807: lcmp
    //   808: ifne +47 -> 855
    //   811: aload 4
    //   813: getfield 259	com/tencent/mm/plugin/wenote/model/c:sbE	Ljava/util/HashMap;
    //   816: aload 4
    //   818: getfield 249	com/tencent/mm/plugin/wenote/model/c:sbC	Lcom/tencent/mm/plugin/wenote/model/a/l;
    //   821: getfield 262	com/tencent/mm/plugin/wenote/model/a/l:eDr	J
    //   824: invokestatic 268	java/lang/Long:toString	(J)Ljava/lang/String;
    //   827: invokevirtual 125	java/util/HashMap:get	(Ljava/lang/Object;)Ljava/lang/Object;
    //   830: checkcast 270	com/tencent/mm/plugin/wenote/model/a/v
    //   833: astore_0
    //   834: aload_0
    //   835: ifnull +10 -> 845
    //   838: aload_0
    //   839: getfield 274	com/tencent/mm/plugin/wenote/model/a/v:sdx	Ljava/util/ArrayList;
    //   842: ifnonnull +39 -> 881
    //   845: ldc2_w 45
    //   848: ldc 47
    //   850: invokestatic 39	com/tencent/gmtrace/GMTrace:o	(JI)V
    //   853: iconst_0
    //   854: ireturn
    //   855: aload 4
    //   857: getfield 259	com/tencent/mm/plugin/wenote/model/c:sbE	Ljava/util/HashMap;
    //   860: aload 4
    //   862: getfield 249	com/tencent/mm/plugin/wenote/model/c:sbC	Lcom/tencent/mm/plugin/wenote/model/a/l;
    //   865: getfield 254	com/tencent/mm/plugin/wenote/model/a/l:eOS	J
    //   868: invokestatic 268	java/lang/Long:toString	(J)Ljava/lang/String;
    //   871: invokevirtual 125	java/util/HashMap:get	(Ljava/lang/Object;)Ljava/lang/Object;
    //   874: checkcast 270	com/tencent/mm/plugin/wenote/model/a/v
    //   877: astore_0
    //   878: goto -44 -> 834
    //   881: aload_0
    //   882: getfield 274	com/tencent/mm/plugin/wenote/model/a/v:sdx	Ljava/util/ArrayList;
    //   885: invokevirtual 280	java/util/ArrayList:iterator	()Ljava/util/Iterator;
    //   888: astore 7
    //   890: aload 7
    //   892: invokeinterface 286 1 0
    //   897: ifeq -134 -> 763
    //   900: aload 7
    //   902: invokeinterface 290 1 0
    //   907: checkcast 149	com/tencent/mm/plugin/wenote/model/a/n
    //   910: astore_0
    //   911: aload_0
    //   912: getfield 293	com/tencent/mm/plugin/wenote/model/a/n:sde	Ljava/lang/String;
    //   915: aload 6
    //   917: invokevirtual 175	java/lang/String:equals	(Ljava/lang/Object;)Z
    //   920: ifeq -30 -> 890
    //   923: aload_0
    //   924: iconst_1
    //   925: putfield 207	com/tencent/mm/plugin/wenote/model/a/n:sdf	Z
    //   928: aload_0
    //   929: getfield 195	com/tencent/mm/plugin/wenote/model/a/n:type	I
    //   932: iconst_4
    //   933: if_icmpne +91 -> 1024
    //   936: aload_0
    //   937: checkcast 295	com/tencent/mm/plugin/wenote/model/a/u
    //   940: astore 7
    //   942: aload 7
    //   944: getstatic 298	com/tencent/mm/plugin/wenote/model/c:sbO	Ljava/lang/String;
    //   947: putfield 301	com/tencent/mm/plugin/wenote/model/a/u:sdc	Ljava/lang/String;
    //   950: aload 4
    //   952: aload 5
    //   954: getfield 98	com/tencent/mm/plugin/wenote/model/d:field_dataId	Ljava/lang/String;
    //   957: invokevirtual 217	com/tencent/mm/plugin/wenote/model/c:Nz	(Ljava/lang/String;)Lcom/tencent/mm/protocal/c/th;
    //   960: astore 8
    //   962: iconst_0
    //   963: istore_1
    //   964: aload 8
    //   966: ifnonnull +49 -> 1015
    //   969: ldc -124
    //   971: ldc -37
    //   973: invokestatic 223	com/tencent/mm/sdk/platformtools/w:e	(Ljava/lang/String;Ljava/lang/String;)V
    //   976: aload 7
    //   978: iload_1
    //   979: i2l
    //   980: invokestatic 305	com/tencent/mm/plugin/wenote/model/f:aD	(J)F
    //   983: f2i
    //   984: putfield 308	com/tencent/mm/plugin/wenote/model/a/u:length	I
    //   987: aload 7
    //   989: invokestatic 314	com/tencent/mm/sdk/platformtools/ab:getContext	()Landroid/content/Context;
    //   992: aload 7
    //   994: getfield 308	com/tencent/mm/plugin/wenote/model/a/u:length	I
    //   997: invokestatic 318	com/tencent/mm/plugin/wenote/model/f:K	(Landroid/content/Context;I)Ljava/lang/String;
    //   1000: putfield 321	com/tencent/mm/plugin/wenote/model/a/u:sdu	Ljava/lang/String;
    //   1003: invokestatic 161	com/tencent/mm/plugin/wenote/model/nativenote/manager/c:bHo	()Lcom/tencent/mm/plugin/wenote/model/nativenote/manager/c;
    //   1006: aload 6
    //   1008: aload_0
    //   1009: invokevirtual 166	com/tencent/mm/plugin/wenote/model/nativenote/manager/c:a	(Ljava/lang/String;Lcom/tencent/mm/plugin/wenote/model/a/b;)V
    //   1012: goto -249 -> 763
    //   1015: aload 8
    //   1017: getfield 245	com/tencent/mm/protocal/c/th:duration	I
    //   1020: istore_1
    //   1021: goto -45 -> 976
    //   1024: aload_0
    //   1025: invokevirtual 152	com/tencent/mm/plugin/wenote/model/a/n:getType	()I
    //   1028: iconst_2
    //   1029: if_icmpne +31 -> 1060
    //   1032: aload 5
    //   1034: getfield 109	com/tencent/mm/plugin/wenote/model/d:field_path	Ljava/lang/String;
    //   1037: aload 4
    //   1039: getfield 147	com/tencent/mm/plugin/wenote/model/c:sbG	Ljava/util/HashMap;
    //   1042: aload 6
    //   1044: invokevirtual 125	java/util/HashMap:get	(Ljava/lang/Object;)Ljava/lang/Object;
    //   1047: checkcast 149	com/tencent/mm/plugin/wenote/model/a/n
    //   1050: getfield 155	com/tencent/mm/plugin/wenote/model/a/n:eOR	Ljava/lang/String;
    //   1053: invokestatic 213	com/tencent/mm/plugin/wenote/b/b:eA	(Ljava/lang/String;Ljava/lang/String;)Ljava/lang/String;
    //   1056: pop
    //   1057: goto -54 -> 1003
    //   1060: aload_0
    //   1061: aload 5
    //   1063: getfield 109	com/tencent/mm/plugin/wenote/model/d:field_path	Ljava/lang/String;
    //   1066: putfield 155	com/tencent/mm/plugin/wenote/model/a/n:eOR	Ljava/lang/String;
    //   1069: goto -66 -> 1003
    //   1072: ldc -124
    //   1074: ldc_w 323
    //   1077: invokestatic 325	com/tencent/mm/sdk/platformtools/w:d	(Ljava/lang/String;Ljava/lang/String;)V
    //   1080: aload 4
    //   1082: getfield 249	com/tencent/mm/plugin/wenote/model/c:sbC	Lcom/tencent/mm/plugin/wenote/model/a/l;
    //   1085: getfield 254	com/tencent/mm/plugin/wenote/model/a/l:eOS	J
    //   1088: ldc2_w 255
    //   1091: lcmp
    //   1092: ifne +40 -> 1132
    //   1095: aload 4
    //   1097: getfield 259	com/tencent/mm/plugin/wenote/model/c:sbE	Ljava/util/HashMap;
    //   1100: aload 4
    //   1102: getfield 249	com/tencent/mm/plugin/wenote/model/c:sbC	Lcom/tencent/mm/plugin/wenote/model/a/l;
    //   1105: getfield 262	com/tencent/mm/plugin/wenote/model/a/l:eDr	J
    //   1108: invokestatic 268	java/lang/Long:toString	(J)Ljava/lang/String;
    //   1111: invokevirtual 125	java/util/HashMap:get	(Ljava/lang/Object;)Ljava/lang/Object;
    //   1114: checkcast 270	com/tencent/mm/plugin/wenote/model/a/v
    //   1117: astore_0
    //   1118: aload_0
    //   1119: ifnonnull +39 -> 1158
    //   1122: ldc2_w 45
    //   1125: ldc 47
    //   1127: invokestatic 39	com/tencent/gmtrace/GMTrace:o	(JI)V
    //   1130: iconst_0
    //   1131: ireturn
    //   1132: aload 4
    //   1134: getfield 259	com/tencent/mm/plugin/wenote/model/c:sbE	Ljava/util/HashMap;
    //   1137: aload 4
    //   1139: getfield 249	com/tencent/mm/plugin/wenote/model/c:sbC	Lcom/tencent/mm/plugin/wenote/model/a/l;
    //   1142: getfield 254	com/tencent/mm/plugin/wenote/model/a/l:eOS	J
    //   1145: invokestatic 268	java/lang/Long:toString	(J)Ljava/lang/String;
    //   1148: invokevirtual 125	java/util/HashMap:get	(Ljava/lang/Object;)Ljava/lang/Object;
    //   1151: checkcast 270	com/tencent/mm/plugin/wenote/model/a/v
    //   1154: astore_0
    //   1155: goto -37 -> 1118
    //   1158: aload_0
    //   1159: aload 5
    //   1161: getfield 109	com/tencent/mm/plugin/wenote/model/d:field_path	Ljava/lang/String;
    //   1164: invokestatic 329	com/tencent/mm/plugin/wenote/b/b:NR	(Ljava/lang/String;)Ljava/lang/String;
    //   1167: putfield 332	com/tencent/mm/plugin/wenote/model/a/v:sdw	Ljava/lang/String;
    //   1170: invokestatic 161	com/tencent/mm/plugin/wenote/model/nativenote/manager/c:bHo	()Lcom/tencent/mm/plugin/wenote/model/nativenote/manager/c;
    //   1173: astore 6
    //   1175: aload_0
    //   1176: getfield 332	com/tencent/mm/plugin/wenote/model/a/v:sdw	Ljava/lang/String;
    //   1179: astore_0
    //   1180: aload_0
    //   1181: invokestatic 130	com/tencent/mm/sdk/platformtools/bg:nm	(Ljava/lang/String;)Z
    //   1184: ifne -421 -> 763
    //   1187: aload 6
    //   1189: getfield 335	com/tencent/mm/plugin/wenote/model/nativenote/manager/c:iFZ	Ljava/util/ArrayList;
    //   1192: ifnull -429 -> 763
    //   1195: aload_0
    //   1196: invokestatic 341	com/tencent/mm/plugin/wenote/b/a:NK	(Ljava/lang/String;)Ljava/util/ArrayList;
    //   1199: astore 7
    //   1201: aload 7
    //   1203: ifnull -440 -> 763
    //   1206: aload 7
    //   1208: invokevirtual 344	java/util/ArrayList:size	()I
    //   1211: ifle -448 -> 763
    //   1214: aload 6
    //   1216: monitorenter
    //   1217: ldc_w 346
    //   1220: ldc_w 348
    //   1223: iconst_1
    //   1224: anewarray 136	java/lang/Object
    //   1227: dup
    //   1228: iconst_0
    //   1229: aload 6
    //   1231: getfield 351	com/tencent/mm/plugin/wenote/model/nativenote/manager/c:sdZ	Z
    //   1234: invokestatic 357	java/lang/Boolean:valueOf	(Z)Ljava/lang/Boolean;
    //   1237: aastore
    //   1238: invokestatic 230	com/tencent/mm/sdk/platformtools/w:i	(Ljava/lang/String;Ljava/lang/String;[Ljava/lang/Object;)V
    //   1241: invokestatic 363	com/tencent/mm/y/at:xB	()Lcom/tencent/mm/sdk/platformtools/af;
    //   1244: astore_0
    //   1245: new 365	com/tencent/mm/plugin/wenote/model/nativenote/manager/c$2
    //   1248: dup
    //   1249: aload 6
    //   1251: aload 7
    //   1253: invokespecial 368	com/tencent/mm/plugin/wenote/model/nativenote/manager/c$2:<init>	(Lcom/tencent/mm/plugin/wenote/model/nativenote/manager/c;Ljava/util/ArrayList;)V
    //   1256: astore 7
    //   1258: aload 6
    //   1260: getfield 351	com/tencent/mm/plugin/wenote/model/nativenote/manager/c:sdZ	Z
    //   1263: ifeq +44 -> 1307
    //   1266: ldc2_w 369
    //   1269: lstore_2
    //   1270: aload_0
    //   1271: aload 7
    //   1273: lload_2
    //   1274: invokevirtual 376	com/tencent/mm/sdk/platformtools/af:h	(Ljava/lang/Runnable;J)I
    //   1277: pop
    //   1278: aload 6
    //   1280: monitorexit
    //   1281: goto -518 -> 763
    //   1284: astore_0
    //   1285: aload 6
    //   1287: monitorexit
    //   1288: aload_0
    //   1289: athrow
    //   1290: astore_0
    //   1291: ldc -124
    //   1293: aload_0
    //   1294: ldc_w 378
    //   1297: iconst_0
    //   1298: anewarray 136	java/lang/Object
    //   1301: invokestatic 382	com/tencent/mm/sdk/platformtools/w:printErrStackTrace	(Ljava/lang/String;Ljava/lang/Throwable;Ljava/lang/String;[Ljava/lang/Object;)V
    //   1304: goto -541 -> 763
    //   1307: ldc2_w 383
    //   1310: lstore_2
    //   1311: goto -41 -> 1270
    //   1314: astore_0
    //   1315: ldc_w 346
    //   1318: ldc_w 386
    //   1321: iconst_1
    //   1322: anewarray 136	java/lang/Object
    //   1325: dup
    //   1326: iconst_0
    //   1327: aload_0
    //   1328: invokevirtual 388	java/lang/Exception:toString	()Ljava/lang/String;
    //   1331: aastore
    //   1332: invokestatic 390	com/tencent/mm/sdk/platformtools/w:e	(Ljava/lang/String;Ljava/lang/String;[Ljava/lang/Object;)V
    //   1335: goto -57 -> 1278
    // Local variable table:
    //   start	length	slot	name	signature
    //   0	1338	0	paramkl	kl
    //   210	811	1	i	int
    //   1269	42	2	l	long
    //   81	1057	4	localc	com.tencent.mm.plugin.wenote.model.c
    //   105	1055	5	locald	com.tencent.mm.plugin.wenote.model.d
    //   257	1029	6	localObject1	Object
    //   635	637	7	localObject2	Object
    //   960	56	8	localth	com.tencent.mm.protocal.c.th
    // Exception table:
    //   from	to	target	type
    //   1217	1266	1284	finally
    //   1270	1278	1284	finally
    //   1278	1281	1284	finally
    //   1285	1288	1284	finally
    //   1315	1335	1284	finally
    //   1158	1201	1290	java/lang/Exception
    //   1206	1217	1290	java/lang/Exception
    //   1288	1290	1290	java/lang/Exception
    //   1217	1266	1314	java/lang/Exception
    //   1270	1278	1314	java/lang/Exception
  }
}


/* Location:              D:\tools\apktool\weixin6519android1140\jar\classes3-dex2jar.jar!\com\tencent\mm\plugin\wenote\a\a.class
 * Java compiler version: 6 (50.0)
 * JD-Core Version:       0.7.1
 */