package c.t.m.g;

final class br
  implements Runnable
{
  br(bm parambm) {}
  
  /* Error */
  public final void run()
  {
    // Byte code:
    //   0: iconst_0
    //   1: istore_3
    //   2: iconst_0
    //   3: istore_2
    //   4: invokestatic 25	android/os/SystemClock:elapsedRealtime	()J
    //   7: lstore 4
    //   9: new 27	c/t/m/g/be
    //   12: dup
    //   13: invokespecial 28	c/t/m/g/be:<init>	()V
    //   16: astore 7
    //   18: aload_0
    //   19: getfield 12	c/t/m/g/br:a	Lc/t/m/g/bm;
    //   22: getfield 34	c/t/m/g/bm:d	Ljava/util/Map;
    //   25: invokeinterface 40 1 0
    //   30: invokeinterface 46 1 0
    //   35: astore 8
    //   37: aload 8
    //   39: invokeinterface 52 1 0
    //   44: ifeq +69 -> 113
    //   47: aload 8
    //   49: invokeinterface 56 1 0
    //   54: checkcast 58	c/t/m/g/bi
    //   57: aload 7
    //   59: invokevirtual 61	c/t/m/g/bi:a	(Lc/t/m/g/be;)V
    //   62: goto -25 -> 37
    //   65: astore 7
    //   67: iload_2
    //   68: istore_1
    //   69: aload_0
    //   70: getfield 12	c/t/m/g/br:a	Lc/t/m/g/bm;
    //   73: invokestatic 67	c/t/m/g/o:b	()Ljava/lang/String;
    //   76: invokestatic 70	c/t/m/g/bm:a	(Lc/t/m/g/bm;Ljava/lang/String;)Lc/t/m/g/bm$a;
    //   79: astore 7
    //   81: aload 7
    //   83: invokestatic 25	android/os/SystemClock:elapsedRealtime	()J
    //   86: putfield 75	c/t/m/g/bm$a:a	J
    //   89: aload 7
    //   91: iload_1
    //   92: putfield 78	c/t/m/g/bm$a:b	I
    //   95: aload_0
    //   96: getfield 12	c/t/m/g/br:a	Lc/t/m/g/bm;
    //   99: getfield 82	c/t/m/g/bm:c	Landroid/os/Handler;
    //   102: aload_0
    //   103: getfield 12	c/t/m/g/br:a	Lc/t/m/g/bm;
    //   106: getfield 86	c/t/m/g/bm:f	Ljava/lang/Runnable;
    //   109: invokevirtual 92	android/os/Handler:removeCallbacks	(Ljava/lang/Runnable;)V
    //   112: return
    //   113: aload 7
    //   115: invokevirtual 95	c/t/m/g/be:a	()[B
    //   118: astore 7
    //   120: aload 7
    //   122: invokestatic 100	c/t/m/g/ce:a	([B)Z
    //   125: ifne +278 -> 403
    //   128: new 102	c/t/m/g/af
    //   131: dup
    //   132: ldc 104
    //   134: aconst_null
    //   135: aload 7
    //   137: sipush 15000
    //   140: invokestatic 106	c/t/m/g/ce:d	()Ljava/lang/String;
    //   143: iconst_1
    //   144: invokestatic 111	c/t/m/g/bv:c	()Lc/t/m/g/bv;
    //   147: invokevirtual 115	c/t/m/g/bv:e	()Lc/t/m/g/r;
    //   150: invokespecial 118	c/t/m/g/af:<init>	(Ljava/lang/String;Ljava/util/Map;[BILjava/lang/String;ZLc/t/m/g/r;)V
    //   153: astore 7
    //   155: aload 7
    //   157: ldc 120
    //   159: putfield 124	c/t/m/g/af:m	Ljava/lang/String;
    //   162: aload 7
    //   164: invokevirtual 127	c/t/m/g/af:a	()Lc/t/m/g/ah;
    //   167: astore 8
    //   169: aload 8
    //   171: getfield 131	c/t/m/g/ah:a	I
    //   174: istore_1
    //   175: aload 8
    //   177: getfield 131	c/t/m/g/ah:a	I
    //   180: ifne +102 -> 282
    //   183: aload 8
    //   185: getfield 133	c/t/m/g/ah:c	I
    //   188: sipush 200
    //   191: if_icmpne +91 -> 282
    //   194: aload 8
    //   196: getfield 136	c/t/m/g/ah:d	[B
    //   199: invokestatic 100	c/t/m/g/ce:a	([B)Z
    //   202: istore 6
    //   204: iload 6
    //   206: ifne +76 -> 282
    //   209: new 138	org/json/JSONObject
    //   212: dup
    //   213: new 140	java/lang/String
    //   216: dup
    //   217: aload 8
    //   219: getfield 136	c/t/m/g/ah:d	[B
    //   222: invokespecial 143	java/lang/String:<init>	([B)V
    //   225: invokespecial 146	org/json/JSONObject:<init>	(Ljava/lang/String;)V
    //   228: astore 8
    //   230: invokestatic 148	c/t/m/g/o:e	()V
    //   233: aload_0
    //   234: getfield 12	c/t/m/g/br:a	Lc/t/m/g/bm;
    //   237: getfield 34	c/t/m/g/bm:d	Ljava/util/Map;
    //   240: invokeinterface 40 1 0
    //   245: invokeinterface 46 1 0
    //   250: astore 9
    //   252: aload 9
    //   254: invokeinterface 52 1 0
    //   259: ifeq +23 -> 282
    //   262: aload 9
    //   264: invokeinterface 56 1 0
    //   269: checkcast 58	c/t/m/g/bi
    //   272: aload 8
    //   274: invokevirtual 151	c/t/m/g/bi:a	(Lorg/json/JSONObject;)V
    //   277: goto -25 -> 252
    //   280: astore 8
    //   282: aload 7
    //   284: invokestatic 25	android/os/SystemClock:elapsedRealtime	()J
    //   287: lload 4
    //   289: lsub
    //   290: putfield 154	c/t/m/g/af:j	J
    //   293: aload 7
    //   295: iconst_0
    //   296: invokevirtual 157	c/t/m/g/af:a	(Z)V
    //   299: aload_0
    //   300: getfield 12	c/t/m/g/br:a	Lc/t/m/g/bm;
    //   303: invokestatic 67	c/t/m/g/o:b	()Ljava/lang/String;
    //   306: invokestatic 70	c/t/m/g/bm:a	(Lc/t/m/g/bm;Ljava/lang/String;)Lc/t/m/g/bm$a;
    //   309: astore 7
    //   311: aload 7
    //   313: invokestatic 25	android/os/SystemClock:elapsedRealtime	()J
    //   316: putfield 75	c/t/m/g/bm$a:a	J
    //   319: aload 7
    //   321: iload_1
    //   322: putfield 78	c/t/m/g/bm$a:b	I
    //   325: aload_0
    //   326: getfield 12	c/t/m/g/br:a	Lc/t/m/g/bm;
    //   329: getfield 82	c/t/m/g/bm:c	Landroid/os/Handler;
    //   332: aload_0
    //   333: getfield 12	c/t/m/g/br:a	Lc/t/m/g/bm;
    //   336: getfield 86	c/t/m/g/bm:f	Ljava/lang/Runnable;
    //   339: invokevirtual 92	android/os/Handler:removeCallbacks	(Ljava/lang/Runnable;)V
    //   342: return
    //   343: astore 7
    //   345: iload_3
    //   346: istore_1
    //   347: aload_0
    //   348: getfield 12	c/t/m/g/br:a	Lc/t/m/g/bm;
    //   351: invokestatic 67	c/t/m/g/o:b	()Ljava/lang/String;
    //   354: invokestatic 70	c/t/m/g/bm:a	(Lc/t/m/g/bm;Ljava/lang/String;)Lc/t/m/g/bm$a;
    //   357: astore 8
    //   359: aload 8
    //   361: invokestatic 25	android/os/SystemClock:elapsedRealtime	()J
    //   364: putfield 75	c/t/m/g/bm$a:a	J
    //   367: aload 8
    //   369: iload_1
    //   370: putfield 78	c/t/m/g/bm$a:b	I
    //   373: aload_0
    //   374: getfield 12	c/t/m/g/br:a	Lc/t/m/g/bm;
    //   377: getfield 82	c/t/m/g/bm:c	Landroid/os/Handler;
    //   380: aload_0
    //   381: getfield 12	c/t/m/g/br:a	Lc/t/m/g/bm;
    //   384: getfield 86	c/t/m/g/bm:f	Ljava/lang/Runnable;
    //   387: invokevirtual 92	android/os/Handler:removeCallbacks	(Ljava/lang/Runnable;)V
    //   390: aload 7
    //   392: athrow
    //   393: astore 7
    //   395: goto -48 -> 347
    //   398: astore 7
    //   400: goto -331 -> 69
    //   403: iconst_0
    //   404: istore_1
    //   405: goto -106 -> 299
    // Local variable table:
    //   start	length	slot	name	signature
    //   0	408	0	this	br
    //   68	337	1	i	int
    //   3	65	2	j	int
    //   1	345	3	k	int
    //   7	281	4	l	long
    //   202	3	6	bool	boolean
    //   16	42	7	localbe	be
    //   65	1	7	localThrowable1	Throwable
    //   79	241	7	localObject1	Object
    //   343	48	7	localObject2	Object
    //   393	1	7	localObject3	Object
    //   398	1	7	localThrowable2	Throwable
    //   35	238	8	localObject4	Object
    //   280	1	8	localThrowable3	Throwable
    //   357	11	8	locala	bm.a
    //   250	13	9	localIterator	java.util.Iterator
    // Exception table:
    //   from	to	target	type
    //   9	37	65	java/lang/Throwable
    //   37	62	65	java/lang/Throwable
    //   113	175	65	java/lang/Throwable
    //   209	252	280	java/lang/Throwable
    //   252	277	280	java/lang/Throwable
    //   9	37	343	finally
    //   37	62	343	finally
    //   113	175	343	finally
    //   175	204	393	finally
    //   209	252	393	finally
    //   252	277	393	finally
    //   282	299	393	finally
    //   175	204	398	java/lang/Throwable
    //   282	299	398	java/lang/Throwable
  }
}


/* Location:              D:\tools\apktool\weixin6519android1140\jar\classes-dex2jar.jar!\c\t\m\g\br.class
 * Java compiler version: 6 (50.0)
 * JD-Core Version:       0.7.1
 */