package com.tencent.smtt.sdk;

import android.annotation.TargetApi;
import android.content.Context;
import android.content.SharedPreferences;
import android.os.Build.VERSION;
import android.os.Bundle;
import android.os.Handler;
import android.os.Looper;
import android.os.Message;
import android.util.Log;
import com.tencent.smtt.utils.TbsLog;
import com.tencent.smtt.utils.a;
import com.tencent.smtt.utils.c;
import com.tencent.smtt.utils.f;
import com.tencent.smtt.utils.u;
import java.io.Closeable;
import java.io.File;
import java.io.IOException;
import java.net.HttpURLConnection;
import java.net.InetAddress;
import java.net.URL;
import java.util.HashSet;
import java.util.Map;
import java.util.Set;

final class h
{
  private static int xUA = 1;
  private static final String[] xUB = { "tbs_downloading_com.tencent.mtt", "tbs_downloading_com.tencent.mm", "tbs_downloading_com.tencent.mobileqq", "tbs_downloading_com.tencent.tbs", "tbs_downloading_com.qzone" };
  private static int xUz = 5;
  private boolean Lv;
  private int hiz;
  private long mContentLength;
  Context mContext;
  private String mDownloadUrl;
  private boolean mFinished;
  private String xUC;
  private String xUD;
  File xUE;
  private int xUF = 30000;
  private int xUG = 20000;
  private boolean xUH;
  private int xUI;
  private HttpURLConnection xUJ;
  private String xUK;
  private r.b xUL;
  private String xUM;
  private int xUN;
  private boolean xUO;
  private Handler xUP;
  private Set<String> xUQ;
  private int xUR = xUz;
  boolean xUS;
  String xUT;
  String[] xUU = null;
  int xUV = 0;
  
  public h(Context paramContext)
  {
    this.mContext = paramContext.getApplicationContext();
    r.gR(this.mContext);
    this.xUL = r.coy();
    this.xUQ = new HashSet();
    this.xUK = ("tbs_downloading_" + this.mContext.getPackageName());
    p.cov();
    this.xUE = p.gM(this.mContext);
    if (this.xUE == null) {
      throw new NullPointerException("TbsCorePrivateDir is null!");
    }
    cnT();
    this.xUM = null;
    this.xUN = -1;
  }
  
  private boolean Fe(int paramInt)
  {
    boolean bool = false;
    try
    {
      File localFile1 = new File(this.xUE, "x5.tbs");
      File localFile2 = gh(this.mContext);
      if (localFile2 != null)
      {
        if (l.gp(this.mContext)) {}
        for (Object localObject = "x5.oversea.tbs.org";; localObject = "x5.tbs.org")
        {
          localObject = new File(localFile2, (String)localObject);
          localFile1.delete();
          f.i((File)localObject, localFile1);
          if (a.a(this.mContext, localFile1, paramInt)) {
            break;
          }
          TbsLog.i("TbsDownload", "[TbsApkDownloader.copyTbsApkFromBackupToInstall] verifyTbsApk error!!");
          return false;
        }
        bool = true;
      }
    }
    catch (Exception localException)
    {
      TbsLog.e("TbsDownload", "[TbsApkDownloader.copyTbsApkFromBackupToInstall] Exception is " + localException.getMessage());
      return false;
    }
    return bool;
  }
  
  private boolean Q(boolean paramBoolean1, boolean paramBoolean2)
  {
    long l2 = 0L;
    TbsLog.i("TbsDownload", "[TbsApkDownloader.verifyTbsApk] isTempFile=" + paramBoolean1);
    Object localObject2 = this.xUE;
    Object localObject1;
    if (!paramBoolean1)
    {
      localObject1 = "x5.tbs";
      localObject1 = new File((File)localObject2, (String)localObject1);
      if (((File)localObject1).exists()) {
        break label68;
      }
    }
    label68:
    Object localObject3;
    do
    {
      return false;
      localObject1 = "x5.tbs.temp";
      break;
      localObject2 = k.gl(this.mContext).xVi.getString("tbs_apk_md5", null);
      localObject3 = a.L((File)localObject1);
      if ((localObject2 != null) && (((String)localObject2).equals(localObject3))) {
        break label151;
      }
      TbsLog.i("TbsDownload", "[TbsApkDownloader.verifyTbsApk] isTempFile=" + paramBoolean1 + " md5 failed");
    } while (!paramBoolean1);
    this.xUL.Yj("fileMd5 not match");
    return false;
    label151:
    TbsLog.i("TbsDownload", "[TbsApkDownloader.verifyTbsApk] md5(" + (String)localObject3 + ") successful!");
    long l1 = l2;
    long l3;
    if (paramBoolean1)
    {
      l3 = k.gl(this.mContext).xVi.getLong("tbs_apkfilesize", 0L);
      if (!((File)localObject1).exists()) {
        break label690;
      }
      l1 = l2;
      if (l3 > 0L)
      {
        l1 = ((File)localObject1).length();
        if (l3 == l1) {}
      }
    }
    for (;;)
    {
      TbsLog.i("TbsDownload", "[TbsApkDownloader.verifyTbsApk] isTempFile=" + paramBoolean1 + " filelength failed");
      this.xUL.Yj("fileLength:" + l1 + ",contentLength:" + l3);
      return false;
      TbsLog.i("TbsDownload", "[TbsApkDownloader.verifyTbsApk] length(" + l1 + ") successful!");
      int i = -1;
      if (paramBoolean2)
      {
        int j = a.c(this.mContext, (File)localObject1);
        int k = k.gl(this.mContext).xVi.getInt("tbs_download_version", 0);
        i = j;
        if (k != j)
        {
          TbsLog.i("TbsDownload", "[TbsApkDownloader.verifyTbsApk] isTempFile=" + paramBoolean1 + " versionCode failed");
          if (!paramBoolean1) {
            break;
          }
          this.xUL.Yj("fileVersion:" + j + ",configVersion:" + k);
          return false;
        }
      }
      TbsLog.i("TbsDownload", "[TbsApkDownloader.verifyTbsApk] tbsApkVersionCode(" + i + ") successful!");
      if (paramBoolean2)
      {
        String str = c.d(this.mContext, (File)localObject1);
        if (!"3082023f308201a8a00302010202044c46914a300d06092a864886f70d01010505003064310b30090603550406130238363110300e060355040813074265696a696e673110300e060355040713074265696a696e673110300e060355040a130754656e63656e74310c300a060355040b13035753443111300f0603550403130873616d75656c6d6f301e170d3130303732313036313835305a170d3430303731333036313835305a3064310b30090603550406130238363110300e060355040813074265696a696e673110300e060355040713074265696a696e673110300e060355040a130754656e63656e74310c300a060355040b13035753443111300f0603550403130873616d75656c6d6f30819f300d06092a864886f70d010101050003818d0030818902818100c209077044bd0d63ea00ede5b839914cabcc912a87f0f8b390877e0f7a2583f0d5933443c40431c35a4433bc4c965800141961adc44c9625b1d321385221fd097e5bdc2f44a1840d643ab59dc070cf6c4b4b4d98bed5cbb8046e0a7078ae134da107cdf2bfc9b440fe5cb2f7549b44b73202cc6f7c2c55b8cfb0d333a021f01f0203010001300d06092a864886f70d010105050003818100b007db9922774ef4ccfee81ba514a8d57c410257e7a2eba64bfa17c9e690da08106d32f637ac41fbc9f205176c71bde238c872c3ee2f8313502bee44c80288ea4ef377a6f2cdfe4d3653c145c4acfedbfbadea23b559d41980cc3cdd35d79a68240693739aabf5c5ed26148756cf88264226de394c8a24ac35b712b120d4d23a".equals(str))
        {
          TbsLog.i("TbsDownload", "[TbsApkDownloader.verifyTbsApk] isTempFile=" + paramBoolean1 + " signature failed");
          if (!paramBoolean1) {
            break;
          }
          localObject2 = this.xUL;
          localObject3 = new StringBuilder("signature:");
          if (str == null) {}
          for (localObject1 = "null";; localObject1 = Integer.valueOf(str.length()))
          {
            ((r.b)localObject2).Yj(localObject1);
            return false;
          }
        }
      }
      TbsLog.i("TbsDownload", "[TbsApkDownloader.verifyTbsApk] signature successful!");
      if (paramBoolean1)
      {
        try
        {
          paramBoolean1 = ((File)localObject1).renameTo(new File(this.xUE, "x5.tbs"));
          localObject1 = null;
        }
        catch (Exception localException)
        {
          for (;;)
          {
            paramBoolean1 = false;
          }
        }
        paramBoolean2 = paramBoolean1;
        if (paramBoolean1) {
          break label660;
        }
        j(109, i((Throwable)localObject1), true);
        return false;
      }
      paramBoolean2 = false;
      label660:
      TbsLog.i("TbsDownload", "[TbsApkDownloader.verifyTbsApk] rename(" + paramBoolean2 + ") successful!");
      return true;
      label690:
      l1 = 0L;
    }
  }
  
  public static void a(File paramFile, Context paramContext)
  {
    if (!paramFile.exists()) {}
    for (;;)
    {
      return;
      try
      {
        File localFile = gh(paramContext);
        if (localFile == null) {
          continue;
        }
        if (k.gl(paramContext).xVi.getInt("tbs_download_version_type", 0) == 1)
        {
          localObject = new File(localFile, "x5.tbs.decouple");
          ((File)localObject).delete();
          f.i(paramFile, (File)localObject);
          if ((k.gl(paramContext).xVi.getInt("tbs_download_version_type", 0) == 1) || (k.gl(paramContext).xVi.getInt("tbs_decouplecoreversion", 0) != a.c(paramContext, paramFile))) {
            continue;
          }
          localObject = new File(localFile, "x5.tbs.decouple");
          if (a.c(paramContext, paramFile) == a.c(paramContext, (File)localObject)) {
            continue;
          }
          ((File)localObject).delete();
          f.i(paramFile, (File)localObject);
          return;
        }
        if (l.gp(paramContext)) {}
        for (Object localObject = "x5.oversea.tbs.org";; localObject = "x5.tbs.org")
        {
          localObject = new File(localFile, (String)localObject);
          break;
        }
        return;
      }
      catch (Exception paramFile) {}
    }
  }
  
  private static File aj(Context paramContext, int paramInt)
  {
    File localFile = new File(f.an(paramContext, paramInt));
    if ((!localFile.exists()) || (!localFile.isDirectory())) {
      return null;
    }
    if (l.gp(paramContext)) {}
    for (paramContext = "x5.oversea.tbs.org"; new File(localFile, paramContext).exists(); paramContext = "x5.tbs.org") {
      return localFile;
    }
    return null;
  }
  
  private void cnT()
  {
    this.hiz = 0;
    this.xUI = 0;
    this.mContentLength = -1L;
    this.xUD = null;
    this.xUH = false;
    this.Lv = false;
    this.mFinished = false;
    this.xUO = false;
  }
  
  private boolean cnV()
  {
    boolean bool2 = false;
    boolean bool1 = bool2;
    if (this.xUU != null)
    {
      bool1 = bool2;
      if (this.xUV >= 0)
      {
        bool1 = bool2;
        if (this.xUV < this.xUU.length)
        {
          String[] arrayOfString = this.xUU;
          int i = this.xUV;
          this.xUV = (i + 1);
          this.xUD = arrayOfString[i];
          this.hiz = 0;
          this.xUI = 0;
          this.mContentLength = -1L;
          this.xUH = false;
          this.Lv = false;
          this.mFinished = false;
          this.xUO = false;
          bool1 = true;
        }
      }
    }
    return bool1;
  }
  
  private long cnW()
  {
    long l = 0L;
    File localFile = new File(this.xUE, "x5.tbs.temp");
    if (localFile.exists()) {
      l = localFile.length();
    }
    return l;
  }
  
  /* Error */
  private static boolean cnX()
  {
    // Byte code:
    //   0: iconst_0
    //   1: istore_3
    //   2: aconst_null
    //   3: astore 7
    //   5: aconst_null
    //   6: astore 8
    //   8: invokestatic 388	java/lang/Runtime:getRuntime	()Ljava/lang/Runtime;
    //   11: astore 4
    //   13: aload 4
    //   15: new 109	java/lang/StringBuilder
    //   18: dup
    //   19: ldc_w 390
    //   22: invokespecial 114	java/lang/StringBuilder:<init>	(Ljava/lang/String;)V
    //   25: ldc_w 392
    //   28: invokevirtual 122	java/lang/StringBuilder:append	(Ljava/lang/String;)Ljava/lang/StringBuilder;
    //   31: invokevirtual 125	java/lang/StringBuilder:toString	()Ljava/lang/String;
    //   34: invokevirtual 396	java/lang/Runtime:exec	(Ljava/lang/String;)Ljava/lang/Process;
    //   37: invokevirtual 402	java/lang/Process:getInputStream	()Ljava/io/InputStream;
    //   40: astore 4
    //   42: new 404	java/io/InputStreamReader
    //   45: dup
    //   46: aload 4
    //   48: invokespecial 407	java/io/InputStreamReader:<init>	(Ljava/io/InputStream;)V
    //   51: astore 6
    //   53: new 409	java/io/BufferedReader
    //   56: dup
    //   57: aload 6
    //   59: invokespecial 412	java/io/BufferedReader:<init>	(Ljava/io/Reader;)V
    //   62: astore 5
    //   64: iconst_0
    //   65: istore_0
    //   66: aload 5
    //   68: invokevirtual 415	java/io/BufferedReader:readLine	()Ljava/lang/String;
    //   71: astore 7
    //   73: iload_3
    //   74: istore_2
    //   75: aload 7
    //   77: ifnull +29 -> 106
    //   80: aload 7
    //   82: ldc_w 417
    //   85: invokevirtual 421	java/lang/String:contains	(Ljava/lang/CharSequence;)Z
    //   88: ifne +16 -> 104
    //   91: aload 7
    //   93: ldc_w 423
    //   96: invokevirtual 421	java/lang/String:contains	(Ljava/lang/CharSequence;)Z
    //   99: istore_2
    //   100: iload_2
    //   101: ifeq +22 -> 123
    //   104: iconst_1
    //   105: istore_2
    //   106: aload 4
    //   108: invokestatic 427	com/tencent/smtt/sdk/h:h	(Ljava/io/Closeable;)V
    //   111: aload 6
    //   113: invokestatic 427	com/tencent/smtt/sdk/h:h	(Ljava/io/Closeable;)V
    //   116: aload 5
    //   118: invokestatic 427	com/tencent/smtt/sdk/h:h	(Ljava/io/Closeable;)V
    //   121: iload_2
    //   122: ireturn
    //   123: iload_0
    //   124: iconst_1
    //   125: iadd
    //   126: istore_1
    //   127: iload_1
    //   128: istore_0
    //   129: iload_1
    //   130: iconst_5
    //   131: if_icmplt -65 -> 66
    //   134: iload_3
    //   135: istore_2
    //   136: goto -30 -> 106
    //   139: astore 4
    //   141: aconst_null
    //   142: astore 4
    //   144: aconst_null
    //   145: astore 5
    //   147: aload 8
    //   149: astore 6
    //   151: aload 5
    //   153: invokestatic 427	com/tencent/smtt/sdk/h:h	(Ljava/io/Closeable;)V
    //   156: aload 6
    //   158: invokestatic 427	com/tencent/smtt/sdk/h:h	(Ljava/io/Closeable;)V
    //   161: aload 4
    //   163: invokestatic 427	com/tencent/smtt/sdk/h:h	(Ljava/io/Closeable;)V
    //   166: iconst_0
    //   167: ireturn
    //   168: astore 5
    //   170: aconst_null
    //   171: astore 6
    //   173: aconst_null
    //   174: astore 4
    //   176: aload 4
    //   178: invokestatic 427	com/tencent/smtt/sdk/h:h	(Ljava/io/Closeable;)V
    //   181: aload 6
    //   183: invokestatic 427	com/tencent/smtt/sdk/h:h	(Ljava/io/Closeable;)V
    //   186: aload 7
    //   188: invokestatic 427	com/tencent/smtt/sdk/h:h	(Ljava/io/Closeable;)V
    //   191: aload 5
    //   193: athrow
    //   194: astore 5
    //   196: aconst_null
    //   197: astore 6
    //   199: goto -23 -> 176
    //   202: astore 5
    //   204: goto -28 -> 176
    //   207: astore 8
    //   209: aload 5
    //   211: astore 7
    //   213: aload 8
    //   215: astore 5
    //   217: goto -41 -> 176
    //   220: astore 5
    //   222: aconst_null
    //   223: astore 6
    //   225: aload 4
    //   227: astore 5
    //   229: aload 6
    //   231: astore 4
    //   233: aload 8
    //   235: astore 6
    //   237: goto -86 -> 151
    //   240: astore 5
    //   242: aconst_null
    //   243: astore 7
    //   245: aload 4
    //   247: astore 5
    //   249: aload 7
    //   251: astore 4
    //   253: goto -102 -> 151
    //   256: astore 7
    //   258: aload 4
    //   260: astore 7
    //   262: aload 5
    //   264: astore 4
    //   266: aload 7
    //   268: astore 5
    //   270: goto -119 -> 151
    // Local variable table:
    //   start	length	slot	name	signature
    //   65	64	0	i	int
    //   126	6	1	j	int
    //   74	62	2	bool1	boolean
    //   1	134	3	bool2	boolean
    //   11	96	4	localObject1	Object
    //   139	1	4	localThrowable1	Throwable
    //   142	123	4	localObject2	Object
    //   62	90	5	localBufferedReader	java.io.BufferedReader
    //   168	24	5	localObject3	Object
    //   194	1	5	localObject4	Object
    //   202	8	5	localObject5	Object
    //   215	1	5	localObject6	Object
    //   220	1	5	localThrowable2	Throwable
    //   227	1	5	localObject7	Object
    //   240	1	5	localThrowable3	Throwable
    //   247	22	5	localObject8	Object
    //   51	185	6	localObject9	Object
    //   3	247	7	localObject10	Object
    //   256	1	7	localThrowable4	Throwable
    //   260	7	7	localObject11	Object
    //   6	142	8	localObject12	Object
    //   207	27	8	localObject13	Object
    // Exception table:
    //   from	to	target	type
    //   13	42	139	java/lang/Throwable
    //   13	42	168	finally
    //   42	53	194	finally
    //   53	64	202	finally
    //   66	73	207	finally
    //   80	100	207	finally
    //   42	53	220	java/lang/Throwable
    //   53	64	240	java/lang/Throwable
    //   66	73	256	java/lang/Throwable
    //   80	100	256	java/lang/Throwable
  }
  
  private static String d(URL paramURL)
  {
    try
    {
      paramURL = InetAddress.getByName(paramURL.getHost()).getHostAddress();
      return paramURL;
    }
    catch (Error paramURL)
    {
      return "";
    }
    catch (Exception paramURL) {}
    return "";
  }
  
  private void fr(long paramLong)
  {
    this.hiz += 1;
    if (paramLong <= 0L) {}
    for (;;)
    {
      try
      {
        switch (this.hiz)
        {
        case 1: 
          Thread.sleep(paramLong);
          return;
        }
      }
      catch (Exception localException)
      {
        int i;
        return;
      }
      i = this.hiz;
      paramLong = 20000L * i;
      continue;
      paramLong = 100000L;
      continue;
      continue;
      paramLong = 200000L;
    }
  }
  
  @TargetApi(8)
  static File gh(Context paramContext)
  {
    for (;;)
    {
      try
      {
        if (Build.VERSION.SDK_INT >= 8)
        {
          paramContext = new File(f.an(paramContext, 4));
          if ((paramContext != null) && (!paramContext.exists()) && (!paramContext.isDirectory())) {
            paramContext.mkdirs();
          }
          return paramContext;
        }
      }
      catch (Exception paramContext)
      {
        TbsLog.e("TbsDownload", "[TbsApkDownloader.backupApkPath] Exception is " + paramContext.getMessage());
        return null;
      }
      paramContext = null;
    }
  }
  
  @TargetApi(8)
  static File gi(Context paramContext)
  {
    try
    {
      if (Build.VERSION.SDK_INT >= 8)
      {
        Object localObject2 = aj(paramContext, 4);
        Object localObject1 = localObject2;
        if (localObject2 == null) {
          localObject1 = aj(paramContext, 3);
        }
        localObject2 = localObject1;
        if (localObject1 == null) {
          localObject2 = aj(paramContext, 2);
        }
        localObject1 = localObject2;
        if (localObject2 == null) {
          localObject1 = aj(paramContext, 1);
        }
        return (File)localObject1;
      }
    }
    catch (Exception paramContext)
    {
      TbsLog.e("TbsDownload", "[TbsApkDownloader.backupApkPath] Exception is " + paramContext.getMessage());
      return null;
    }
    return null;
  }
  
  public static void gj(Context paramContext)
  {
    try
    {
      p.cov();
      File localFile = p.gM(paramContext);
      new File(localFile, "x5.tbs").delete();
      new File(localFile, "x5.tbs.temp").delete();
      paramContext = gh(paramContext);
      if (paramContext != null)
      {
        new File(paramContext, "x5.tbs.org").delete();
        new File(paramContext, "x5.oversea.tbs.org").delete();
      }
      return;
    }
    catch (Exception paramContext) {}
  }
  
  private static void h(Closeable paramCloseable)
  {
    if (paramCloseable != null) {}
    try
    {
      paramCloseable.close();
      return;
    }
    catch (IOException paramCloseable) {}
  }
  
  private static String i(Throwable paramThrowable)
  {
    String str = Log.getStackTraceString(paramThrowable);
    paramThrowable = str;
    if (str.length() > 1024) {
      paramThrowable = str.substring(0, 1024);
    }
    return paramThrowable;
  }
  
  private void j(int paramInt, String paramString, boolean paramBoolean)
  {
    if ((paramBoolean) || (this.hiz > this.xUR))
    {
      this.xUL.setErrorCode(paramInt);
      this.xUL.Yk(paramString);
    }
  }
  
  private void mY(boolean paramBoolean)
  {
    u.hC(this.mContext);
    Object localObject2 = k.gl(this.mContext);
    ((k)localObject2).xVh.put("request_full_package", Boolean.valueOf(false));
    ((k)localObject2).xVh.put("tbs_needdownload", Boolean.valueOf(false));
    ((k)localObject2).xVh.put("tbs_download_interrupt_code_reason", Integer.valueOf(-123));
    ((k)localObject2).commit();
    Object localObject1 = QbSdk.xUb;
    File localFile;
    label172:
    int j;
    if (paramBoolean)
    {
      i = 100;
      ((q)localObject1).jA(i);
      i = ((k)localObject2).xVi.getInt("tbs_responsecode", 0);
      k.gl(this.mContext).xVi.getInt("tbs_downloaddecouplecore", 0);
      if ((i != 3) && (i <= 10000)) {
        break label371;
      }
      localFile = gh(this.mContext);
      if (localFile == null) {
        break label343;
      }
      if (!l.gp(this.mContext)) {
        break label330;
      }
      localObject1 = "x5.oversea.tbs.org";
      localFile = new File(localFile, (String)localObject1);
      j = a.c(this.mContext, localFile);
      localObject1 = new File(this.xUE, "x5.tbs");
      if (!((File)localObject1).exists()) {
        break label337;
      }
    }
    label330:
    label337:
    for (localObject1 = ((File)localObject1).getAbsolutePath();; localObject1 = null)
    {
      int k = ((k)localObject2).xVi.getInt("tbs_download_version", 0);
      localObject2 = new Bundle();
      ((Bundle)localObject2).putInt("operation", i);
      ((Bundle)localObject2).putInt("old_core_ver", j);
      ((Bundle)localObject2).putInt("new_core_ver", k);
      ((Bundle)localObject2).putString("old_apk_location", localFile.getAbsolutePath());
      ((Bundle)localObject2).putString("new_apk_location", (String)localObject1);
      ((Bundle)localObject2).putString("diff_file_location", (String)localObject1);
      p.cov().f(this.mContext, (Bundle)localObject2);
      return;
      i = 120;
      break;
      localObject1 = "x5.tbs.org";
      break label172;
    }
    label343:
    clearCache();
    ((k)localObject2).xVh.put("tbs_needdownload", Boolean.valueOf(true));
    ((k)localObject2).commit();
    return;
    label371:
    int i = ((k)localObject2).xVi.getInt("tbs_download_version", 0);
    p.cov();
    p.q(this.mContext, new File(this.xUE, "x5.tbs").getAbsolutePath(), i);
    a(new File(this.xUE, "x5.tbs"), this.mContext);
  }
  
  private boolean mZ(boolean paramBoolean)
  {
    TbsLog.i("TbsDownload", "[TbsApkDownloader.deleteFile] isApk=" + paramBoolean);
    if (paramBoolean) {}
    for (File localFile = new File(this.xUE, "x5.tbs"); localFile.exists(); localFile = new File(this.xUE, "x5.tbs.temp")) {
      return localFile.delete();
    }
    return true;
  }
  
  /* Error */
  public final void P(boolean paramBoolean1, boolean paramBoolean2)
  {
    // Byte code:
    //   0: invokestatic 133	com/tencent/smtt/sdk/p:cov	()Lcom/tencent/smtt/sdk/p;
    //   3: aload_0
    //   4: getfield 90	com/tencent/smtt/sdk/h:mContext	Landroid/content/Context;
    //   7: invokevirtual 593	com/tencent/smtt/sdk/p:gt	(Landroid/content/Context;)Z
    //   10: ifeq +25 -> 35
    //   13: iload_1
    //   14: ifne +21 -> 35
    //   17: iconst_0
    //   18: putstatic 596	com/tencent/smtt/sdk/l:xVq	Z
    //   21: aload_0
    //   22: getfield 90	com/tencent/smtt/sdk/h:mContext	Landroid/content/Context;
    //   25: invokestatic 226	com/tencent/smtt/sdk/k:gl	(Landroid/content/Context;)Lcom/tencent/smtt/sdk/k;
    //   28: sipush 65214
    //   31: invokevirtual 599	com/tencent/smtt/sdk/k:Ff	(I)V
    //   34: return
    //   35: aload_0
    //   36: getfield 90	com/tencent/smtt/sdk/h:mContext	Landroid/content/Context;
    //   39: invokestatic 226	com/tencent/smtt/sdk/k:gl	(Landroid/content/Context;)Lcom/tencent/smtt/sdk/k;
    //   42: getfield 230	com/tencent/smtt/sdk/k:xVi	Landroid/content/SharedPreferences;
    //   45: ldc_w 544
    //   48: iconst_0
    //   49: invokeinterface 290 3 0
    //   54: istore_3
    //   55: iload_3
    //   56: iconst_1
    //   57: if_icmpeq +13 -> 70
    //   60: iload_3
    //   61: iconst_2
    //   62: if_icmpeq +8 -> 70
    //   65: iload_3
    //   66: iconst_4
    //   67: if_icmpne +24 -> 91
    //   70: iconst_1
    //   71: istore 5
    //   73: iload_2
    //   74: ifne +23 -> 97
    //   77: aload_0
    //   78: iload 5
    //   80: invokevirtual 602	com/tencent/smtt/sdk/h:mX	(Z)Z
    //   83: ifeq +14 -> 97
    //   86: iconst_0
    //   87: putstatic 596	com/tencent/smtt/sdk/l:xVq	Z
    //   90: return
    //   91: iconst_0
    //   92: istore 5
    //   94: goto -21 -> 73
    //   97: aload_0
    //   98: iload_1
    //   99: putfield 604	com/tencent/smtt/sdk/h:xUS	Z
    //   102: aload_0
    //   103: aload_0
    //   104: getfield 90	com/tencent/smtt/sdk/h:mContext	Landroid/content/Context;
    //   107: invokestatic 226	com/tencent/smtt/sdk/k:gl	(Landroid/content/Context;)Lcom/tencent/smtt/sdk/k;
    //   110: getfield 230	com/tencent/smtt/sdk/k:xVi	Landroid/content/SharedPreferences;
    //   113: ldc_w 606
    //   116: aconst_null
    //   117: invokeinterface 238 3 0
    //   122: putfield 608	com/tencent/smtt/sdk/h:mDownloadUrl	Ljava/lang/String;
    //   125: aload_0
    //   126: getfield 90	com/tencent/smtt/sdk/h:mContext	Landroid/content/Context;
    //   129: invokestatic 226	com/tencent/smtt/sdk/k:gl	(Landroid/content/Context;)Lcom/tencent/smtt/sdk/k;
    //   132: getfield 230	com/tencent/smtt/sdk/k:xVi	Landroid/content/SharedPreferences;
    //   135: ldc_w 610
    //   138: aconst_null
    //   139: invokeinterface 238 3 0
    //   144: astore 27
    //   146: ldc -65
    //   148: new 109	java/lang/StringBuilder
    //   151: dup
    //   152: ldc_w 612
    //   155: invokespecial 114	java/lang/StringBuilder:<init>	(Ljava/lang/String;)V
    //   158: aload 27
    //   160: invokevirtual 122	java/lang/StringBuilder:append	(Ljava/lang/String;)Ljava/lang/StringBuilder;
    //   163: invokevirtual 125	java/lang/StringBuilder:toString	()Ljava/lang/String;
    //   166: iconst_1
    //   167: invokestatic 615	com/tencent/smtt/utils/TbsLog:i	(Ljava/lang/String;Ljava/lang/String;Z)V
    //   170: aload_0
    //   171: aconst_null
    //   172: putfield 80	com/tencent/smtt/sdk/h:xUU	[Ljava/lang/String;
    //   175: aload_0
    //   176: iconst_0
    //   177: putfield 82	com/tencent/smtt/sdk/h:xUV	I
    //   180: iload_1
    //   181: ifne +37 -> 218
    //   184: aload 27
    //   186: ifnull +32 -> 218
    //   189: ldc_w 446
    //   192: aload 27
    //   194: invokevirtual 618	java/lang/String:trim	()Ljava/lang/String;
    //   197: invokevirtual 246	java/lang/String:equals	(Ljava/lang/Object;)Z
    //   200: ifne +18 -> 218
    //   203: aload_0
    //   204: aload 27
    //   206: invokevirtual 618	java/lang/String:trim	()Ljava/lang/String;
    //   209: ldc_w 620
    //   212: invokevirtual 624	java/lang/String:split	(Ljava/lang/String;)[Ljava/lang/String;
    //   215: putfield 80	com/tencent/smtt/sdk/h:xUU	[Ljava/lang/String;
    //   218: ldc -65
    //   220: new 109	java/lang/StringBuilder
    //   223: dup
    //   224: ldc_w 626
    //   227: invokespecial 114	java/lang/StringBuilder:<init>	(Ljava/lang/String;)V
    //   230: aload_0
    //   231: getfield 608	com/tencent/smtt/sdk/h:mDownloadUrl	Ljava/lang/String;
    //   234: invokevirtual 122	java/lang/StringBuilder:append	(Ljava/lang/String;)Ljava/lang/StringBuilder;
    //   237: ldc_w 628
    //   240: invokevirtual 122	java/lang/StringBuilder:append	(Ljava/lang/String;)Ljava/lang/StringBuilder;
    //   243: aload 27
    //   245: invokevirtual 122	java/lang/StringBuilder:append	(Ljava/lang/String;)Ljava/lang/StringBuilder;
    //   248: ldc_w 630
    //   251: invokevirtual 122	java/lang/StringBuilder:append	(Ljava/lang/String;)Ljava/lang/StringBuilder;
    //   254: aload_0
    //   255: getfield 369	com/tencent/smtt/sdk/h:xUD	Ljava/lang/String;
    //   258: invokevirtual 122	java/lang/StringBuilder:append	(Ljava/lang/String;)Ljava/lang/StringBuilder;
    //   261: ldc_w 632
    //   264: invokevirtual 122	java/lang/StringBuilder:append	(Ljava/lang/String;)Ljava/lang/StringBuilder;
    //   267: aload_0
    //   268: getfield 373	com/tencent/smtt/sdk/h:Lv	Z
    //   271: invokevirtual 215	java/lang/StringBuilder:append	(Z)Ljava/lang/StringBuilder;
    //   274: ldc_w 634
    //   277: invokevirtual 122	java/lang/StringBuilder:append	(Ljava/lang/String;)Ljava/lang/StringBuilder;
    //   280: aload_0
    //   281: getfield 636	com/tencent/smtt/sdk/h:xUJ	Ljava/net/HttpURLConnection;
    //   284: invokevirtual 318	java/lang/StringBuilder:append	(Ljava/lang/Object;)Ljava/lang/StringBuilder;
    //   287: invokevirtual 125	java/lang/StringBuilder:toString	()Ljava/lang/String;
    //   290: invokestatic 198	com/tencent/smtt/utils/TbsLog:i	(Ljava/lang/String;Ljava/lang/String;)V
    //   293: aload_0
    //   294: getfield 608	com/tencent/smtt/sdk/h:mDownloadUrl	Ljava/lang/String;
    //   297: ifnonnull +34 -> 331
    //   300: aload_0
    //   301: getfield 369	com/tencent/smtt/sdk/h:xUD	Ljava/lang/String;
    //   304: ifnonnull +27 -> 331
    //   307: getstatic 537	com/tencent/smtt/sdk/QbSdk:xUb	Lcom/tencent/smtt/sdk/q;
    //   310: bipush 110
    //   312: invokeinterface 542 2 0
    //   317: aload_0
    //   318: getfield 90	com/tencent/smtt/sdk/h:mContext	Landroid/content/Context;
    //   321: invokestatic 226	com/tencent/smtt/sdk/k:gl	(Landroid/content/Context;)Lcom/tencent/smtt/sdk/k;
    //   324: sipush 65234
    //   327: invokevirtual 599	com/tencent/smtt/sdk/k:Ff	(I)V
    //   330: return
    //   331: aload_0
    //   332: getfield 636	com/tencent/smtt/sdk/h:xUJ	Ljava/net/HttpURLConnection;
    //   335: ifnull +34 -> 369
    //   338: aload_0
    //   339: getfield 373	com/tencent/smtt/sdk/h:Lv	Z
    //   342: ifne +27 -> 369
    //   345: getstatic 537	com/tencent/smtt/sdk/QbSdk:xUb	Lcom/tencent/smtt/sdk/q;
    //   348: bipush 110
    //   350: invokeinterface 542 2 0
    //   355: aload_0
    //   356: getfield 90	com/tencent/smtt/sdk/h:mContext	Landroid/content/Context;
    //   359: invokestatic 226	com/tencent/smtt/sdk/k:gl	(Landroid/content/Context;)Lcom/tencent/smtt/sdk/k;
    //   362: sipush 65233
    //   365: invokevirtual 599	com/tencent/smtt/sdk/k:Ff	(I)V
    //   368: return
    //   369: iload_1
    //   370: ifne +54 -> 424
    //   373: aload_0
    //   374: getfield 107	com/tencent/smtt/sdk/h:xUQ	Ljava/util/Set;
    //   377: aload_0
    //   378: getfield 90	com/tencent/smtt/sdk/h:mContext	Landroid/content/Context;
    //   381: invokestatic 642	com/tencent/smtt/utils/b:hp	(Landroid/content/Context;)Ljava/lang/String;
    //   384: invokeinterface 646 2 0
    //   389: ifeq +35 -> 424
    //   392: ldc -65
    //   394: ldc_w 648
    //   397: invokestatic 198	com/tencent/smtt/utils/TbsLog:i	(Ljava/lang/String;Ljava/lang/String;)V
    //   400: getstatic 537	com/tencent/smtt/sdk/QbSdk:xUb	Lcom/tencent/smtt/sdk/q;
    //   403: bipush 110
    //   405: invokeinterface 542 2 0
    //   410: aload_0
    //   411: getfield 90	com/tencent/smtt/sdk/h:mContext	Landroid/content/Context;
    //   414: invokestatic 226	com/tencent/smtt/sdk/k:gl	(Landroid/content/Context;)Lcom/tencent/smtt/sdk/k;
    //   417: sipush 65232
    //   420: invokevirtual 599	com/tencent/smtt/sdk/k:Ff	(I)V
    //   423: return
    //   424: aload_0
    //   425: invokespecial 147	com/tencent/smtt/sdk/h:cnT	()V
    //   428: ldc -65
    //   430: ldc_w 650
    //   433: iconst_1
    //   434: invokestatic 615	com/tencent/smtt/utils/TbsLog:i	(Ljava/lang/String;Ljava/lang/String;Z)V
    //   437: aload_0
    //   438: getfield 90	com/tencent/smtt/sdk/h:mContext	Landroid/content/Context;
    //   441: invokestatic 226	com/tencent/smtt/sdk/k:gl	(Landroid/content/Context;)Lcom/tencent/smtt/sdk/k;
    //   444: invokevirtual 653	com/tencent/smtt/sdk/k:cod	()J
    //   447: lstore 25
    //   449: iconst_0
    //   450: istore_2
    //   451: aload_0
    //   452: getfield 90	com/tencent/smtt/sdk/h:mContext	Landroid/content/Context;
    //   455: invokestatic 226	com/tencent/smtt/sdk/k:gl	(Landroid/content/Context;)Lcom/tencent/smtt/sdk/k;
    //   458: getfield 230	com/tencent/smtt/sdk/k:xVi	Landroid/content/SharedPreferences;
    //   461: ldc_w 655
    //   464: lconst_0
    //   465: invokeinterface 265 4 0
    //   470: lstore 9
    //   472: iload_1
    //   473: ifeq +525 -> 998
    //   476: aload_0
    //   477: getstatic 53	com/tencent/smtt/sdk/h:xUA	I
    //   480: putfield 78	com/tencent/smtt/sdk/h:xUR	I
    //   483: iconst_0
    //   484: istore_2
    //   485: iload 5
    //   487: istore 8
    //   489: iload_2
    //   490: istore 5
    //   492: aload_0
    //   493: getfield 361	com/tencent/smtt/sdk/h:hiz	I
    //   496: aload_0
    //   497: getfield 78	com/tencent/smtt/sdk/h:xUR	I
    //   500: if_icmpgt +36 -> 536
    //   503: aload_0
    //   504: getfield 363	com/tencent/smtt/sdk/h:xUI	I
    //   507: bipush 8
    //   509: if_icmple +521 -> 1030
    //   512: aload_0
    //   513: bipush 123
    //   515: aconst_null
    //   516: iconst_1
    //   517: invokespecial 340	com/tencent/smtt/sdk/h:j	(ILjava/lang/String;Z)V
    //   520: aload_0
    //   521: getfield 90	com/tencent/smtt/sdk/h:mContext	Landroid/content/Context;
    //   524: invokestatic 226	com/tencent/smtt/sdk/k:gl	(Landroid/content/Context;)Lcom/tencent/smtt/sdk/k;
    //   527: sipush 65230
    //   530: invokevirtual 599	com/tencent/smtt/sdk/k:Ff	(I)V
    //   533: iload_2
    //   534: istore 5
    //   536: aload_0
    //   537: getfield 373	com/tencent/smtt/sdk/h:Lv	Z
    //   540: ifne +183 -> 723
    //   543: iload 5
    //   545: istore_1
    //   546: aload_0
    //   547: getfield 375	com/tencent/smtt/sdk/h:mFinished	Z
    //   550: ifeq +102 -> 652
    //   553: iload 5
    //   555: istore_1
    //   556: aload_0
    //   557: getfield 80	com/tencent/smtt/sdk/h:xUU	[Ljava/lang/String;
    //   560: ifnonnull +19 -> 579
    //   563: iload 5
    //   565: istore_1
    //   566: iload 5
    //   568: ifne +11 -> 579
    //   571: aload_0
    //   572: iconst_1
    //   573: iload 8
    //   575: invokespecial 657	com/tencent/smtt/sdk/h:Q	(ZZ)Z
    //   578: istore_1
    //   579: aload_0
    //   580: getfield 102	com/tencent/smtt/sdk/h:xUL	Lcom/tencent/smtt/sdk/r$b;
    //   583: astore 27
    //   585: iload_1
    //   586: ifeq +6045 -> 6631
    //   589: iconst_1
    //   590: istore_3
    //   591: aload 27
    //   593: iload_3
    //   594: putfield 660	com/tencent/smtt/sdk/r$b:xWn	I
    //   597: iload 8
    //   599: ifne +6042 -> 6641
    //   602: aload_0
    //   603: getfield 102	com/tencent/smtt/sdk/h:xUL	Lcom/tencent/smtt/sdk/r$b;
    //   606: astore 27
    //   608: iload_1
    //   609: ifeq +6027 -> 6636
    //   612: iconst_1
    //   613: istore_3
    //   614: aload 27
    //   616: iload_3
    //   617: putfield 663	com/tencent/smtt/sdk/r$b:xWl	I
    //   620: iload_1
    //   621: ifeq +6031 -> 6652
    //   624: aload_0
    //   625: iconst_1
    //   626: invokespecial 665	com/tencent/smtt/sdk/h:mY	(Z)V
    //   629: aload_0
    //   630: getfield 90	com/tencent/smtt/sdk/h:mContext	Landroid/content/Context;
    //   633: invokestatic 226	com/tencent/smtt/sdk/k:gl	(Landroid/content/Context;)Lcom/tencent/smtt/sdk/k;
    //   636: sipush 65219
    //   639: invokevirtual 599	com/tencent/smtt/sdk/k:Ff	(I)V
    //   642: aload_0
    //   643: bipush 100
    //   645: ldc_w 667
    //   648: iconst_1
    //   649: invokespecial 340	com/tencent/smtt/sdk/h:j	(ILjava/lang/String;Z)V
    //   652: aload_0
    //   653: getfield 90	com/tencent/smtt/sdk/h:mContext	Landroid/content/Context;
    //   656: invokestatic 226	com/tencent/smtt/sdk/k:gl	(Landroid/content/Context;)Lcom/tencent/smtt/sdk/k;
    //   659: astore 27
    //   661: iload_1
    //   662: ifeq +6012 -> 6674
    //   665: aload 27
    //   667: getfield 230	com/tencent/smtt/sdk/k:xVi	Landroid/content/SharedPreferences;
    //   670: ldc_w 669
    //   673: iconst_0
    //   674: invokeinterface 290 3 0
    //   679: istore_3
    //   680: aload 27
    //   682: getfield 511	com/tencent/smtt/sdk/k:xVh	Ljava/util/Map;
    //   685: ldc_w 669
    //   688: iload_3
    //   689: iconst_1
    //   690: iadd
    //   691: invokestatic 327	java/lang/Integer:valueOf	(I)Ljava/lang/Integer;
    //   694: invokeinterface 524 3 0
    //   699: pop
    //   700: aload 27
    //   702: invokevirtual 531	com/tencent/smtt/sdk/k:commit	()V
    //   705: aload_0
    //   706: getfield 102	com/tencent/smtt/sdk/h:xUL	Lcom/tencent/smtt/sdk/r$b;
    //   709: astore 27
    //   711: iload_1
    //   712: ifeq +6023 -> 6735
    //   715: iconst_1
    //   716: istore_3
    //   717: aload 27
    //   719: iload_3
    //   720: putfield 672	com/tencent/smtt/sdk/r$b:xWq	I
    //   723: ldc -65
    //   725: ldc_w 674
    //   728: invokestatic 198	com/tencent/smtt/utils/TbsLog:i	(Ljava/lang/String;Ljava/lang/String;)V
    //   731: aload_0
    //   732: getfield 636	com/tencent/smtt/sdk/h:xUJ	Ljava/net/HttpURLConnection;
    //   735: ifnull +39 -> 774
    //   738: aload_0
    //   739: getfield 373	com/tencent/smtt/sdk/h:Lv	Z
    //   742: ifne +20 -> 762
    //   745: aload_0
    //   746: getfield 102	com/tencent/smtt/sdk/h:xUL	Lcom/tencent/smtt/sdk/r$b;
    //   749: aload_0
    //   750: getfield 636	com/tencent/smtt/sdk/h:xUJ	Ljava/net/HttpURLConnection;
    //   753: invokevirtual 680	java/net/HttpURLConnection:getURL	()Ljava/net/URL;
    //   756: invokestatic 682	com/tencent/smtt/sdk/h:d	(Ljava/net/URL;)Ljava/lang/String;
    //   759: putfield 685	com/tencent/smtt/sdk/r$b:xWj	Ljava/lang/String;
    //   762: aload_0
    //   763: getfield 636	com/tencent/smtt/sdk/h:xUJ	Ljava/net/HttpURLConnection;
    //   766: invokevirtual 688	java/net/HttpURLConnection:disconnect	()V
    //   769: aload_0
    //   770: aconst_null
    //   771: putfield 636	com/tencent/smtt/sdk/h:xUJ	Ljava/net/HttpURLConnection;
    //   774: aload_0
    //   775: getfield 102	com/tencent/smtt/sdk/h:xUL	Lcom/tencent/smtt/sdk/r$b;
    //   778: getfield 691	com/tencent/smtt/sdk/r$b:mErrorCode	I
    //   781: istore_3
    //   782: aload_0
    //   783: getfield 373	com/tencent/smtt/sdk/h:Lv	Z
    //   786: ifne +6022 -> 6808
    //   789: aload_0
    //   790: getfield 377	com/tencent/smtt/sdk/h:xUO	Z
    //   793: ifeq +6015 -> 6808
    //   796: aload_0
    //   797: getfield 102	com/tencent/smtt/sdk/h:xUL	Lcom/tencent/smtt/sdk/r$b;
    //   800: invokestatic 696	java/lang/System:currentTimeMillis	()J
    //   803: putfield 699	com/tencent/smtt/sdk/r$b:xWh	J
    //   806: aload_0
    //   807: getfield 90	com/tencent/smtt/sdk/h:mContext	Landroid/content/Context;
    //   810: invokestatic 702	com/tencent/smtt/utils/b:hn	(Landroid/content/Context;)Ljava/lang/String;
    //   813: astore 28
    //   815: aload 28
    //   817: astore 27
    //   819: aload 28
    //   821: ifnonnull +8 -> 829
    //   824: ldc_w 446
    //   827: astore 27
    //   829: aload_0
    //   830: getfield 90	com/tencent/smtt/sdk/h:mContext	Landroid/content/Context;
    //   833: invokestatic 706	com/tencent/smtt/utils/b:ho	(Landroid/content/Context;)I
    //   836: istore 4
    //   838: aload_0
    //   839: getfield 102	com/tencent/smtt/sdk/h:xUL	Lcom/tencent/smtt/sdk/r$b;
    //   842: aload 27
    //   844: putfield 709	com/tencent/smtt/sdk/r$b:xWo	Ljava/lang/String;
    //   847: aload_0
    //   848: getfield 102	com/tencent/smtt/sdk/h:xUL	Lcom/tencent/smtt/sdk/r$b;
    //   851: iload 4
    //   853: putfield 712	com/tencent/smtt/sdk/r$b:xWp	I
    //   856: iload 4
    //   858: aload_0
    //   859: getfield 151	com/tencent/smtt/sdk/h:xUN	I
    //   862: if_icmpne +15 -> 877
    //   865: aload 27
    //   867: aload_0
    //   868: getfield 149	com/tencent/smtt/sdk/h:xUM	Ljava/lang/String;
    //   871: invokevirtual 246	java/lang/String:equals	(Ljava/lang/Object;)Z
    //   874: ifne +11 -> 885
    //   877: aload_0
    //   878: getfield 102	com/tencent/smtt/sdk/h:xUL	Lcom/tencent/smtt/sdk/r$b;
    //   881: iconst_0
    //   882: putfield 715	com/tencent/smtt/sdk/r$b:xWt	I
    //   885: aload_0
    //   886: getfield 102	com/tencent/smtt/sdk/h:xUL	Lcom/tencent/smtt/sdk/r$b;
    //   889: getfield 691	com/tencent/smtt/sdk/r$b:mErrorCode	I
    //   892: ifeq +15 -> 907
    //   895: aload_0
    //   896: getfield 102	com/tencent/smtt/sdk/h:xUL	Lcom/tencent/smtt/sdk/r$b;
    //   899: getfield 691	com/tencent/smtt/sdk/r$b:mErrorCode	I
    //   902: bipush 107
    //   904: if_icmpne +31 -> 935
    //   907: aload_0
    //   908: getfield 102	com/tencent/smtt/sdk/h:xUL	Lcom/tencent/smtt/sdk/r$b;
    //   911: getfield 672	com/tencent/smtt/sdk/r$b:xWq	I
    //   914: ifne +21 -> 935
    //   917: aload_0
    //   918: getfield 90	com/tencent/smtt/sdk/h:mContext	Landroid/content/Context;
    //   921: invokestatic 718	com/tencent/smtt/utils/b:isNetworkAvailable	(Landroid/content/Context;)Z
    //   924: ifne +5847 -> 6771
    //   927: aload_0
    //   928: bipush 101
    //   930: aconst_null
    //   931: iconst_1
    //   932: invokespecial 340	com/tencent/smtt/sdk/h:j	(ILjava/lang/String;Z)V
    //   935: aload_0
    //   936: getfield 90	com/tencent/smtt/sdk/h:mContext	Landroid/content/Context;
    //   939: invokestatic 226	com/tencent/smtt/sdk/k:gl	(Landroid/content/Context;)Lcom/tencent/smtt/sdk/k;
    //   942: getfield 230	com/tencent/smtt/sdk/k:xVi	Landroid/content/SharedPreferences;
    //   945: ldc_w 546
    //   948: iconst_0
    //   949: invokeinterface 290 3 0
    //   954: iconst_1
    //   955: if_icmpne +5833 -> 6788
    //   958: aload_0
    //   959: getfield 90	com/tencent/smtt/sdk/h:mContext	Landroid/content/Context;
    //   962: invokestatic 96	com/tencent/smtt/sdk/r:gR	(Landroid/content/Context;)Lcom/tencent/smtt/sdk/r;
    //   965: getstatic 724	com/tencent/smtt/sdk/r$a:xWd	Lcom/tencent/smtt/sdk/r$a;
    //   968: aload_0
    //   969: getfield 102	com/tencent/smtt/sdk/h:xUL	Lcom/tencent/smtt/sdk/r$b;
    //   972: invokevirtual 727	com/tencent/smtt/sdk/r:a	(Lcom/tencent/smtt/sdk/r$a;Lcom/tencent/smtt/sdk/r$b;)V
    //   975: aload_0
    //   976: getfield 102	com/tencent/smtt/sdk/h:xUL	Lcom/tencent/smtt/sdk/r$b;
    //   979: invokevirtual 728	com/tencent/smtt/sdk/r$b:cnT	()V
    //   982: iload_3
    //   983: bipush 100
    //   985: if_icmpeq -951 -> 34
    //   988: getstatic 537	com/tencent/smtt/sdk/QbSdk:xUb	Lcom/tencent/smtt/sdk/q;
    //   991: iload_3
    //   992: invokeinterface 542 2 0
    //   997: return
    //   998: aload_0
    //   999: getstatic 51	com/tencent/smtt/sdk/h:xUz	I
    //   1002: putfield 78	com/tencent/smtt/sdk/h:xUR	I
    //   1005: iload 5
    //   1007: istore 6
    //   1009: iload_2
    //   1010: istore 5
    //   1012: lload 9
    //   1014: lstore 11
    //   1016: iload 5
    //   1018: istore_2
    //   1019: lload 11
    //   1021: lstore 9
    //   1023: iload 6
    //   1025: istore 8
    //   1027: goto -538 -> 489
    //   1030: invokestatic 696	java/lang/System:currentTimeMillis	()J
    //   1033: lstore 23
    //   1035: iload_1
    //   1036: ifne +379 -> 1415
    //   1039: lload 9
    //   1041: lstore 11
    //   1043: lload 23
    //   1045: aload_0
    //   1046: getfield 90	com/tencent/smtt/sdk/h:mContext	Landroid/content/Context;
    //   1049: invokestatic 226	com/tencent/smtt/sdk/k:gl	(Landroid/content/Context;)Lcom/tencent/smtt/sdk/k;
    //   1052: getfield 230	com/tencent/smtt/sdk/k:xVi	Landroid/content/SharedPreferences;
    //   1055: ldc_w 730
    //   1058: lconst_0
    //   1059: invokeinterface 265 4 0
    //   1064: lsub
    //   1065: ldc2_w 731
    //   1068: lcmp
    //   1069: ifle +222 -> 1291
    //   1072: lload 9
    //   1074: lstore 11
    //   1076: ldc -65
    //   1078: ldc_w 734
    //   1081: invokestatic 198	com/tencent/smtt/utils/TbsLog:i	(Ljava/lang/String;Ljava/lang/String;)V
    //   1084: lload 9
    //   1086: lstore 11
    //   1088: aload_0
    //   1089: getfield 90	com/tencent/smtt/sdk/h:mContext	Landroid/content/Context;
    //   1092: invokestatic 226	com/tencent/smtt/sdk/k:gl	(Landroid/content/Context;)Lcom/tencent/smtt/sdk/k;
    //   1095: getfield 511	com/tencent/smtt/sdk/k:xVh	Ljava/util/Map;
    //   1098: ldc_w 730
    //   1101: lload 23
    //   1103: invokestatic 739	java/lang/Long:valueOf	(J)Ljava/lang/Long;
    //   1106: invokeinterface 524 3 0
    //   1111: pop
    //   1112: lload 9
    //   1114: lstore 11
    //   1116: aload_0
    //   1117: getfield 90	com/tencent/smtt/sdk/h:mContext	Landroid/content/Context;
    //   1120: invokestatic 226	com/tencent/smtt/sdk/k:gl	(Landroid/content/Context;)Lcom/tencent/smtt/sdk/k;
    //   1123: getfield 511	com/tencent/smtt/sdk/k:xVh	Ljava/util/Map;
    //   1126: ldc_w 655
    //   1129: lconst_0
    //   1130: invokestatic 739	java/lang/Long:valueOf	(J)Ljava/lang/Long;
    //   1133: invokeinterface 524 3 0
    //   1138: pop
    //   1139: lload 9
    //   1141: lstore 11
    //   1143: aload_0
    //   1144: getfield 90	com/tencent/smtt/sdk/h:mContext	Landroid/content/Context;
    //   1147: invokestatic 226	com/tencent/smtt/sdk/k:gl	(Landroid/content/Context;)Lcom/tencent/smtt/sdk/k;
    //   1150: invokevirtual 531	com/tencent/smtt/sdk/k:commit	()V
    //   1153: lconst_0
    //   1154: lstore 15
    //   1156: lload 15
    //   1158: lstore 9
    //   1160: lload 15
    //   1162: lstore 11
    //   1164: iload_2
    //   1165: istore 5
    //   1167: lload 15
    //   1169: lstore 13
    //   1171: aload_0
    //   1172: getfield 90	com/tencent/smtt/sdk/h:mContext	Landroid/content/Context;
    //   1175: invokestatic 742	com/tencent/smtt/utils/f:hv	(Landroid/content/Context;)Z
    //   1178: ifne +237 -> 1415
    //   1181: lload 15
    //   1183: lstore 11
    //   1185: iload_2
    //   1186: istore 5
    //   1188: lload 15
    //   1190: lstore 13
    //   1192: ldc -65
    //   1194: ldc_w 744
    //   1197: iconst_1
    //   1198: invokestatic 615	com/tencent/smtt/utils/TbsLog:i	(Ljava/lang/String;Ljava/lang/String;Z)V
    //   1201: lload 15
    //   1203: lstore 11
    //   1205: iload_2
    //   1206: istore 5
    //   1208: lload 15
    //   1210: lstore 13
    //   1212: aload_0
    //   1213: bipush 105
    //   1215: aconst_null
    //   1216: iconst_1
    //   1217: invokespecial 340	com/tencent/smtt/sdk/h:j	(ILjava/lang/String;Z)V
    //   1220: lload 15
    //   1222: lstore 11
    //   1224: iload_2
    //   1225: istore 5
    //   1227: lload 15
    //   1229: lstore 13
    //   1231: aload_0
    //   1232: getfield 90	com/tencent/smtt/sdk/h:mContext	Landroid/content/Context;
    //   1235: invokestatic 226	com/tencent/smtt/sdk/k:gl	(Landroid/content/Context;)Lcom/tencent/smtt/sdk/k;
    //   1238: sipush 65228
    //   1241: invokevirtual 599	com/tencent/smtt/sdk/k:Ff	(I)V
    //   1244: iload_2
    //   1245: istore 5
    //   1247: iload_1
    //   1248: ifne -712 -> 536
    //   1251: aload_0
    //   1252: getfield 90	com/tencent/smtt/sdk/h:mContext	Landroid/content/Context;
    //   1255: invokestatic 226	com/tencent/smtt/sdk/k:gl	(Landroid/content/Context;)Lcom/tencent/smtt/sdk/k;
    //   1258: getfield 511	com/tencent/smtt/sdk/k:xVh	Ljava/util/Map;
    //   1261: ldc_w 655
    //   1264: lload 15
    //   1266: invokestatic 739	java/lang/Long:valueOf	(J)Ljava/lang/Long;
    //   1269: invokeinterface 524 3 0
    //   1274: pop
    //   1275: aload_0
    //   1276: getfield 90	com/tencent/smtt/sdk/h:mContext	Landroid/content/Context;
    //   1279: invokestatic 226	com/tencent/smtt/sdk/k:gl	(Landroid/content/Context;)Lcom/tencent/smtt/sdk/k;
    //   1282: invokevirtual 531	com/tencent/smtt/sdk/k:commit	()V
    //   1285: iload_2
    //   1286: istore 5
    //   1288: goto -752 -> 536
    //   1291: lload 9
    //   1293: lstore 11
    //   1295: ldc -65
    //   1297: new 109	java/lang/StringBuilder
    //   1300: dup
    //   1301: ldc_w 746
    //   1304: invokespecial 114	java/lang/StringBuilder:<init>	(Ljava/lang/String;)V
    //   1307: lload 9
    //   1309: invokevirtual 276	java/lang/StringBuilder:append	(J)Ljava/lang/StringBuilder;
    //   1312: invokevirtual 125	java/lang/StringBuilder:toString	()Ljava/lang/String;
    //   1315: invokestatic 198	com/tencent/smtt/utils/TbsLog:i	(Ljava/lang/String;Ljava/lang/String;)V
    //   1318: lload 9
    //   1320: lload 25
    //   1322: lcmp
    //   1323: iflt +5662 -> 6985
    //   1326: lload 9
    //   1328: lstore 11
    //   1330: ldc -65
    //   1332: ldc_w 748
    //   1335: iconst_1
    //   1336: invokestatic 615	com/tencent/smtt/utils/TbsLog:i	(Ljava/lang/String;Ljava/lang/String;Z)V
    //   1339: lload 9
    //   1341: lstore 11
    //   1343: aload_0
    //   1344: bipush 112
    //   1346: aconst_null
    //   1347: iconst_1
    //   1348: invokespecial 340	com/tencent/smtt/sdk/h:j	(ILjava/lang/String;Z)V
    //   1351: lload 9
    //   1353: lstore 11
    //   1355: aload_0
    //   1356: getfield 90	com/tencent/smtt/sdk/h:mContext	Landroid/content/Context;
    //   1359: invokestatic 226	com/tencent/smtt/sdk/k:gl	(Landroid/content/Context;)Lcom/tencent/smtt/sdk/k;
    //   1362: sipush 65229
    //   1365: invokevirtual 599	com/tencent/smtt/sdk/k:Ff	(I)V
    //   1368: iload_2
    //   1369: istore 5
    //   1371: iload_1
    //   1372: ifne -836 -> 536
    //   1375: aload_0
    //   1376: getfield 90	com/tencent/smtt/sdk/h:mContext	Landroid/content/Context;
    //   1379: invokestatic 226	com/tencent/smtt/sdk/k:gl	(Landroid/content/Context;)Lcom/tencent/smtt/sdk/k;
    //   1382: getfield 511	com/tencent/smtt/sdk/k:xVh	Ljava/util/Map;
    //   1385: ldc_w 655
    //   1388: lload 9
    //   1390: invokestatic 739	java/lang/Long:valueOf	(J)Ljava/lang/Long;
    //   1393: invokeinterface 524 3 0
    //   1398: pop
    //   1399: aload_0
    //   1400: getfield 90	com/tencent/smtt/sdk/h:mContext	Landroid/content/Context;
    //   1403: invokestatic 226	com/tencent/smtt/sdk/k:gl	(Landroid/content/Context;)Lcom/tencent/smtt/sdk/k;
    //   1406: invokevirtual 531	com/tencent/smtt/sdk/k:commit	()V
    //   1409: iload_2
    //   1410: istore 5
    //   1412: goto -876 -> 536
    //   1415: lload 9
    //   1417: lstore 11
    //   1419: iload_2
    //   1420: istore 5
    //   1422: lload 9
    //   1424: lstore 13
    //   1426: aload_0
    //   1427: iconst_1
    //   1428: putfield 377	com/tencent/smtt/sdk/h:xUO	Z
    //   1431: lload 9
    //   1433: lstore 11
    //   1435: iload_2
    //   1436: istore 5
    //   1438: lload 9
    //   1440: lstore 13
    //   1442: aload_0
    //   1443: getfield 369	com/tencent/smtt/sdk/h:xUD	Ljava/lang/String;
    //   1446: ifnull +1057 -> 2503
    //   1449: lload 9
    //   1451: lstore 11
    //   1453: iload_2
    //   1454: istore 5
    //   1456: lload 9
    //   1458: lstore 13
    //   1460: aload_0
    //   1461: getfield 369	com/tencent/smtt/sdk/h:xUD	Ljava/lang/String;
    //   1464: astore 27
    //   1466: lload 9
    //   1468: lstore 11
    //   1470: iload_2
    //   1471: istore 5
    //   1473: lload 9
    //   1475: lstore 13
    //   1477: ldc -65
    //   1479: new 109	java/lang/StringBuilder
    //   1482: dup
    //   1483: ldc_w 750
    //   1486: invokespecial 114	java/lang/StringBuilder:<init>	(Ljava/lang/String;)V
    //   1489: aload 27
    //   1491: invokevirtual 122	java/lang/StringBuilder:append	(Ljava/lang/String;)Ljava/lang/StringBuilder;
    //   1494: ldc_w 752
    //   1497: invokevirtual 122	java/lang/StringBuilder:append	(Ljava/lang/String;)Ljava/lang/StringBuilder;
    //   1500: aload_0
    //   1501: getfield 361	com/tencent/smtt/sdk/h:hiz	I
    //   1504: invokevirtual 297	java/lang/StringBuilder:append	(I)Ljava/lang/StringBuilder;
    //   1507: invokevirtual 125	java/lang/StringBuilder:toString	()Ljava/lang/String;
    //   1510: iconst_1
    //   1511: invokestatic 615	com/tencent/smtt/utils/TbsLog:i	(Ljava/lang/String;Ljava/lang/String;Z)V
    //   1514: lload 9
    //   1516: lstore 11
    //   1518: iload_2
    //   1519: istore 5
    //   1521: lload 9
    //   1523: lstore 13
    //   1525: aload 27
    //   1527: aload_0
    //   1528: getfield 754	com/tencent/smtt/sdk/h:xUC	Ljava/lang/String;
    //   1531: invokevirtual 246	java/lang/String:equals	(Ljava/lang/Object;)Z
    //   1534: ifne +57 -> 1591
    //   1537: lload 9
    //   1539: lstore 11
    //   1541: iload_2
    //   1542: istore 5
    //   1544: lload 9
    //   1546: lstore 13
    //   1548: aload_0
    //   1549: getfield 102	com/tencent/smtt/sdk/h:xUL	Lcom/tencent/smtt/sdk/r$b;
    //   1552: astore 28
    //   1554: lload 9
    //   1556: lstore 11
    //   1558: iload_2
    //   1559: istore 5
    //   1561: lload 9
    //   1563: lstore 13
    //   1565: aload 28
    //   1567: getfield 757	com/tencent/smtt/sdk/r$b:xWi	Ljava/lang/String;
    //   1570: ifnonnull +953 -> 2523
    //   1573: lload 9
    //   1575: lstore 11
    //   1577: iload_2
    //   1578: istore 5
    //   1580: lload 9
    //   1582: lstore 13
    //   1584: aload 28
    //   1586: aload 27
    //   1588: putfield 757	com/tencent/smtt/sdk/r$b:xWi	Ljava/lang/String;
    //   1591: lload 9
    //   1593: lstore 11
    //   1595: iload_2
    //   1596: istore 5
    //   1598: lload 9
    //   1600: lstore 13
    //   1602: aload_0
    //   1603: aload 27
    //   1605: putfield 754	com/tencent/smtt/sdk/h:xUC	Ljava/lang/String;
    //   1608: lload 9
    //   1610: lstore 11
    //   1612: iload_2
    //   1613: istore 5
    //   1615: lload 9
    //   1617: lstore 13
    //   1619: new 432	java/net/URL
    //   1622: dup
    //   1623: aload 27
    //   1625: invokespecial 758	java/net/URL:<init>	(Ljava/lang/String;)V
    //   1628: astore 27
    //   1630: lload 9
    //   1632: lstore 11
    //   1634: iload_2
    //   1635: istore 5
    //   1637: lload 9
    //   1639: lstore 13
    //   1641: aload_0
    //   1642: getfield 636	com/tencent/smtt/sdk/h:xUJ	Ljava/net/HttpURLConnection;
    //   1645: astore 28
    //   1647: aload 28
    //   1649: ifnull +14 -> 1663
    //   1652: lload 9
    //   1654: lstore 13
    //   1656: aload_0
    //   1657: getfield 636	com/tencent/smtt/sdk/h:xUJ	Ljava/net/HttpURLConnection;
    //   1660: invokevirtual 688	java/net/HttpURLConnection:disconnect	()V
    //   1663: lload 9
    //   1665: lstore 11
    //   1667: iload_2
    //   1668: istore 5
    //   1670: lload 9
    //   1672: lstore 13
    //   1674: aload_0
    //   1675: aload 27
    //   1677: invokevirtual 762	java/net/URL:openConnection	()Ljava/net/URLConnection;
    //   1680: checkcast 676	java/net/HttpURLConnection
    //   1683: putfield 636	com/tencent/smtt/sdk/h:xUJ	Ljava/net/HttpURLConnection;
    //   1686: lload 9
    //   1688: lstore 11
    //   1690: iload_2
    //   1691: istore 5
    //   1693: lload 9
    //   1695: lstore 13
    //   1697: aload_0
    //   1698: getfield 636	com/tencent/smtt/sdk/h:xUJ	Ljava/net/HttpURLConnection;
    //   1701: ldc_w 764
    //   1704: invokestatic 767	com/tencent/smtt/sdk/l:cor	()Ljava/lang/String;
    //   1707: invokevirtual 770	java/net/HttpURLConnection:setRequestProperty	(Ljava/lang/String;Ljava/lang/String;)V
    //   1710: lload 9
    //   1712: lstore 11
    //   1714: iload_2
    //   1715: istore 5
    //   1717: lload 9
    //   1719: lstore 13
    //   1721: aload_0
    //   1722: getfield 636	com/tencent/smtt/sdk/h:xUJ	Ljava/net/HttpURLConnection;
    //   1725: ldc_w 772
    //   1728: ldc_w 774
    //   1731: invokevirtual 770	java/net/HttpURLConnection:setRequestProperty	(Ljava/lang/String;Ljava/lang/String;)V
    //   1734: lload 9
    //   1736: lstore 11
    //   1738: iload_2
    //   1739: istore 5
    //   1741: lload 9
    //   1743: lstore 13
    //   1745: aload_0
    //   1746: getfield 636	com/tencent/smtt/sdk/h:xUJ	Ljava/net/HttpURLConnection;
    //   1749: ldc_w 776
    //   1752: invokevirtual 779	java/net/HttpURLConnection:setRequestMethod	(Ljava/lang/String;)V
    //   1755: lload 9
    //   1757: lstore 11
    //   1759: iload_2
    //   1760: istore 5
    //   1762: lload 9
    //   1764: lstore 13
    //   1766: aload_0
    //   1767: getfield 636	com/tencent/smtt/sdk/h:xUJ	Ljava/net/HttpURLConnection;
    //   1770: iconst_0
    //   1771: invokevirtual 782	java/net/HttpURLConnection:setInstanceFollowRedirects	(Z)V
    //   1774: lload 9
    //   1776: lstore 11
    //   1778: iload_2
    //   1779: istore 5
    //   1781: lload 9
    //   1783: lstore 13
    //   1785: aload_0
    //   1786: getfield 636	com/tencent/smtt/sdk/h:xUJ	Ljava/net/HttpURLConnection;
    //   1789: aload_0
    //   1790: getfield 76	com/tencent/smtt/sdk/h:xUG	I
    //   1793: invokevirtual 785	java/net/HttpURLConnection:setConnectTimeout	(I)V
    //   1796: lload 9
    //   1798: lstore 11
    //   1800: iload_2
    //   1801: istore 5
    //   1803: lload 9
    //   1805: lstore 13
    //   1807: aload_0
    //   1808: getfield 636	com/tencent/smtt/sdk/h:xUJ	Ljava/net/HttpURLConnection;
    //   1811: aload_0
    //   1812: getfield 74	com/tencent/smtt/sdk/h:xUF	I
    //   1815: invokevirtual 788	java/net/HttpURLConnection:setReadTimeout	(I)V
    //   1818: lconst_0
    //   1819: lstore 19
    //   1821: lload 9
    //   1823: lstore 11
    //   1825: iload_2
    //   1826: istore 5
    //   1828: lload 9
    //   1830: lstore 13
    //   1832: aload_0
    //   1833: getfield 371	com/tencent/smtt/sdk/h:xUH	Z
    //   1836: ifne +154 -> 1990
    //   1839: lload 9
    //   1841: lstore 11
    //   1843: iload_2
    //   1844: istore 5
    //   1846: lload 9
    //   1848: lstore 13
    //   1850: aload_0
    //   1851: invokespecial 790	com/tencent/smtt/sdk/h:cnW	()J
    //   1854: lstore 19
    //   1856: lload 9
    //   1858: lstore 11
    //   1860: iload_2
    //   1861: istore 5
    //   1863: lload 9
    //   1865: lstore 13
    //   1867: ldc -65
    //   1869: new 109	java/lang/StringBuilder
    //   1872: dup
    //   1873: ldc_w 792
    //   1876: invokespecial 114	java/lang/StringBuilder:<init>	(Ljava/lang/String;)V
    //   1879: lload 19
    //   1881: invokevirtual 276	java/lang/StringBuilder:append	(J)Ljava/lang/StringBuilder;
    //   1884: invokevirtual 125	java/lang/StringBuilder:toString	()Ljava/lang/String;
    //   1887: invokestatic 198	com/tencent/smtt/utils/TbsLog:i	(Ljava/lang/String;Ljava/lang/String;)V
    //   1890: lload 9
    //   1892: lstore 11
    //   1894: iload_2
    //   1895: istore 5
    //   1897: lload 9
    //   1899: lstore 13
    //   1901: aload_0
    //   1902: getfield 367	com/tencent/smtt/sdk/h:mContentLength	J
    //   1905: lconst_0
    //   1906: lcmp
    //   1907: ifgt +920 -> 2827
    //   1910: lload 9
    //   1912: lstore 11
    //   1914: iload_2
    //   1915: istore 5
    //   1917: lload 9
    //   1919: lstore 13
    //   1921: ldc -65
    //   1923: new 109	java/lang/StringBuilder
    //   1926: dup
    //   1927: ldc_w 794
    //   1930: invokespecial 114	java/lang/StringBuilder:<init>	(Ljava/lang/String;)V
    //   1933: lload 19
    //   1935: invokevirtual 276	java/lang/StringBuilder:append	(J)Ljava/lang/StringBuilder;
    //   1938: invokevirtual 125	java/lang/StringBuilder:toString	()Ljava/lang/String;
    //   1941: iconst_1
    //   1942: invokestatic 615	com/tencent/smtt/utils/TbsLog:i	(Ljava/lang/String;Ljava/lang/String;Z)V
    //   1945: lload 9
    //   1947: lstore 11
    //   1949: iload_2
    //   1950: istore 5
    //   1952: lload 9
    //   1954: lstore 13
    //   1956: aload_0
    //   1957: getfield 636	com/tencent/smtt/sdk/h:xUJ	Ljava/net/HttpURLConnection;
    //   1960: ldc_w 796
    //   1963: new 109	java/lang/StringBuilder
    //   1966: dup
    //   1967: ldc_w 798
    //   1970: invokespecial 114	java/lang/StringBuilder:<init>	(Ljava/lang/String;)V
    //   1973: lload 19
    //   1975: invokevirtual 276	java/lang/StringBuilder:append	(J)Ljava/lang/StringBuilder;
    //   1978: ldc_w 800
    //   1981: invokevirtual 122	java/lang/StringBuilder:append	(Ljava/lang/String;)Ljava/lang/StringBuilder;
    //   1984: invokevirtual 125	java/lang/StringBuilder:toString	()Ljava/lang/String;
    //   1987: invokevirtual 770	java/net/HttpURLConnection:setRequestProperty	(Ljava/lang/String;Ljava/lang/String;)V
    //   1990: lload 9
    //   1992: lstore 11
    //   1994: iload_2
    //   1995: istore 5
    //   1997: lload 9
    //   1999: lstore 13
    //   2001: aload_0
    //   2002: getfield 102	com/tencent/smtt/sdk/h:xUL	Lcom/tencent/smtt/sdk/r$b;
    //   2005: astore 27
    //   2007: lload 19
    //   2009: lconst_0
    //   2010: lcmp
    //   2011: ifne +4981 -> 6992
    //   2014: iconst_0
    //   2015: istore_3
    //   2016: lload 9
    //   2018: lstore 11
    //   2020: iload_2
    //   2021: istore 5
    //   2023: lload 9
    //   2025: lstore 13
    //   2027: aload 27
    //   2029: iload_3
    //   2030: putfield 803	com/tencent/smtt/sdk/r$b:xWm	I
    //   2033: lload 9
    //   2035: lstore 11
    //   2037: iload_2
    //   2038: istore 5
    //   2040: lload 9
    //   2042: lstore 13
    //   2044: aload_0
    //   2045: getfield 90	com/tencent/smtt/sdk/h:mContext	Landroid/content/Context;
    //   2048: invokestatic 706	com/tencent/smtt/utils/b:ho	(Landroid/content/Context;)I
    //   2051: istore_3
    //   2052: lload 9
    //   2054: lstore 11
    //   2056: iload_2
    //   2057: istore 5
    //   2059: lload 9
    //   2061: lstore 13
    //   2063: aload_0
    //   2064: getfield 90	com/tencent/smtt/sdk/h:mContext	Landroid/content/Context;
    //   2067: invokestatic 702	com/tencent/smtt/utils/b:hn	(Landroid/content/Context;)Ljava/lang/String;
    //   2070: astore 27
    //   2072: lload 9
    //   2074: lstore 11
    //   2076: iload_2
    //   2077: istore 5
    //   2079: lload 9
    //   2081: lstore 13
    //   2083: aload_0
    //   2084: getfield 149	com/tencent/smtt/sdk/h:xUM	Ljava/lang/String;
    //   2087: ifnonnull +843 -> 2930
    //   2090: lload 9
    //   2092: lstore 11
    //   2094: iload_2
    //   2095: istore 5
    //   2097: lload 9
    //   2099: lstore 13
    //   2101: aload_0
    //   2102: getfield 151	com/tencent/smtt/sdk/h:xUN	I
    //   2105: iconst_m1
    //   2106: if_icmpne +824 -> 2930
    //   2109: lload 9
    //   2111: lstore 11
    //   2113: iload_2
    //   2114: istore 5
    //   2116: lload 9
    //   2118: lstore 13
    //   2120: aload_0
    //   2121: aload 27
    //   2123: putfield 149	com/tencent/smtt/sdk/h:xUM	Ljava/lang/String;
    //   2126: lload 9
    //   2128: lstore 11
    //   2130: iload_2
    //   2131: istore 5
    //   2133: lload 9
    //   2135: lstore 13
    //   2137: aload_0
    //   2138: iload_3
    //   2139: putfield 151	com/tencent/smtt/sdk/h:xUN	I
    //   2142: lload 9
    //   2144: lstore 11
    //   2146: iload_2
    //   2147: istore 5
    //   2149: lload 9
    //   2151: lstore 13
    //   2153: aload_0
    //   2154: getfield 361	com/tencent/smtt/sdk/h:hiz	I
    //   2157: ifle +28 -> 2185
    //   2160: lload 9
    //   2162: lstore 11
    //   2164: iload_2
    //   2165: istore 5
    //   2167: lload 9
    //   2169: lstore 13
    //   2171: aload_0
    //   2172: getfield 636	com/tencent/smtt/sdk/h:xUJ	Ljava/net/HttpURLConnection;
    //   2175: ldc_w 805
    //   2178: aload_0
    //   2179: getfield 608	com/tencent/smtt/sdk/h:mDownloadUrl	Ljava/lang/String;
    //   2182: invokevirtual 808	java/net/HttpURLConnection:addRequestProperty	(Ljava/lang/String;Ljava/lang/String;)V
    //   2185: lload 9
    //   2187: lstore 11
    //   2189: iload_2
    //   2190: istore 5
    //   2192: lload 9
    //   2194: lstore 13
    //   2196: aload_0
    //   2197: getfield 636	com/tencent/smtt/sdk/h:xUJ	Ljava/net/HttpURLConnection;
    //   2200: invokevirtual 811	java/net/HttpURLConnection:getResponseCode	()I
    //   2203: istore_3
    //   2204: lload 9
    //   2206: lstore 11
    //   2208: iload_2
    //   2209: istore 5
    //   2211: lload 9
    //   2213: lstore 13
    //   2215: ldc -65
    //   2217: new 109	java/lang/StringBuilder
    //   2220: dup
    //   2221: ldc_w 813
    //   2224: invokespecial 114	java/lang/StringBuilder:<init>	(Ljava/lang/String;)V
    //   2227: iload_3
    //   2228: invokevirtual 297	java/lang/StringBuilder:append	(I)Ljava/lang/StringBuilder;
    //   2231: invokevirtual 125	java/lang/StringBuilder:toString	()Ljava/lang/String;
    //   2234: invokestatic 198	com/tencent/smtt/utils/TbsLog:i	(Ljava/lang/String;Ljava/lang/String;)V
    //   2237: lload 9
    //   2239: lstore 11
    //   2241: iload_2
    //   2242: istore 5
    //   2244: lload 9
    //   2246: lstore 13
    //   2248: aload_0
    //   2249: getfield 102	com/tencent/smtt/sdk/h:xUL	Lcom/tencent/smtt/sdk/r$b;
    //   2252: iload_3
    //   2253: putfield 816	com/tencent/smtt/sdk/r$b:xWk	I
    //   2256: iload_1
    //   2257: ifne +157 -> 2414
    //   2260: lload 9
    //   2262: lstore 11
    //   2264: iload_2
    //   2265: istore 5
    //   2267: lload 9
    //   2269: lstore 13
    //   2271: aload_0
    //   2272: getfield 90	com/tencent/smtt/sdk/h:mContext	Landroid/content/Context;
    //   2275: invokestatic 171	com/tencent/smtt/sdk/l:gp	(Landroid/content/Context;)Z
    //   2278: ifne +136 -> 2414
    //   2281: lload 9
    //   2283: lstore 11
    //   2285: iload_2
    //   2286: istore 5
    //   2288: lload 9
    //   2290: lstore 13
    //   2292: aload_0
    //   2293: getfield 90	com/tencent/smtt/sdk/h:mContext	Landroid/content/Context;
    //   2296: invokestatic 706	com/tencent/smtt/utils/b:ho	(Landroid/content/Context;)I
    //   2299: iconst_3
    //   2300: if_icmpeq +20 -> 2320
    //   2303: lload 9
    //   2305: lstore 11
    //   2307: iload_2
    //   2308: istore 5
    //   2310: lload 9
    //   2312: lstore 13
    //   2314: invokestatic 819	com/tencent/smtt/sdk/QbSdk:getDownloadWithoutWifi	()Z
    //   2317: ifeq +24 -> 2341
    //   2320: lload 9
    //   2322: lstore 11
    //   2324: iload_2
    //   2325: istore 5
    //   2327: lload 9
    //   2329: lstore 13
    //   2331: aload_0
    //   2332: getfield 90	com/tencent/smtt/sdk/h:mContext	Landroid/content/Context;
    //   2335: invokestatic 706	com/tencent/smtt/utils/b:ho	(Landroid/content/Context;)I
    //   2338: ifne +76 -> 2414
    //   2341: lload 9
    //   2343: lstore 11
    //   2345: iload_2
    //   2346: istore 5
    //   2348: lload 9
    //   2350: lstore 13
    //   2352: aload_0
    //   2353: invokevirtual 822	com/tencent/smtt/sdk/h:stopDownload	()V
    //   2356: lload 9
    //   2358: lstore 11
    //   2360: iload_2
    //   2361: istore 5
    //   2363: lload 9
    //   2365: lstore 13
    //   2367: getstatic 537	com/tencent/smtt/sdk/QbSdk:xUb	Lcom/tencent/smtt/sdk/q;
    //   2370: ifnull +24 -> 2394
    //   2373: lload 9
    //   2375: lstore 11
    //   2377: iload_2
    //   2378: istore 5
    //   2380: lload 9
    //   2382: lstore 13
    //   2384: getstatic 537	com/tencent/smtt/sdk/QbSdk:xUb	Lcom/tencent/smtt/sdk/q;
    //   2387: bipush 111
    //   2389: invokeinterface 542 2 0
    //   2394: lload 9
    //   2396: lstore 11
    //   2398: iload_2
    //   2399: istore 5
    //   2401: lload 9
    //   2403: lstore 13
    //   2405: ldc -65
    //   2407: ldc_w 824
    //   2410: iconst_0
    //   2411: invokestatic 615	com/tencent/smtt/utils/TbsLog:i	(Ljava/lang/String;Ljava/lang/String;Z)V
    //   2414: lload 9
    //   2416: lstore 11
    //   2418: iload_2
    //   2419: istore 5
    //   2421: lload 9
    //   2423: lstore 13
    //   2425: aload_0
    //   2426: getfield 373	com/tencent/smtt/sdk/h:Lv	Z
    //   2429: ifeq +4568 -> 6997
    //   2432: lload 9
    //   2434: lstore 11
    //   2436: iload_2
    //   2437: istore 5
    //   2439: lload 9
    //   2441: lstore 13
    //   2443: aload_0
    //   2444: getfield 90	com/tencent/smtt/sdk/h:mContext	Landroid/content/Context;
    //   2447: invokestatic 226	com/tencent/smtt/sdk/k:gl	(Landroid/content/Context;)Lcom/tencent/smtt/sdk/k;
    //   2450: sipush 65227
    //   2453: invokevirtual 599	com/tencent/smtt/sdk/k:Ff	(I)V
    //   2456: iload_2
    //   2457: istore 5
    //   2459: iload_1
    //   2460: ifne -1924 -> 536
    //   2463: aload_0
    //   2464: getfield 90	com/tencent/smtt/sdk/h:mContext	Landroid/content/Context;
    //   2467: invokestatic 226	com/tencent/smtt/sdk/k:gl	(Landroid/content/Context;)Lcom/tencent/smtt/sdk/k;
    //   2470: getfield 511	com/tencent/smtt/sdk/k:xVh	Ljava/util/Map;
    //   2473: ldc_w 655
    //   2476: lload 9
    //   2478: invokestatic 739	java/lang/Long:valueOf	(J)Ljava/lang/Long;
    //   2481: invokeinterface 524 3 0
    //   2486: pop
    //   2487: aload_0
    //   2488: getfield 90	com/tencent/smtt/sdk/h:mContext	Landroid/content/Context;
    //   2491: invokestatic 226	com/tencent/smtt/sdk/k:gl	(Landroid/content/Context;)Lcom/tencent/smtt/sdk/k;
    //   2494: invokevirtual 531	com/tencent/smtt/sdk/k:commit	()V
    //   2497: iload_2
    //   2498: istore 5
    //   2500: goto -1964 -> 536
    //   2503: lload 9
    //   2505: lstore 11
    //   2507: iload_2
    //   2508: istore 5
    //   2510: lload 9
    //   2512: lstore 13
    //   2514: aload_0
    //   2515: getfield 608	com/tencent/smtt/sdk/h:mDownloadUrl	Ljava/lang/String;
    //   2518: astore 27
    //   2520: goto -1054 -> 1466
    //   2523: lload 9
    //   2525: lstore 11
    //   2527: iload_2
    //   2528: istore 5
    //   2530: lload 9
    //   2532: lstore 13
    //   2534: aload 28
    //   2536: new 109	java/lang/StringBuilder
    //   2539: dup
    //   2540: invokespecial 825	java/lang/StringBuilder:<init>	()V
    //   2543: aload 28
    //   2545: getfield 757	com/tencent/smtt/sdk/r$b:xWi	Ljava/lang/String;
    //   2548: invokevirtual 122	java/lang/StringBuilder:append	(Ljava/lang/String;)Ljava/lang/StringBuilder;
    //   2551: ldc_w 620
    //   2554: invokevirtual 122	java/lang/StringBuilder:append	(Ljava/lang/String;)Ljava/lang/StringBuilder;
    //   2557: aload 27
    //   2559: invokevirtual 122	java/lang/StringBuilder:append	(Ljava/lang/String;)Ljava/lang/StringBuilder;
    //   2562: invokevirtual 125	java/lang/StringBuilder:toString	()Ljava/lang/String;
    //   2565: putfield 757	com/tencent/smtt/sdk/r$b:xWi	Ljava/lang/String;
    //   2568: goto -977 -> 1591
    //   2571: astore 27
    //   2573: lload 11
    //   2575: lstore 9
    //   2577: iload 5
    //   2579: istore_2
    //   2580: lload 9
    //   2582: lstore 11
    //   2584: aload 27
    //   2586: instanceof 827
    //   2589: ifeq +3942 -> 6531
    //   2592: iload_1
    //   2593: ifne +3938 -> 6531
    //   2596: lload 9
    //   2598: lstore 11
    //   2600: aload_0
    //   2601: getfield 80	com/tencent/smtt/sdk/h:xUU	[Ljava/lang/String;
    //   2604: ifnull +3927 -> 6531
    //   2607: lload 9
    //   2609: lstore 11
    //   2611: aload_0
    //   2612: invokespecial 829	com/tencent/smtt/sdk/h:cnV	()Z
    //   2615: ifeq +3916 -> 6531
    //   2618: lload 9
    //   2620: lstore 11
    //   2622: ldc -65
    //   2624: new 109	java/lang/StringBuilder
    //   2627: dup
    //   2628: ldc_w 831
    //   2631: invokespecial 114	java/lang/StringBuilder:<init>	(Ljava/lang/String;)V
    //   2634: aload_0
    //   2635: getfield 369	com/tencent/smtt/sdk/h:xUD	Ljava/lang/String;
    //   2638: invokevirtual 122	java/lang/StringBuilder:append	(Ljava/lang/String;)Ljava/lang/StringBuilder;
    //   2641: ldc_w 833
    //   2644: invokevirtual 122	java/lang/StringBuilder:append	(Ljava/lang/String;)Ljava/lang/StringBuilder;
    //   2647: aload 27
    //   2649: invokevirtual 834	java/lang/Throwable:toString	()Ljava/lang/String;
    //   2652: invokevirtual 122	java/lang/StringBuilder:append	(Ljava/lang/String;)Ljava/lang/StringBuilder;
    //   2655: invokevirtual 125	java/lang/StringBuilder:toString	()Ljava/lang/String;
    //   2658: invokestatic 208	com/tencent/smtt/utils/TbsLog:e	(Ljava/lang/String;Ljava/lang/String;)V
    //   2661: lload 9
    //   2663: lstore 11
    //   2665: aload_0
    //   2666: bipush 125
    //   2668: aconst_null
    //   2669: iconst_1
    //   2670: invokespecial 340	com/tencent/smtt/sdk/h:j	(ILjava/lang/String;Z)V
    //   2673: lload 9
    //   2675: lstore 11
    //   2677: aload_0
    //   2678: getfield 90	com/tencent/smtt/sdk/h:mContext	Landroid/content/Context;
    //   2681: invokestatic 226	com/tencent/smtt/sdk/k:gl	(Landroid/content/Context;)Lcom/tencent/smtt/sdk/k;
    //   2684: sipush 65220
    //   2687: invokevirtual 599	com/tencent/smtt/sdk/k:Ff	(I)V
    //   2690: lload 9
    //   2692: lstore 11
    //   2694: iload_2
    //   2695: istore 5
    //   2697: iload 8
    //   2699: istore 6
    //   2701: iload_1
    //   2702: ifne -1686 -> 1016
    //   2705: aload_0
    //   2706: getfield 90	com/tencent/smtt/sdk/h:mContext	Landroid/content/Context;
    //   2709: invokestatic 226	com/tencent/smtt/sdk/k:gl	(Landroid/content/Context;)Lcom/tencent/smtt/sdk/k;
    //   2712: getfield 511	com/tencent/smtt/sdk/k:xVh	Ljava/util/Map;
    //   2715: ldc_w 655
    //   2718: lload 9
    //   2720: invokestatic 739	java/lang/Long:valueOf	(J)Ljava/lang/Long;
    //   2723: invokeinterface 524 3 0
    //   2728: pop
    //   2729: aload_0
    //   2730: getfield 90	com/tencent/smtt/sdk/h:mContext	Landroid/content/Context;
    //   2733: invokestatic 226	com/tencent/smtt/sdk/k:gl	(Landroid/content/Context;)Lcom/tencent/smtt/sdk/k;
    //   2736: invokevirtual 531	com/tencent/smtt/sdk/k:commit	()V
    //   2739: goto -2250 -> 489
    //   2742: astore 28
    //   2744: lload 9
    //   2746: lstore 11
    //   2748: iload_2
    //   2749: istore 5
    //   2751: lload 9
    //   2753: lstore 13
    //   2755: ldc -65
    //   2757: new 109	java/lang/StringBuilder
    //   2760: dup
    //   2761: ldc_w 836
    //   2764: invokespecial 114	java/lang/StringBuilder:<init>	(Ljava/lang/String;)V
    //   2767: aload 28
    //   2769: invokevirtual 834	java/lang/Throwable:toString	()Ljava/lang/String;
    //   2772: invokevirtual 122	java/lang/StringBuilder:append	(Ljava/lang/String;)Ljava/lang/StringBuilder;
    //   2775: invokevirtual 125	java/lang/StringBuilder:toString	()Ljava/lang/String;
    //   2778: invokestatic 208	com/tencent/smtt/utils/TbsLog:e	(Ljava/lang/String;Ljava/lang/String;)V
    //   2781: goto -1118 -> 1663
    //   2784: astore 27
    //   2786: iload_1
    //   2787: ifne +37 -> 2824
    //   2790: aload_0
    //   2791: getfield 90	com/tencent/smtt/sdk/h:mContext	Landroid/content/Context;
    //   2794: invokestatic 226	com/tencent/smtt/sdk/k:gl	(Landroid/content/Context;)Lcom/tencent/smtt/sdk/k;
    //   2797: getfield 511	com/tencent/smtt/sdk/k:xVh	Ljava/util/Map;
    //   2800: ldc_w 655
    //   2803: lload 13
    //   2805: invokestatic 739	java/lang/Long:valueOf	(J)Ljava/lang/Long;
    //   2808: invokeinterface 524 3 0
    //   2813: pop
    //   2814: aload_0
    //   2815: getfield 90	com/tencent/smtt/sdk/h:mContext	Landroid/content/Context;
    //   2818: invokestatic 226	com/tencent/smtt/sdk/k:gl	(Landroid/content/Context;)Lcom/tencent/smtt/sdk/k;
    //   2821: invokevirtual 531	com/tencent/smtt/sdk/k:commit	()V
    //   2824: aload 27
    //   2826: athrow
    //   2827: lload 9
    //   2829: lstore 11
    //   2831: iload_2
    //   2832: istore 5
    //   2834: lload 9
    //   2836: lstore 13
    //   2838: ldc -65
    //   2840: new 109	java/lang/StringBuilder
    //   2843: dup
    //   2844: ldc_w 838
    //   2847: invokespecial 114	java/lang/StringBuilder:<init>	(Ljava/lang/String;)V
    //   2850: lload 19
    //   2852: invokevirtual 276	java/lang/StringBuilder:append	(J)Ljava/lang/StringBuilder;
    //   2855: ldc_w 840
    //   2858: invokevirtual 122	java/lang/StringBuilder:append	(Ljava/lang/String;)Ljava/lang/StringBuilder;
    //   2861: aload_0
    //   2862: getfield 367	com/tencent/smtt/sdk/h:mContentLength	J
    //   2865: invokevirtual 276	java/lang/StringBuilder:append	(J)Ljava/lang/StringBuilder;
    //   2868: invokevirtual 125	java/lang/StringBuilder:toString	()Ljava/lang/String;
    //   2871: iconst_1
    //   2872: invokestatic 615	com/tencent/smtt/utils/TbsLog:i	(Ljava/lang/String;Ljava/lang/String;Z)V
    //   2875: lload 9
    //   2877: lstore 11
    //   2879: iload_2
    //   2880: istore 5
    //   2882: lload 9
    //   2884: lstore 13
    //   2886: aload_0
    //   2887: getfield 636	com/tencent/smtt/sdk/h:xUJ	Ljava/net/HttpURLConnection;
    //   2890: ldc_w 796
    //   2893: new 109	java/lang/StringBuilder
    //   2896: dup
    //   2897: ldc_w 798
    //   2900: invokespecial 114	java/lang/StringBuilder:<init>	(Ljava/lang/String;)V
    //   2903: lload 19
    //   2905: invokevirtual 276	java/lang/StringBuilder:append	(J)Ljava/lang/StringBuilder;
    //   2908: ldc_w 800
    //   2911: invokevirtual 122	java/lang/StringBuilder:append	(Ljava/lang/String;)Ljava/lang/StringBuilder;
    //   2914: aload_0
    //   2915: getfield 367	com/tencent/smtt/sdk/h:mContentLength	J
    //   2918: invokevirtual 276	java/lang/StringBuilder:append	(J)Ljava/lang/StringBuilder;
    //   2921: invokevirtual 125	java/lang/StringBuilder:toString	()Ljava/lang/String;
    //   2924: invokevirtual 770	java/net/HttpURLConnection:setRequestProperty	(Ljava/lang/String;Ljava/lang/String;)V
    //   2927: goto -937 -> 1990
    //   2930: lload 9
    //   2932: lstore 11
    //   2934: iload_2
    //   2935: istore 5
    //   2937: lload 9
    //   2939: lstore 13
    //   2941: iload_3
    //   2942: aload_0
    //   2943: getfield 151	com/tencent/smtt/sdk/h:xUN	I
    //   2946: if_icmpne +26 -> 2972
    //   2949: lload 9
    //   2951: lstore 11
    //   2953: iload_2
    //   2954: istore 5
    //   2956: lload 9
    //   2958: lstore 13
    //   2960: aload 27
    //   2962: aload_0
    //   2963: getfield 149	com/tencent/smtt/sdk/h:xUM	Ljava/lang/String;
    //   2966: invokevirtual 246	java/lang/String:equals	(Ljava/lang/Object;)Z
    //   2969: ifne -827 -> 2142
    //   2972: lload 9
    //   2974: lstore 11
    //   2976: iload_2
    //   2977: istore 5
    //   2979: lload 9
    //   2981: lstore 13
    //   2983: aload_0
    //   2984: getfield 102	com/tencent/smtt/sdk/h:xUL	Lcom/tencent/smtt/sdk/r$b;
    //   2987: iconst_0
    //   2988: putfield 715	com/tencent/smtt/sdk/r$b:xWt	I
    //   2991: lload 9
    //   2993: lstore 11
    //   2995: iload_2
    //   2996: istore 5
    //   2998: lload 9
    //   3000: lstore 13
    //   3002: aload_0
    //   3003: aload 27
    //   3005: putfield 149	com/tencent/smtt/sdk/h:xUM	Ljava/lang/String;
    //   3008: lload 9
    //   3010: lstore 11
    //   3012: iload_2
    //   3013: istore 5
    //   3015: lload 9
    //   3017: lstore 13
    //   3019: aload_0
    //   3020: iload_3
    //   3021: putfield 151	com/tencent/smtt/sdk/h:xUN	I
    //   3024: goto -882 -> 2142
    //   3027: lload 9
    //   3029: lstore 11
    //   3031: iload_2
    //   3032: istore 5
    //   3034: lload 9
    //   3036: lstore 13
    //   3038: aload_0
    //   3039: aload_0
    //   3040: getfield 636	com/tencent/smtt/sdk/h:xUJ	Ljava/net/HttpURLConnection;
    //   3043: invokevirtual 843	java/net/HttpURLConnection:getContentLength	()I
    //   3046: i2l
    //   3047: lload 19
    //   3049: ladd
    //   3050: putfield 367	com/tencent/smtt/sdk/h:mContentLength	J
    //   3053: lload 9
    //   3055: lstore 11
    //   3057: iload_2
    //   3058: istore 5
    //   3060: lload 9
    //   3062: lstore 13
    //   3064: ldc -65
    //   3066: new 109	java/lang/StringBuilder
    //   3069: dup
    //   3070: ldc_w 845
    //   3073: invokespecial 114	java/lang/StringBuilder:<init>	(Ljava/lang/String;)V
    //   3076: aload_0
    //   3077: getfield 367	com/tencent/smtt/sdk/h:mContentLength	J
    //   3080: invokevirtual 276	java/lang/StringBuilder:append	(J)Ljava/lang/StringBuilder;
    //   3083: invokevirtual 125	java/lang/StringBuilder:toString	()Ljava/lang/String;
    //   3086: invokestatic 198	com/tencent/smtt/utils/TbsLog:i	(Ljava/lang/String;Ljava/lang/String;)V
    //   3089: lload 9
    //   3091: lstore 11
    //   3093: iload_2
    //   3094: istore 5
    //   3096: lload 9
    //   3098: lstore 13
    //   3100: aload_0
    //   3101: getfield 102	com/tencent/smtt/sdk/h:xUL	Lcom/tencent/smtt/sdk/r$b;
    //   3104: aload_0
    //   3105: getfield 367	com/tencent/smtt/sdk/h:mContentLength	J
    //   3108: putfield 848	com/tencent/smtt/sdk/r$b:xWr	J
    //   3111: lload 9
    //   3113: lstore 11
    //   3115: iload_2
    //   3116: istore 5
    //   3118: lload 9
    //   3120: lstore 13
    //   3122: aload_0
    //   3123: getfield 90	com/tencent/smtt/sdk/h:mContext	Landroid/content/Context;
    //   3126: invokestatic 226	com/tencent/smtt/sdk/k:gl	(Landroid/content/Context;)Lcom/tencent/smtt/sdk/k;
    //   3129: getfield 230	com/tencent/smtt/sdk/k:xVi	Landroid/content/SharedPreferences;
    //   3132: ldc_w 261
    //   3135: lconst_0
    //   3136: invokeinterface 265 4 0
    //   3141: lstore 15
    //   3143: lload 15
    //   3145: lconst_0
    //   3146: lcmp
    //   3147: ifeq +381 -> 3528
    //   3150: lload 9
    //   3152: lstore 11
    //   3154: iload_2
    //   3155: istore 5
    //   3157: lload 9
    //   3159: lstore 13
    //   3161: aload_0
    //   3162: getfield 367	com/tencent/smtt/sdk/h:mContentLength	J
    //   3165: lload 15
    //   3167: lcmp
    //   3168: ifeq +360 -> 3528
    //   3171: lload 9
    //   3173: lstore 11
    //   3175: iload_2
    //   3176: istore 5
    //   3178: lload 9
    //   3180: lstore 13
    //   3182: ldc -65
    //   3184: new 109	java/lang/StringBuilder
    //   3187: dup
    //   3188: ldc_w 850
    //   3191: invokespecial 114	java/lang/StringBuilder:<init>	(Ljava/lang/String;)V
    //   3194: lload 15
    //   3196: invokevirtual 276	java/lang/StringBuilder:append	(J)Ljava/lang/StringBuilder;
    //   3199: ldc_w 852
    //   3202: invokevirtual 122	java/lang/StringBuilder:append	(Ljava/lang/String;)Ljava/lang/StringBuilder;
    //   3205: aload_0
    //   3206: getfield 367	com/tencent/smtt/sdk/h:mContentLength	J
    //   3209: invokevirtual 276	java/lang/StringBuilder:append	(J)Ljava/lang/StringBuilder;
    //   3212: invokevirtual 125	java/lang/StringBuilder:toString	()Ljava/lang/String;
    //   3215: iconst_1
    //   3216: invokestatic 615	com/tencent/smtt/utils/TbsLog:i	(Ljava/lang/String;Ljava/lang/String;Z)V
    //   3219: iload_1
    //   3220: ifne +260 -> 3480
    //   3223: lload 9
    //   3225: lstore 11
    //   3227: iload_2
    //   3228: istore 5
    //   3230: lload 9
    //   3232: lstore 13
    //   3234: aload_0
    //   3235: invokevirtual 855	com/tencent/smtt/sdk/h:cnY	()Z
    //   3238: ifne +41 -> 3279
    //   3241: lload 9
    //   3243: lstore 11
    //   3245: iload_2
    //   3246: istore 5
    //   3248: lload 9
    //   3250: lstore 13
    //   3252: invokestatic 819	com/tencent/smtt/sdk/QbSdk:getDownloadWithoutWifi	()Z
    //   3255: ifeq +225 -> 3480
    //   3258: lload 9
    //   3260: lstore 11
    //   3262: iload_2
    //   3263: istore 5
    //   3265: lload 9
    //   3267: lstore 13
    //   3269: aload_0
    //   3270: getfield 90	com/tencent/smtt/sdk/h:mContext	Landroid/content/Context;
    //   3273: invokestatic 718	com/tencent/smtt/utils/b:isNetworkAvailable	(Landroid/content/Context;)Z
    //   3276: ifeq +204 -> 3480
    //   3279: lload 9
    //   3281: lstore 11
    //   3283: iload_2
    //   3284: istore 5
    //   3286: lload 9
    //   3288: lstore 13
    //   3290: aload_0
    //   3291: getfield 80	com/tencent/smtt/sdk/h:xUU	[Ljava/lang/String;
    //   3294: ifnull +66 -> 3360
    //   3297: lload 9
    //   3299: lstore 11
    //   3301: iload_2
    //   3302: istore 5
    //   3304: lload 9
    //   3306: lstore 13
    //   3308: aload_0
    //   3309: invokespecial 829	com/tencent/smtt/sdk/h:cnV	()Z
    //   3312: istore 6
    //   3314: iload 6
    //   3316: ifeq +44 -> 3360
    //   3319: iload_1
    //   3320: ifne +3642 -> 6962
    //   3323: aload_0
    //   3324: getfield 90	com/tencent/smtt/sdk/h:mContext	Landroid/content/Context;
    //   3327: invokestatic 226	com/tencent/smtt/sdk/k:gl	(Landroid/content/Context;)Lcom/tencent/smtt/sdk/k;
    //   3330: getfield 511	com/tencent/smtt/sdk/k:xVh	Ljava/util/Map;
    //   3333: ldc_w 655
    //   3336: lload 9
    //   3338: invokestatic 739	java/lang/Long:valueOf	(J)Ljava/lang/Long;
    //   3341: invokeinterface 524 3 0
    //   3346: pop
    //   3347: aload_0
    //   3348: getfield 90	com/tencent/smtt/sdk/h:mContext	Landroid/content/Context;
    //   3351: invokestatic 226	com/tencent/smtt/sdk/k:gl	(Landroid/content/Context;)Lcom/tencent/smtt/sdk/k;
    //   3354: invokevirtual 531	com/tencent/smtt/sdk/k:commit	()V
    //   3357: goto -2868 -> 489
    //   3360: lload 9
    //   3362: lstore 11
    //   3364: iload_2
    //   3365: istore 5
    //   3367: lload 9
    //   3369: lstore 13
    //   3371: aload_0
    //   3372: bipush 113
    //   3374: new 109	java/lang/StringBuilder
    //   3377: dup
    //   3378: ldc_w 857
    //   3381: invokespecial 114	java/lang/StringBuilder:<init>	(Ljava/lang/String;)V
    //   3384: lload 15
    //   3386: invokevirtual 276	java/lang/StringBuilder:append	(J)Ljava/lang/StringBuilder;
    //   3389: ldc_w 852
    //   3392: invokevirtual 122	java/lang/StringBuilder:append	(Ljava/lang/String;)Ljava/lang/StringBuilder;
    //   3395: aload_0
    //   3396: getfield 367	com/tencent/smtt/sdk/h:mContentLength	J
    //   3399: invokevirtual 276	java/lang/StringBuilder:append	(J)Ljava/lang/StringBuilder;
    //   3402: invokevirtual 125	java/lang/StringBuilder:toString	()Ljava/lang/String;
    //   3405: iconst_1
    //   3406: invokespecial 340	com/tencent/smtt/sdk/h:j	(ILjava/lang/String;Z)V
    //   3409: lload 9
    //   3411: lstore 11
    //   3413: iload_2
    //   3414: istore 5
    //   3416: lload 9
    //   3418: lstore 13
    //   3420: aload_0
    //   3421: getfield 90	com/tencent/smtt/sdk/h:mContext	Landroid/content/Context;
    //   3424: invokestatic 226	com/tencent/smtt/sdk/k:gl	(Landroid/content/Context;)Lcom/tencent/smtt/sdk/k;
    //   3427: sipush 65226
    //   3430: invokevirtual 599	com/tencent/smtt/sdk/k:Ff	(I)V
    //   3433: iload_2
    //   3434: istore 5
    //   3436: iload_1
    //   3437: ifne -2901 -> 536
    //   3440: aload_0
    //   3441: getfield 90	com/tencent/smtt/sdk/h:mContext	Landroid/content/Context;
    //   3444: invokestatic 226	com/tencent/smtt/sdk/k:gl	(Landroid/content/Context;)Lcom/tencent/smtt/sdk/k;
    //   3447: getfield 511	com/tencent/smtt/sdk/k:xVh	Ljava/util/Map;
    //   3450: ldc_w 655
    //   3453: lload 9
    //   3455: invokestatic 739	java/lang/Long:valueOf	(J)Ljava/lang/Long;
    //   3458: invokeinterface 524 3 0
    //   3463: pop
    //   3464: aload_0
    //   3465: getfield 90	com/tencent/smtt/sdk/h:mContext	Landroid/content/Context;
    //   3468: invokestatic 226	com/tencent/smtt/sdk/k:gl	(Landroid/content/Context;)Lcom/tencent/smtt/sdk/k;
    //   3471: invokevirtual 531	com/tencent/smtt/sdk/k:commit	()V
    //   3474: iload_2
    //   3475: istore 5
    //   3477: goto -2941 -> 536
    //   3480: lload 9
    //   3482: lstore 11
    //   3484: iload_2
    //   3485: istore 5
    //   3487: lload 9
    //   3489: lstore 13
    //   3491: aload_0
    //   3492: bipush 101
    //   3494: ldc_w 859
    //   3497: iconst_1
    //   3498: invokespecial 340	com/tencent/smtt/sdk/h:j	(ILjava/lang/String;Z)V
    //   3501: lload 9
    //   3503: lstore 11
    //   3505: iload_2
    //   3506: istore 5
    //   3508: lload 9
    //   3510: lstore 13
    //   3512: aload_0
    //   3513: getfield 90	com/tencent/smtt/sdk/h:mContext	Landroid/content/Context;
    //   3516: invokestatic 226	com/tencent/smtt/sdk/k:gl	(Landroid/content/Context;)Lcom/tencent/smtt/sdk/k;
    //   3519: sipush 65232
    //   3522: invokevirtual 599	com/tencent/smtt/sdk/k:Ff	(I)V
    //   3525: goto -92 -> 3433
    //   3528: aconst_null
    //   3529: astore 31
    //   3531: aconst_null
    //   3532: astore 28
    //   3534: lload 9
    //   3536: lstore 11
    //   3538: iload_2
    //   3539: istore 5
    //   3541: lload 9
    //   3543: lstore 13
    //   3545: ldc -65
    //   3547: ldc_w 861
    //   3550: invokestatic 198	com/tencent/smtt/utils/TbsLog:i	(Ljava/lang/String;Ljava/lang/String;)V
    //   3553: aload_0
    //   3554: getfield 636	com/tencent/smtt/sdk/h:xUJ	Ljava/net/HttpURLConnection;
    //   3557: invokevirtual 862	java/net/HttpURLConnection:getInputStream	()Ljava/io/InputStream;
    //   3560: astore 27
    //   3562: aload 27
    //   3564: astore 28
    //   3566: aload 28
    //   3568: ifnull +3408 -> 6976
    //   3571: aload_0
    //   3572: getfield 636	com/tencent/smtt/sdk/h:xUJ	Ljava/net/HttpURLConnection;
    //   3575: invokevirtual 865	java/net/HttpURLConnection:getContentEncoding	()Ljava/lang/String;
    //   3578: astore 27
    //   3580: aload 27
    //   3582: ifnull +263 -> 3845
    //   3585: aload 27
    //   3587: ldc_w 867
    //   3590: invokevirtual 421	java/lang/String:contains	(Ljava/lang/CharSequence;)Z
    //   3593: ifeq +252 -> 3845
    //   3596: new 869	java/util/zip/GZIPInputStream
    //   3599: dup
    //   3600: aload 28
    //   3602: invokespecial 870	java/util/zip/GZIPInputStream:<init>	(Ljava/io/InputStream;)V
    //   3605: astore 27
    //   3607: sipush 8192
    //   3610: newarray <illegal type>
    //   3612: astore 29
    //   3614: new 872	java/io/FileOutputStream
    //   3617: dup
    //   3618: new 157	java/io/File
    //   3621: dup
    //   3622: aload_0
    //   3623: getfield 139	com/tencent/smtt/sdk/h:xUE	Ljava/io/File;
    //   3626: ldc -36
    //   3628: invokespecial 162	java/io/File:<init>	(Ljava/io/File;Ljava/lang/String;)V
    //   3631: iconst_1
    //   3632: invokespecial 875	java/io/FileOutputStream:<init>	(Ljava/io/File;Z)V
    //   3635: astore 30
    //   3637: lload 9
    //   3639: lstore 15
    //   3641: iload_2
    //   3642: istore 6
    //   3644: lload 9
    //   3646: lstore 17
    //   3648: iload_2
    //   3649: istore 7
    //   3651: invokestatic 696	java/lang/System:currentTimeMillis	()J
    //   3654: lstore 11
    //   3656: lload 19
    //   3658: lstore 13
    //   3660: lload 19
    //   3662: lstore 21
    //   3664: lload 11
    //   3666: lstore 19
    //   3668: lload 9
    //   3670: lstore 15
    //   3672: iload_2
    //   3673: istore 6
    //   3675: lload 9
    //   3677: lstore 17
    //   3679: iload_2
    //   3680: istore 7
    //   3682: aload_0
    //   3683: getfield 373	com/tencent/smtt/sdk/h:Lv	Z
    //   3686: ifeq +353 -> 4039
    //   3689: lload 9
    //   3691: lstore 15
    //   3693: iload_2
    //   3694: istore 6
    //   3696: lload 9
    //   3698: lstore 17
    //   3700: iload_2
    //   3701: istore 7
    //   3703: ldc -65
    //   3705: ldc_w 877
    //   3708: iconst_1
    //   3709: invokestatic 615	com/tencent/smtt/utils/TbsLog:i	(Ljava/lang/String;Ljava/lang/String;Z)V
    //   3712: lload 9
    //   3714: lstore 15
    //   3716: iload_2
    //   3717: istore 6
    //   3719: lload 9
    //   3721: lstore 17
    //   3723: iload_2
    //   3724: istore 7
    //   3726: aload_0
    //   3727: getfield 90	com/tencent/smtt/sdk/h:mContext	Landroid/content/Context;
    //   3730: invokestatic 226	com/tencent/smtt/sdk/k:gl	(Landroid/content/Context;)Lcom/tencent/smtt/sdk/k;
    //   3733: sipush 65227
    //   3736: invokevirtual 599	com/tencent/smtt/sdk/k:Ff	(I)V
    //   3739: iconst_0
    //   3740: istore_3
    //   3741: iload_3
    //   3742: ifeq +1107 -> 4849
    //   3745: lload 9
    //   3747: lstore 11
    //   3749: lload 9
    //   3751: lstore 13
    //   3753: iload_2
    //   3754: istore 5
    //   3756: aload 30
    //   3758: invokestatic 427	com/tencent/smtt/sdk/h:h	(Ljava/io/Closeable;)V
    //   3761: lload 9
    //   3763: lstore 11
    //   3765: lload 9
    //   3767: lstore 13
    //   3769: iload_2
    //   3770: istore 5
    //   3772: aload 27
    //   3774: invokestatic 427	com/tencent/smtt/sdk/h:h	(Ljava/io/Closeable;)V
    //   3777: lload 9
    //   3779: lstore 11
    //   3781: lload 9
    //   3783: lstore 13
    //   3785: iload_2
    //   3786: istore 5
    //   3788: aload 28
    //   3790: invokestatic 427	com/tencent/smtt/sdk/h:h	(Ljava/io/Closeable;)V
    //   3793: lload 9
    //   3795: lstore 11
    //   3797: iload_2
    //   3798: istore 5
    //   3800: iload 8
    //   3802: istore 6
    //   3804: iload_1
    //   3805: ifne -2789 -> 1016
    //   3808: aload_0
    //   3809: getfield 90	com/tencent/smtt/sdk/h:mContext	Landroid/content/Context;
    //   3812: invokestatic 226	com/tencent/smtt/sdk/k:gl	(Landroid/content/Context;)Lcom/tencent/smtt/sdk/k;
    //   3815: getfield 511	com/tencent/smtt/sdk/k:xVh	Ljava/util/Map;
    //   3818: ldc_w 655
    //   3821: lload 9
    //   3823: invokestatic 739	java/lang/Long:valueOf	(J)Ljava/lang/Long;
    //   3826: invokeinterface 524 3 0
    //   3831: pop
    //   3832: aload_0
    //   3833: getfield 90	com/tencent/smtt/sdk/h:mContext	Landroid/content/Context;
    //   3836: invokestatic 226	com/tencent/smtt/sdk/k:gl	(Landroid/content/Context;)Lcom/tencent/smtt/sdk/k;
    //   3839: invokevirtual 531	com/tencent/smtt/sdk/k:commit	()V
    //   3842: goto -3353 -> 489
    //   3845: aload 27
    //   3847: ifnull +185 -> 4032
    //   3850: aload 27
    //   3852: ldc_w 879
    //   3855: invokevirtual 421	java/lang/String:contains	(Ljava/lang/CharSequence;)Z
    //   3858: ifeq +174 -> 4032
    //   3861: new 881	java/util/zip/InflaterInputStream
    //   3864: dup
    //   3865: aload 28
    //   3867: new 883	java/util/zip/Inflater
    //   3870: dup
    //   3871: iconst_1
    //   3872: invokespecial 885	java/util/zip/Inflater:<init>	(Z)V
    //   3875: invokespecial 888	java/util/zip/InflaterInputStream:<init>	(Ljava/io/InputStream;Ljava/util/zip/Inflater;)V
    //   3878: astore 27
    //   3880: goto -273 -> 3607
    //   3883: astore 29
    //   3885: aconst_null
    //   3886: astore 27
    //   3888: aload 31
    //   3890: astore 30
    //   3892: aload 29
    //   3894: instanceof 890
    //   3897: ifne +11 -> 3908
    //   3900: aload 29
    //   3902: instanceof 892
    //   3905: ifeq +1081 -> 4986
    //   3908: aload_0
    //   3909: ldc_w 893
    //   3912: putfield 74	com/tencent/smtt/sdk/h:xUF	I
    //   3915: aload_0
    //   3916: lconst_0
    //   3917: invokespecial 895	com/tencent/smtt/sdk/h:fr	(J)V
    //   3920: aload_0
    //   3921: bipush 103
    //   3923: aload 29
    //   3925: invokestatic 336	com/tencent/smtt/sdk/h:i	(Ljava/lang/Throwable;)Ljava/lang/String;
    //   3928: iconst_0
    //   3929: invokespecial 340	com/tencent/smtt/sdk/h:j	(ILjava/lang/String;Z)V
    //   3932: lload 9
    //   3934: lstore 11
    //   3936: lload 9
    //   3938: lstore 13
    //   3940: iload_2
    //   3941: istore 5
    //   3943: aload 30
    //   3945: invokestatic 427	com/tencent/smtt/sdk/h:h	(Ljava/io/Closeable;)V
    //   3948: lload 9
    //   3950: lstore 11
    //   3952: lload 9
    //   3954: lstore 13
    //   3956: iload_2
    //   3957: istore 5
    //   3959: aload 27
    //   3961: invokestatic 427	com/tencent/smtt/sdk/h:h	(Ljava/io/Closeable;)V
    //   3964: lload 9
    //   3966: lstore 11
    //   3968: lload 9
    //   3970: lstore 13
    //   3972: iload_2
    //   3973: istore 5
    //   3975: aload 28
    //   3977: invokestatic 427	com/tencent/smtt/sdk/h:h	(Ljava/io/Closeable;)V
    //   3980: lload 9
    //   3982: lstore 11
    //   3984: iload_2
    //   3985: istore 5
    //   3987: iload 8
    //   3989: istore 6
    //   3991: iload_1
    //   3992: ifne -2976 -> 1016
    //   3995: aload_0
    //   3996: getfield 90	com/tencent/smtt/sdk/h:mContext	Landroid/content/Context;
    //   3999: invokestatic 226	com/tencent/smtt/sdk/k:gl	(Landroid/content/Context;)Lcom/tencent/smtt/sdk/k;
    //   4002: getfield 511	com/tencent/smtt/sdk/k:xVh	Ljava/util/Map;
    //   4005: ldc_w 655
    //   4008: lload 9
    //   4010: invokestatic 739	java/lang/Long:valueOf	(J)Ljava/lang/Long;
    //   4013: invokeinterface 524 3 0
    //   4018: pop
    //   4019: aload_0
    //   4020: getfield 90	com/tencent/smtt/sdk/h:mContext	Landroid/content/Context;
    //   4023: invokestatic 226	com/tencent/smtt/sdk/k:gl	(Landroid/content/Context;)Lcom/tencent/smtt/sdk/k;
    //   4026: invokevirtual 531	com/tencent/smtt/sdk/k:commit	()V
    //   4029: goto -3540 -> 489
    //   4032: aload 28
    //   4034: astore 27
    //   4036: goto -429 -> 3607
    //   4039: lload 9
    //   4041: lstore 15
    //   4043: iload_2
    //   4044: istore 6
    //   4046: lload 9
    //   4048: lstore 17
    //   4050: iload_2
    //   4051: istore 7
    //   4053: aload 27
    //   4055: aload 29
    //   4057: iconst_0
    //   4058: sipush 8192
    //   4061: invokevirtual 901	java/io/InputStream:read	([BII)I
    //   4064: istore_3
    //   4065: iload_3
    //   4066: ifgt +187 -> 4253
    //   4069: lload 9
    //   4071: lstore 15
    //   4073: iload_2
    //   4074: istore 6
    //   4076: lload 9
    //   4078: lstore 17
    //   4080: iload_2
    //   4081: istore 7
    //   4083: aload_0
    //   4084: getfield 80	com/tencent/smtt/sdk/h:xUU	[Ljava/lang/String;
    //   4087: ifnull +83 -> 4170
    //   4090: lload 9
    //   4092: lstore 15
    //   4094: iload_2
    //   4095: istore 6
    //   4097: lload 9
    //   4099: lstore 17
    //   4101: iload_2
    //   4102: istore 7
    //   4104: aload_0
    //   4105: iconst_1
    //   4106: iload 8
    //   4108: invokespecial 657	com/tencent/smtt/sdk/h:Q	(ZZ)Z
    //   4111: ifne +59 -> 4170
    //   4114: iload_1
    //   4115: ifne +29 -> 4144
    //   4118: lload 9
    //   4120: lstore 15
    //   4122: iload_2
    //   4123: istore 6
    //   4125: lload 9
    //   4127: lstore 17
    //   4129: iload_2
    //   4130: istore 7
    //   4132: aload_0
    //   4133: invokespecial 829	com/tencent/smtt/sdk/h:cnV	()Z
    //   4136: ifeq +8 -> 4144
    //   4139: iconst_1
    //   4140: istore_3
    //   4141: goto -400 -> 3741
    //   4144: lload 9
    //   4146: lstore 15
    //   4148: iload_2
    //   4149: istore 6
    //   4151: lload 9
    //   4153: lstore 17
    //   4155: iload_2
    //   4156: istore 7
    //   4158: aload_0
    //   4159: iconst_1
    //   4160: putfield 375	com/tencent/smtt/sdk/h:mFinished	Z
    //   4163: iconst_0
    //   4164: istore_3
    //   4165: iconst_0
    //   4166: istore_2
    //   4167: goto -426 -> 3741
    //   4170: lload 9
    //   4172: lstore 15
    //   4174: iload_2
    //   4175: istore 6
    //   4177: lload 9
    //   4179: lstore 17
    //   4181: iload_2
    //   4182: istore 7
    //   4184: aload_0
    //   4185: iconst_1
    //   4186: putfield 375	com/tencent/smtt/sdk/h:mFinished	Z
    //   4189: iload_2
    //   4190: istore 5
    //   4192: lload 9
    //   4194: lstore 15
    //   4196: iload_2
    //   4197: istore 6
    //   4199: lload 9
    //   4201: lstore 17
    //   4203: iload_2
    //   4204: istore 7
    //   4206: aload_0
    //   4207: getfield 80	com/tencent/smtt/sdk/h:xUU	[Ljava/lang/String;
    //   4210: ifnull +6 -> 4216
    //   4213: iconst_1
    //   4214: istore 5
    //   4216: lload 9
    //   4218: lstore 15
    //   4220: iload 5
    //   4222: istore 6
    //   4224: lload 9
    //   4226: lstore 17
    //   4228: iload 5
    //   4230: istore 7
    //   4232: aload_0
    //   4233: getfield 90	com/tencent/smtt/sdk/h:mContext	Landroid/content/Context;
    //   4236: invokestatic 226	com/tencent/smtt/sdk/k:gl	(Landroid/content/Context;)Lcom/tencent/smtt/sdk/k;
    //   4239: sipush 65225
    //   4242: invokevirtual 599	com/tencent/smtt/sdk/k:Ff	(I)V
    //   4245: iconst_0
    //   4246: istore_3
    //   4247: iload 5
    //   4249: istore_2
    //   4250: goto -509 -> 3741
    //   4253: lload 9
    //   4255: lstore 15
    //   4257: iload_2
    //   4258: istore 6
    //   4260: lload 9
    //   4262: lstore 17
    //   4264: iload_2
    //   4265: istore 7
    //   4267: aload 30
    //   4269: aload 29
    //   4271: iconst_0
    //   4272: iload_3
    //   4273: invokevirtual 905	java/io/FileOutputStream:write	([BII)V
    //   4276: lload 9
    //   4278: lstore 15
    //   4280: iload_2
    //   4281: istore 6
    //   4283: lload 9
    //   4285: lstore 17
    //   4287: iload_2
    //   4288: istore 7
    //   4290: aload 30
    //   4292: invokevirtual 908	java/io/FileOutputStream:flush	()V
    //   4295: lload 9
    //   4297: lstore 11
    //   4299: iload_1
    //   4300: ifne +265 -> 4565
    //   4303: lload 9
    //   4305: iload_3
    //   4306: i2l
    //   4307: ladd
    //   4308: lstore 9
    //   4310: lload 9
    //   4312: lload 25
    //   4314: lcmp
    //   4315: iflt +108 -> 4423
    //   4318: lload 9
    //   4320: lstore 15
    //   4322: iload_2
    //   4323: istore 6
    //   4325: lload 9
    //   4327: lstore 17
    //   4329: iload_2
    //   4330: istore 7
    //   4332: ldc -65
    //   4334: ldc_w 748
    //   4337: iconst_1
    //   4338: invokestatic 615	com/tencent/smtt/utils/TbsLog:i	(Ljava/lang/String;Ljava/lang/String;Z)V
    //   4341: lload 9
    //   4343: lstore 15
    //   4345: iload_2
    //   4346: istore 6
    //   4348: lload 9
    //   4350: lstore 17
    //   4352: iload_2
    //   4353: istore 7
    //   4355: aload_0
    //   4356: bipush 112
    //   4358: new 109	java/lang/StringBuilder
    //   4361: dup
    //   4362: ldc_w 910
    //   4365: invokespecial 114	java/lang/StringBuilder:<init>	(Ljava/lang/String;)V
    //   4368: lload 9
    //   4370: invokevirtual 276	java/lang/StringBuilder:append	(J)Ljava/lang/StringBuilder;
    //   4373: ldc_w 912
    //   4376: invokevirtual 122	java/lang/StringBuilder:append	(Ljava/lang/String;)Ljava/lang/StringBuilder;
    //   4379: lload 25
    //   4381: invokevirtual 276	java/lang/StringBuilder:append	(J)Ljava/lang/StringBuilder;
    //   4384: invokevirtual 125	java/lang/StringBuilder:toString	()Ljava/lang/String;
    //   4387: iconst_1
    //   4388: invokespecial 340	com/tencent/smtt/sdk/h:j	(ILjava/lang/String;Z)V
    //   4391: lload 9
    //   4393: lstore 15
    //   4395: iload_2
    //   4396: istore 6
    //   4398: lload 9
    //   4400: lstore 17
    //   4402: iload_2
    //   4403: istore 7
    //   4405: aload_0
    //   4406: getfield 90	com/tencent/smtt/sdk/h:mContext	Landroid/content/Context;
    //   4409: invokestatic 226	com/tencent/smtt/sdk/k:gl	(Landroid/content/Context;)Lcom/tencent/smtt/sdk/k;
    //   4412: sipush 65229
    //   4415: invokevirtual 599	com/tencent/smtt/sdk/k:Ff	(I)V
    //   4418: iconst_0
    //   4419: istore_3
    //   4420: goto -679 -> 3741
    //   4423: lload 9
    //   4425: lstore 11
    //   4427: lload 9
    //   4429: lstore 15
    //   4431: iload_2
    //   4432: istore 6
    //   4434: lload 9
    //   4436: lstore 17
    //   4438: iload_2
    //   4439: istore 7
    //   4441: aload_0
    //   4442: getfield 90	com/tencent/smtt/sdk/h:mContext	Landroid/content/Context;
    //   4445: invokestatic 742	com/tencent/smtt/utils/f:hv	(Landroid/content/Context;)Z
    //   4448: ifne +117 -> 4565
    //   4451: lload 9
    //   4453: lstore 15
    //   4455: iload_2
    //   4456: istore 6
    //   4458: lload 9
    //   4460: lstore 17
    //   4462: iload_2
    //   4463: istore 7
    //   4465: ldc -65
    //   4467: ldc_w 914
    //   4470: iconst_1
    //   4471: invokestatic 615	com/tencent/smtt/utils/TbsLog:i	(Ljava/lang/String;Ljava/lang/String;Z)V
    //   4474: lload 9
    //   4476: lstore 15
    //   4478: iload_2
    //   4479: istore 6
    //   4481: lload 9
    //   4483: lstore 17
    //   4485: iload_2
    //   4486: istore 7
    //   4488: aload_0
    //   4489: bipush 105
    //   4491: new 109	java/lang/StringBuilder
    //   4494: dup
    //   4495: ldc_w 916
    //   4498: invokespecial 114	java/lang/StringBuilder:<init>	(Ljava/lang/String;)V
    //   4501: invokestatic 919	com/tencent/smtt/utils/u:cpv	()J
    //   4504: invokevirtual 276	java/lang/StringBuilder:append	(J)Ljava/lang/StringBuilder;
    //   4507: ldc_w 921
    //   4510: invokevirtual 122	java/lang/StringBuilder:append	(Ljava/lang/String;)Ljava/lang/StringBuilder;
    //   4513: aload_0
    //   4514: getfield 90	com/tencent/smtt/sdk/h:mContext	Landroid/content/Context;
    //   4517: invokestatic 226	com/tencent/smtt/sdk/k:gl	(Landroid/content/Context;)Lcom/tencent/smtt/sdk/k;
    //   4520: invokevirtual 924	com/tencent/smtt/sdk/k:cof	()J
    //   4523: invokevirtual 276	java/lang/StringBuilder:append	(J)Ljava/lang/StringBuilder;
    //   4526: invokevirtual 125	java/lang/StringBuilder:toString	()Ljava/lang/String;
    //   4529: iconst_1
    //   4530: invokespecial 340	com/tencent/smtt/sdk/h:j	(ILjava/lang/String;Z)V
    //   4533: lload 9
    //   4535: lstore 15
    //   4537: iload_2
    //   4538: istore 6
    //   4540: lload 9
    //   4542: lstore 17
    //   4544: iload_2
    //   4545: istore 7
    //   4547: aload_0
    //   4548: getfield 90	com/tencent/smtt/sdk/h:mContext	Landroid/content/Context;
    //   4551: invokestatic 226	com/tencent/smtt/sdk/k:gl	(Landroid/content/Context;)Lcom/tencent/smtt/sdk/k;
    //   4554: sipush 65228
    //   4557: invokevirtual 599	com/tencent/smtt/sdk/k:Ff	(I)V
    //   4560: iconst_0
    //   4561: istore_3
    //   4562: goto -821 -> 3741
    //   4565: iload_3
    //   4566: i2l
    //   4567: lstore 9
    //   4569: invokestatic 696	java/lang/System:currentTimeMillis	()J
    //   4572: lstore 17
    //   4574: aload_0
    //   4575: getfield 102	com/tencent/smtt/sdk/h:xUL	Lcom/tencent/smtt/sdk/r$b;
    //   4578: astore 31
    //   4580: aload 31
    //   4582: lload 17
    //   4584: lload 23
    //   4586: lsub
    //   4587: aload 31
    //   4589: getfield 927	com/tencent/smtt/sdk/r$b:xWs	J
    //   4592: ladd
    //   4593: putfield 927	com/tencent/smtt/sdk/r$b:xWs	J
    //   4596: aload_0
    //   4597: getfield 102	com/tencent/smtt/sdk/h:xUL	Lcom/tencent/smtt/sdk/r$b;
    //   4600: astore 31
    //   4602: aload 31
    //   4604: lload 9
    //   4606: aload 31
    //   4608: getfield 930	com/tencent/smtt/sdk/r$b:xWw	J
    //   4611: ladd
    //   4612: putfield 930	com/tencent/smtt/sdk/r$b:xWw	J
    //   4615: invokestatic 696	java/lang/System:currentTimeMillis	()J
    //   4618: lstore 23
    //   4620: iload_3
    //   4621: i2l
    //   4622: lload 21
    //   4624: ladd
    //   4625: lstore 15
    //   4627: lload 23
    //   4629: lload 19
    //   4631: lsub
    //   4632: ldc2_w 931
    //   4635: lcmp
    //   4636: ifle +2329 -> 6965
    //   4639: ldc -65
    //   4641: new 109	java/lang/StringBuilder
    //   4644: dup
    //   4645: ldc_w 934
    //   4648: invokespecial 114	java/lang/StringBuilder:<init>	(Ljava/lang/String;)V
    //   4651: lload 15
    //   4653: invokevirtual 276	java/lang/StringBuilder:append	(J)Ljava/lang/StringBuilder;
    //   4656: ldc_w 840
    //   4659: invokevirtual 122	java/lang/StringBuilder:append	(Ljava/lang/String;)Ljava/lang/StringBuilder;
    //   4662: aload_0
    //   4663: getfield 367	com/tencent/smtt/sdk/h:mContentLength	J
    //   4666: invokevirtual 276	java/lang/StringBuilder:append	(J)Ljava/lang/StringBuilder;
    //   4669: invokevirtual 125	java/lang/StringBuilder:toString	()Ljava/lang/String;
    //   4672: iconst_1
    //   4673: invokestatic 615	com/tencent/smtt/utils/TbsLog:i	(Ljava/lang/String;Ljava/lang/String;Z)V
    //   4676: getstatic 537	com/tencent/smtt/sdk/QbSdk:xUb	Lcom/tencent/smtt/sdk/q;
    //   4679: ifnull +27 -> 4706
    //   4682: lload 15
    //   4684: l2d
    //   4685: aload_0
    //   4686: getfield 367	com/tencent/smtt/sdk/h:mContentLength	J
    //   4689: l2d
    //   4690: ddiv
    //   4691: ldc2_w 935
    //   4694: dmul
    //   4695: d2i
    //   4696: istore_3
    //   4697: getstatic 537	com/tencent/smtt/sdk/QbSdk:xUb	Lcom/tencent/smtt/sdk/q;
    //   4700: iload_3
    //   4701: invokeinterface 939 2 0
    //   4706: lload 13
    //   4708: lstore 9
    //   4710: iload_1
    //   4711: ifne +111 -> 4822
    //   4714: lload 13
    //   4716: lstore 9
    //   4718: lload 15
    //   4720: lload 13
    //   4722: lsub
    //   4723: ldc2_w 940
    //   4726: lcmp
    //   4727: ifle +95 -> 4822
    //   4730: aload_0
    //   4731: getfield 90	com/tencent/smtt/sdk/h:mContext	Landroid/content/Context;
    //   4734: invokestatic 171	com/tencent/smtt/sdk/l:gp	(Landroid/content/Context;)Z
    //   4737: ifne +81 -> 4818
    //   4740: aload_0
    //   4741: getfield 90	com/tencent/smtt/sdk/h:mContext	Landroid/content/Context;
    //   4744: invokestatic 706	com/tencent/smtt/utils/b:ho	(Landroid/content/Context;)I
    //   4747: iconst_3
    //   4748: if_icmpeq +9 -> 4757
    //   4751: invokestatic 819	com/tencent/smtt/sdk/QbSdk:getDownloadWithoutWifi	()Z
    //   4754: ifeq +13 -> 4767
    //   4757: aload_0
    //   4758: getfield 90	com/tencent/smtt/sdk/h:mContext	Landroid/content/Context;
    //   4761: invokestatic 706	com/tencent/smtt/utils/b:ho	(Landroid/content/Context;)I
    //   4764: ifne +54 -> 4818
    //   4767: aload_0
    //   4768: invokevirtual 822	com/tencent/smtt/sdk/h:stopDownload	()V
    //   4771: getstatic 537	com/tencent/smtt/sdk/QbSdk:xUb	Lcom/tencent/smtt/sdk/q;
    //   4774: ifnull +13 -> 4787
    //   4777: getstatic 537	com/tencent/smtt/sdk/QbSdk:xUb	Lcom/tencent/smtt/sdk/q;
    //   4780: bipush 111
    //   4782: invokeinterface 542 2 0
    //   4787: ldc -65
    //   4789: ldc_w 943
    //   4792: iconst_0
    //   4793: invokestatic 615	com/tencent/smtt/utils/TbsLog:i	(Ljava/lang/String;Ljava/lang/String;Z)V
    //   4796: aload_0
    //   4797: getfield 90	com/tencent/smtt/sdk/h:mContext	Landroid/content/Context;
    //   4800: invokestatic 226	com/tencent/smtt/sdk/k:gl	(Landroid/content/Context;)Lcom/tencent/smtt/sdk/k;
    //   4803: sipush 65232
    //   4806: invokevirtual 599	com/tencent/smtt/sdk/k:Ff	(I)V
    //   4809: iconst_0
    //   4810: istore_3
    //   4811: lload 11
    //   4813: lstore 9
    //   4815: goto -1074 -> 3741
    //   4818: lload 15
    //   4820: lstore 9
    //   4822: lload 23
    //   4824: lstore 13
    //   4826: lload 13
    //   4828: lstore 19
    //   4830: lload 17
    //   4832: lstore 23
    //   4834: lload 9
    //   4836: lstore 13
    //   4838: lload 11
    //   4840: lstore 9
    //   4842: lload 15
    //   4844: lstore 21
    //   4846: goto -1178 -> 3668
    //   4849: lload 9
    //   4851: lstore 11
    //   4853: iload_2
    //   4854: istore 5
    //   4856: lload 9
    //   4858: lstore 13
    //   4860: aload 30
    //   4862: invokestatic 427	com/tencent/smtt/sdk/h:h	(Ljava/io/Closeable;)V
    //   4865: lload 9
    //   4867: lstore 11
    //   4869: iload_2
    //   4870: istore 5
    //   4872: lload 9
    //   4874: lstore 13
    //   4876: aload 27
    //   4878: invokestatic 427	com/tencent/smtt/sdk/h:h	(Ljava/io/Closeable;)V
    //   4881: lload 9
    //   4883: lstore 11
    //   4885: iload_2
    //   4886: istore 5
    //   4888: lload 9
    //   4890: lstore 13
    //   4892: aload 28
    //   4894: invokestatic 427	com/tencent/smtt/sdk/h:h	(Ljava/io/Closeable;)V
    //   4897: lload 9
    //   4899: lstore 11
    //   4901: iload_2
    //   4902: istore 5
    //   4904: lload 9
    //   4906: lstore 13
    //   4908: aload_0
    //   4909: getfield 375	com/tencent/smtt/sdk/h:mFinished	Z
    //   4912: ifne +27 -> 4939
    //   4915: lload 9
    //   4917: lstore 11
    //   4919: iload_2
    //   4920: istore 5
    //   4922: lload 9
    //   4924: lstore 13
    //   4926: aload_0
    //   4927: getfield 90	com/tencent/smtt/sdk/h:mContext	Landroid/content/Context;
    //   4930: invokestatic 226	com/tencent/smtt/sdk/k:gl	(Landroid/content/Context;)Lcom/tencent/smtt/sdk/k;
    //   4933: sipush 65217
    //   4936: invokevirtual 599	com/tencent/smtt/sdk/k:Ff	(I)V
    //   4939: iload_2
    //   4940: istore 5
    //   4942: iload_1
    //   4943: ifne -4407 -> 536
    //   4946: aload_0
    //   4947: getfield 90	com/tencent/smtt/sdk/h:mContext	Landroid/content/Context;
    //   4950: invokestatic 226	com/tencent/smtt/sdk/k:gl	(Landroid/content/Context;)Lcom/tencent/smtt/sdk/k;
    //   4953: getfield 511	com/tencent/smtt/sdk/k:xVh	Ljava/util/Map;
    //   4956: ldc_w 655
    //   4959: lload 9
    //   4961: invokestatic 739	java/lang/Long:valueOf	(J)Ljava/lang/Long;
    //   4964: invokeinterface 524 3 0
    //   4969: pop
    //   4970: aload_0
    //   4971: getfield 90	com/tencent/smtt/sdk/h:mContext	Landroid/content/Context;
    //   4974: invokestatic 226	com/tencent/smtt/sdk/k:gl	(Landroid/content/Context;)Lcom/tencent/smtt/sdk/k;
    //   4977: invokevirtual 531	com/tencent/smtt/sdk/k:commit	()V
    //   4980: iload_2
    //   4981: istore 5
    //   4983: goto -4447 -> 536
    //   4986: iload_1
    //   4987: ifne +166 -> 5153
    //   4990: aload_0
    //   4991: getfield 90	com/tencent/smtt/sdk/h:mContext	Landroid/content/Context;
    //   4994: invokestatic 742	com/tencent/smtt/utils/f:hv	(Landroid/content/Context;)Z
    //   4997: ifne +156 -> 5153
    //   5000: aload_0
    //   5001: bipush 105
    //   5003: new 109	java/lang/StringBuilder
    //   5006: dup
    //   5007: ldc_w 916
    //   5010: invokespecial 114	java/lang/StringBuilder:<init>	(Ljava/lang/String;)V
    //   5013: invokestatic 919	com/tencent/smtt/utils/u:cpv	()J
    //   5016: invokevirtual 276	java/lang/StringBuilder:append	(J)Ljava/lang/StringBuilder;
    //   5019: ldc_w 921
    //   5022: invokevirtual 122	java/lang/StringBuilder:append	(Ljava/lang/String;)Ljava/lang/StringBuilder;
    //   5025: aload_0
    //   5026: getfield 90	com/tencent/smtt/sdk/h:mContext	Landroid/content/Context;
    //   5029: invokestatic 226	com/tencent/smtt/sdk/k:gl	(Landroid/content/Context;)Lcom/tencent/smtt/sdk/k;
    //   5032: invokevirtual 924	com/tencent/smtt/sdk/k:cof	()J
    //   5035: invokevirtual 276	java/lang/StringBuilder:append	(J)Ljava/lang/StringBuilder;
    //   5038: invokevirtual 125	java/lang/StringBuilder:toString	()Ljava/lang/String;
    //   5041: iconst_1
    //   5042: invokespecial 340	com/tencent/smtt/sdk/h:j	(ILjava/lang/String;Z)V
    //   5045: aload_0
    //   5046: getfield 90	com/tencent/smtt/sdk/h:mContext	Landroid/content/Context;
    //   5049: invokestatic 226	com/tencent/smtt/sdk/k:gl	(Landroid/content/Context;)Lcom/tencent/smtt/sdk/k;
    //   5052: sipush 65228
    //   5055: invokevirtual 599	com/tencent/smtt/sdk/k:Ff	(I)V
    //   5058: lload 9
    //   5060: lstore 11
    //   5062: lload 9
    //   5064: lstore 13
    //   5066: iload_2
    //   5067: istore 5
    //   5069: aload 30
    //   5071: invokestatic 427	com/tencent/smtt/sdk/h:h	(Ljava/io/Closeable;)V
    //   5074: lload 9
    //   5076: lstore 11
    //   5078: lload 9
    //   5080: lstore 13
    //   5082: iload_2
    //   5083: istore 5
    //   5085: aload 27
    //   5087: invokestatic 427	com/tencent/smtt/sdk/h:h	(Ljava/io/Closeable;)V
    //   5090: lload 9
    //   5092: lstore 11
    //   5094: lload 9
    //   5096: lstore 13
    //   5098: iload_2
    //   5099: istore 5
    //   5101: aload 28
    //   5103: invokestatic 427	com/tencent/smtt/sdk/h:h	(Ljava/io/Closeable;)V
    //   5106: iload_2
    //   5107: istore 5
    //   5109: iload_1
    //   5110: ifne +1849 -> 6959
    //   5113: aload_0
    //   5114: getfield 90	com/tencent/smtt/sdk/h:mContext	Landroid/content/Context;
    //   5117: invokestatic 226	com/tencent/smtt/sdk/k:gl	(Landroid/content/Context;)Lcom/tencent/smtt/sdk/k;
    //   5120: getfield 511	com/tencent/smtt/sdk/k:xVh	Ljava/util/Map;
    //   5123: ldc_w 655
    //   5126: lload 9
    //   5128: invokestatic 739	java/lang/Long:valueOf	(J)Ljava/lang/Long;
    //   5131: invokeinterface 524 3 0
    //   5136: pop
    //   5137: aload_0
    //   5138: getfield 90	com/tencent/smtt/sdk/h:mContext	Landroid/content/Context;
    //   5141: invokestatic 226	com/tencent/smtt/sdk/k:gl	(Landroid/content/Context;)Lcom/tencent/smtt/sdk/k;
    //   5144: invokevirtual 531	com/tencent/smtt/sdk/k:commit	()V
    //   5147: iload_2
    //   5148: istore 5
    //   5150: goto -4614 -> 536
    //   5153: aload_0
    //   5154: lconst_0
    //   5155: invokespecial 895	com/tencent/smtt/sdk/h:fr	(J)V
    //   5158: iconst_0
    //   5159: istore_3
    //   5160: new 157	java/io/File
    //   5163: dup
    //   5164: aload_0
    //   5165: getfield 139	com/tencent/smtt/sdk/h:xUE	Ljava/io/File;
    //   5168: ldc -36
    //   5170: invokespecial 162	java/io/File:<init>	(Ljava/io/File;Ljava/lang/String;)V
    //   5173: invokevirtual 218	java/io/File:exists	()Z
    //   5176: ifeq +5 -> 5181
    //   5179: iconst_1
    //   5180: istore_3
    //   5181: iload_3
    //   5182: ifne +115 -> 5297
    //   5185: aload_0
    //   5186: bipush 106
    //   5188: aload 29
    //   5190: invokestatic 336	com/tencent/smtt/sdk/h:i	(Ljava/lang/Throwable;)Ljava/lang/String;
    //   5193: iconst_0
    //   5194: invokespecial 340	com/tencent/smtt/sdk/h:j	(ILjava/lang/String;Z)V
    //   5197: lload 9
    //   5199: lstore 11
    //   5201: lload 9
    //   5203: lstore 13
    //   5205: iload_2
    //   5206: istore 5
    //   5208: aload 30
    //   5210: invokestatic 427	com/tencent/smtt/sdk/h:h	(Ljava/io/Closeable;)V
    //   5213: lload 9
    //   5215: lstore 11
    //   5217: lload 9
    //   5219: lstore 13
    //   5221: iload_2
    //   5222: istore 5
    //   5224: aload 27
    //   5226: invokestatic 427	com/tencent/smtt/sdk/h:h	(Ljava/io/Closeable;)V
    //   5229: lload 9
    //   5231: lstore 11
    //   5233: lload 9
    //   5235: lstore 13
    //   5237: iload_2
    //   5238: istore 5
    //   5240: aload 28
    //   5242: invokestatic 427	com/tencent/smtt/sdk/h:h	(Ljava/io/Closeable;)V
    //   5245: lload 9
    //   5247: lstore 11
    //   5249: iload_2
    //   5250: istore 5
    //   5252: iload 8
    //   5254: istore 6
    //   5256: iload_1
    //   5257: ifne -4241 -> 1016
    //   5260: aload_0
    //   5261: getfield 90	com/tencent/smtt/sdk/h:mContext	Landroid/content/Context;
    //   5264: invokestatic 226	com/tencent/smtt/sdk/k:gl	(Landroid/content/Context;)Lcom/tencent/smtt/sdk/k;
    //   5267: getfield 511	com/tencent/smtt/sdk/k:xVh	Ljava/util/Map;
    //   5270: ldc_w 655
    //   5273: lload 9
    //   5275: invokestatic 739	java/lang/Long:valueOf	(J)Ljava/lang/Long;
    //   5278: invokeinterface 524 3 0
    //   5283: pop
    //   5284: aload_0
    //   5285: getfield 90	com/tencent/smtt/sdk/h:mContext	Landroid/content/Context;
    //   5288: invokestatic 226	com/tencent/smtt/sdk/k:gl	(Landroid/content/Context;)Lcom/tencent/smtt/sdk/k;
    //   5291: invokevirtual 531	com/tencent/smtt/sdk/k:commit	()V
    //   5294: goto -4805 -> 489
    //   5297: aload_0
    //   5298: bipush 104
    //   5300: aload 29
    //   5302: invokestatic 336	com/tencent/smtt/sdk/h:i	(Ljava/lang/Throwable;)Ljava/lang/String;
    //   5305: iconst_0
    //   5306: invokespecial 340	com/tencent/smtt/sdk/h:j	(ILjava/lang/String;Z)V
    //   5309: goto -112 -> 5197
    //   5312: astore 29
    //   5314: aload 27
    //   5316: astore 31
    //   5318: aload 30
    //   5320: astore 27
    //   5322: lload 9
    //   5324: lstore 11
    //   5326: iload_2
    //   5327: istore 5
    //   5329: lload 9
    //   5331: lstore 13
    //   5333: aload 27
    //   5335: invokestatic 427	com/tencent/smtt/sdk/h:h	(Ljava/io/Closeable;)V
    //   5338: lload 9
    //   5340: lstore 11
    //   5342: iload_2
    //   5343: istore 5
    //   5345: lload 9
    //   5347: lstore 13
    //   5349: aload 31
    //   5351: invokestatic 427	com/tencent/smtt/sdk/h:h	(Ljava/io/Closeable;)V
    //   5354: lload 9
    //   5356: lstore 11
    //   5358: iload_2
    //   5359: istore 5
    //   5361: lload 9
    //   5363: lstore 13
    //   5365: aload 28
    //   5367: invokestatic 427	com/tencent/smtt/sdk/h:h	(Ljava/io/Closeable;)V
    //   5370: lload 9
    //   5372: lstore 11
    //   5374: iload_2
    //   5375: istore 5
    //   5377: lload 9
    //   5379: lstore 13
    //   5381: aload 29
    //   5383: athrow
    //   5384: iload_3
    //   5385: sipush 300
    //   5388: if_icmplt +221 -> 5609
    //   5391: iload_3
    //   5392: sipush 307
    //   5395: if_icmpgt +214 -> 5609
    //   5398: lload 9
    //   5400: lstore 11
    //   5402: iload_2
    //   5403: istore 5
    //   5405: lload 9
    //   5407: lstore 13
    //   5409: aload_0
    //   5410: getfield 636	com/tencent/smtt/sdk/h:xUJ	Ljava/net/HttpURLConnection;
    //   5413: ldc_w 945
    //   5416: invokevirtual 949	java/net/HttpURLConnection:getHeaderField	(Ljava/lang/String;)Ljava/lang/String;
    //   5419: astore 27
    //   5421: lload 9
    //   5423: lstore 11
    //   5425: iload_2
    //   5426: istore 5
    //   5428: lload 9
    //   5430: lstore 13
    //   5432: aload 27
    //   5434: invokestatic 954	android/text/TextUtils:isEmpty	(Ljava/lang/CharSequence;)Z
    //   5437: ifne +82 -> 5519
    //   5440: lload 9
    //   5442: lstore 11
    //   5444: iload_2
    //   5445: istore 5
    //   5447: lload 9
    //   5449: lstore 13
    //   5451: aload_0
    //   5452: aload 27
    //   5454: putfield 369	com/tencent/smtt/sdk/h:xUD	Ljava/lang/String;
    //   5457: lload 9
    //   5459: lstore 11
    //   5461: iload_2
    //   5462: istore 5
    //   5464: lload 9
    //   5466: lstore 13
    //   5468: aload_0
    //   5469: aload_0
    //   5470: getfield 363	com/tencent/smtt/sdk/h:xUI	I
    //   5473: iconst_1
    //   5474: iadd
    //   5475: putfield 363	com/tencent/smtt/sdk/h:xUI	I
    //   5478: iload_1
    //   5479: ifne +1483 -> 6962
    //   5482: aload_0
    //   5483: getfield 90	com/tencent/smtt/sdk/h:mContext	Landroid/content/Context;
    //   5486: invokestatic 226	com/tencent/smtt/sdk/k:gl	(Landroid/content/Context;)Lcom/tencent/smtt/sdk/k;
    //   5489: getfield 511	com/tencent/smtt/sdk/k:xVh	Ljava/util/Map;
    //   5492: ldc_w 655
    //   5495: lload 9
    //   5497: invokestatic 739	java/lang/Long:valueOf	(J)Ljava/lang/Long;
    //   5500: invokeinterface 524 3 0
    //   5505: pop
    //   5506: aload_0
    //   5507: getfield 90	com/tencent/smtt/sdk/h:mContext	Landroid/content/Context;
    //   5510: invokestatic 226	com/tencent/smtt/sdk/k:gl	(Landroid/content/Context;)Lcom/tencent/smtt/sdk/k;
    //   5513: invokevirtual 531	com/tencent/smtt/sdk/k:commit	()V
    //   5516: goto -5027 -> 489
    //   5519: lload 9
    //   5521: lstore 11
    //   5523: iload_2
    //   5524: istore 5
    //   5526: lload 9
    //   5528: lstore 13
    //   5530: aload_0
    //   5531: bipush 124
    //   5533: aconst_null
    //   5534: iconst_1
    //   5535: invokespecial 340	com/tencent/smtt/sdk/h:j	(ILjava/lang/String;Z)V
    //   5538: lload 9
    //   5540: lstore 11
    //   5542: iload_2
    //   5543: istore 5
    //   5545: lload 9
    //   5547: lstore 13
    //   5549: aload_0
    //   5550: getfield 90	com/tencent/smtt/sdk/h:mContext	Landroid/content/Context;
    //   5553: invokestatic 226	com/tencent/smtt/sdk/k:gl	(Landroid/content/Context;)Lcom/tencent/smtt/sdk/k;
    //   5556: sipush 65224
    //   5559: invokevirtual 599	com/tencent/smtt/sdk/k:Ff	(I)V
    //   5562: iload_2
    //   5563: istore 5
    //   5565: iload_1
    //   5566: ifne -5030 -> 536
    //   5569: aload_0
    //   5570: getfield 90	com/tencent/smtt/sdk/h:mContext	Landroid/content/Context;
    //   5573: invokestatic 226	com/tencent/smtt/sdk/k:gl	(Landroid/content/Context;)Lcom/tencent/smtt/sdk/k;
    //   5576: getfield 511	com/tencent/smtt/sdk/k:xVh	Ljava/util/Map;
    //   5579: ldc_w 655
    //   5582: lload 9
    //   5584: invokestatic 739	java/lang/Long:valueOf	(J)Ljava/lang/Long;
    //   5587: invokeinterface 524 3 0
    //   5592: pop
    //   5593: aload_0
    //   5594: getfield 90	com/tencent/smtt/sdk/h:mContext	Landroid/content/Context;
    //   5597: invokestatic 226	com/tencent/smtt/sdk/k:gl	(Landroid/content/Context;)Lcom/tencent/smtt/sdk/k;
    //   5600: invokevirtual 531	com/tencent/smtt/sdk/k:commit	()V
    //   5603: iload_2
    //   5604: istore 5
    //   5606: goto -5070 -> 536
    //   5609: lload 9
    //   5611: lstore 11
    //   5613: iload_2
    //   5614: istore 5
    //   5616: lload 9
    //   5618: lstore 13
    //   5620: aload_0
    //   5621: bipush 102
    //   5623: iload_3
    //   5624: invokestatic 957	java/lang/String:valueOf	(I)Ljava/lang/String;
    //   5627: iconst_0
    //   5628: invokespecial 340	com/tencent/smtt/sdk/h:j	(ILjava/lang/String;Z)V
    //   5631: iload_3
    //   5632: sipush 416
    //   5635: if_icmpne +185 -> 5820
    //   5638: lload 9
    //   5640: lstore 11
    //   5642: iload_2
    //   5643: istore 5
    //   5645: lload 9
    //   5647: lstore 13
    //   5649: aload_0
    //   5650: iconst_1
    //   5651: iload 8
    //   5653: invokespecial 657	com/tencent/smtt/sdk/h:Q	(ZZ)Z
    //   5656: ifeq +76 -> 5732
    //   5659: iconst_1
    //   5660: istore 5
    //   5662: iconst_1
    //   5663: istore_2
    //   5664: lload 9
    //   5666: lstore 11
    //   5668: lload 9
    //   5670: lstore 13
    //   5672: aload_0
    //   5673: getfield 90	com/tencent/smtt/sdk/h:mContext	Landroid/content/Context;
    //   5676: invokestatic 226	com/tencent/smtt/sdk/k:gl	(Landroid/content/Context;)Lcom/tencent/smtt/sdk/k;
    //   5679: sipush 65322
    //   5682: invokevirtual 599	com/tencent/smtt/sdk/k:Ff	(I)V
    //   5685: iload_2
    //   5686: istore 5
    //   5688: iload_1
    //   5689: ifne -5153 -> 536
    //   5692: aload_0
    //   5693: getfield 90	com/tencent/smtt/sdk/h:mContext	Landroid/content/Context;
    //   5696: invokestatic 226	com/tencent/smtt/sdk/k:gl	(Landroid/content/Context;)Lcom/tencent/smtt/sdk/k;
    //   5699: getfield 511	com/tencent/smtt/sdk/k:xVh	Ljava/util/Map;
    //   5702: ldc_w 655
    //   5705: lload 9
    //   5707: invokestatic 739	java/lang/Long:valueOf	(J)Ljava/lang/Long;
    //   5710: invokeinterface 524 3 0
    //   5715: pop
    //   5716: aload_0
    //   5717: getfield 90	com/tencent/smtt/sdk/h:mContext	Landroid/content/Context;
    //   5720: invokestatic 226	com/tencent/smtt/sdk/k:gl	(Landroid/content/Context;)Lcom/tencent/smtt/sdk/k;
    //   5723: invokevirtual 531	com/tencent/smtt/sdk/k:commit	()V
    //   5726: iload_2
    //   5727: istore 5
    //   5729: goto -5193 -> 536
    //   5732: lload 9
    //   5734: lstore 11
    //   5736: iload_2
    //   5737: istore 5
    //   5739: lload 9
    //   5741: lstore 13
    //   5743: aload_0
    //   5744: iconst_0
    //   5745: invokespecial 959	com/tencent/smtt/sdk/h:mZ	(Z)Z
    //   5748: pop
    //   5749: lload 9
    //   5751: lstore 11
    //   5753: iload_2
    //   5754: istore 5
    //   5756: lload 9
    //   5758: lstore 13
    //   5760: aload_0
    //   5761: getfield 90	com/tencent/smtt/sdk/h:mContext	Landroid/content/Context;
    //   5764: invokestatic 226	com/tencent/smtt/sdk/k:gl	(Landroid/content/Context;)Lcom/tencent/smtt/sdk/k;
    //   5767: sipush 65223
    //   5770: invokevirtual 599	com/tencent/smtt/sdk/k:Ff	(I)V
    //   5773: iload_2
    //   5774: istore 5
    //   5776: iload_1
    //   5777: ifne -5241 -> 536
    //   5780: aload_0
    //   5781: getfield 90	com/tencent/smtt/sdk/h:mContext	Landroid/content/Context;
    //   5784: invokestatic 226	com/tencent/smtt/sdk/k:gl	(Landroid/content/Context;)Lcom/tencent/smtt/sdk/k;
    //   5787: getfield 511	com/tencent/smtt/sdk/k:xVh	Ljava/util/Map;
    //   5790: ldc_w 655
    //   5793: lload 9
    //   5795: invokestatic 739	java/lang/Long:valueOf	(J)Ljava/lang/Long;
    //   5798: invokeinterface 524 3 0
    //   5803: pop
    //   5804: aload_0
    //   5805: getfield 90	com/tencent/smtt/sdk/h:mContext	Landroid/content/Context;
    //   5808: invokestatic 226	com/tencent/smtt/sdk/k:gl	(Landroid/content/Context;)Lcom/tencent/smtt/sdk/k;
    //   5811: invokevirtual 531	com/tencent/smtt/sdk/k:commit	()V
    //   5814: iload_2
    //   5815: istore 5
    //   5817: goto -5281 -> 536
    //   5820: iload_3
    //   5821: sipush 403
    //   5824: if_icmpeq +10 -> 5834
    //   5827: iload_3
    //   5828: sipush 406
    //   5831: if_icmpne +96 -> 5927
    //   5834: lload 9
    //   5836: lstore 11
    //   5838: iload_2
    //   5839: istore 5
    //   5841: lload 9
    //   5843: lstore 13
    //   5845: aload_0
    //   5846: getfield 367	com/tencent/smtt/sdk/h:mContentLength	J
    //   5849: ldc2_w 364
    //   5852: lcmp
    //   5853: ifne +74 -> 5927
    //   5856: lload 9
    //   5858: lstore 11
    //   5860: iload_2
    //   5861: istore 5
    //   5863: lload 9
    //   5865: lstore 13
    //   5867: aload_0
    //   5868: getfield 90	com/tencent/smtt/sdk/h:mContext	Landroid/content/Context;
    //   5871: invokestatic 226	com/tencent/smtt/sdk/k:gl	(Landroid/content/Context;)Lcom/tencent/smtt/sdk/k;
    //   5874: sipush 65222
    //   5877: invokevirtual 599	com/tencent/smtt/sdk/k:Ff	(I)V
    //   5880: iload_2
    //   5881: istore 5
    //   5883: iload_1
    //   5884: ifne -5348 -> 536
    //   5887: aload_0
    //   5888: getfield 90	com/tencent/smtt/sdk/h:mContext	Landroid/content/Context;
    //   5891: invokestatic 226	com/tencent/smtt/sdk/k:gl	(Landroid/content/Context;)Lcom/tencent/smtt/sdk/k;
    //   5894: getfield 511	com/tencent/smtt/sdk/k:xVh	Ljava/util/Map;
    //   5897: ldc_w 655
    //   5900: lload 9
    //   5902: invokestatic 739	java/lang/Long:valueOf	(J)Ljava/lang/Long;
    //   5905: invokeinterface 524 3 0
    //   5910: pop
    //   5911: aload_0
    //   5912: getfield 90	com/tencent/smtt/sdk/h:mContext	Landroid/content/Context;
    //   5915: invokestatic 226	com/tencent/smtt/sdk/k:gl	(Landroid/content/Context;)Lcom/tencent/smtt/sdk/k;
    //   5918: invokevirtual 531	com/tencent/smtt/sdk/k:commit	()V
    //   5921: iload_2
    //   5922: istore 5
    //   5924: goto -5388 -> 536
    //   5927: iload_3
    //   5928: sipush 202
    //   5931: if_icmpne +44 -> 5975
    //   5934: iload_1
    //   5935: ifne +1027 -> 6962
    //   5938: aload_0
    //   5939: getfield 90	com/tencent/smtt/sdk/h:mContext	Landroid/content/Context;
    //   5942: invokestatic 226	com/tencent/smtt/sdk/k:gl	(Landroid/content/Context;)Lcom/tencent/smtt/sdk/k;
    //   5945: getfield 511	com/tencent/smtt/sdk/k:xVh	Ljava/util/Map;
    //   5948: ldc_w 655
    //   5951: lload 9
    //   5953: invokestatic 739	java/lang/Long:valueOf	(J)Ljava/lang/Long;
    //   5956: invokeinterface 524 3 0
    //   5961: pop
    //   5962: aload_0
    //   5963: getfield 90	com/tencent/smtt/sdk/h:mContext	Landroid/content/Context;
    //   5966: invokestatic 226	com/tencent/smtt/sdk/k:gl	(Landroid/content/Context;)Lcom/tencent/smtt/sdk/k;
    //   5969: invokevirtual 531	com/tencent/smtt/sdk/k:commit	()V
    //   5972: goto -5483 -> 489
    //   5975: lload 9
    //   5977: lstore 11
    //   5979: iload_2
    //   5980: istore 5
    //   5982: lload 9
    //   5984: lstore 13
    //   5986: aload_0
    //   5987: getfield 361	com/tencent/smtt/sdk/h:hiz	I
    //   5990: aload_0
    //   5991: getfield 78	com/tencent/smtt/sdk/h:xUR	I
    //   5994: if_icmpge +168 -> 6162
    //   5997: iload_3
    //   5998: sipush 503
    //   6001: if_icmpne +161 -> 6162
    //   6004: lload 9
    //   6006: lstore 11
    //   6008: iload_2
    //   6009: istore 5
    //   6011: lload 9
    //   6013: lstore 13
    //   6015: aload_0
    //   6016: aload_0
    //   6017: getfield 636	com/tencent/smtt/sdk/h:xUJ	Ljava/net/HttpURLConnection;
    //   6020: ldc_w 961
    //   6023: invokevirtual 949	java/net/HttpURLConnection:getHeaderField	(Ljava/lang/String;)Ljava/lang/String;
    //   6026: invokestatic 965	java/lang/Long:parseLong	(Ljava/lang/String;)J
    //   6029: invokespecial 895	com/tencent/smtt/sdk/h:fr	(J)V
    //   6032: lload 9
    //   6034: lstore 11
    //   6036: iload_2
    //   6037: istore 5
    //   6039: lload 9
    //   6041: lstore 13
    //   6043: aload_0
    //   6044: getfield 373	com/tencent/smtt/sdk/h:Lv	Z
    //   6047: ifeq +74 -> 6121
    //   6050: lload 9
    //   6052: lstore 11
    //   6054: iload_2
    //   6055: istore 5
    //   6057: lload 9
    //   6059: lstore 13
    //   6061: aload_0
    //   6062: getfield 90	com/tencent/smtt/sdk/h:mContext	Landroid/content/Context;
    //   6065: invokestatic 226	com/tencent/smtt/sdk/k:gl	(Landroid/content/Context;)Lcom/tencent/smtt/sdk/k;
    //   6068: sipush 65227
    //   6071: invokevirtual 599	com/tencent/smtt/sdk/k:Ff	(I)V
    //   6074: iload_2
    //   6075: istore 5
    //   6077: iload_1
    //   6078: ifne -5542 -> 536
    //   6081: aload_0
    //   6082: getfield 90	com/tencent/smtt/sdk/h:mContext	Landroid/content/Context;
    //   6085: invokestatic 226	com/tencent/smtt/sdk/k:gl	(Landroid/content/Context;)Lcom/tencent/smtt/sdk/k;
    //   6088: getfield 511	com/tencent/smtt/sdk/k:xVh	Ljava/util/Map;
    //   6091: ldc_w 655
    //   6094: lload 9
    //   6096: invokestatic 739	java/lang/Long:valueOf	(J)Ljava/lang/Long;
    //   6099: invokeinterface 524 3 0
    //   6104: pop
    //   6105: aload_0
    //   6106: getfield 90	com/tencent/smtt/sdk/h:mContext	Landroid/content/Context;
    //   6109: invokestatic 226	com/tencent/smtt/sdk/k:gl	(Landroid/content/Context;)Lcom/tencent/smtt/sdk/k;
    //   6112: invokevirtual 531	com/tencent/smtt/sdk/k:commit	()V
    //   6115: iload_2
    //   6116: istore 5
    //   6118: goto -5582 -> 536
    //   6121: iload_1
    //   6122: ifne +840 -> 6962
    //   6125: aload_0
    //   6126: getfield 90	com/tencent/smtt/sdk/h:mContext	Landroid/content/Context;
    //   6129: invokestatic 226	com/tencent/smtt/sdk/k:gl	(Landroid/content/Context;)Lcom/tencent/smtt/sdk/k;
    //   6132: getfield 511	com/tencent/smtt/sdk/k:xVh	Ljava/util/Map;
    //   6135: ldc_w 655
    //   6138: lload 9
    //   6140: invokestatic 739	java/lang/Long:valueOf	(J)Ljava/lang/Long;
    //   6143: invokeinterface 524 3 0
    //   6148: pop
    //   6149: aload_0
    //   6150: getfield 90	com/tencent/smtt/sdk/h:mContext	Landroid/content/Context;
    //   6153: invokestatic 226	com/tencent/smtt/sdk/k:gl	(Landroid/content/Context;)Lcom/tencent/smtt/sdk/k;
    //   6156: invokevirtual 531	com/tencent/smtt/sdk/k:commit	()V
    //   6159: goto -5670 -> 489
    //   6162: lload 9
    //   6164: lstore 11
    //   6166: iload_2
    //   6167: istore 5
    //   6169: lload 9
    //   6171: lstore 13
    //   6173: aload_0
    //   6174: getfield 361	com/tencent/smtt/sdk/h:hiz	I
    //   6177: aload_0
    //   6178: getfield 78	com/tencent/smtt/sdk/h:xUR	I
    //   6181: if_icmpge +177 -> 6358
    //   6184: iload_3
    //   6185: sipush 408
    //   6188: if_icmpeq +24 -> 6212
    //   6191: iload_3
    //   6192: sipush 504
    //   6195: if_icmpeq +17 -> 6212
    //   6198: iload_3
    //   6199: sipush 502
    //   6202: if_icmpeq +10 -> 6212
    //   6205: iload_3
    //   6206: sipush 408
    //   6209: if_icmpne +149 -> 6358
    //   6212: lload 9
    //   6214: lstore 11
    //   6216: iload_2
    //   6217: istore 5
    //   6219: lload 9
    //   6221: lstore 13
    //   6223: aload_0
    //   6224: lconst_0
    //   6225: invokespecial 895	com/tencent/smtt/sdk/h:fr	(J)V
    //   6228: lload 9
    //   6230: lstore 11
    //   6232: iload_2
    //   6233: istore 5
    //   6235: lload 9
    //   6237: lstore 13
    //   6239: aload_0
    //   6240: getfield 373	com/tencent/smtt/sdk/h:Lv	Z
    //   6243: ifeq +74 -> 6317
    //   6246: lload 9
    //   6248: lstore 11
    //   6250: iload_2
    //   6251: istore 5
    //   6253: lload 9
    //   6255: lstore 13
    //   6257: aload_0
    //   6258: getfield 90	com/tencent/smtt/sdk/h:mContext	Landroid/content/Context;
    //   6261: invokestatic 226	com/tencent/smtt/sdk/k:gl	(Landroid/content/Context;)Lcom/tencent/smtt/sdk/k;
    //   6264: sipush 65227
    //   6267: invokevirtual 599	com/tencent/smtt/sdk/k:Ff	(I)V
    //   6270: iload_2
    //   6271: istore 5
    //   6273: iload_1
    //   6274: ifne -5738 -> 536
    //   6277: aload_0
    //   6278: getfield 90	com/tencent/smtt/sdk/h:mContext	Landroid/content/Context;
    //   6281: invokestatic 226	com/tencent/smtt/sdk/k:gl	(Landroid/content/Context;)Lcom/tencent/smtt/sdk/k;
    //   6284: getfield 511	com/tencent/smtt/sdk/k:xVh	Ljava/util/Map;
    //   6287: ldc_w 655
    //   6290: lload 9
    //   6292: invokestatic 739	java/lang/Long:valueOf	(J)Ljava/lang/Long;
    //   6295: invokeinterface 524 3 0
    //   6300: pop
    //   6301: aload_0
    //   6302: getfield 90	com/tencent/smtt/sdk/h:mContext	Landroid/content/Context;
    //   6305: invokestatic 226	com/tencent/smtt/sdk/k:gl	(Landroid/content/Context;)Lcom/tencent/smtt/sdk/k;
    //   6308: invokevirtual 531	com/tencent/smtt/sdk/k:commit	()V
    //   6311: iload_2
    //   6312: istore 5
    //   6314: goto -5778 -> 536
    //   6317: iload_1
    //   6318: ifne +644 -> 6962
    //   6321: aload_0
    //   6322: getfield 90	com/tencent/smtt/sdk/h:mContext	Landroid/content/Context;
    //   6325: invokestatic 226	com/tencent/smtt/sdk/k:gl	(Landroid/content/Context;)Lcom/tencent/smtt/sdk/k;
    //   6328: getfield 511	com/tencent/smtt/sdk/k:xVh	Ljava/util/Map;
    //   6331: ldc_w 655
    //   6334: lload 9
    //   6336: invokestatic 739	java/lang/Long:valueOf	(J)Ljava/lang/Long;
    //   6339: invokeinterface 524 3 0
    //   6344: pop
    //   6345: aload_0
    //   6346: getfield 90	com/tencent/smtt/sdk/h:mContext	Landroid/content/Context;
    //   6349: invokestatic 226	com/tencent/smtt/sdk/k:gl	(Landroid/content/Context;)Lcom/tencent/smtt/sdk/k;
    //   6352: invokevirtual 531	com/tencent/smtt/sdk/k:commit	()V
    //   6355: goto -5866 -> 489
    //   6358: lload 9
    //   6360: lstore 11
    //   6362: iload_2
    //   6363: istore 5
    //   6365: lload 9
    //   6367: lstore 13
    //   6369: aload_0
    //   6370: invokespecial 790	com/tencent/smtt/sdk/h:cnW	()J
    //   6373: lconst_0
    //   6374: lcmp
    //   6375: ifgt +85 -> 6460
    //   6378: lload 9
    //   6380: lstore 11
    //   6382: iload_2
    //   6383: istore 5
    //   6385: lload 9
    //   6387: lstore 13
    //   6389: aload_0
    //   6390: getfield 371	com/tencent/smtt/sdk/h:xUH	Z
    //   6393: ifne +67 -> 6460
    //   6396: iload_3
    //   6397: sipush 410
    //   6400: if_icmpeq +60 -> 6460
    //   6403: lload 9
    //   6405: lstore 11
    //   6407: iload_2
    //   6408: istore 5
    //   6410: lload 9
    //   6412: lstore 13
    //   6414: aload_0
    //   6415: iconst_1
    //   6416: putfield 371	com/tencent/smtt/sdk/h:xUH	Z
    //   6419: iload_1
    //   6420: ifne +542 -> 6962
    //   6423: aload_0
    //   6424: getfield 90	com/tencent/smtt/sdk/h:mContext	Landroid/content/Context;
    //   6427: invokestatic 226	com/tencent/smtt/sdk/k:gl	(Landroid/content/Context;)Lcom/tencent/smtt/sdk/k;
    //   6430: getfield 511	com/tencent/smtt/sdk/k:xVh	Ljava/util/Map;
    //   6433: ldc_w 655
    //   6436: lload 9
    //   6438: invokestatic 739	java/lang/Long:valueOf	(J)Ljava/lang/Long;
    //   6441: invokeinterface 524 3 0
    //   6446: pop
    //   6447: aload_0
    //   6448: getfield 90	com/tencent/smtt/sdk/h:mContext	Landroid/content/Context;
    //   6451: invokestatic 226	com/tencent/smtt/sdk/k:gl	(Landroid/content/Context;)Lcom/tencent/smtt/sdk/k;
    //   6454: invokevirtual 531	com/tencent/smtt/sdk/k:commit	()V
    //   6457: goto -5968 -> 489
    //   6460: lload 9
    //   6462: lstore 11
    //   6464: iload_2
    //   6465: istore 5
    //   6467: lload 9
    //   6469: lstore 13
    //   6471: aload_0
    //   6472: getfield 90	com/tencent/smtt/sdk/h:mContext	Landroid/content/Context;
    //   6475: invokestatic 226	com/tencent/smtt/sdk/k:gl	(Landroid/content/Context;)Lcom/tencent/smtt/sdk/k;
    //   6478: sipush 65221
    //   6481: invokevirtual 599	com/tencent/smtt/sdk/k:Ff	(I)V
    //   6484: iload_2
    //   6485: istore 5
    //   6487: iload_1
    //   6488: ifne -5952 -> 536
    //   6491: aload_0
    //   6492: getfield 90	com/tencent/smtt/sdk/h:mContext	Landroid/content/Context;
    //   6495: invokestatic 226	com/tencent/smtt/sdk/k:gl	(Landroid/content/Context;)Lcom/tencent/smtt/sdk/k;
    //   6498: getfield 511	com/tencent/smtt/sdk/k:xVh	Ljava/util/Map;
    //   6501: ldc_w 655
    //   6504: lload 9
    //   6506: invokestatic 739	java/lang/Long:valueOf	(J)Ljava/lang/Long;
    //   6509: invokeinterface 524 3 0
    //   6514: pop
    //   6515: aload_0
    //   6516: getfield 90	com/tencent/smtt/sdk/h:mContext	Landroid/content/Context;
    //   6519: invokestatic 226	com/tencent/smtt/sdk/k:gl	(Landroid/content/Context;)Lcom/tencent/smtt/sdk/k;
    //   6522: invokevirtual 531	com/tencent/smtt/sdk/k:commit	()V
    //   6525: iload_2
    //   6526: istore 5
    //   6528: goto -5992 -> 536
    //   6531: lload 9
    //   6533: lstore 11
    //   6535: aload_0
    //   6536: lconst_0
    //   6537: invokespecial 895	com/tencent/smtt/sdk/h:fr	(J)V
    //   6540: lload 9
    //   6542: lstore 11
    //   6544: aload_0
    //   6545: bipush 107
    //   6547: aload 27
    //   6549: invokestatic 336	com/tencent/smtt/sdk/h:i	(Ljava/lang/Throwable;)Ljava/lang/String;
    //   6552: iconst_0
    //   6553: invokespecial 340	com/tencent/smtt/sdk/h:j	(ILjava/lang/String;Z)V
    //   6556: lload 9
    //   6558: lstore 11
    //   6560: aload_0
    //   6561: getfield 373	com/tencent/smtt/sdk/h:Lv	Z
    //   6564: ifeq -3891 -> 2673
    //   6567: lload 9
    //   6569: lstore 11
    //   6571: aload_0
    //   6572: getfield 90	com/tencent/smtt/sdk/h:mContext	Landroid/content/Context;
    //   6575: invokestatic 226	com/tencent/smtt/sdk/k:gl	(Landroid/content/Context;)Lcom/tencent/smtt/sdk/k;
    //   6578: sipush 65227
    //   6581: invokevirtual 599	com/tencent/smtt/sdk/k:Ff	(I)V
    //   6584: iload_2
    //   6585: istore 5
    //   6587: iload_1
    //   6588: ifne +371 -> 6959
    //   6591: aload_0
    //   6592: getfield 90	com/tencent/smtt/sdk/h:mContext	Landroid/content/Context;
    //   6595: invokestatic 226	com/tencent/smtt/sdk/k:gl	(Landroid/content/Context;)Lcom/tencent/smtt/sdk/k;
    //   6598: getfield 511	com/tencent/smtt/sdk/k:xVh	Ljava/util/Map;
    //   6601: ldc_w 655
    //   6604: lload 9
    //   6606: invokestatic 739	java/lang/Long:valueOf	(J)Ljava/lang/Long;
    //   6609: invokeinterface 524 3 0
    //   6614: pop
    //   6615: aload_0
    //   6616: getfield 90	com/tencent/smtt/sdk/h:mContext	Landroid/content/Context;
    //   6619: invokestatic 226	com/tencent/smtt/sdk/k:gl	(Landroid/content/Context;)Lcom/tencent/smtt/sdk/k;
    //   6622: invokevirtual 531	com/tencent/smtt/sdk/k:commit	()V
    //   6625: iload_2
    //   6626: istore 5
    //   6628: goto -6092 -> 536
    //   6631: iconst_0
    //   6632: istore_3
    //   6633: goto -6042 -> 591
    //   6636: iconst_2
    //   6637: istore_3
    //   6638: goto -6024 -> 614
    //   6641: aload_0
    //   6642: getfield 102	com/tencent/smtt/sdk/h:xUL	Lcom/tencent/smtt/sdk/r$b;
    //   6645: iconst_0
    //   6646: putfield 663	com/tencent/smtt/sdk/r$b:xWl	I
    //   6649: goto -6029 -> 620
    //   6652: aload_0
    //   6653: getfield 90	com/tencent/smtt/sdk/h:mContext	Landroid/content/Context;
    //   6656: invokestatic 226	com/tencent/smtt/sdk/k:gl	(Landroid/content/Context;)Lcom/tencent/smtt/sdk/k;
    //   6659: sipush 65218
    //   6662: invokevirtual 599	com/tencent/smtt/sdk/k:Ff	(I)V
    //   6665: aload_0
    //   6666: iconst_0
    //   6667: invokespecial 959	com/tencent/smtt/sdk/h:mZ	(Z)Z
    //   6670: pop
    //   6671: goto -6019 -> 652
    //   6674: aload 27
    //   6676: getfield 230	com/tencent/smtt/sdk/k:xVi	Landroid/content/SharedPreferences;
    //   6679: ldc_w 967
    //   6682: iconst_0
    //   6683: invokeinterface 290 3 0
    //   6688: istore_3
    //   6689: aload 27
    //   6691: getfield 511	com/tencent/smtt/sdk/k:xVh	Ljava/util/Map;
    //   6694: astore 28
    //   6696: iload_3
    //   6697: iconst_1
    //   6698: iadd
    //   6699: istore_3
    //   6700: aload 28
    //   6702: ldc_w 967
    //   6705: iload_3
    //   6706: invokestatic 327	java/lang/Integer:valueOf	(I)Ljava/lang/Integer;
    //   6709: invokeinterface 524 3 0
    //   6714: pop
    //   6715: iload_3
    //   6716: aload 27
    //   6718: invokevirtual 970	com/tencent/smtt/sdk/k:coh	()I
    //   6721: if_icmpne -6021 -> 700
    //   6724: aload_0
    //   6725: getfield 102	com/tencent/smtt/sdk/h:xUL	Lcom/tencent/smtt/sdk/r$b;
    //   6728: iconst_2
    //   6729: putfield 803	com/tencent/smtt/sdk/r$b:xWm	I
    //   6732: goto -6032 -> 700
    //   6735: iconst_0
    //   6736: istore_3
    //   6737: goto -6020 -> 717
    //   6740: astore 27
    //   6742: ldc -65
    //   6744: new 109	java/lang/StringBuilder
    //   6747: dup
    //   6748: ldc_w 972
    //   6751: invokespecial 114	java/lang/StringBuilder:<init>	(Ljava/lang/String;)V
    //   6754: aload 27
    //   6756: invokevirtual 834	java/lang/Throwable:toString	()Ljava/lang/String;
    //   6759: invokevirtual 122	java/lang/StringBuilder:append	(Ljava/lang/String;)Ljava/lang/StringBuilder;
    //   6762: invokevirtual 125	java/lang/StringBuilder:toString	()Ljava/lang/String;
    //   6765: invokestatic 208	com/tencent/smtt/utils/TbsLog:e	(Ljava/lang/String;Ljava/lang/String;)V
    //   6768: goto -5999 -> 769
    //   6771: invokestatic 974	com/tencent/smtt/sdk/h:cnX	()Z
    //   6774: ifne -5839 -> 935
    //   6777: aload_0
    //   6778: bipush 101
    //   6780: aconst_null
    //   6781: iconst_1
    //   6782: invokespecial 340	com/tencent/smtt/sdk/h:j	(ILjava/lang/String;Z)V
    //   6785: goto -5850 -> 935
    //   6788: aload_0
    //   6789: getfield 90	com/tencent/smtt/sdk/h:mContext	Landroid/content/Context;
    //   6792: invokestatic 96	com/tencent/smtt/sdk/r:gR	(Landroid/content/Context;)Lcom/tencent/smtt/sdk/r;
    //   6795: getstatic 977	com/tencent/smtt/sdk/r$a:xWa	Lcom/tencent/smtt/sdk/r$a;
    //   6798: aload_0
    //   6799: getfield 102	com/tencent/smtt/sdk/h:xUL	Lcom/tencent/smtt/sdk/r$b;
    //   6802: invokevirtual 727	com/tencent/smtt/sdk/r:a	(Lcom/tencent/smtt/sdk/r$a;Lcom/tencent/smtt/sdk/r$b;)V
    //   6805: goto -5830 -> 975
    //   6808: iconst_0
    //   6809: putstatic 596	com/tencent/smtt/sdk/l:xVq	Z
    //   6812: return
    //   6813: astore 27
    //   6815: lload 11
    //   6817: lstore 13
    //   6819: goto -4033 -> 2786
    //   6822: astore 27
    //   6824: goto -4244 -> 2580
    //   6827: astore 27
    //   6829: lload 13
    //   6831: lstore 9
    //   6833: iload 5
    //   6835: istore_2
    //   6836: goto -4256 -> 2580
    //   6839: astore 29
    //   6841: aconst_null
    //   6842: astore 28
    //   6844: aconst_null
    //   6845: astore 27
    //   6847: aconst_null
    //   6848: astore 31
    //   6850: goto -1528 -> 5322
    //   6853: astore 29
    //   6855: aconst_null
    //   6856: astore 31
    //   6858: aconst_null
    //   6859: astore 27
    //   6861: goto -1539 -> 5322
    //   6864: astore 29
    //   6866: aconst_null
    //   6867: astore 30
    //   6869: aload 27
    //   6871: astore 31
    //   6873: aload 30
    //   6875: astore 27
    //   6877: goto -1555 -> 5322
    //   6880: astore 29
    //   6882: lload 15
    //   6884: lstore 9
    //   6886: iload 6
    //   6888: istore_2
    //   6889: aload 27
    //   6891: astore 31
    //   6893: aload 30
    //   6895: astore 27
    //   6897: goto -1575 -> 5322
    //   6900: astore 29
    //   6902: lload 11
    //   6904: lstore 9
    //   6906: aload 27
    //   6908: astore 31
    //   6910: aload 30
    //   6912: astore 27
    //   6914: goto -1592 -> 5322
    //   6917: astore 29
    //   6919: aconst_null
    //   6920: astore 27
    //   6922: aload 31
    //   6924: astore 30
    //   6926: goto -3034 -> 3892
    //   6929: astore 29
    //   6931: aload 31
    //   6933: astore 30
    //   6935: goto -3043 -> 3892
    //   6938: astore 29
    //   6940: iload 7
    //   6942: istore_2
    //   6943: lload 17
    //   6945: lstore 9
    //   6947: goto -3055 -> 3892
    //   6950: astore 29
    //   6952: lload 11
    //   6954: lstore 9
    //   6956: goto -3064 -> 3892
    //   6959: goto -6423 -> 536
    //   6962: goto -6473 -> 489
    //   6965: lload 13
    //   6967: lstore 9
    //   6969: lload 19
    //   6971: lstore 13
    //   6973: goto -2147 -> 4826
    //   6976: aconst_null
    //   6977: astore 27
    //   6979: aconst_null
    //   6980: astore 30
    //   6982: goto -2133 -> 4849
    //   6985: lload 9
    //   6987: lstore 15
    //   6989: goto -5833 -> 1156
    //   6992: iconst_1
    //   6993: istore_3
    //   6994: goto -4978 -> 2016
    //   6997: iload_3
    //   6998: sipush 200
    //   7001: if_icmpeq -3974 -> 3027
    //   7004: iload_3
    //   7005: sipush 206
    //   7008: if_icmpne -1624 -> 5384
    //   7011: goto -3984 -> 3027
    // Local variable table:
    //   start	length	slot	name	signature
    //   0	7014	0	this	h
    //   0	7014	1	paramBoolean1	boolean
    //   0	7014	2	paramBoolean2	boolean
    //   54	6955	3	i	int
    //   836	27	4	j	int
    //   71	6763	5	bool1	boolean
    //   1007	5880	6	bool2	boolean
    //   3649	3292	7	bool3	boolean
    //   487	5165	8	bool4	boolean
    //   470	6516	9	l1	long
    //   1014	5939	11	l2	long
    //   1169	5803	13	l3	long
    //   1154	5834	15	l4	long
    //   3646	3298	17	l5	long
    //   1819	5151	19	l6	long
    //   3662	1183	21	l7	long
    //   1033	3800	23	l8	long
    //   447	3933	25	l9	long
    //   144	2414	27	localObject1	Object
    //   2571	77	27	localThrowable1	Throwable
    //   2784	220	27	str	String
    //   3560	3157	27	localObject2	Object
    //   6740	15	27	localThrowable2	Throwable
    //   6813	1	27	localObject3	Object
    //   6822	1	27	localThrowable3	Throwable
    //   6827	1	27	localThrowable4	Throwable
    //   6845	133	27	localObject4	Object
    //   813	1731	28	localObject5	Object
    //   2742	26	28	localThrowable5	Throwable
    //   3532	3311	28	localObject6	Object
    //   3612	1	29	arrayOfByte	byte[]
    //   3883	1418	29	localIOException1	IOException
    //   5312	70	29	localObject7	Object
    //   6839	1	29	localObject8	Object
    //   6853	1	29	localObject9	Object
    //   6864	1	29	localObject10	Object
    //   6880	1	29	localObject11	Object
    //   6900	1	29	localObject12	Object
    //   6917	1	29	localIOException2	IOException
    //   6929	1	29	localIOException3	IOException
    //   6938	1	29	localIOException4	IOException
    //   6950	1	29	localIOException5	IOException
    //   3635	3346	30	localObject13	Object
    //   3529	3403	31	localObject14	Object
    // Exception table:
    //   from	to	target	type
    //   1171	1181	2571	java/lang/Throwable
    //   1192	1201	2571	java/lang/Throwable
    //   1212	1220	2571	java/lang/Throwable
    //   1231	1244	2571	java/lang/Throwable
    //   1426	1431	2571	java/lang/Throwable
    //   1442	1449	2571	java/lang/Throwable
    //   1460	1466	2571	java/lang/Throwable
    //   1477	1514	2571	java/lang/Throwable
    //   1525	1537	2571	java/lang/Throwable
    //   1548	1554	2571	java/lang/Throwable
    //   1565	1573	2571	java/lang/Throwable
    //   1584	1591	2571	java/lang/Throwable
    //   1602	1608	2571	java/lang/Throwable
    //   1619	1630	2571	java/lang/Throwable
    //   1641	1647	2571	java/lang/Throwable
    //   1674	1686	2571	java/lang/Throwable
    //   1697	1710	2571	java/lang/Throwable
    //   1721	1734	2571	java/lang/Throwable
    //   1745	1755	2571	java/lang/Throwable
    //   1766	1774	2571	java/lang/Throwable
    //   1785	1796	2571	java/lang/Throwable
    //   1807	1818	2571	java/lang/Throwable
    //   1832	1839	2571	java/lang/Throwable
    //   1850	1856	2571	java/lang/Throwable
    //   1867	1890	2571	java/lang/Throwable
    //   1901	1910	2571	java/lang/Throwable
    //   1921	1945	2571	java/lang/Throwable
    //   1956	1990	2571	java/lang/Throwable
    //   2001	2007	2571	java/lang/Throwable
    //   2027	2033	2571	java/lang/Throwable
    //   2044	2052	2571	java/lang/Throwable
    //   2063	2072	2571	java/lang/Throwable
    //   2083	2090	2571	java/lang/Throwable
    //   2101	2109	2571	java/lang/Throwable
    //   2120	2126	2571	java/lang/Throwable
    //   2137	2142	2571	java/lang/Throwable
    //   2153	2160	2571	java/lang/Throwable
    //   2171	2185	2571	java/lang/Throwable
    //   2196	2204	2571	java/lang/Throwable
    //   2215	2237	2571	java/lang/Throwable
    //   2248	2256	2571	java/lang/Throwable
    //   2271	2281	2571	java/lang/Throwable
    //   2292	2303	2571	java/lang/Throwable
    //   2314	2320	2571	java/lang/Throwable
    //   2331	2341	2571	java/lang/Throwable
    //   2352	2356	2571	java/lang/Throwable
    //   2367	2373	2571	java/lang/Throwable
    //   2384	2394	2571	java/lang/Throwable
    //   2405	2414	2571	java/lang/Throwable
    //   2425	2432	2571	java/lang/Throwable
    //   2443	2456	2571	java/lang/Throwable
    //   2514	2520	2571	java/lang/Throwable
    //   2534	2568	2571	java/lang/Throwable
    //   2755	2781	2571	java/lang/Throwable
    //   2838	2875	2571	java/lang/Throwable
    //   2886	2927	2571	java/lang/Throwable
    //   2941	2949	2571	java/lang/Throwable
    //   2960	2972	2571	java/lang/Throwable
    //   2983	2991	2571	java/lang/Throwable
    //   3002	3008	2571	java/lang/Throwable
    //   3019	3024	2571	java/lang/Throwable
    //   3038	3053	2571	java/lang/Throwable
    //   3064	3089	2571	java/lang/Throwable
    //   3100	3111	2571	java/lang/Throwable
    //   3122	3143	2571	java/lang/Throwable
    //   3161	3171	2571	java/lang/Throwable
    //   3182	3219	2571	java/lang/Throwable
    //   3234	3241	2571	java/lang/Throwable
    //   3252	3258	2571	java/lang/Throwable
    //   3269	3279	2571	java/lang/Throwable
    //   3290	3297	2571	java/lang/Throwable
    //   3308	3314	2571	java/lang/Throwable
    //   3371	3409	2571	java/lang/Throwable
    //   3420	3433	2571	java/lang/Throwable
    //   3491	3501	2571	java/lang/Throwable
    //   3512	3525	2571	java/lang/Throwable
    //   3545	3553	2571	java/lang/Throwable
    //   4860	4865	2571	java/lang/Throwable
    //   4876	4881	2571	java/lang/Throwable
    //   4892	4897	2571	java/lang/Throwable
    //   4908	4915	2571	java/lang/Throwable
    //   4926	4939	2571	java/lang/Throwable
    //   5333	5338	2571	java/lang/Throwable
    //   5349	5354	2571	java/lang/Throwable
    //   5365	5370	2571	java/lang/Throwable
    //   5381	5384	2571	java/lang/Throwable
    //   5409	5421	2571	java/lang/Throwable
    //   5432	5440	2571	java/lang/Throwable
    //   5451	5457	2571	java/lang/Throwable
    //   5468	5478	2571	java/lang/Throwable
    //   5530	5538	2571	java/lang/Throwable
    //   5549	5562	2571	java/lang/Throwable
    //   5620	5631	2571	java/lang/Throwable
    //   5649	5659	2571	java/lang/Throwable
    //   5672	5685	2571	java/lang/Throwable
    //   5743	5749	2571	java/lang/Throwable
    //   5760	5773	2571	java/lang/Throwable
    //   5845	5856	2571	java/lang/Throwable
    //   5867	5880	2571	java/lang/Throwable
    //   5986	5997	2571	java/lang/Throwable
    //   6015	6032	2571	java/lang/Throwable
    //   6043	6050	2571	java/lang/Throwable
    //   6061	6074	2571	java/lang/Throwable
    //   6173	6184	2571	java/lang/Throwable
    //   6223	6228	2571	java/lang/Throwable
    //   6239	6246	2571	java/lang/Throwable
    //   6257	6270	2571	java/lang/Throwable
    //   6369	6378	2571	java/lang/Throwable
    //   6389	6396	2571	java/lang/Throwable
    //   6414	6419	2571	java/lang/Throwable
    //   6471	6484	2571	java/lang/Throwable
    //   1656	1663	2742	java/lang/Throwable
    //   1171	1181	2784	finally
    //   1192	1201	2784	finally
    //   1212	1220	2784	finally
    //   1231	1244	2784	finally
    //   1426	1431	2784	finally
    //   1442	1449	2784	finally
    //   1460	1466	2784	finally
    //   1477	1514	2784	finally
    //   1525	1537	2784	finally
    //   1548	1554	2784	finally
    //   1565	1573	2784	finally
    //   1584	1591	2784	finally
    //   1602	1608	2784	finally
    //   1619	1630	2784	finally
    //   1641	1647	2784	finally
    //   1656	1663	2784	finally
    //   1674	1686	2784	finally
    //   1697	1710	2784	finally
    //   1721	1734	2784	finally
    //   1745	1755	2784	finally
    //   1766	1774	2784	finally
    //   1785	1796	2784	finally
    //   1807	1818	2784	finally
    //   1832	1839	2784	finally
    //   1850	1856	2784	finally
    //   1867	1890	2784	finally
    //   1901	1910	2784	finally
    //   1921	1945	2784	finally
    //   1956	1990	2784	finally
    //   2001	2007	2784	finally
    //   2027	2033	2784	finally
    //   2044	2052	2784	finally
    //   2063	2072	2784	finally
    //   2083	2090	2784	finally
    //   2101	2109	2784	finally
    //   2120	2126	2784	finally
    //   2137	2142	2784	finally
    //   2153	2160	2784	finally
    //   2171	2185	2784	finally
    //   2196	2204	2784	finally
    //   2215	2237	2784	finally
    //   2248	2256	2784	finally
    //   2271	2281	2784	finally
    //   2292	2303	2784	finally
    //   2314	2320	2784	finally
    //   2331	2341	2784	finally
    //   2352	2356	2784	finally
    //   2367	2373	2784	finally
    //   2384	2394	2784	finally
    //   2405	2414	2784	finally
    //   2425	2432	2784	finally
    //   2443	2456	2784	finally
    //   2514	2520	2784	finally
    //   2534	2568	2784	finally
    //   2755	2781	2784	finally
    //   2838	2875	2784	finally
    //   2886	2927	2784	finally
    //   2941	2949	2784	finally
    //   2960	2972	2784	finally
    //   2983	2991	2784	finally
    //   3002	3008	2784	finally
    //   3019	3024	2784	finally
    //   3038	3053	2784	finally
    //   3064	3089	2784	finally
    //   3100	3111	2784	finally
    //   3122	3143	2784	finally
    //   3161	3171	2784	finally
    //   3182	3219	2784	finally
    //   3234	3241	2784	finally
    //   3252	3258	2784	finally
    //   3269	3279	2784	finally
    //   3290	3297	2784	finally
    //   3308	3314	2784	finally
    //   3371	3409	2784	finally
    //   3420	3433	2784	finally
    //   3491	3501	2784	finally
    //   3512	3525	2784	finally
    //   3545	3553	2784	finally
    //   4860	4865	2784	finally
    //   4876	4881	2784	finally
    //   4892	4897	2784	finally
    //   4908	4915	2784	finally
    //   4926	4939	2784	finally
    //   5333	5338	2784	finally
    //   5349	5354	2784	finally
    //   5365	5370	2784	finally
    //   5381	5384	2784	finally
    //   5409	5421	2784	finally
    //   5432	5440	2784	finally
    //   5451	5457	2784	finally
    //   5468	5478	2784	finally
    //   5530	5538	2784	finally
    //   5549	5562	2784	finally
    //   5620	5631	2784	finally
    //   5649	5659	2784	finally
    //   5672	5685	2784	finally
    //   5743	5749	2784	finally
    //   5760	5773	2784	finally
    //   5845	5856	2784	finally
    //   5867	5880	2784	finally
    //   5986	5997	2784	finally
    //   6015	6032	2784	finally
    //   6043	6050	2784	finally
    //   6061	6074	2784	finally
    //   6173	6184	2784	finally
    //   6223	6228	2784	finally
    //   6239	6246	2784	finally
    //   6257	6270	2784	finally
    //   6369	6378	2784	finally
    //   6389	6396	2784	finally
    //   6414	6419	2784	finally
    //   6471	6484	2784	finally
    //   3571	3580	3883	java/io/IOException
    //   3585	3607	3883	java/io/IOException
    //   3850	3880	3883	java/io/IOException
    //   3892	3908	5312	finally
    //   3908	3932	5312	finally
    //   4990	5058	5312	finally
    //   5153	5158	5312	finally
    //   5160	5179	5312	finally
    //   5185	5197	5312	finally
    //   5297	5309	5312	finally
    //   762	769	6740	java/lang/Throwable
    //   1043	1072	6813	finally
    //   1076	1084	6813	finally
    //   1088	1112	6813	finally
    //   1116	1139	6813	finally
    //   1143	1153	6813	finally
    //   1295	1318	6813	finally
    //   1330	1339	6813	finally
    //   1343	1351	6813	finally
    //   1355	1368	6813	finally
    //   2584	2592	6813	finally
    //   2600	2607	6813	finally
    //   2611	2618	6813	finally
    //   2622	2661	6813	finally
    //   2665	2673	6813	finally
    //   2677	2690	6813	finally
    //   3756	3761	6813	finally
    //   3772	3777	6813	finally
    //   3788	3793	6813	finally
    //   3943	3948	6813	finally
    //   3959	3964	6813	finally
    //   3975	3980	6813	finally
    //   5069	5074	6813	finally
    //   5085	5090	6813	finally
    //   5101	5106	6813	finally
    //   5208	5213	6813	finally
    //   5224	5229	6813	finally
    //   5240	5245	6813	finally
    //   6535	6540	6813	finally
    //   6544	6556	6813	finally
    //   6560	6567	6813	finally
    //   6571	6584	6813	finally
    //   1043	1072	6822	java/lang/Throwable
    //   1076	1084	6822	java/lang/Throwable
    //   1088	1112	6822	java/lang/Throwable
    //   1116	1139	6822	java/lang/Throwable
    //   1143	1153	6822	java/lang/Throwable
    //   1295	1318	6822	java/lang/Throwable
    //   1330	1339	6822	java/lang/Throwable
    //   1343	1351	6822	java/lang/Throwable
    //   1355	1368	6822	java/lang/Throwable
    //   3756	3761	6827	java/lang/Throwable
    //   3772	3777	6827	java/lang/Throwable
    //   3788	3793	6827	java/lang/Throwable
    //   3943	3948	6827	java/lang/Throwable
    //   3959	3964	6827	java/lang/Throwable
    //   3975	3980	6827	java/lang/Throwable
    //   5069	5074	6827	java/lang/Throwable
    //   5085	5090	6827	java/lang/Throwable
    //   5101	5106	6827	java/lang/Throwable
    //   5208	5213	6827	java/lang/Throwable
    //   5224	5229	6827	java/lang/Throwable
    //   5240	5245	6827	java/lang/Throwable
    //   3553	3562	6839	finally
    //   3571	3580	6853	finally
    //   3585	3607	6853	finally
    //   3850	3880	6853	finally
    //   3607	3637	6864	finally
    //   3651	3656	6880	finally
    //   3682	3689	6880	finally
    //   3703	3712	6880	finally
    //   3726	3739	6880	finally
    //   4053	4065	6880	finally
    //   4083	4090	6880	finally
    //   4104	4114	6880	finally
    //   4132	4139	6880	finally
    //   4158	4163	6880	finally
    //   4184	4189	6880	finally
    //   4206	4213	6880	finally
    //   4232	4245	6880	finally
    //   4267	4276	6880	finally
    //   4290	4295	6880	finally
    //   4332	4341	6880	finally
    //   4355	4391	6880	finally
    //   4405	4418	6880	finally
    //   4441	4451	6880	finally
    //   4465	4474	6880	finally
    //   4488	4533	6880	finally
    //   4547	4560	6880	finally
    //   4569	4620	6900	finally
    //   4639	4706	6900	finally
    //   4730	4757	6900	finally
    //   4757	4767	6900	finally
    //   4767	4787	6900	finally
    //   4787	4809	6900	finally
    //   3553	3562	6917	java/io/IOException
    //   3607	3637	6929	java/io/IOException
    //   3651	3656	6938	java/io/IOException
    //   3682	3689	6938	java/io/IOException
    //   3703	3712	6938	java/io/IOException
    //   3726	3739	6938	java/io/IOException
    //   4053	4065	6938	java/io/IOException
    //   4083	4090	6938	java/io/IOException
    //   4104	4114	6938	java/io/IOException
    //   4132	4139	6938	java/io/IOException
    //   4158	4163	6938	java/io/IOException
    //   4184	4189	6938	java/io/IOException
    //   4206	4213	6938	java/io/IOException
    //   4232	4245	6938	java/io/IOException
    //   4267	4276	6938	java/io/IOException
    //   4290	4295	6938	java/io/IOException
    //   4332	4341	6938	java/io/IOException
    //   4355	4391	6938	java/io/IOException
    //   4405	4418	6938	java/io/IOException
    //   4441	4451	6938	java/io/IOException
    //   4465	4474	6938	java/io/IOException
    //   4488	4533	6938	java/io/IOException
    //   4547	4560	6938	java/io/IOException
    //   4569	4620	6950	java/io/IOException
    //   4639	4706	6950	java/io/IOException
    //   4730	4757	6950	java/io/IOException
    //   4757	4767	6950	java/io/IOException
    //   4767	4787	6950	java/io/IOException
    //   4787	4809	6950	java/io/IOException
  }
  
  public final void clearCache()
  {
    stopDownload();
    mZ(false);
    mZ(true);
  }
  
  public final boolean cnU()
  {
    TbsLog.i("TbsApkDownloader", "verifyAndInstallDecoupleCoreFromBackup #1");
    try
    {
      File localFile1 = new File(f.an(this.mContext, 4), "x5.tbs.decouple");
      if (localFile1.exists()) {
        TbsLog.i("TbsApkDownloader", "verifyAndInstallDecoupleCoreFromBackup #2");
      }
      while (a.a(this.mContext, localFile1, k.gl(this.mContext).xVi.getInt("tbs_decouplecoreversion", -1)))
      {
        TbsLog.i("TbsApkDownloader", "verifyAndInstallDecoupleCoreFromBackup #3");
        p.cov();
        return p.gv(this.mContext);
        File localFile2 = l.Fi(k.gl(this.mContext).xVi.getInt("tbs_decouplecoreversion", -1));
        if ((localFile2 != null) && (localFile2.exists())) {
          f.i(localFile2, localFile1);
        }
      }
      TbsLog.i("TbsApkDownloader", "verifyAndInstallDecoupleCoreFromBackup no backup file !!!");
      localFile1 = new File(f.an(this.mContext, 4), "x5.tbs.decouple");
      if (localFile1.exists()) {
        localFile1.delete();
      }
    }
    catch (Exception localException) {}
    return false;
  }
  
  /* Error */
  public final boolean cnY()
  {
    // Byte code:
    //   0: aconst_null
    //   1: astore 8
    //   3: aconst_null
    //   4: astore 6
    //   6: iconst_1
    //   7: istore 4
    //   9: iconst_0
    //   10: istore 5
    //   12: aload_0
    //   13: getfield 90	com/tencent/smtt/sdk/h:mContext	Landroid/content/Context;
    //   16: invokestatic 706	com/tencent/smtt/utils/b:ho	(Landroid/content/Context;)I
    //   19: iconst_3
    //   20: if_icmpne +288 -> 308
    //   23: iconst_1
    //   24: istore_3
    //   25: ldc -65
    //   27: new 109	java/lang/StringBuilder
    //   30: dup
    //   31: ldc_w 999
    //   34: invokespecial 114	java/lang/StringBuilder:<init>	(Ljava/lang/String;)V
    //   37: iload_3
    //   38: invokevirtual 215	java/lang/StringBuilder:append	(Z)Ljava/lang/StringBuilder;
    //   41: invokevirtual 125	java/lang/StringBuilder:toString	()Ljava/lang/String;
    //   44: invokestatic 198	com/tencent/smtt/utils/TbsLog:i	(Ljava/lang/String;Ljava/lang/String;)V
    //   47: iload 5
    //   49: istore_2
    //   50: iload_3
    //   51: ifeq +135 -> 186
    //   54: aload_0
    //   55: getfield 90	com/tencent/smtt/sdk/h:mContext	Landroid/content/Context;
    //   58: invokestatic 642	com/tencent/smtt/utils/b:hp	(Landroid/content/Context;)Ljava/lang/String;
    //   61: astore 6
    //   63: ldc -65
    //   65: new 109	java/lang/StringBuilder
    //   68: dup
    //   69: ldc_w 1001
    //   72: invokespecial 114	java/lang/StringBuilder:<init>	(Ljava/lang/String;)V
    //   75: aload 6
    //   77: invokevirtual 122	java/lang/StringBuilder:append	(Ljava/lang/String;)Ljava/lang/StringBuilder;
    //   80: invokevirtual 125	java/lang/StringBuilder:toString	()Ljava/lang/String;
    //   83: invokestatic 198	com/tencent/smtt/utils/TbsLog:i	(Ljava/lang/String;Ljava/lang/String;)V
    //   86: new 432	java/net/URL
    //   89: dup
    //   90: ldc_w 1003
    //   93: invokespecial 758	java/net/URL:<init>	(Ljava/lang/String;)V
    //   96: invokevirtual 762	java/net/URL:openConnection	()Ljava/net/URLConnection;
    //   99: checkcast 676	java/net/HttpURLConnection
    //   102: astore 7
    //   104: aload 7
    //   106: iconst_0
    //   107: invokevirtual 782	java/net/HttpURLConnection:setInstanceFollowRedirects	(Z)V
    //   110: aload 7
    //   112: sipush 10000
    //   115: invokevirtual 785	java/net/HttpURLConnection:setConnectTimeout	(I)V
    //   118: aload 7
    //   120: sipush 10000
    //   123: invokevirtual 788	java/net/HttpURLConnection:setReadTimeout	(I)V
    //   126: aload 7
    //   128: iconst_0
    //   129: invokevirtual 1006	java/net/HttpURLConnection:setUseCaches	(Z)V
    //   132: aload 7
    //   134: invokevirtual 862	java/net/HttpURLConnection:getInputStream	()Ljava/io/InputStream;
    //   137: pop
    //   138: aload 7
    //   140: invokevirtual 811	java/net/HttpURLConnection:getResponseCode	()I
    //   143: istore_1
    //   144: ldc -65
    //   146: new 109	java/lang/StringBuilder
    //   149: dup
    //   150: ldc_w 1008
    //   153: invokespecial 114	java/lang/StringBuilder:<init>	(Ljava/lang/String;)V
    //   156: iload_1
    //   157: invokevirtual 297	java/lang/StringBuilder:append	(I)Ljava/lang/StringBuilder;
    //   160: invokevirtual 125	java/lang/StringBuilder:toString	()Ljava/lang/String;
    //   163: invokestatic 198	com/tencent/smtt/utils/TbsLog:i	(Ljava/lang/String;Ljava/lang/String;)V
    //   166: iload_1
    //   167: sipush 204
    //   170: if_icmpne +143 -> 313
    //   173: iload 4
    //   175: istore_2
    //   176: aload 7
    //   178: ifnull +214 -> 392
    //   181: aload 7
    //   183: invokevirtual 688	java/net/HttpURLConnection:disconnect	()V
    //   186: iload_2
    //   187: ifne +89 -> 276
    //   190: aload 6
    //   192: invokestatic 954	android/text/TextUtils:isEmpty	(Ljava/lang/CharSequence;)Z
    //   195: ifne +81 -> 276
    //   198: aload_0
    //   199: getfield 107	com/tencent/smtt/sdk/h:xUQ	Ljava/util/Set;
    //   202: aload 6
    //   204: invokeinterface 646 2 0
    //   209: ifne +67 -> 276
    //   212: aload_0
    //   213: getfield 107	com/tencent/smtt/sdk/h:xUQ	Ljava/util/Set;
    //   216: aload 6
    //   218: invokeinterface 1011 2 0
    //   223: pop
    //   224: aload_0
    //   225: getfield 1013	com/tencent/smtt/sdk/h:xUP	Landroid/os/Handler;
    //   228: ifnonnull +21 -> 249
    //   231: aload_0
    //   232: new 6	com/tencent/smtt/sdk/h$1
    //   235: dup
    //   236: aload_0
    //   237: invokestatic 1019	com/tencent/smtt/sdk/n:cou	()Lcom/tencent/smtt/sdk/n;
    //   240: invokevirtual 1023	com/tencent/smtt/sdk/n:getLooper	()Landroid/os/Looper;
    //   243: invokespecial 1026	com/tencent/smtt/sdk/h$1:<init>	(Lcom/tencent/smtt/sdk/h;Landroid/os/Looper;)V
    //   246: putfield 1013	com/tencent/smtt/sdk/h:xUP	Landroid/os/Handler;
    //   249: aload_0
    //   250: getfield 1013	com/tencent/smtt/sdk/h:xUP	Landroid/os/Handler;
    //   253: sipush 150
    //   256: aload 6
    //   258: invokevirtual 1032	android/os/Handler:obtainMessage	(ILjava/lang/Object;)Landroid/os/Message;
    //   261: astore 7
    //   263: aload_0
    //   264: getfield 1013	com/tencent/smtt/sdk/h:xUP	Landroid/os/Handler;
    //   267: aload 7
    //   269: ldc2_w 1033
    //   272: invokevirtual 1038	android/os/Handler:sendMessageDelayed	(Landroid/os/Message;J)Z
    //   275: pop
    //   276: iload_2
    //   277: ifeq +29 -> 306
    //   280: aload_0
    //   281: getfield 107	com/tencent/smtt/sdk/h:xUQ	Ljava/util/Set;
    //   284: aload 6
    //   286: invokeinterface 646 2 0
    //   291: ifeq +15 -> 306
    //   294: aload_0
    //   295: getfield 107	com/tencent/smtt/sdk/h:xUQ	Ljava/util/Set;
    //   298: aload 6
    //   300: invokeinterface 1041 2 0
    //   305: pop
    //   306: iload_2
    //   307: ireturn
    //   308: iconst_0
    //   309: istore_3
    //   310: goto -285 -> 25
    //   313: iconst_0
    //   314: istore_2
    //   315: goto -139 -> 176
    //   318: astore 7
    //   320: goto -134 -> 186
    //   323: astore 7
    //   325: aconst_null
    //   326: astore 7
    //   328: aload 7
    //   330: ifnull +56 -> 386
    //   333: aload 7
    //   335: invokevirtual 688	java/net/HttpURLConnection:disconnect	()V
    //   338: iload 5
    //   340: istore_2
    //   341: goto -155 -> 186
    //   344: astore 7
    //   346: iload 5
    //   348: istore_2
    //   349: goto -163 -> 186
    //   352: astore 6
    //   354: aload 8
    //   356: astore 7
    //   358: aload 7
    //   360: ifnull +8 -> 368
    //   363: aload 7
    //   365: invokevirtual 688	java/net/HttpURLConnection:disconnect	()V
    //   368: aload 6
    //   370: athrow
    //   371: astore 7
    //   373: goto -5 -> 368
    //   376: astore 6
    //   378: goto -20 -> 358
    //   381: astore 8
    //   383: goto -55 -> 328
    //   386: iload 5
    //   388: istore_2
    //   389: goto -203 -> 186
    //   392: goto -206 -> 186
    // Local variable table:
    //   start	length	slot	name	signature
    //   0	395	0	this	h
    //   143	28	1	i	int
    //   49	340	2	bool1	boolean
    //   24	286	3	bool2	boolean
    //   7	167	4	bool3	boolean
    //   10	377	5	bool4	boolean
    //   4	295	6	str	String
    //   352	17	6	localObject1	Object
    //   376	1	6	localObject2	Object
    //   102	166	7	localObject3	Object
    //   318	1	7	localException1	Exception
    //   323	1	7	localThrowable1	Throwable
    //   326	8	7	localObject4	Object
    //   344	1	7	localException2	Exception
    //   356	8	7	localObject5	Object
    //   371	1	7	localException3	Exception
    //   1	354	8	localObject6	Object
    //   381	1	8	localThrowable2	Throwable
    // Exception table:
    //   from	to	target	type
    //   181	186	318	java/lang/Exception
    //   86	104	323	java/lang/Throwable
    //   333	338	344	java/lang/Exception
    //   86	104	352	finally
    //   363	368	371	java/lang/Exception
    //   104	166	376	finally
    //   104	166	381	java/lang/Throwable
  }
  
  public final boolean mX(boolean paramBoolean)
  {
    boolean bool = true;
    int i = k.gl(this.mContext).xVi.getInt("use_backup_version", 0);
    int j = p.cov().gC(this.mContext);
    if (i == 0) {
      i = k.gl(this.mContext).xVi.getInt("tbs_download_version", 0);
    }
    for (this.xUT = "by default key"; (i == 0) || (i == j); this.xUT = "by new key")
    {
      paramBoolean = false;
      return paramBoolean;
    }
    File localFile;
    String str;
    label135:
    label426:
    label431:
    Object localObject2;
    if (paramBoolean)
    {
      localFile = l.Fh(i);
      Object localObject1;
      if ((localFile != null) && (localFile.exists()))
      {
        str = f.an(this.mContext, 4);
        if (l.gp(this.mContext))
        {
          localObject1 = "x5.oversea.tbs.org";
          localObject1 = new File(str, (String)localObject1);
        }
      }
      for (;;)
      {
        try
        {
          if (k.gl(this.mContext).xVi.getInt("tbs_download_version_type", 0) == 1) {
            break label426;
          }
          f.i(localFile, (File)localObject1);
          j = 1;
          str = f.an(this.mContext, 4);
          if (!l.gp(this.mContext)) {
            break label431;
          }
          localObject1 = "x5.oversea.tbs.org";
          localObject1 = new File(str, (String)localObject1);
          int m = k.gl(this.mContext).xVi.getInt("use_backup_version", 0);
          int k = m;
          if (m == 0) {
            k = k.gl(this.mContext).xVi.getInt("tbs_download_version", 0);
          }
          if (!a.a(this.mContext, (File)localObject1, k)) {
            break label458;
          }
          if (!Fe(i)) {
            break label501;
          }
          k.gl(this.mContext).xVh.put("tbs_download_interrupt_code_reason", Integer.valueOf(65322));
          k.gl(this.mContext).Ff(65322);
          mY(false);
          paramBoolean = bool;
          if (j == 0) {
            break;
          }
          j(100, "use local backup apk in startDownload" + this.xUT, true);
          if (k.gl(this.mContext).xVi.getInt("tbs_downloaddecouplecore", 0) != 1) {
            break label438;
          }
          r.gR(this.mContext).a(r.a.xWd, this.xUL);
          this.xUL.cnT();
          return true;
        }
        catch (Exception localException1) {}
        localObject1 = "x5.tbs.org";
        break label135;
        j = 0;
        continue;
        localObject2 = "x5.tbs.org";
        continue;
        label438:
        r.gR(this.mContext).a(r.a.xWa, this.xUL);
      }
    }
    try
    {
      label458:
      j = k.gl(this.mContext).xVi.getInt("tbs_downloaddecouplecore", 0);
      if (j != 1) {
        break label555;
      }
    }
    catch (Exception localException2)
    {
      for (;;) {}
    }
    if (!a.a(this.mContext, localFile, i)) {
      f.O(localFile);
    }
    label501:
    if (Q(false, paramBoolean))
    {
      k.gl(this.mContext).xVh.put("tbs_download_interrupt_code_reason", Integer.valueOf(65322));
      k.gl(this.mContext).Ff(65322);
      mY(false);
      return true;
      label555:
      str = f.an(this.mContext, 4);
      if (l.gp(this.mContext)) {}
      for (localObject2 = "x5.oversea.tbs.org";; localObject2 = "x5.tbs.org")
      {
        localObject2 = new File(str, (String)localObject2);
        if (!((File)localObject2).exists()) {
          break;
        }
        ((File)localObject2).delete();
        break;
      }
    }
    if ((!mZ(true)) && (!mZ(true)))
    {
      TbsLog.e("TbsDownload", "[TbsApkDownloader] delete file failed!");
      k.gl(this.mContext).Ff(65235);
    }
    return false;
  }
  
  public final void stopDownload()
  {
    this.Lv = true;
    r.b localb;
    if (t.gU(this.mContext))
    {
      r.gR(this.mContext);
      localb = r.coy();
      localb.setErrorCode(65227);
      localb.j(new Exception());
      if (k.gl(this.mContext).xVi.getInt("tbs_downloaddecouplecore", 0) == 1) {
        r.gR(this.mContext).a(r.a.xWd, localb);
      }
    }
    else
    {
      return;
    }
    r.gR(this.mContext).a(r.a.xWa, localb);
  }
}


/* Location:              D:\tools\apktool\weixin6519android1140\jar\classes2-dex2jar.jar!\com\tencent\smtt\sdk\h.class
 * Java compiler version: 6 (50.0)
 * JD-Core Version:       0.7.1
 */